Workbook

Sheet Raw
B3: 2025 | C3: 2024 | D3: 2023 | E3: 2022 | F3: 2021 | G3: 2020 | H3: 2019 | I3: 2018 | J3: 2017 | K3: 2016 | L3: 2015 | M3: 2014 | N3: 2013 | O3: 2012 | P3: 2011 | Q3: 2010 | R3: 2009 | S3: 2008 | T3: 2007 | U3: 2006 | V3: 2005 | W3: 2004 | X3: 2003 | Y3: 2002 | Z3: 2001 | AA3: 2000 | AB3: 1999 | AC3: 1998 | AD3: 1997 | AE3: 1996 | AF3: 1995 | AG3: 1994 | AH3: 1993 | AI3: 1992 | AJ3: 1991 | AK3: 1990 | AL3: 1989 | AM3: 1988 | AN3: 1987 | AO3: 1986
A5: Revenue | B5: 47941000000 | C5: 47061000000 | D5: 45754000000 | E5: 43004000000 | F5: 38655000000 | G5: 33014000000 | H5: 37266000000 | I5: 34300000000 | J5: 36212000000 | K5: 41863000000 | L5: 44294000000 | M5: 45998000000 | N5: 46854000000 | O5: 48017000000 | P5: 46542000000 | Q5: 35119000000 | R5: 30990000000 | S5: 31944000000 | T5: 28857000000 | U5: 24088000000 | V5: 23104000000 | W5: 21742000000 | X5: 20857000000 | Y5: 19564000000 | Z5: 17545000000 | AA5: 17354000000 | AB5: 0 | AC5: 18813000000 | AD5: 18868000000 | AE5: 18546000000 | AF5: 18018000000 | AG5: 16172000000 | AH5: 13957000000 | AI5: 13073860000 | AJ5: 11571610000 | AK5: 10236350000 | AL5: 8965786000 | AM5: 8337831000 | AN5: 7658341000 | AO5: 6976558000
A6: Cost Of Goods Sold | B6: 18397000000 | C6: 18324000000 | D6: 18520000000 | E6: 18000000000 | F6: 15357000000 | G6: 13433000000 | H6: 14619000000 | I6: 13067000000 | J6: 13721000000 | K6: 16465000000 | L6: 17482000000 | M6: 17889000000 | N6: 18421000000 | O6: 19053000000 | P6: 18215000000 | Q6: 12693000000 | R6: 11088000000 | S6: 11374000000 | T6: 10406000000 | U6: 8164000000 | V6: 8195000000 | W6: 7674000000 | X6: 7776000000 | Y6: 7105000000 | Z6: 6044000000 | AA6: 6204000000 | AB6: 0 | AC6: 5562000000 | AD6: 6015000000 | AE6: 6738000000 | AF6: 6940000000 | AG6: 6167000000 | AH6: 5160000000 | AI6: 5054377000 | AJ6: 4648385000 | AK6: 4.20885e+09 | AL6: 3892069000 | AM6: 3701472000 | AN6: 3633159000 | AO6: 3453891000
A7: Gross Profit | B7: 29544000000 | C7: 28737000000 | D7: 27234000000 | E7: 25004000000 | F7: 23298000000 | G7: 19581000000 | H7: 22647000000 | I7: 21233000000 | J7: 22491000000 | K7: 25398000000 | L7: 26812000000 | M7: 28109000000 | N7: 28433000000 | O7: 28964000000 | P7: 28327000000 | Q7: 22426000000 | R7: 19902000000 | S7: 20570000000 | T7: 18451000000 | U7: 15924000000 | V7: 14909000000 | W7: 14068000000 | X7: 13081000000 | Y7: 12459000000 | Z7: 11501000000 | AA7: 11150000000 | AB7: 0 | AC7: 13251000000 | AD7: 12853000000 | AE7: 11808000000 | AF7: 11078000000 | AG7: 10005000000 | AH7: 8797000000 | AI7: 8019483000 | AJ7: 6923226000 | AK7: 6027500000 | AL7: 5073717000 | AM7: 4636359000 | AN7: 4025182000 | AO7: 3522667000
A9: Research And Development Expenses | AC9: 0 | AD9: 0 | AE9: 0 | AF9: 0 | AG9: 0 | AH9: 0 | AI9: 0 | AJ9: 0 | AK9: 0 | AL9: 0 | AM9: 0 | AN9: 0 | AO9: 0
A10: SG&A Expenses | B10: 14521000000 | C10: 14582000000 | D10: 13972000000 | E10: 12880000000 | F10: 12144000000 | G10: 9731000000 | H10: 12103000000 | I10: 11002000000 | J10: 12834000000 | K10: 15370000000 | L10: 16427000000 | M10: 17218000000 | N10: 17310000000 | O10: 17738000000 | P10: 17422000000 | Q10: 13194000000 | R10: 11358000000 | S10: 11774000000 | T10: 10945000000 | U10: 9431000000 | V10: 8739000000 | W10: 7890000000 | X10: 7287000000 | Y10: 7001000000 | Z10: 6149000000 | AA10: 6016000000 | AB10: 0 | AC10: 8284000000 | AD10: 7852000000 | AE10: 7893000000 | AF10: 6986000000 | AG10: 6297000000 | AH10: 5695000000 | AI10: 5249392000 | AJ10: 4604184000 | AK10: 4075936000 | AL10: 3347932000 | AM10: 3038058000 | AN10: 2701392000 | AO10: 2625602000
A11: Other Operating Income Or Expenses | B11: -1261000000 | C11: -4163000000 | D11: -1951000000 | E11: -1215000000 | F11: -846000000 | G11: -853000000 | H11: -458000000 | I11: -1079000000 | J11: -1902000000 | K11: -1371000000 | L11: -1657000000 | M11: -1183000000 | N11: -895000000 | O11: -447000000 | P11: -732000000 | Q11: -819000000 | R11: -313000000 | S11: -350000000 | T11: -254000000 | U11: -185000000 | V11: -85000000 | W11: -480000000 | X11: -573000000 | Y11: 0 | Z11: 0 | AA11: -1443000000 | AB11: 0 | AC11: 0 | AD11: 0 | AE11: 0 | AF11: 0 | AG11: 0 | AH11: 0 | AI11: 0 | AJ11: 0 | AK11: 0 | AL11: 0 | AM11: 0 | AN11: 0 | AO11: 0
A12: Operating Expenses | B12: 15782000000 | C12: 18745000000 | D12: 15923000000 | E12: 14095000000 | F12: 12990000000 | G12: 10584000000 | H12: 12561000000 | I12: 12081000000 | J12: 14736000000 | K12: 16741000000 | L12: 18084000000 | M12: 18401000000 | N12: 18205000000 | O12: 18185000000 | P12: 18154000000 | Q12: 14013000000 | R12: 11671000000 | S12: 12124000000 | T12: 11199000000 | U12: 9616000000 | V12: 8824000000 | W12: 8370000000 | X12: 7860000000 | Y12: 7001000000 | Z12: 6149000000 | AA12: 7459000000 | AB12: 0 | AC12: 8284000000 | AD12: 7852000000 | AE12: 7893000000 | AF12: 6986000000 | AG12: 6297000000 | AH12: 5695000000 | AI12: 5249393000 | AJ12: 4604183000 | AK12: 4075936000 | AL12: 3347932000 | AM12: 3038058000 | AN12: 2701392000 | AO12: 2625602000
A13: Operating Income | B13: 13762000000 | C13: 9992000000 | D13: 11311000000 | E13: 10909000000 | F13: 10308000000 | G13: 8997000000 | H13: 10086000000 | I13: 9152000000 | J13: 7755000000 | K13: 8657000000 | L13: 8728000000 | M13: 9708000000 | N13: 10228000000 | O13: 10779000000 | P13: 10173000000 | Q13: 8413000000 | R13: 8231000000 | S13: 8446000000 | T13: 7252000000 | U13: 6308000000 | V13: 6085000000 | W13: 5698000000 | X13: 5221000000 | Y13: 5458000000 | Z13: 5352000000 | AA13: 3691000000 | AB13: 3982000000 | AC13: 4967000000 | AD13: 5001000000 | AE13: 3915000000 | AF13: 4092000000 | AG13: 3708000000 | AH13: 3102000000 | AI13: 2770091000 | AJ13: 2319042000 | AK13: 1951563000 | AL13: 1725785000 | AM13: 1598301000 | AN13: 1323790000 | AO13: 897064900
A14: Total Non-Operating Income/Expense | B14: 2236000000 | C14: 3094000000 | D14: 1641000000 | E14: 777000000 | F14: 2117000000 | G14: 752000000 | H14: 700000000 | I14: -927000000 | J14: -865000000 | K14: -521000000 | L14: 877000000 | M14: -383000000 | N14: 1249000000 | O14: 1030000000 | P14: 1285000000 | Q14: 5794000000 | R14: 715000000 | S14: -940000000 | T14: 667000000 | U14: 270000000 | V14: 605000000 | W14: 524000000 | X14: 274000000 | Y14: 41000000 | Z14: 318000000 | AA14: -292000000 | AB14: 0 | AC14: 231000000 | AD14: 1054000000 | AE14: 681000000 | AF14: 236000000 | AG14: 20000000 | AH14: 83000000 | AI14: -24003000 | AJ14: 64234000 | AK14: 62872000 | AL14: 38525000 | AM14: -16164000 | AN14: 88694000 | AO14: 507860000
A15: Pre-Tax Income | B15: 15998000000 | C15: 13086000000 | D15: 12952000000 | E15: 11686000000 | F15: 12425000000 | G15: 9749000000 | H15: 10786000000 | I15: 8225000000 | J15: 6890000000 | K15: 8136000000 | L15: 9605000000 | M15: 9325000000 | N15: 11477000000 | O15: 11809000000 | P15: 11458000000 | Q15: 14207000000 | R15: 8946000000 | S15: 7506000000 | T15: 7919000000 | U15: 6578000000 | V15: 6690000000 | W15: 6222000000 | X15: 5495000000 | Y15: 5499000000 | Z15: 5670000000 | AA15: 3399000000 | AB15: 0 | AC15: 5198000000 | AD15: 6055000000 | AE15: 4596000000 | AF15: 4328000000 | AG15: 3728000000 | AH15: 3185000000 | AI15: 2746088000 | AJ15: 2383279000 | AK15: 2014436000 | AL15: 1764310000 | AM15: 1582137000 | AN15: 1412484000 | AO15: 1404925000
A16: Income Taxes | B16: 2861000000 | C16: 2437000000 | D16: 2249000000 | E16: 2115000000 | F16: 2621000000 | G16: 1981000000 | H16: 1801000000 | I16: 1749000000 | J16: 5607000000 | K16: 1586000000 | L16: 2239000000 | M16: 2201000000 | N16: 2851000000 | O16: 2723000000 | P16: 2812000000 | Q16: 2370000000 | R16: 2040000000 | S16: 1632000000 | T16: 1892000000 | U16: 1498000000 | V16: 1818000000 | W16: 1375000000 | X16: 1148000000 | Y16: 1523000000 | Z16: 1691000000 | AA16: 1222000000 | AB16: 0 | AC16: 1665000000 | AD16: 1926000000 | AE16: 1104000000 | AF16: 1342000000 | AG16: 1174000000 | AH16: 997000000 | AI16: 862273000 | AJ16: 765277000 | AK16: 632532000 | AL16: 571471000 | AM16: 537434000 | AN16: 496348000 | AO16: 470578000
A17: Income After Taxes | B17: 13137000000 | C17: 10649000000 | D17: 10703000000 | E17: 9571000000 | F17: 9804000000 | G17: 7768000000 | H17: 8985000000 | I17: 6476000000 | J17: 1283000000 | K17: 6550000000 | L17: 7366000000 | M17: 7124000000 | N17: 8626000000 | O17: 9086000000 | P17: 8646000000 | Q17: 11837000000 | R17: 6906000000 | S17: 5874000000 | T17: 6027000000 | U17: 5080000000 | V17: 4872000000 | W17: 4847000000 | X17: 4347000000 | Y17: 3976000000 | Z17: 3979000000 | AA17: 2177000000 | AB17: 0 | AC17: 3533000000 | AD17: 4129000000 | AE17: 3492000000 | AF17: 2986000000 | AG17: 2554000000 | AH17: 2188000000 | AI17: 1883815000 | AJ17: 1618002000 | AK17: 1381904000 | AL17: 1192839000 | AM17: 1044703000 | AN17: 916136000 | AO17: 934347000
A19: Other Income | AC19: 0 | AD19: 0 | AE19: 0 | AF19: 0 | AG19: 0 | AH19: 0 | AI19: 0 | AJ19: 0 | AK19: 0 | AL19: 0 | AM19: 0 | AN19: 0 | AO19: 0
A20: Income From Continuous Operations | B20: 13137000000 | C20: 10649000000 | D20: 10703000000 | E20: 9571000000 | F20: 9804000000 | G20: 7768000000 | H20: 8985000000 | I20: 6476000000 | J20: 1283000000 | K20: 6550000000 | L20: 7366000000 | M20: 7124000000 | N20: 8626000000 | O20: 9086000000 | P20: 8646000000 | Q20: 11837000000 | R20: 6906000000 | S20: 5874000000 | T20: 6027000000 | U20: 5080000000 | V20: 4872000000 | W20: 4847000000 | X20: 4347000000 | Y20: 3976000000 | Z20: 3979000000 | AA20: 2177000000 | AB20: 0 | AC20: 3483670000 | AD20: 4129000000 | AE20: 3492000000 | AF20: 3001600000 | AG20: 2554000000 | AH20: 2232000000 | AI20: 1897273000 | AJ20: 1613410000 | AK20: 1381904000 | AL20: 1192839000 | AM20: 1044703000 | AN20: 916136000 | AO20: 934347000
A21: Income From Discontinued Operations | B21: 0 | C21: 0 | D21: 0 | E21: 0 | F21: 0 | G21: 0 | H21: 0 | I21: 0 | J21: 0 | K21: 0 | L21: 0 | M21: 0 | N21: 0 | O21: 0 | P21: 0 | Q21: 0 | R21: 0 | S21: 0 | T21: 0 | U21: 0 | V21: 0 | W21: 0 | X21: 0 | Y21: 0 | Z21: 0 | AA21: 0 | AB21: 0 | AC21: 0 | AD21: 0 | AE21: 0 | AF21: 0 | AG21: 0 | AH21: -12000000 | AI21: -219433000 | AJ21: 0 | AK21: 0 | AL21: 530986000 | AM21: 0 | AN21: 0 | AO21: 0
A23: Net Income | B23: 13107 | C23: 10631 | D23: 10714 | E23: 9542 | F23: 9771 | G23: 7747 | H23: 8920 | I23: 6434 | J23: 1248 | K23: 6527 | L23: 7351 | M23: 7098 | N23: 8584 | O23: 9019 | P23: 8584 | Q23: 11787 | R23: 6824 | S23: 5807 | T23: 5981 | U23: 5080 | V23: 4872 | W23: 4847 | X23: 4347 | Y23: 3050 | Z23: 3969 | AA23: 2177 | AC23: 3533 | AD23: 4129 | AE23: 3492 | AF23: 2986 | AG23: 2554 | AH23: 2176 | AI23: 1664.382 | AJ23: 1618.002 | AK23: 1381.904 | AL23: 1723.825 | AM23: 1044.703 | AN23: 916.136 | AO23: 934.347
A25: EBITDA | B25: 14812000000 | C25: 11067000000 | D25: 12439000000 | E25: 12169000000 | F25: 11760000000 | G25: 10533000000 | H25: 11451000000 | I25: 10238000000 | J25: 9015000000 | K25: 10444000000 | L25: 10698000000 | M25: 11684000000 | N25: 12205000000 | O25: 12761000000 | P25: 12127000000 | Q25: 9856000000 | R25: 9467000000 | S25: 9674000000 | T25: 8415000000 | U25: 7246000000 | V25: 7017000000 | W25: 6591000000 | X25: 6071000000 | Y25: 6264000000 | Z25: 6155000000 | AA25: 4464000000 | AB25: 792000000 | AC25: 5612000000 | AD25: 5627000000 | AE25: 4394000000 | AF25: 4546000000 | AG25: 4119000000 | AH25: 3462000000 | AI25: 3092013000 | AJ25: 2580469000 | AK25: 2195451000 | AL25: 1909550000 | AM25: 1768069000 | AN25: 1475694000 | AO25: 1063894000
A26: EBIT | B26: 13762000000 | C26: 9992000000 | D26: 11311000000 | E26: 10909000000 | F26: 10308000000 | G26: 8997000000 | H26: 10086000000 | I26: 9152000000 | J26: 7755000000 | K26: 8657000000 | L26: 8728000000 | M26: 9708000000 | N26: 10228000000 | O26: 10779000000 | P26: 10173000000 | Q26: 8413000000 | R26: 8231000000 | S26: 8446000000 | T26: 7252000000 | U26: 6308000000 | V26: 6085000000 | W26: 5698000000 | X26: 5221000000 | Y26: 5458000000 | Z26: 5352000000 | AA26: 3691000000 | AB26: 0 | AC26: 4967000000 | AD26: 5001000000 | AE26: 3915000000 | AF26: 4092000000 | AG26: 3708000000 | AH26: 3102000000 | AI26: 2770091000 | AJ26: 2319042000 | AK26: 1951563000 | AL26: 1725785000 | AM26: 1598301000 | AN26: 1323790000 | AO26: 897064900
A27: Basic Shares Outstanding | B27: 4303000000 | C27: 4309000000 | D27: 4323000000 | E27: 4328000000 | F27: 4315000000 | G27: 4295000000 | H27: 4276000000 | I27: 4259000000 | J27: 4272000000 | K27: 4317000000 | L27: 4352000000 | M27: 4387000000 | N27: 4434000000 | O27: 4504000000 | P27: 4568000000 | Q27: 4616000000 | R27: 4628000000 | S27: 4630000000 | T27: 4626000000 | U27: 4696000000 | V27: 4784000000 | W27: 4852000000 | X27: 4918000000 | Y27: 4956000000 | Z27: 4974000000 | AA27: 4954000000 | AB27: 0 | AC27: 4934000000 | AD27: 4954000000 | AE27: 4988000000 | AF27: 5049000000 | AG27: 5160000000 | AH27: 5208000000 | AI27: 5227084000 | AJ27: 5315840000 | AK27: 5345914000 | AL27: 5392238000 | AM27: 5676616000 | AN27: 5957698000 | AO27: 7103570000
A28: Shares Outstanding | B28: 4313000000 | C28: 4320000000 | D28: 4339000000 | E28: 4350000000 | F28: 4340000000 | G28: 4323000000 | H28: 4314000000 | I28: 4299000000 | J28: 4324000000 | K28: 4367000000 | L28: 4405000000 | M28: 4450000000 | N28: 4509000000 | O28: 4584000000 | P28: 4646000000 | Q28: 4667000000 | R28: 4658000000 | S28: 4672000000 | T28: 4662000000 | U28: 4700000000 | V28: 4786000000 | W28: 4858000000 | X28: 4924000000 | Y28: 4966000000 | Z28: 4974000000 | AA28: 4974000000 | AB28: 0 | AC28: 4992000000 | AD28: 5030000000 | AE28: 4988000000 | AF28: 5049000000 | AG28: 5160000000 | AH28: 5208000000 | AI28: 5227084000 | AJ28: 10631680000 | AK28: 5345914000 | AL28: 5392238000 | AM28: 5676616000 | AN28: 5957698000 | AO28: 7103570000
A29: Basic EPS | B29: 3.05 | C29: 2.47 | D29: 2.48 | E29: 2.2 | F29: 2.26 | G29: 1.8 | H29: 2.09 | I29: 1.51 | J29: 0.29 | K29: 1.51 | L29: 1.69 | M29: 1.62 | N29: 1.94 | O29: 2 | P29: 1.88 | Q29: 2.55 | R29: 1.475 | S29: 1.255 | T29: 1.295 | U29: 1.08 | V29: 1.02 | W29: 1 | X29: 0.885 | Y29: 0.615 | Z29: 0.8 | AA29: 0.44 | AC29: 0.715 | AD29: 0.835 | AE29: 0.7 | AF29: 0.5925 | AG29: 0.495 | AH29: 0.4175 | AI29: 0.3171 | AJ29: 0.3038 | AK29: 0.2587 | AL29: 0.3136 | AM29: 0.1803 | AN29: 0.1523 | AO29: 0.1511
A30: EPS | B30: 3.04 | C30: 2.46 | D30: 2.47 | E30: 2.19 | F30: 2.25 | G30: 1.79 | H30: 2.07 | I30: 1.5 | J30: 0.29 | K30: 1.49 | L30: 1.67 | M30: 1.6 | N30: 1.9 | O30: 1.97 | P30: 1.85 | Q30: 2.53 | R30: 1.465 | S30: 1.245 | T30: 1.285 | U30: 1.08 | V30: 1.02 | W30: 1 | X30: 0.885 | Y30: 0.615 | Z30: 0.8 | AA30: 0.44 | AB30: 0 | AC30: 0.71 | AD30: 0.82 | AE30: 0.7 | AF30: 0.5925 | AG30: 0.495 | AH30: 0.4175 | AI30: 0.3184 | AJ30: 0.1522 | AK30: 0.2585 | AL30: 0.3197 | AM30: 0.184 | AN30: 0.1538 | AO30: 0.1315

Sheet Lookup
A1: TICKER | B1: ASOF_DATE | C1: YR | D1: Revenue | E1: Cost Of Goods Sold | F1: Gross Profit | G1: SG&A Expenses | H1: Other Operating Income Or Expenses | I1: Operating Expenses | J1: Operating Income | K1: Total Non-Operating Income/Expense | L1: Pre-Tax Income | M1: Income Taxes | N1: Income After Taxes | O1: Other Income | P1: Income From Continuous Operations | Q1: Income From Discontinued Operations | R1: Net Income | S1: EBITDA | T1: EBIT | U1: Basic Shares Outstanding | V1: Shares Outstanding | W1: Basic EPS | X1: EPS
A2: KO | B2: =TODAY() -> 46088 | C2: 2025 | D2: =INDEX(Raw!$B$5:$AO$30, MATCH(D$1, Raw!$A$5:$A$30, 0), MATCH($C2, Raw!$B$3:$AO$3, 0)) -> 47941000000 | E2: =INDEX(Raw!$B$5:$AO$30, MATCH(E$1, Raw!$A$5:$A$30, 0), MATCH($C2, Raw!$B$3:$AO$3, 0)) -> 18397000000 | F2: =INDEX(Raw!$B$5:$AO$30, MATCH(F$1, Raw!$A$5:$A$30, 0), MATCH($C2, Raw!$B$3:$AO$3, 0)) -> 29544000000 | G2: =INDEX(Raw!$B$5:$AO$30, MATCH(G$1, Raw!$A$5:$A$30, 0), MATCH($C2, Raw!$B$3:$AO$3, 0)) -> 14521000000 | H2: =INDEX(Raw!$B$5:$AO$30, MATCH(H$1, Raw!$A$5:$A$30, 0), MATCH($C2, Raw!$B$3:$AO$3, 0)) -> -1261000000 | I2: =INDEX(Raw!$B$5:$AO$30, MATCH(I$1, Raw!$A$5:$A$30, 0), MATCH($C2, Raw!$B$3:$AO$3, 0)) -> 15782000000 | J2: =INDEX(Raw!$B$5:$AO$30, MATCH(J$1, Raw!$A$5:$A$30, 0), MATCH($C2, Raw!$B$3:$AO$3, 0)) -> 13762000000 | K2: =INDEX(Raw!$B$5:$AO$30, MATCH(K$1, Raw!$A$5:$A$30, 0), MATCH($C2, Raw!$B$3:$AO$3, 0)) -> 2236000000 | ... X2: =INDEX(Raw!$B$5:$AO$30, MATCH(X$1, Raw!$A$5:$A$30, 0), MATCH($C2, Raw!$B$3:$AO$3, 0)) -> 3.04
A3: KO | B3: =TODAY() -> 46088 | C3: 2024 | D3: =INDEX(Raw!$B$5:$AO$30, MATCH(D$1, Raw!$A$5:$A$30, 0), MATCH($C3, Raw!$B$3:$AO$3, 0)) -> 47061000000 | E3: =INDEX(Raw!$B$5:$AO$30, MATCH(E$1, Raw!$A$5:$A$30, 0), MATCH($C3, Raw!$B$3:$AO$3, 0)) -> 18324000000 | F3: =INDEX(Raw!$B$5:$AO$30, MATCH(F$1, Raw!$A$5:$A$30, 0), MATCH($C3, Raw!$B$3:$AO$3, 0)) -> 28737000000 | G3: =INDEX(Raw!$B$5:$AO$30, MATCH(G$1, Raw!$A$5:$A$30, 0), MATCH($C3, Raw!$B$3:$AO$3, 0)) -> 14582000000 | H3: =INDEX(Raw!$B$5:$AO$30, MATCH(H$1, Raw!$A$5:$A$30, 0), MATCH($C3, Raw!$B$3:$AO$3, 0)) -> -4163000000 | I3: =INDEX(Raw!$B$5:$AO$30, MATCH(I$1, Raw!$A$5:$A$30, 0), MATCH($C3, Raw!$B$3:$AO$3, 0)) -> 18745000000 | J3: =INDEX(Raw!$B$5:$AO$30, MATCH(J$1, Raw!$A$5:$A$30, 0), MATCH($C3, Raw!$B$3:$AO$3, 0)) -> 9992000000 | K3: =INDEX(Raw!$B$5:$AO$30, MATCH(K$1, Raw!$A$5:$A$30, 0), MATCH($C3, Raw!$B$3:$AO$3, 0)) -> 3094000000 | ... X3: =INDEX(Raw!$B$5:$AO$30, MATCH(X$1, Raw!$A$5:$A$30, 0), MATCH($C3, Raw!$B$3:$AO$3, 0)) -> 2.46
A4: KO | B4: =TODAY() -> 46088 | C4: 2023 | D4: =INDEX(Raw!$B$5:$AO$30, MATCH(D$1, Raw!$A$5:$A$30, 0), MATCH($C4, Raw!$B$3:$AO$3, 0)) -> 45754000000 | E4: =INDEX(Raw!$B$5:$AO$30, MATCH(E$1, Raw!$A$5:$A$30, 0), MATCH($C4, Raw!$B$3:$AO$3, 0)) -> 18520000000 | F4: =INDEX(Raw!$B$5:$AO$30, MATCH(F$1, Raw!$A$5:$A$30, 0), MATCH($C4, Raw!$B$3:$AO$3, 0)) -> 27234000000 | G4: =INDEX(Raw!$B$5:$AO$30, MATCH(G$1, Raw!$A$5:$A$30, 0), MATCH($C4, Raw!$B$3:$AO$3, 0)) -> 13972000000 | H4: =INDEX(Raw!$B$5:$AO$30, MATCH(H$1, Raw!$A$5:$A$30, 0), MATCH($C4, Raw!$B$3:$AO$3, 0)) -> -1951000000 | I4: =INDEX(Raw!$B$5:$AO$30, MATCH(I$1, Raw!$A$5:$A$30, 0), MATCH($C4, Raw!$B$3:$AO$3, 0)) -> 15923000000 | J4: =INDEX(Raw!$B$5:$AO$30, MATCH(J$1, Raw!$A$5:$A$30, 0), MATCH($C4, Raw!$B$3:$AO$3, 0)) -> 11311000000 | K4: =INDEX(Raw!$B$5:$AO$30, MATCH(K$1, Raw!$A$5:$A$30, 0), MATCH($C4, Raw!$B$3:$AO$3, 0)) -> 1641000000 | ... X4: =INDEX(Raw!$B$5:$AO$30, MATCH(X$1, Raw!$A$5:$A$30, 0), MATCH($C4, Raw!$B$3:$AO$3, 0)) -> 2.47
A5: KO | B5: =TODAY() -> 46088 | C5: 2022 | D5: =INDEX(Raw!$B$5:$AO$30, MATCH(D$1, Raw!$A$5:$A$30, 0), MATCH($C5, Raw!$B$3:$AO$3, 0)) -> 43004000000 | E5: =INDEX(Raw!$B$5:$AO$30, MATCH(E$1, Raw!$A$5:$A$30, 0), MATCH($C5, Raw!$B$3:$AO$3, 0)) -> 18000000000 | F5: =INDEX(Raw!$B$5:$AO$30, MATCH(F$1, Raw!$A$5:$A$30, 0), MATCH($C5, Raw!$B$3:$AO$3, 0)) -> 25004000000 | G5: =INDEX(Raw!$B$5:$AO$30, MATCH(G$1, Raw!$A$5:$A$30, 0), MATCH($C5, Raw!$B$3:$AO$3, 0)) -> 12880000000 | H5: =INDEX(Raw!$B$5:$AO$30, MATCH(H$1, Raw!$A$5:$A$30, 0), MATCH($C5, Raw!$B$3:$AO$3, 0)) -> -1215000000 | I5: =INDEX(Raw!$B$5:$AO$30, MATCH(I$1, Raw!$A$5:$A$30, 0), MATCH($C5, Raw!$B$3:$AO$3, 0)) -> 14095000000 | J5: =INDEX(Raw!$B$5:$AO$30, MATCH(J$1, Raw!$A$5:$A$30, 0), MATCH($C5, Raw!$B$3:$AO$3, 0)) -> 10909000000 | K5: =INDEX(Raw!$B$5:$AO$30, MATCH(K$1, Raw!$A$5:$A$30, 0), MATCH($C5, Raw!$B$3:$AO$3, 0)) -> 777000000 | ... X5: =INDEX(Raw!$B$5:$AO$30, MATCH(X$1, Raw!$A$5:$A$30, 0), MATCH($C5, Raw!$B$3:$AO$3, 0)) -> 2.19
A6: KO | B6: =TODAY() -> 46088 | C6: 2021 | D6: =INDEX(Raw!$B$5:$AO$30, MATCH(D$1, Raw!$A$5:$A$30, 0), MATCH($C6, Raw!$B$3:$AO$3, 0)) -> 38655000000 | E6: =INDEX(Raw!$B$5:$AO$30, MATCH(E$1, Raw!$A$5:$A$30, 0), MATCH($C6, Raw!$B$3:$AO$3, 0)) -> 15357000000 | F6: =INDEX(Raw!$B$5:$AO$30, MATCH(F$1, Raw!$A$5:$A$30, 0), MATCH($C6, Raw!$B$3:$AO$3, 0)) -> 23298000000 | G6: =INDEX(Raw!$B$5:$AO$30, MATCH(G$1, Raw!$A$5:$A$30, 0), MATCH($C6, Raw!$B$3:$AO$3, 0)) -> 12144000000 | H6: =INDEX(Raw!$B$5:$AO$30, MATCH(H$1, Raw!$A$5:$A$30, 0), MATCH($C6, Raw!$B$3:$AO$3, 0)) -> -846000000 | I6: =INDEX(Raw!$B$5:$AO$30, MATCH(I$1, Raw!$A$5:$A$30, 0), MATCH($C6, Raw!$B$3:$AO$3, 0)) -> 12990000000 | J6: =INDEX(Raw!$B$5:$AO$30, MATCH(J$1, Raw!$A$5:$A$30, 0), MATCH($C6, Raw!$B$3:$AO$3, 0)) -> 10308000000 | K6: =INDEX(Raw!$B$5:$AO$30, MATCH(K$1, Raw!$A$5:$A$30, 0), MATCH($C6, Raw!$B$3:$AO$3, 0)) -> 2117000000 | ... X6: =INDEX(Raw!$B$5:$AO$30, MATCH(X$1, Raw!$A$5:$A$30, 0), MATCH($C6, Raw!$B$3:$AO$3, 0)) -> 2.25
A7: KO | B7: =TODAY() -> 46088 | C7: 2020 | D7: =INDEX(Raw!$B$5:$AO$30, MATCH(D$1, Raw!$A$5:$A$30, 0), MATCH($C7, Raw!$B$3:$AO$3, 0)) -> 33014000000 | E7: =INDEX(Raw!$B$5:$AO$30, MATCH(E$1, Raw!$A$5:$A$30, 0), MATCH($C7, Raw!$B$3:$AO$3, 0)) -> 13433000000 | F7: =INDEX(Raw!$B$5:$AO$30, MATCH(F$1, Raw!$A$5:$A$30, 0), MATCH($C7, Raw!$B$3:$AO$3, 0)) -> 19581000000 | G7: =INDEX(Raw!$B$5:$AO$30, MATCH(G$1, Raw!$A$5:$A$30, 0), MATCH($C7, Raw!$B$3:$AO$3, 0)) -> 9731000000 | H7: =INDEX(Raw!$B$5:$AO$30, MATCH(H$1, Raw!$A$5:$A$30, 0), MATCH($C7, Raw!$B$3:$AO$3, 0)) -> -853000000 | I7: =INDEX(Raw!$B$5:$AO$30, MATCH(I$1, Raw!$A$5:$A$30, 0), MATCH($C7, Raw!$B$3:$AO$3, 0)) -> 10584000000 | J7: =INDEX(Raw!$B$5:$AO$30, MATCH(J$1, Raw!$A$5:$A$30, 0), MATCH($C7, Raw!$B$3:$AO$3, 0)) -> 8997000000 | K7: =INDEX(Raw!$B$5:$AO$30, MATCH(K$1, Raw!$A$5:$A$30, 0), MATCH($C7, Raw!$B$3:$AO$3, 0)) -> 752000000 | ... X7: =INDEX(Raw!$B$5:$AO$30, MATCH(X$1, Raw!$A$5:$A$30, 0), MATCH($C7, Raw!$B$3:$AO$3, 0)) -> 1.79
A8: KO | B8: =TODAY() -> 46088 | C8: 2019 | D8: =INDEX(Raw!$B$5:$AO$30, MATCH(D$1, Raw!$A$5:$A$30, 0), MATCH($C8, Raw!$B$3:$AO$3, 0)) -> 37266000000 | E8: =INDEX(Raw!$B$5:$AO$30, MATCH(E$1, Raw!$A$5:$A$30, 0), MATCH($C8, Raw!$B$3:$AO$3, 0)) -> 14619000000 | F8: =INDEX(Raw!$B$5:$AO$30, MATCH(F$1, Raw!$A$5:$A$30, 0), MATCH($C8, Raw!$B$3:$AO$3, 0)) -> 22647000000 | G8: =INDEX(Raw!$B$5:$AO$30, MATCH(G$1, Raw!$A$5:$A$30, 0), MATCH($C8, Raw!$B$3:$AO$3, 0)) -> 12103000000 | H8: =INDEX(Raw!$B$5:$AO$30, MATCH(H$1, Raw!$A$5:$A$30, 0), MATCH($C8, Raw!$B$3:$AO$3, 0)) -> -458000000 | I8: =INDEX(Raw!$B$5:$AO$30, MATCH(I$1, Raw!$A$5:$A$30, 0), MATCH($C8, Raw!$B$3:$AO$3, 0)) -> 12561000000 | J8: =INDEX(Raw!$B$5:$AO$30, MATCH(J$1, Raw!$A$5:$A$30, 0), MATCH($C8, Raw!$B$3:$AO$3, 0)) -> 10086000000 | K8: =INDEX(Raw!$B$5:$AO$30, MATCH(K$1, Raw!$A$5:$A$30, 0), MATCH($C8, Raw!$B$3:$AO$3, 0)) -> 700000000 | ... X8: =INDEX(Raw!$B$5:$AO$30, MATCH(X$1, Raw!$A$5:$A$30, 0), MATCH($C8, Raw!$B$3:$AO$3, 0)) -> 2.07
A9: KO | B9: =TODAY() -> 46088 | C9: 2018 | D9: =INDEX(Raw!$B$5:$AO$30, MATCH(D$1, Raw!$A$5:$A$30, 0), MATCH($C9, Raw!$B$3:$AO$3, 0)) -> 34300000000 | E9: =INDEX(Raw!$B$5:$AO$30, MATCH(E$1, Raw!$A$5:$A$30, 0), MATCH($C9, Raw!$B$3:$AO$3, 0)) -> 13067000000 | F9: =INDEX(Raw!$B$5:$AO$30, MATCH(F$1, Raw!$A$5:$A$30, 0), MATCH($C9, Raw!$B$3:$AO$3, 0)) -> 21233000000 | G9: =INDEX(Raw!$B$5:$AO$30, MATCH(G$1, Raw!$A$5:$A$30, 0), MATCH($C9, Raw!$B$3:$AO$3, 0)) -> 11002000000 | H9: =INDEX(Raw!$B$5:$AO$30, MATCH(H$1, Raw!$A$5:$A$30, 0), MATCH($C9, Raw!$B$3:$AO$3, 0)) -> -1079000000 | I9: =INDEX(Raw!$B$5:$AO$30, MATCH(I$1, Raw!$A$5:$A$30, 0), MATCH($C9, Raw!$B$3:$AO$3, 0)) -> 12081000000 | J9: =INDEX(Raw!$B$5:$AO$30, MATCH(J$1, Raw!$A$5:$A$30, 0), MATCH($C9, Raw!$B$3:$AO$3, 0)) -> 9152000000 | K9: =INDEX(Raw!$B$5:$AO$30, MATCH(K$1, Raw!$A$5:$A$30, 0), MATCH($C9, Raw!$B$3:$AO$3, 0)) -> -927000000 | ... X9: =INDEX(Raw!$B$5:$AO$30, MATCH(X$1, Raw!$A$5:$A$30, 0), MATCH($C9, Raw!$B$3:$AO$3, 0)) -> 1.5
A10: KO | B10: =TODAY() -> 46088 | C10: 2017 | D10: =INDEX(Raw!$B$5:$AO$30, MATCH(D$1, Raw!$A$5:$A$30, 0), MATCH($C10, Raw!$B$3:$AO$3, 0)) -> 36212000000 | E10: =INDEX(Raw!$B$5:$AO$30, MATCH(E$1, Raw!$A$5:$A$30, 0), MATCH($C10, Raw!$B$3:$AO$3, 0)) -> 13721000000 | F10: =INDEX(Raw!$B$5:$AO$30, MATCH(F$1, Raw!$A$5:$A$30, 0), MATCH($C10, Raw!$B$3:$AO$3, 0)) -> 22491000000 | G10: =INDEX(Raw!$B$5:$AO$30, MATCH(G$1, Raw!$A$5:$A$30, 0), MATCH($C10, Raw!$B$3:$AO$3, 0)) -> 12834000000 | H10: =INDEX(Raw!$B$5:$AO$30, MATCH(H$1, Raw!$A$5:$A$30, 0), MATCH($C10, Raw!$B$3:$AO$3, 0)) -> -1902000000 | I10: =INDEX(Raw!$B$5:$AO$30, MATCH(I$1, Raw!$A$5:$A$30, 0), MATCH($C10, Raw!$B$3:$AO$3, 0)) -> 14736000000 | J10: =INDEX(Raw!$B$5:$AO$30, MATCH(J$1, Raw!$A$5:$A$30, 0), MATCH($C10, Raw!$B$3:$AO$3, 0)) -> 7755000000 | K10: =INDEX(Raw!$B$5:$AO$30, MATCH(K$1, Raw!$A$5:$A$30, 0), MATCH($C10, Raw!$B$3:$AO$3, 0)) -> -865000000 | ... X10: =INDEX(Raw!$B$5:$AO$30, MATCH(X$1, Raw!$A$5:$A$30, 0), MATCH($C10, Raw!$B$3:$AO$3, 0)) -> 0.29
A11: KO | B11: =TODAY() -> 46088 | C11: 2016 | D11: =INDEX(Raw!$B$5:$AO$30, MATCH(D$1, Raw!$A$5:$A$30, 0), MATCH($C11, Raw!$B$3:$AO$3, 0)) -> 41863000000 | E11: =INDEX(Raw!$B$5:$AO$30, MATCH(E$1, Raw!$A$5:$A$30, 0), MATCH($C11, Raw!$B$3:$AO$3, 0)) -> 16465000000 | F11: =INDEX(Raw!$B$5:$AO$30, MATCH(F$1, Raw!$A$5:$A$30, 0), MATCH($C11, Raw!$B$3:$AO$3, 0)) -> 25398000000 | G11: =INDEX(Raw!$B$5:$AO$30, MATCH(G$1, Raw!$A$5:$A$30, 0), MATCH($C11, Raw!$B$3:$AO$3, 0)) -> 15370000000 | H11: =INDEX(Raw!$B$5:$AO$30, MATCH(H$1, Raw!$A$5:$A$30, 0), MATCH($C11, Raw!$B$3:$AO$3, 0)) -> -1371000000 | I11: =INDEX(Raw!$B$5:$AO$30, MATCH(I$1, Raw!$A$5:$A$30, 0), MATCH($C11, Raw!$B$3:$AO$3, 0)) -> 16741000000 | J11: =INDEX(Raw!$B$5:$AO$30, MATCH(J$1, Raw!$A$5:$A$30, 0), MATCH($C11, Raw!$B$3:$AO$3, 0)) -> 8657000000 | K11: =INDEX(Raw!$B$5:$AO$30, MATCH(K$1, Raw!$A$5:$A$30, 0), MATCH($C11, Raw!$B$3:$AO$3, 0)) -> -521000000 | ... X11: =INDEX(Raw!$B$5:$AO$30, MATCH(X$1, Raw!$A$5:$A$30, 0), MATCH($C11, Raw!$B$3:$AO$3, 0)) -> 1.49
A12: KO | B12: =TODAY() -> 46088 | C12: 2015 | D12: =INDEX(Raw!$B$5:$AO$30, MATCH(D$1, Raw!$A$5:$A$30, 0), MATCH($C12, Raw!$B$3:$AO$3, 0)) -> 44294000000 | E12: =INDEX(Raw!$B$5:$AO$30, MATCH(E$1, Raw!$A$5:$A$30, 0), MATCH($C12, Raw!$B$3:$AO$3, 0)) -> 17482000000 | F12: =INDEX(Raw!$B$5:$AO$30, MATCH(F$1, Raw!$A$5:$A$30, 0), MATCH($C12, Raw!$B$3:$AO$3, 0)) -> 26812000000 | G12: =INDEX(Raw!$B$5:$AO$30, MATCH(G$1, Raw!$A$5:$A$30, 0), MATCH($C12, Raw!$B$3:$AO$3, 0)) -> 16427000000 | H12: =INDEX(Raw!$B$5:$AO$30, MATCH(H$1, Raw!$A$5:$A$30, 0), MATCH($C12, Raw!$B$3:$AO$3, 0)) -> -1657000000 | I12: =INDEX(Raw!$B$5:$AO$30, MATCH(I$1, Raw!$A$5:$A$30, 0), MATCH($C12, Raw!$B$3:$AO$3, 0)) -> 18084000000 | J12: =INDEX(Raw!$B$5:$AO$30, MATCH(J$1, Raw!$A$5:$A$30, 0), MATCH($C12, Raw!$B$3:$AO$3, 0)) -> 8728000000 | K12: =INDEX(Raw!$B$5:$AO$30, MATCH(K$1, Raw!$A$5:$A$30, 0), MATCH($C12, Raw!$B$3:$AO$3, 0)) -> 877000000 | ... X12: =INDEX(Raw!$B$5:$AO$30, MATCH(X$1, Raw!$A$5:$A$30, 0), MATCH($C12, Raw!$B$3:$AO$3, 0)) -> 1.67
A13: KO | B13: =TODAY() -> 46088 | C13: 2014 | D13: =INDEX(Raw!$B$5:$AO$30, MATCH(D$1, Raw!$A$5:$A$30, 0), MATCH($C13, Raw!$B$3:$AO$3, 0)) -> 45998000000 | E13: =INDEX(Raw!$B$5:$AO$30, MATCH(E$1, Raw!$A$5:$A$30, 0), MATCH($C13, Raw!$B$3:$AO$3, 0)) -> 17889000000 | F13: =INDEX(Raw!$B$5:$AO$30, MATCH(F$1, Raw!$A$5:$A$30, 0), MATCH($C13, Raw!$B$3:$AO$3, 0)) -> 28109000000 | G13: =INDEX(Raw!$B$5:$AO$30, MATCH(G$1, Raw!$A$5:$A$30, 0), MATCH($C13, Raw!$B$3:$AO$3, 0)) -> 17218000000 | H13: =INDEX(Raw!$B$5:$AO$30, MATCH(H$1, Raw!$A$5:$A$30, 0), MATCH($C13, Raw!$B$3:$AO$3, 0)) -> -1183000000 | I13: =INDEX(Raw!$B$5:$AO$30, MATCH(I$1, Raw!$A$5:$A$30, 0), MATCH($C13, Raw!$B$3:$AO$3, 0)) -> 18401000000 | J13: =INDEX(Raw!$B$5:$AO$30, MATCH(J$1, Raw!$A$5:$A$30, 0), MATCH($C13, Raw!$B$3:$AO$3, 0)) -> 9708000000 | K13: =INDEX(Raw!$B$5:$AO$30, MATCH(K$1, Raw!$A$5:$A$30, 0), MATCH($C13, Raw!$B$3:$AO$3, 0)) -> -383000000 | ... X13: =INDEX(Raw!$B$5:$AO$30, MATCH(X$1, Raw!$A$5:$A$30, 0), MATCH($C13, Raw!$B$3:$AO$3, 0)) -> 1.6
... A40: KO | B40: =TODAY() -> 46088 | C40: 1987 | D40: =INDEX(Raw!$B$5:$AO$30, MATCH(D$1, Raw!$A$5:$A$30, 0), MATCH($C40, Raw!$B$3:$AO$3, 0)) -> 7658341000 | E40: =INDEX(Raw!$B$5:$AO$30, MATCH(E$1, Raw!$A$5:$A$30, 0), MATCH($C40, Raw!$B$3:$AO$3, 0)) -> 3633159000 | F40: =INDEX(Raw!$B$5:$AO$30, MATCH(F$1, Raw!$A$5:$A$30, 0), MATCH($C40, Raw!$B$3:$AO$3, 0)) -> 4025182000 | G40: =INDEX(Raw!$B$5:$AO$30, MATCH(G$1, Raw!$A$5:$A$30, 0), MATCH($C40, Raw!$B$3:$AO$3, 0)) -> 2701392000 | H40: =INDEX(Raw!$B$5:$AO$30, MATCH(H$1, Raw!$A$5:$A$30, 0), MATCH($C40, Raw!$B$3:$AO$3, 0)) -> 0 | I40: =INDEX(Raw!$B$5:$AO$30, MATCH(I$1, Raw!$A$5:$A$30, 0), MATCH($C40, Raw!$B$3:$AO$3, 0)) -> 2701392000 | J40: =INDEX(Raw!$B$5:$AO$30, MATCH(J$1, Raw!$A$5:$A$30, 0), MATCH($C40, Raw!$B$3:$AO$3, 0)) -> 1323790000 | K40: =INDEX(Raw!$B$5:$AO$30, MATCH(K$1, Raw!$A$5:$A$30, 0), MATCH($C40, Raw!$B$3:$AO$3, 0)) -> 88694000 | ... X40: =INDEX(Raw!$B$5:$AO$30, MATCH(X$1, Raw!$A$5:$A$30, 0), MATCH($C40, Raw!$B$3:$AO$3, 0)) -> 0.1538

Sheet Export
A1: TICKER | B1: ASOF_DATE | C1: YR | D1: REVENUE | E1: COGS | F1: GROSS_PROFIT | G1: SGA_EXPENSES | H1: OTHER_OPERATING_INCOME_OR_EXPENSES | I1: OPERATING_EXPENSES | J1: OPERATING_INCOME | K1: TOTAL_NONOPERATING_INCOME_OR_EXPENSE | L1: PRETAX_INCOME | M1: INCOME_TAXES | N1: INCOME_AFTER_TAXES | O1: OTHER_INCOME | P1: INCOME_FROM_CONTINUOUS_OPERATIONS | Q1: INCOME_FROM_DISCONTINUED_OPERATIONS | R1: NET_INCOME | S1: EBITDA | T1: EBIT | U1: BASIC_SHARES | V1: DILUTED_SHARES | W1: BASIC_EPS | X1: DILUTED_EPS | Y1: SOURCE_FILE | Z1: LOAD_BATCH_ID | AA1: LOADED_AT
A2: =Lookup!A2 -> KO | B2: =Lookup!B2 -> 46088 | C2: =Lookup!C2 -> 2025 | D2: =Lookup!D2 -> 47941000000 | E2: =Lookup!E2 -> 18397000000 | F2: =Lookup!F2 -> 29544000000 | G2: =Lookup!G2 -> 14521000000 | H2: =Lookup!H2 -> -1261000000 | ... X2: =Lookup!X2 -> 3.04 | Y2: {=MID(CELL("filename",A1),FIND("[",CELL("filename",A1))+1,FIND("]",CELL("filename",A1))-FIND("[",CELL("filename",A1))-1)} -> KO_INC-ST_YRLY.xlsx | Z2: =_xlfn.CONCAT(LEFT(Y2,14),"-002") -> KO_INC-ST_YRLY-002 | AA2: =NOW() -> 46088.84
A3: =Lookup!A3 -> KO | B3: =Lookup!B3 -> 46088 | C3: =Lookup!C3 -> 2024 | D3: =Lookup!D3 -> 47061000000 | E3: =Lookup!E3 -> 18324000000 | F3: =Lookup!F3 -> 28737000000 | G3: =Lookup!G3 -> 14582000000 | H3: =Lookup!H3 -> -4163000000 | ... X3: =Lookup!X3 -> 2.46 | Y3: =$Y$2 -> KO_INC-ST_YRLY.xlsx | Z3: =$Z$2 -> KO_INC-ST_YRLY-002 | AA3: =NOW() -> 46088.84
A4: =Lookup!A4 -> KO | B4: =Lookup!B4 -> 46088 | C4: =Lookup!C4 -> 2023 | D4: =Lookup!D4 -> 45754000000 | E4: =Lookup!E4 -> 18520000000 | F4: =Lookup!F4 -> 27234000000 | G4: =Lookup!G4 -> 13972000000 | H4: =Lookup!H4 -> -1951000000 | ... X4: =Lookup!X4 -> 2.47 | Y4: =$Y$2 -> KO_INC-ST_YRLY.xlsx | Z4: =$Z$2 -> KO_INC-ST_YRLY-002 | AA4: =NOW() -> 46088.84
A5: =Lookup!A5 -> KO | B5: =Lookup!B5 -> 46088 | C5: =Lookup!C5 -> 2022 | D5: =Lookup!D5 -> 43004000000 | E5: =Lookup!E5 -> 18000000000 | F5: =Lookup!F5 -> 25004000000 | G5: =Lookup!G5 -> 12880000000 | H5: =Lookup!H5 -> -1215000000 | ... X5: =Lookup!X5 -> 2.19 | Y5: =$Y$2 -> KO_INC-ST_YRLY.xlsx | Z5: =$Z$2 -> KO_INC-ST_YRLY-002 | AA5: =NOW() -> 46088.84
A6: =Lookup!A6 -> KO | B6: =Lookup!B6 -> 46088 | C6: =Lookup!C6 -> 2021 | D6: =Lookup!D6 -> 38655000000 | E6: =Lookup!E6 -> 15357000000 | F6: =Lookup!F6 -> 23298000000 | G6: =Lookup!G6 -> 12144000000 | H6: =Lookup!H6 -> -846000000 | ... X6: =Lookup!X6 -> 2.25 | Y6: =$Y$2 -> KO_INC-ST_YRLY.xlsx | Z6: =$Z$2 -> KO_INC-ST_YRLY-002 | AA6: =NOW() -> 46088.84
A7: =Lookup!A7 -> KO | B7: =Lookup!B7 -> 46088 | C7: =Lookup!C7 -> 2020 | D7: =Lookup!D7 -> 33014000000 | E7: =Lookup!E7 -> 13433000000 | F7: =Lookup!F7 -> 19581000000 | G7: =Lookup!G7 -> 9731000000 | H7: =Lookup!H7 -> -853000000 | ... X7: =Lookup!X7 -> 1.79 | Y7: =$Y$2 -> KO_INC-ST_YRLY.xlsx | Z7: =$Z$2 -> KO_INC-ST_YRLY-002 | AA7: =NOW() -> 46088.84
A8: =Lookup!A8 -> KO | B8: =Lookup!B8 -> 46088 | C8: =Lookup!C8 -> 2019 | D8: =Lookup!D8 -> 37266000000 | E8: =Lookup!E8 -> 14619000000 | F8: =Lookup!F8 -> 22647000000 | G8: =Lookup!G8 -> 12103000000 | H8: =Lookup!H8 -> -458000000 | ... X8: =Lookup!X8 -> 2.07 | Y8: =$Y$2 -> KO_INC-ST_YRLY.xlsx | Z8: =$Z$2 -> KO_INC-ST_YRLY-002 | AA8: =NOW() -> 46088.84
A9: =Lookup!A9 -> KO | B9: =Lookup!B9 -> 46088 | C9: =Lookup!C9 -> 2018 | D9: =Lookup!D9 -> 34300000000 | E9: =Lookup!E9 -> 13067000000 | F9: =Lookup!F9 -> 21233000000 | G9: =Lookup!G9 -> 11002000000 | H9: =Lookup!H9 -> -1079000000 | ... X9: =Lookup!X9 -> 1.5 | Y9: =$Y$2 -> KO_INC-ST_YRLY.xlsx | Z9: =$Z$2 -> KO_INC-ST_YRLY-002 | AA9: =NOW() -> 46088.84
A10: =Lookup!A10 -> KO | B10: =Lookup!B10 -> 46088 | C10: =Lookup!C10 -> 2017 | D10: =Lookup!D10 -> 36212000000 | E10: =Lookup!E10 -> 13721000000 | F10: =Lookup!F10 -> 22491000000 | G10: =Lookup!G10 -> 12834000000 | H10: =Lookup!H10 -> -1902000000 | ... X10: =Lookup!X10 -> 0.29 | Y10: =$Y$2 -> KO_INC-ST_YRLY.xlsx | Z10: =$Z$2 -> KO_INC-ST_YRLY-002 | AA10: =NOW() -> 46088.84
A11: =Lookup!A11 -> KO | B11: =Lookup!B11 -> 46088 | C11: =Lookup!C11 -> 2016 | D11: =Lookup!D11 -> 41863000000 | E11: =Lookup!E11 -> 16465000000 | F11: =Lookup!F11 -> 25398000000 | G11: =Lookup!G11 -> 15370000000 | H11: =Lookup!H11 -> -1371000000 | ... X11: =Lookup!X11 -> 1.49 | Y11: =$Y$2 -> KO_INC-ST_YRLY.xlsx | Z11: =$Z$2 -> KO_INC-ST_YRLY-002 | AA11: =NOW() -> 46088.84
A12: =Lookup!A12 -> KO | B12: =Lookup!B12 -> 46088 | C12: =Lookup!C12 -> 2015 | D12: =Lookup!D12 -> 44294000000 | E12: =Lookup!E12 -> 17482000000 | F12: =Lookup!F12 -> 26812000000 | G12: =Lookup!G12 -> 16427000000 | H12: =Lookup!H12 -> -1657000000 | ... X12: =Lookup!X12 -> 1.67 | Y12: =$Y$2 -> KO_INC-ST_YRLY.xlsx | Z12: =$Z$2 -> KO_INC-ST_YRLY-002 | AA12: =NOW() -> 46088.84
A13: =Lookup!A13 -> KO | B13: =Lookup!B13 -> 46088 | C13: =Lookup!C13 -> 2014 | D13: =Lookup!D13 -> 45998000000 | E13: =Lookup!E13 -> 17889000000 | F13: =Lookup!F13 -> 28109000000 | G13: =Lookup!G13 -> 17218000000 | H13: =Lookup!H13 -> -1183000000 | ... X13: =Lookup!X13 -> 1.6 | Y13: =$Y$2 -> KO_INC-ST_YRLY.xlsx | Z13: =$Z$2 -> KO_INC-ST_YRLY-002 | AA13: =NOW() -> 46088.84
A14: =Lookup!A14 -> KO | B14: =Lookup!B14 -> 46088 | C14: =Lookup!C14 -> 2013 | D14: =Lookup!D14 -> 46854000000 | E14: =Lookup!E14 -> 18421000000 | F14: =Lookup!F14 -> 28433000000 | G14: =Lookup!G14 -> 17310000000 | H14: =Lookup!H14 -> -895000000 | ... X14: =Lookup!X14 -> 1.9 | Y14: =$Y$2 -> KO_INC-ST_YRLY.xlsx | Z14: =$Z$2 -> KO_INC-ST_YRLY-002 | AA14: =NOW() -> 46088.84
... A40: =Lookup!A40 -> KO | B40: =Lookup!B40 -> 46088 | C40: =Lookup!C40 -> 1987 | D40: =Lookup!D40 -> 7658341000 | E40: =Lookup!E40 -> 3633159000 | F40: =Lookup!F40 -> 4025182000 | G40: =Lookup!G40 -> 2701392000 | H40: =Lookup!H40 -> 0 | ... X40: =Lookup!X40 -> 0.1538 | Y40: =$Y$2 -> KO_INC-ST_YRLY.xlsx | Z40: =$Z$2 -> KO_INC-ST_YRLY-002 | AA40: =NOW() -> 46088.84
