Workbook

Sheet Raw
B1: =YEAR(B2) -> 2024 | C1: =YEAR(C2) -> 2023 | D1: =YEAR(D2) -> 2022 | E1: =YEAR(E2) -> 2021 | F1: =YEAR(F2) -> 2020 | G1: =YEAR(G2) -> 2019 | H1: =YEAR(H2) -> 2018 | I1: =YEAR(I2) -> 2017 | ... AN1: =YEAR(AN2) -> 1986
A2: Metric Name | B2: 45657 | C2: 45291 | D2: 44926 | E2: 44561 | F2: 44196 | G2: 43830 | H2: 43465 | I2: 43100 | J2: 42735 | K2: 42369 | L2: 42004 | M2: 41639 | N2: 41274 | O2: 40908 | P2: 40543 | Q2: 40178 | R2: 39813 | S2: 39447 | T2: 39082 | U2: 38717 | V2: 38352 | W2: 37986 | X2: 37621 | Y2: 37256 | Z2: 36891 | AA2: 36525 | AB2: 36160 | AC2: 35795 | AD2: 35430 | AE2: 35064 | AF2: 34699 | AG2: 34334 | AH2: 33969 | AI2: 33603 | AJ2: 33238 | AK2: 32873 | AL2: 32508 | AM2: 32142 | AN2: 31777
A4: Cash On Hand | B4: 14571 | C4: 13663 | D4: 11631 | E4: 12625 | F4: 10914 | G4: 11175 | H4: 16115 | I4: 20675 | J4: 22201 | K4: 19900 | L4: 21675 | M4: 20268 | N4: 16551 | O4: 14035 | P4: 11337 | Q4: 9213 | R4: 4979 | S4: 4308 | T4: 2590 | U4: 4767 | V4: 6768 | W4: 3482 | X4: 2345 | Y4: 1934 | Z4: 1892 | AA4: 1812 | AB4: 1807 | AC4: 1843 | AD4: 1658 | AE4: 1315 | AF4: 1531 | AG4: 1078 | AH4: 1062.988 | AI4: 1117.196 | AJ4: 1492.124 | AK4: 1181.691 | AL4: 1231.19 | AM4: 1489.106 | AN4: 868.6331
A5: Receivables | B5: 3569 | C5: 3410 | D5: 3487 | E5: 3512 | F5: 3144 | G5: 3971 | H5: 3685 | I5: 3667 | J5: 3856 | K5: 3941 | L5: 4466 | M5: 4873 | N5: 4759 | O5: 4920 | P5: 4430 | Q5: 3758 | R5: 3090 | S5: 3317 | T5: 2587 | U5: 2281 | V5: 2244 | W5: 2091 | X5: 2097 | Y5: 1882 | Z5: 1757 | AA5: 1798 | AB5: 1666 | AC5: 1639 | AD5: 1641 | AE5: 1695 | AF5: 1470 | AG5: 1210 | AH5: 1085.636 | AI5: 933.448 | AJ5: 913.541 | AK5: 820.428 | AL5: 627.248 | AM5: 672.16 | AN5: 672.568
A6: Inventory | B6: 4728 | C6: 4424 | D6: 4233 | E6: 3414 | F6: 3266 | G6: 3379 | H6: 3071 | I6: 2655 | J6: 2675 | K6: 2902 | L6: 3100 | M6: 3277 | N6: 3264 | O6: 3092 | P6: 2650 | Q6: 2354 | R6: 2187 | S6: 2220 | T6: 1641 | U6: 1379 | V6: 1420 | W6: 1252 | X6: 1294 | Y6: 1055 | Z6: 1066 | AA6: 1076 | AB6: 890 | AC6: 959 | AD6: 952 | AE6: 1117 | AF6: 1047 | AG6: 1049 | AH6: 1018.621 | AI6: 987.764 | AJ6: 982.313 | AK6: 789.077 | AL6: 778.816 | AM6: 776.74 | AN6: 695.437
A7: Pre-Paid Expenses | B7: 3129 | C7: 5235 | D7: 3240 | E7: 2994 | F7: 1916 | G7: 1886 | H7: 2059 | I7: 2000 | J7: 2481 | K7: 2752 | L7: 3066 | M7: 2886 | N7: 2781 | O7: 3450 | P7: 3162 | Q7: 2226 | R7: 1920 | S7: 2260 | T7: 1623 | U7: 1778 | V7: 1849 | W7: 1571 | X7: 1616 | Y7: 2300 | Z7: 1905
A8: Other Current Assets | I8: 219 | J8: 2797 | K8: 3900 | L8: 679 | N8: 2973 | AA8: 1794 | AB8: 2017 | AC8: 1528 | AD8: 1659 | AE8: 1323 | AF8: 1157 | AG8: 1097 | AH8: 1080.432 | AI8: 1069.664 | AJ8: 754.8 | AK8: 812.304 | AL8: 608.178 | AM8: 1219.037 | AN8: 837.512
A9: Total Current Assets | B9: 25997 | C9: 26732 | D9: 22591 | E9: 22545 | F9: 19240 | G9: 20411 | H9: 24930 | I9: 36545 | J9: 34010 | K9: 33395 | L9: 32986 | M9: 31304 | N9: 30328 | O9: 25497 | P9: 21579 | Q9: 17551 | R9: 12176 | S9: 12105 | T9: 8441 | U9: 10205 | V9: 12281 | W9: 8396 | X9: 7352 | Y9: 7171 | Z9: 6620 | AA9: 6480 | AB9: 6380 | AC9: 5969 | AD9: 5910 | AE9: 5450 | AF9: 5205 | AG9: 4434 | AH9: 4247.677 | AI9: 4144.244 | AJ9: 4142.778 | AK9: 3603.5 | AL9: 3245.432 | AM9: 4231.921 | AN9: 3169.268
A10: Property, Plant, And Equipment | B10: 10303 | C10: 9236 | D10: 9841 | E10: 9920 | F10: 10777 | G10: 10838 | H10: 9598 | I10: 8203 | J10: 10635 | K10: 12571 | L10: 14633 | M10: 14967 | N10: 14476 | O10: 14939 | P10: 14727 | Q10: 9561 | R10: 8326 | S10: 8493 | T10: 6903 | U10: 5831 | V10: 6091 | W10: 6097 | X10: 5911 | Y10: 4453 | Z10: 4168 | AA10: 4267 | AB10: 3669 | AC10: 3743 | AD10: 3550 | AE10: 4336 | AF10: 4080 | AG10: 3729 | AH10: 3526.261 | AI10: 2889.882 | AJ10: 2385.565 | AK10: 2021.219 | AL10: 1759.075 | AM10: 1601.528 | AN10: 1537.553
A11: Long-Term Investments | B11: 18087 | C11: 19671 | D11: 18765 | E11: 18416 | F11: 20085 | G11: 19879 | H11: 20279 | I11: 21952 | J11: 17249 | K11: 15788 | L11: 13625 | M11: 11512 | N11: 10448 | O11: 8374 | P11: 15096 | Q11: 8708 | R11: 5779 | S11: 7777 | T11: 6783 | U11: 6922 | V11: 6252 | W11: 5538 | X11: 4991 | Y11: 5422 | Z11: 8129 | AA11: 8916 | AB11: 8549 | AC11: 6044 | AD11: 5211 | AE11: 3960 | AF11: 3673 | AG11: 3083 | AH11: 2163.094 | AI11: 2154.015 | AJ11: 2024.622 | AK11: 1930.423 | AL11: 1911.973 | AM11: 2258.545 | AN11: 1096.442
A12: Goodwill And Intangible Assets | B12: 31440 | C12: 32707 | D12: 33631 | E12: 34613 | F12: 28550 | G12: 26766 | H12: 21587 | I12: 16636 | J12: 21128 | K12: 24132 | L12: 26372 | M12: 27611 | N12: 27337 | O12: 27669 | P12: 2.3652 | Q12: 10875 | R12: 12505 | S12: 12219 | T12: 5135 | U12: 3821 | V12: 3836 | W12: 3989 | X12: 3458 | Y12: 2579 | Z12: 1917 | AA12: 1960 | AB12: 547 | AC12: 727 | AD12: 753 | AE12: 944 | AF12: 660 | AG12: 549 | AH12: 383.304 | AI12: 303.681 | AJ12: 275.126 | AK12: 231.993 | AL12: 56.546 | AM12: 74.155 | AN12: 659.053
A13: Other Long-Term Assets | B13: 13403 | C13: 7796 | D13: 6189 | E13: 6731 | F13: 6184 | G13: 6075 | H13: 4148 | I13: 4230 | J13: 4248 | K13: 4110 | L13: 4407 | M13: 4661 | N13: 3585 | O13: 3495 | P13: 2121 | Q13: 1976 | R13: 1733 | S13: 2675 | T13: 2701 | U13: 2648 | V13: 2981 | W13: 3322 | X13: 2694 | Y13: 2792 | AC13: 457 | AD13: 737 | AE13: 351 | AF13: 255 | AG13: 226 | AH13: 731.598 | AI13: 730.606 | AJ13: 450.096 | AK13: 495.401 | AL13: 477.586 | AM13: 289 | AN13: 1114.803
A14: Total Long-Term Assets | B14: 74552 | C14: 70971 | D14: 70172 | E14: 71809 | F14: 68056 | G14: 65970 | H14: 58286 | I14: 51351 | J14: 53260 | K14: 56601 | L14: 59037 | M14: 58751 | N14: 55846 | O14: 54477 | P14: 31946.37 | Q14: 31120 | R14: 28343 | S14: 31164 | T14: 21522 | U14: 19222 | V14: 19160 | W14: 18946 | X14: 17054 | Y14: 15246 | Z14: 14214 | AA14: 15143 | AB14: 12765 | AC14: 10971 | AD14: 10251 | AE14: 9591 | AF14: 8668 | AG14: 7587 | AH14: 6804.257 | AI14: 6078.184 | AJ14: 5135.409 | AK14: 4679.036 | AL14: 4205.18 | AM14: 4223.228 | AN14: 4407.851
A15: Total Assets | B15: 100549 | C15: 97703 | D15: 92763 | E15: 94354 | F15: 87296 | G15: 86381 | H15: 83216 | I15: 87896 | J15: 87270 | K15: 89996 | L15: 92023 | M15: 90055 | N15: 86174 | O15: 79974 | P15: 72921 | Q15: 48671 | R15: 40519 | S15: 43269 | T15: 29963 | U15: 29427 | V15: 31441 | W15: 27342 | X15: 24406 | Y15: 22417 | Z15: 20834 | AA15: 21623 | AB15: 19145 | AC15: 16940 | AD15: 16161 | AE15: 15041 | AF15: 13873 | AG15: 12021 | AH15: 11051.93 | AI15: 10189.21 | AJ15: 9278.187 | AK15: 8282.536 | AL15: 7450.612 | AM15: 8605.546 | AN15: 7484.128
A17: Total Current Liabilities | B17: 25249 | C17: 23571 | D17: 19724 | E17: 19950 | F17: 14601 | G17: 26973 | H17: 28782 | I17: 27194 | J17: 26532 | K17: 26929 | L17: 32374 | M17: 27811 | N17: 27821 | O17: 24283 | P17: 18508 | Q17: 13721 | R17: 12988 | S17: 13225 | T17: 8890 | U17: 9836 | V17: 11133 | W17: 7886 | X17: 7341 | Y17: 8429 | Z17: 9321 | AA17: 9856 | AB17: 8640 | AC17: 7379 | AD17: 7406 | AE17: 7348 | AF17: 6177 | AG17: 5171 | AH17: 5303.222 | AI17: 4255.173 | AJ17: 4296.491 | AK17: 3657.93 | AL17: 2868.897 | AM17: 4083.379 | AN17: 2244.919
A18: Long Term Debt | B18: 42375 | C18: 35547 | D18: 36377 | E18: 38116 | F18: 40125 | G18: 27516 | H18: 25376 | I18: 31182 | J18: 29684 | K18: 28311 | L18: 19063 | M18: 19154 | N18: 14736 | O18: 13656 | P18: 3.1221 | Q18: 5059 | R18: 2781 | S18: 3277 | T18: 1314 | U18: 1154 | V18: 1157 | W18: 2517 | X18: 2701 | Y18: 1219 | Z18: 835 | AA18: 854 | AB18: 687 | AC18: 801 | AD18: 1116 | AE18: 1141 | AF18: 1426 | AG18: 1428 | AH18: 1120.064 | AI18: 985.258 | AJ18: 535.861 | AK18: 548.708 | AL18: 761.059 | AM18: 909.465 | AN18: 907.676
A19: Other Non-Current Liabilities | B19: 4084 | C19: 8466 | D19: 7922 | E19: 8607 | F19: 9453 | G19: 8510 | H19: 7646 | I19: 8021 | J19: 4081 | K19: 4301 | L19: 4389 | M19: 3498 | N19: 5468 | O19: 5420 | P19: 4794 | Q19: 2965 | R19: 3011 | S19: 3133 | T19: 2231 | U19: 1730 | V19: 2814 | W19: 2512 | X19: 2260 | Y19: 961 | Z19: 1004 | AA19: 902 | AB19: 991 | AC19: 1001 | AD19: 1182 | AE19: 966 | AF19: 855 | AG19: 725 | AH19: 658.631 | AI19: 493.765 | AJ19: 332.06 | AK19: 294.358 | AL19: 205.702 | AN19: 354.054
A20: Total Long Term Liabilities | B20: 48928 | C20: 46652 | D20: 47213 | E20: 49544 | F20: 51411 | G20: 38310 | H20: 35376 | I20: 41725 | J20: 37518 | K20: 37303 | L20: 29088 | M20: 28804 | N20: 25185 | O20: 23770 | P20: 9058.122 | Q20: 9604 | R20: 6669 | S20: 8300 | T20: 4153 | U20: 3236 | V20: 4373 | W20: 5366 | X20: 5265 | Y20: 2622 | Z20: 2197 | AA20: 2254 | AB20: 2102 | AC20: 2250 | AD20: 2599 | AE20: 2301 | AF20: 2461 | AG20: 2266 | AH20: 1860.324 | AI20: 1679.05 | AJ20: 1132.532 | AK20: 1139.121 | AL20: 1236.413 | AM20: 1119.345 | AN20: 2000.136
A21: Total Liabilities | B21: 74177 | C21: 70223 | D21: 66937 | E21: 69494 | F21: 66012 | G21: 65283 | H21: 64158 | I21: 68919 | J21: 64050 | K21: 64232 | L21: 61462 | M21: 56615 | N21: 53006 | O21: 48053 | P21: 41604 | Q21: 23325 | R21: 19657 | S21: 21525 | T21: 13043 | U21: 13072 | V21: 15506 | W21: 13252 | X21: 12606 | Y21: 11051 | Z21: 11518 | AA21: 12110 | AB21: 10742 | AC21: 9629 | AD21: 10005 | AE21: 9649 | AF21: 8638 | AG21: 7437 | AH21: 7163.546 | AI21: 5950.268 | AJ21: 5429.023 | AK21: 4797.051 | AL21: 4105.31 | AM21: 5418.372 | AN21: 3969.149
A23: Common Stock Net | B23: 1760 | C23: 1760 | D23: 1760 | E23: 1760 | F23: 1760 | G23: 1760 | H23: 1760 | I23: 1760 | J23: 1760 | K23: 1760 | L23: 1760 | M23: 1760 | N23: 1760 | O23: 1760 | P23: 880 | Q23: 880 | R23: 880 | S23: 880 | T23: 878 | U23: 877 | V23: 875 | W23: 874 | X23: 873 | Y23: 873 | Z23: 870 | AA23: 867 | AB23: 865 | AC23: 861 | AD23: 858 | AE23: 428 | AF23: 427 | AG23: 426 | AH23: 424.051 | AI23: 421.838 | AJ23: 420.244 | AK23: 418.91 | AL23: 417.395 | AM23: 415.977 | AN23: 414.492
A24: Retained Earnings (Accumulated Deficit) | B24: 76054 | C24: 73782 | D24: 71019 | E24: 69094 | F24: 66555 | G24: 65855 | H24: 63234 | I24: 60430 | J24: 65502 | K24: 65018 | L24: 63408 | M24: 61660 | N24: 58045 | O24: 53621 | P24: 49278 | Q24: 41537 | R24: 38513 | S24: 36235 | T24: 33468 | U24: 31299 | V24: 29105 | W24: 26687 | X24: 24506 | Y24: 23443 | Z24: 21265 | AA24: 20773 | AB24: 19922 | AC24: 17869 | AD24: 15127 | AE24: 12882 | AF24: 11006 | AG24: 9458 | AH24: 8165.024 | AI24: 7238.643 | AJ24: 6447.576 | AK24: 5618.312 | AL24: 4385.142 | AM24: 3783.625 | AN24: 3624.046
A25: Comprehensive Income | B25: -16843 | C25: -14275 | D25: -14895 | E25: -14330 | F25: -14601 | G25: -13544 | H25: -12814 | I25: -10305 | J25: -11205 | K25: -10174 | L25: -5777 | M25: -3432 | N25: -3385 | O25: -2774 | P25: -0.247 | Q25: -757 | R25: -2674 | S25: 626 | T25: -1291 | U25: -1669 | V25: -1348 | W25: -1995 | X25: -3047 | Y25: -2788 | Z25: -2722
A26: Other Share Holders Equity | AA26: -1551 | AB26: -1434 | AC26: -1364 | AD26: -567 | AE26: -410 | AF26: -298 | AG26: -505 | AH26: -370.842 | AI26: -119.818 | AJ26: -63.729 | AK26: -53.098 | AL26: -68.477 | AM26: -5.047 | AN26: -118.087
A27: Share Holder Equity | B27: 26372 | C27: 27480 | D27: 25826 | E27: 24860 | F27: 21284 | G27: 21098 | H27: 19058 | I27: 18977 | J27: 23220 | K27: 25764 | L27: 30561 | M27: 33440 | N27: 33168 | O27: 31921 | P27: 31317 | Q27: 25346 | R27: 20862 | S27: 21744 | T27: 16920 | U27: 16355 | V27: 15935 | W27: 14090 | X27: 11800 | Y27: 11366 | Z27: 9316 | AA27: 9513 | AB27: 8403 | AC27: 7311 | AD27: 6156 | AE27: 5392 | AF27: 5235 | AG27: 4584 | AH27: 3888.388 | AI27: 4238.947 | AJ27: 3849.164 | AK27: 3485.485 | AL27: 3345.302 | AM27: 3187.174 | AN27: 3514.979
A28: Total Liabilities And Share Holders Equity | B28: 100549 | C28: 97703 | D28: 92763 | E28: 94354 | F28: 87296 | G28: 86381 | H28: 83216 | I28: 87896 | J28: 87270 | K28: 89996 | L28: 92023 | M28: 90055 | N28: 86174 | O28: 79974 | P28: 72921 | Q28: 48671 | R28: 40519 | S28: 43269 | T28: 29963 | U28: 29427 | V28: 31441 | W28: 27342 | X28: 24406 | Y28: 22417 | Z28: 20834 | AA28: 21623 | AB28: 19145 | AC28: 16940 | AD28: 16161 | AE28: 15041 | AF28: 13873 | AG28: 12021 | AH28: 11051.93 | AI28: 10222.43 | AJ28: 9278.187 | AK28: 8282.536 | AL28: 7450.612 | AM28: 8355.56 | AN28: 8373.438

Sheet Lookup
A1: TICKER | B1: ASOF_DATE | C1: YR | D1: Cash On Hand | E1: Receivables | F1: Inventory | G1: Pre-Paid Expenses | H1: Other Current Assets | I1: Total Current Assets | J1: Property, Plant, And Equipment | K1: Long-Term Investments | L1: Goodwill And Intangible Assets | M1: Other Long-Term Assets | N1: Total Long-Term Assets | O1: Total Assets | P1: Total Current Liabilities | Q1: Long Term Debt | R1: Other Non-Current Liabilities | S1: Total Long Term Liabilities | T1: Total Liabilities | U1: Common Stock Net | V1: Retained Earnings (Accumulated Deficit) | W1: Comprehensive Income | X1: Other Share Holders Equity | Y1: Share Holder Equity | Z1: Total Liabilities And Share Holders Equity
A2: KO | B2: =TODAY() -> 46088 | C2: 2024 | D2: =INDEX(Raw!$B$4:$AN$28, MATCH(D$1, Raw!$A$4:$A$28, 0), MATCH($C2, Raw!$B$1:$AN$1, 0)) -> 14571 | E2: =INDEX(Raw!$B$4:$AN$28, MATCH(E$1, Raw!$A$4:$A$28, 0), MATCH($C2, Raw!$B$1:$AN$1, 0)) -> 3569 | F2: =INDEX(Raw!$B$4:$AN$28, MATCH(F$1, Raw!$A$4:$A$28, 0), MATCH($C2, Raw!$B$1:$AN$1, 0)) -> 4728 | G2: =INDEX(Raw!$B$4:$AN$28, MATCH(G$1, Raw!$A$4:$A$28, 0), MATCH($C2, Raw!$B$1:$AN$1, 0)) -> 3129 | H2: =INDEX(Raw!$B$4:$AN$28, MATCH(H$1, Raw!$A$4:$A$28, 0), MATCH($C2, Raw!$B$1:$AN$1, 0)) -> 0 | I2: =INDEX(Raw!$B$4:$AN$28, MATCH(I$1, Raw!$A$4:$A$28, 0), MATCH($C2, Raw!$B$1:$AN$1, 0)) -> 25997 | J2: =INDEX(Raw!$B$4:$AN$28, MATCH(J$1, Raw!$A$4:$A$28, 0), MATCH($C2, Raw!$B$1:$AN$1, 0)) -> 10303 | K2: =INDEX(Raw!$B$4:$AN$28, MATCH(K$1, Raw!$A$4:$A$28, 0), MATCH($C2, Raw!$B$1:$AN$1, 0)) -> 18087 | ... Z2: =INDEX(Raw!$B$4:$AN$28, MATCH(Z$1, Raw!$A$4:$A$28, 0), MATCH($C2, Raw!$B$1:$AN$1, 0)) -> 100549
A3: KO | B3: =TODAY() -> 46088 | C3: 2023 | D3: =INDEX(Raw!$B$4:$AN$28, MATCH(D$1, Raw!$A$4:$A$28, 0), MATCH($C3, Raw!$B$1:$AN$1, 0)) -> 13663 | E3: =INDEX(Raw!$B$4:$AN$28, MATCH(E$1, Raw!$A$4:$A$28, 0), MATCH($C3, Raw!$B$1:$AN$1, 0)) -> 3410 | F3: =INDEX(Raw!$B$4:$AN$28, MATCH(F$1, Raw!$A$4:$A$28, 0), MATCH($C3, Raw!$B$1:$AN$1, 0)) -> 4424 | G3: =INDEX(Raw!$B$4:$AN$28, MATCH(G$1, Raw!$A$4:$A$28, 0), MATCH($C3, Raw!$B$1:$AN$1, 0)) -> 5235 | H3: =INDEX(Raw!$B$4:$AN$28, MATCH(H$1, Raw!$A$4:$A$28, 0), MATCH($C3, Raw!$B$1:$AN$1, 0)) -> 0 | I3: =INDEX(Raw!$B$4:$AN$28, MATCH(I$1, Raw!$A$4:$A$28, 0), MATCH($C3, Raw!$B$1:$AN$1, 0)) -> 26732 | J3: =INDEX(Raw!$B$4:$AN$28, MATCH(J$1, Raw!$A$4:$A$28, 0), MATCH($C3, Raw!$B$1:$AN$1, 0)) -> 9236 | K3: =INDEX(Raw!$B$4:$AN$28, MATCH(K$1, Raw!$A$4:$A$28, 0), MATCH($C3, Raw!$B$1:$AN$1, 0)) -> 19671 | ... Z3: =INDEX(Raw!$B$4:$AN$28, MATCH(Z$1, Raw!$A$4:$A$28, 0), MATCH($C3, Raw!$B$1:$AN$1, 0)) -> 97703
A4: KO | B4: =TODAY() -> 46088 | C4: 2022 | D4: =INDEX(Raw!$B$4:$AN$28, MATCH(D$1, Raw!$A$4:$A$28, 0), MATCH($C4, Raw!$B$1:$AN$1, 0)) -> 11631 | E4: =INDEX(Raw!$B$4:$AN$28, MATCH(E$1, Raw!$A$4:$A$28, 0), MATCH($C4, Raw!$B$1:$AN$1, 0)) -> 3487 | F4: =INDEX(Raw!$B$4:$AN$28, MATCH(F$1, Raw!$A$4:$A$28, 0), MATCH($C4, Raw!$B$1:$AN$1, 0)) -> 4233 | G4: =INDEX(Raw!$B$4:$AN$28, MATCH(G$1, Raw!$A$4:$A$28, 0), MATCH($C4, Raw!$B$1:$AN$1, 0)) -> 3240 | H4: =INDEX(Raw!$B$4:$AN$28, MATCH(H$1, Raw!$A$4:$A$28, 0), MATCH($C4, Raw!$B$1:$AN$1, 0)) -> 0 | I4: =INDEX(Raw!$B$4:$AN$28, MATCH(I$1, Raw!$A$4:$A$28, 0), MATCH($C4, Raw!$B$1:$AN$1, 0)) -> 22591 | J4: =INDEX(Raw!$B$4:$AN$28, MATCH(J$1, Raw!$A$4:$A$28, 0), MATCH($C4, Raw!$B$1:$AN$1, 0)) -> 9841 | K4: =INDEX(Raw!$B$4:$AN$28, MATCH(K$1, Raw!$A$4:$A$28, 0), MATCH($C4, Raw!$B$1:$AN$1, 0)) -> 18765 | ... Z4: =INDEX(Raw!$B$4:$AN$28, MATCH(Z$1, Raw!$A$4:$A$28, 0), MATCH($C4, Raw!$B$1:$AN$1, 0)) -> 92763
A5: KO | B5: =TODAY() -> 46088 | C5: 2021 | D5: =INDEX(Raw!$B$4:$AN$28, MATCH(D$1, Raw!$A$4:$A$28, 0), MATCH($C5, Raw!$B$1:$AN$1, 0)) -> 12625 | E5: =INDEX(Raw!$B$4:$AN$28, MATCH(E$1, Raw!$A$4:$A$28, 0), MATCH($C5, Raw!$B$1:$AN$1, 0)) -> 3512 | F5: =INDEX(Raw!$B$4:$AN$28, MATCH(F$1, Raw!$A$4:$A$28, 0), MATCH($C5, Raw!$B$1:$AN$1, 0)) -> 3414 | G5: =INDEX(Raw!$B$4:$AN$28, MATCH(G$1, Raw!$A$4:$A$28, 0), MATCH($C5, Raw!$B$1:$AN$1, 0)) -> 2994 | H5: =INDEX(Raw!$B$4:$AN$28, MATCH(H$1, Raw!$A$4:$A$28, 0), MATCH($C5, Raw!$B$1:$AN$1, 0)) -> 0 | I5: =INDEX(Raw!$B$4:$AN$28, MATCH(I$1, Raw!$A$4:$A$28, 0), MATCH($C5, Raw!$B$1:$AN$1, 0)) -> 22545 | J5: =INDEX(Raw!$B$4:$AN$28, MATCH(J$1, Raw!$A$4:$A$28, 0), MATCH($C5, Raw!$B$1:$AN$1, 0)) -> 9920 | K5: =INDEX(Raw!$B$4:$AN$28, MATCH(K$1, Raw!$A$4:$A$28, 0), MATCH($C5, Raw!$B$1:$AN$1, 0)) -> 18416 | ... Z5: =INDEX(Raw!$B$4:$AN$28, MATCH(Z$1, Raw!$A$4:$A$28, 0), MATCH($C5, Raw!$B$1:$AN$1, 0)) -> 94354
A6: KO | B6: =TODAY() -> 46088 | C6: 2020 | D6: =INDEX(Raw!$B$4:$AN$28, MATCH(D$1, Raw!$A$4:$A$28, 0), MATCH($C6, Raw!$B$1:$AN$1, 0)) -> 10914 | E6: =INDEX(Raw!$B$4:$AN$28, MATCH(E$1, Raw!$A$4:$A$28, 0), MATCH($C6, Raw!$B$1:$AN$1, 0)) -> 3144 | F6: =INDEX(Raw!$B$4:$AN$28, MATCH(F$1, Raw!$A$4:$A$28, 0), MATCH($C6, Raw!$B$1:$AN$1, 0)) -> 3266 | G6: =INDEX(Raw!$B$4:$AN$28, MATCH(G$1, Raw!$A$4:$A$28, 0), MATCH($C6, Raw!$B$1:$AN$1, 0)) -> 1916 | H6: =INDEX(Raw!$B$4:$AN$28, MATCH(H$1, Raw!$A$4:$A$28, 0), MATCH($C6, Raw!$B$1:$AN$1, 0)) -> 0 | I6: =INDEX(Raw!$B$4:$AN$28, MATCH(I$1, Raw!$A$4:$A$28, 0), MATCH($C6, Raw!$B$1:$AN$1, 0)) -> 19240 | J6: =INDEX(Raw!$B$4:$AN$28, MATCH(J$1, Raw!$A$4:$A$28, 0), MATCH($C6, Raw!$B$1:$AN$1, 0)) -> 10777 | K6: =INDEX(Raw!$B$4:$AN$28, MATCH(K$1, Raw!$A$4:$A$28, 0), MATCH($C6, Raw!$B$1:$AN$1, 0)) -> 20085 | ... Z6: =INDEX(Raw!$B$4:$AN$28, MATCH(Z$1, Raw!$A$4:$A$28, 0), MATCH($C6, Raw!$B$1:$AN$1, 0)) -> 87296
A7: KO | B7: =TODAY() -> 46088 | C7: 2019 | D7: =INDEX(Raw!$B$4:$AN$28, MATCH(D$1, Raw!$A$4:$A$28, 0), MATCH($C7, Raw!$B$1:$AN$1, 0)) -> 11175 | E7: =INDEX(Raw!$B$4:$AN$28, MATCH(E$1, Raw!$A$4:$A$28, 0), MATCH($C7, Raw!$B$1:$AN$1, 0)) -> 3971 | F7: =INDEX(Raw!$B$4:$AN$28, MATCH(F$1, Raw!$A$4:$A$28, 0), MATCH($C7, Raw!$B$1:$AN$1, 0)) -> 3379 | G7: =INDEX(Raw!$B$4:$AN$28, MATCH(G$1, Raw!$A$4:$A$28, 0), MATCH($C7, Raw!$B$1:$AN$1, 0)) -> 1886 | H7: =INDEX(Raw!$B$4:$AN$28, MATCH(H$1, Raw!$A$4:$A$28, 0), MATCH($C7, Raw!$B$1:$AN$1, 0)) -> 0 | I7: =INDEX(Raw!$B$4:$AN$28, MATCH(I$1, Raw!$A$4:$A$28, 0), MATCH($C7, Raw!$B$1:$AN$1, 0)) -> 20411 | J7: =INDEX(Raw!$B$4:$AN$28, MATCH(J$1, Raw!$A$4:$A$28, 0), MATCH($C7, Raw!$B$1:$AN$1, 0)) -> 10838 | K7: =INDEX(Raw!$B$4:$AN$28, MATCH(K$1, Raw!$A$4:$A$28, 0), MATCH($C7, Raw!$B$1:$AN$1, 0)) -> 19879 | ... Z7: =INDEX(Raw!$B$4:$AN$28, MATCH(Z$1, Raw!$A$4:$A$28, 0), MATCH($C7, Raw!$B$1:$AN$1, 0)) -> 86381
A8: KO | B8: =TODAY() -> 46088 | C8: 2018 | D8: =INDEX(Raw!$B$4:$AN$28, MATCH(D$1, Raw!$A$4:$A$28, 0), MATCH($C8, Raw!$B$1:$AN$1, 0)) -> 16115 | E8: =INDEX(Raw!$B$4:$AN$28, MATCH(E$1, Raw!$A$4:$A$28, 0), MATCH($C8, Raw!$B$1:$AN$1, 0)) -> 3685 | F8: =INDEX(Raw!$B$4:$AN$28, MATCH(F$1, Raw!$A$4:$A$28, 0), MATCH($C8, Raw!$B$1:$AN$1, 0)) -> 3071 | G8: =INDEX(Raw!$B$4:$AN$28, MATCH(G$1, Raw!$A$4:$A$28, 0), MATCH($C8, Raw!$B$1:$AN$1, 0)) -> 2059 | H8: =INDEX(Raw!$B$4:$AN$28, MATCH(H$1, Raw!$A$4:$A$28, 0), MATCH($C8, Raw!$B$1:$AN$1, 0)) -> 0 | I8: =INDEX(Raw!$B$4:$AN$28, MATCH(I$1, Raw!$A$4:$A$28, 0), MATCH($C8, Raw!$B$1:$AN$1, 0)) -> 24930 | J8: =INDEX(Raw!$B$4:$AN$28, MATCH(J$1, Raw!$A$4:$A$28, 0), MATCH($C8, Raw!$B$1:$AN$1, 0)) -> 9598 | K8: =INDEX(Raw!$B$4:$AN$28, MATCH(K$1, Raw!$A$4:$A$28, 0), MATCH($C8, Raw!$B$1:$AN$1, 0)) -> 20279 | ... Z8: =INDEX(Raw!$B$4:$AN$28, MATCH(Z$1, Raw!$A$4:$A$28, 0), MATCH($C8, Raw!$B$1:$AN$1, 0)) -> 83216
A9: KO | B9: =TODAY() -> 46088 | C9: 2017 | D9: =INDEX(Raw!$B$4:$AN$28, MATCH(D$1, Raw!$A$4:$A$28, 0), MATCH($C9, Raw!$B$1:$AN$1, 0)) -> 20675 | E9: =INDEX(Raw!$B$4:$AN$28, MATCH(E$1, Raw!$A$4:$A$28, 0), MATCH($C9, Raw!$B$1:$AN$1, 0)) -> 3667 | F9: =INDEX(Raw!$B$4:$AN$28, MATCH(F$1, Raw!$A$4:$A$28, 0), MATCH($C9, Raw!$B$1:$AN$1, 0)) -> 2655 | G9: =INDEX(Raw!$B$4:$AN$28, MATCH(G$1, Raw!$A$4:$A$28, 0), MATCH($C9, Raw!$B$1:$AN$1, 0)) -> 2000 | H9: =INDEX(Raw!$B$4:$AN$28, MATCH(H$1, Raw!$A$4:$A$28, 0), MATCH($C9, Raw!$B$1:$AN$1, 0)) -> 219 | I9: =INDEX(Raw!$B$4:$AN$28, MATCH(I$1, Raw!$A$4:$A$28, 0), MATCH($C9, Raw!$B$1:$AN$1, 0)) -> 36545 | J9: =INDEX(Raw!$B$4:$AN$28, MATCH(J$1, Raw!$A$4:$A$28, 0), MATCH($C9, Raw!$B$1:$AN$1, 0)) -> 8203 | K9: =INDEX(Raw!$B$4:$AN$28, MATCH(K$1, Raw!$A$4:$A$28, 0), MATCH($C9, Raw!$B$1:$AN$1, 0)) -> 21952 | ... Z9: =INDEX(Raw!$B$4:$AN$28, MATCH(Z$1, Raw!$A$4:$A$28, 0), MATCH($C9, Raw!$B$1:$AN$1, 0)) -> 87896
A10: KO | B10: =TODAY() -> 46088 | C10: 2016 | D10: =INDEX(Raw!$B$4:$AN$28, MATCH(D$1, Raw!$A$4:$A$28, 0), MATCH($C10, Raw!$B$1:$AN$1, 0)) -> 22201 | E10: =INDEX(Raw!$B$4:$AN$28, MATCH(E$1, Raw!$A$4:$A$28, 0), MATCH($C10, Raw!$B$1:$AN$1, 0)) -> 3856 | F10: =INDEX(Raw!$B$4:$AN$28, MATCH(F$1, Raw!$A$4:$A$28, 0), MATCH($C10, Raw!$B$1:$AN$1, 0)) -> 2675 | G10: =INDEX(Raw!$B$4:$AN$28, MATCH(G$1, Raw!$A$4:$A$28, 0), MATCH($C10, Raw!$B$1:$AN$1, 0)) -> 2481 | H10: =INDEX(Raw!$B$4:$AN$28, MATCH(H$1, Raw!$A$4:$A$28, 0), MATCH($C10, Raw!$B$1:$AN$1, 0)) -> 2797 | I10: =INDEX(Raw!$B$4:$AN$28, MATCH(I$1, Raw!$A$4:$A$28, 0), MATCH($C10, Raw!$B$1:$AN$1, 0)) -> 34010 | J10: =INDEX(Raw!$B$4:$AN$28, MATCH(J$1, Raw!$A$4:$A$28, 0), MATCH($C10, Raw!$B$1:$AN$1, 0)) -> 10635 | K10: =INDEX(Raw!$B$4:$AN$28, MATCH(K$1, Raw!$A$4:$A$28, 0), MATCH($C10, Raw!$B$1:$AN$1, 0)) -> 17249 | ... Z10: =INDEX(Raw!$B$4:$AN$28, MATCH(Z$1, Raw!$A$4:$A$28, 0), MATCH($C10, Raw!$B$1:$AN$1, 0)) -> 87270
A11: KO | B11: =TODAY() -> 46088 | C11: 2015 | D11: =INDEX(Raw!$B$4:$AN$28, MATCH(D$1, Raw!$A$4:$A$28, 0), MATCH($C11, Raw!$B$1:$AN$1, 0)) -> 19900 | E11: =INDEX(Raw!$B$4:$AN$28, MATCH(E$1, Raw!$A$4:$A$28, 0), MATCH($C11, Raw!$B$1:$AN$1, 0)) -> 3941 | F11: =INDEX(Raw!$B$4:$AN$28, MATCH(F$1, Raw!$A$4:$A$28, 0), MATCH($C11, Raw!$B$1:$AN$1, 0)) -> 2902 | G11: =INDEX(Raw!$B$4:$AN$28, MATCH(G$1, Raw!$A$4:$A$28, 0), MATCH($C11, Raw!$B$1:$AN$1, 0)) -> 2752 | H11: =INDEX(Raw!$B$4:$AN$28, MATCH(H$1, Raw!$A$4:$A$28, 0), MATCH($C11, Raw!$B$1:$AN$1, 0)) -> 3900 | I11: =INDEX(Raw!$B$4:$AN$28, MATCH(I$1, Raw!$A$4:$A$28, 0), MATCH($C11, Raw!$B$1:$AN$1, 0)) -> 33395 | J11: =INDEX(Raw!$B$4:$AN$28, MATCH(J$1, Raw!$A$4:$A$28, 0), MATCH($C11, Raw!$B$1:$AN$1, 0)) -> 12571 | K11: =INDEX(Raw!$B$4:$AN$28, MATCH(K$1, Raw!$A$4:$A$28, 0), MATCH($C11, Raw!$B$1:$AN$1, 0)) -> 15788 | ... Z11: =INDEX(Raw!$B$4:$AN$28, MATCH(Z$1, Raw!$A$4:$A$28, 0), MATCH($C11, Raw!$B$1:$AN$1, 0)) -> 89996
A12: KO | B12: =TODAY() -> 46088 | C12: 2014 | D12: =INDEX(Raw!$B$4:$AN$28, MATCH(D$1, Raw!$A$4:$A$28, 0), MATCH($C12, Raw!$B$1:$AN$1, 0)) -> 21675 | E12: =INDEX(Raw!$B$4:$AN$28, MATCH(E$1, Raw!$A$4:$A$28, 0), MATCH($C12, Raw!$B$1:$AN$1, 0)) -> 4466 | F12: =INDEX(Raw!$B$4:$AN$28, MATCH(F$1, Raw!$A$4:$A$28, 0), MATCH($C12, Raw!$B$1:$AN$1, 0)) -> 3100 | G12: =INDEX(Raw!$B$4:$AN$28, MATCH(G$1, Raw!$A$4:$A$28, 0), MATCH($C12, Raw!$B$1:$AN$1, 0)) -> 3066 | H12: =INDEX(Raw!$B$4:$AN$28, MATCH(H$1, Raw!$A$4:$A$28, 0), MATCH($C12, Raw!$B$1:$AN$1, 0)) -> 679 | I12: =INDEX(Raw!$B$4:$AN$28, MATCH(I$1, Raw!$A$4:$A$28, 0), MATCH($C12, Raw!$B$1:$AN$1, 0)) -> 32986 | J12: =INDEX(Raw!$B$4:$AN$28, MATCH(J$1, Raw!$A$4:$A$28, 0), MATCH($C12, Raw!$B$1:$AN$1, 0)) -> 14633 | K12: =INDEX(Raw!$B$4:$AN$28, MATCH(K$1, Raw!$A$4:$A$28, 0), MATCH($C12, Raw!$B$1:$AN$1, 0)) -> 13625 | ... Z12: =INDEX(Raw!$B$4:$AN$28, MATCH(Z$1, Raw!$A$4:$A$28, 0), MATCH($C12, Raw!$B$1:$AN$1, 0)) -> 92023
A13: KO | B13: =TODAY() -> 46088 | C13: 2013 | D13: =INDEX(Raw!$B$4:$AN$28, MATCH(D$1, Raw!$A$4:$A$28, 0), MATCH($C13, Raw!$B$1:$AN$1, 0)) -> 20268 | E13: =INDEX(Raw!$B$4:$AN$28, MATCH(E$1, Raw!$A$4:$A$28, 0), MATCH($C13, Raw!$B$1:$AN$1, 0)) -> 4873 | F13: =INDEX(Raw!$B$4:$AN$28, MATCH(F$1, Raw!$A$4:$A$28, 0), MATCH($C13, Raw!$B$1:$AN$1, 0)) -> 3277 | G13: =INDEX(Raw!$B$4:$AN$28, MATCH(G$1, Raw!$A$4:$A$28, 0), MATCH($C13, Raw!$B$1:$AN$1, 0)) -> 2886 | H13: =INDEX(Raw!$B$4:$AN$28, MATCH(H$1, Raw!$A$4:$A$28, 0), MATCH($C13, Raw!$B$1:$AN$1, 0)) -> 0 | I13: =INDEX(Raw!$B$4:$AN$28, MATCH(I$1, Raw!$A$4:$A$28, 0), MATCH($C13, Raw!$B$1:$AN$1, 0)) -> 31304 | J13: =INDEX(Raw!$B$4:$AN$28, MATCH(J$1, Raw!$A$4:$A$28, 0), MATCH($C13, Raw!$B$1:$AN$1, 0)) -> 14967 | K13: =INDEX(Raw!$B$4:$AN$28, MATCH(K$1, Raw!$A$4:$A$28, 0), MATCH($C13, Raw!$B$1:$AN$1, 0)) -> 11512 | ... Z13: =INDEX(Raw!$B$4:$AN$28, MATCH(Z$1, Raw!$A$4:$A$28, 0), MATCH($C13, Raw!$B$1:$AN$1, 0)) -> 90055
... A40: KO | B40: =TODAY() -> 46088 | C40: 1986 | D40: =INDEX(Raw!$B$4:$AN$28, MATCH(D$1, Raw!$A$4:$A$28, 0), MATCH($C40, Raw!$B$1:$AN$1, 0)) -> 868.6331 | E40: =INDEX(Raw!$B$4:$AN$28, MATCH(E$1, Raw!$A$4:$A$28, 0), MATCH($C40, Raw!$B$1:$AN$1, 0)) -> 672.568 | F40: =INDEX(Raw!$B$4:$AN$28, MATCH(F$1, Raw!$A$4:$A$28, 0), MATCH($C40, Raw!$B$1:$AN$1, 0)) -> 695.437 | G40: =INDEX(Raw!$B$4:$AN$28, MATCH(G$1, Raw!$A$4:$A$28, 0), MATCH($C40, Raw!$B$1:$AN$1, 0)) -> 0 | H40: =INDEX(Raw!$B$4:$AN$28, MATCH(H$1, Raw!$A$4:$A$28, 0), MATCH($C40, Raw!$B$1:$AN$1, 0)) -> 837.512 | I40: =INDEX(Raw!$B$4:$AN$28, MATCH(I$1, Raw!$A$4:$A$28, 0), MATCH($C40, Raw!$B$1:$AN$1, 0)) -> 3169.268 | J40: =INDEX(Raw!$B$4:$AN$28, MATCH(J$1, Raw!$A$4:$A$28, 0), MATCH($C40, Raw!$B$1:$AN$1, 0)) -> 1537.553 | K40: =INDEX(Raw!$B$4:$AN$28, MATCH(K$1, Raw!$A$4:$A$28, 0), MATCH($C40, Raw!$B$1:$AN$1, 0)) -> 1096.442 | ... Z40: =INDEX(Raw!$B$4:$AN$28, MATCH(Z$1, Raw!$A$4:$A$28, 0), MATCH($C40, Raw!$B$1:$AN$1, 0)) -> 8373.438

Sheet Export
A1: TICKER | B1: ASOF_DATE | C1: YR | D1: CASH | E1: RECEIVABLES | F1: INVENTORY | G1: PREPAID | H1: OTHER_CURRENT_ASSETS | I1: TOTAL_CURRENT_ASSETS | J1: PPE | K1: LONG_TERM_INVESTMENTS | L1: GOODWILL_INTANGIBLE_ASSETS | M1: OTHER_LONG_TERM_ASSETS | N1: TOTAL_LONG_TERM_ASSETS | O1: TOTAL_ASSETS | P1: TOTAL_CURRENT_LIABILITIES | Q1: LONG_TERM_DEBT | R1: OTHER_NONCURRENT_LIABILITIES | S1: TOTAL_LONG_TERM_LIABILITIES | T1: TOTAL_LIABILITIES | U1: NET_COMMON_STOCK | V1: RETAINED_EARNINGS | W1: COMPREHENSIVE_INCOME | X1: OTHER_SHAREHOLDERS_EQUITY | Y1: SHAREHOLDER_EQUITY | Z1: TOTAL_LIABILITIES_AND_SHAREHOLDERS_EQUITY | AA1: SOURCE_FILE | AB1: LOAD_BATCH_ID | AC1: LOADED_AT
A2: =Lookup!A2 -> KO | B2: =Lookup!B2 -> 46088 | C2: =Lookup!C2 -> 2024 | D2: =Lookup!D2 -> 14571 | E2: =Lookup!E2 -> 3569 | F2: =Lookup!F2 -> 4728 | G2: =Lookup!G2 -> 3129 | H2: =Lookup!H2 -> 0 | ... Z2: =Lookup!Z2 -> 100549 | AA2: {=MID(CELL("filename",D1),FIND("[",CELL("filename",D1))+1,FIND("]",CELL("filename",D1))-FIND("[",CELL("filename",D1))-1)} -> KO_BAL-SH_YR.xlsx | AB2: =_xlfn.CONCAT(LEFT(AA2,12),"-002") -> KO_BAL-SH_YR-002 | AC2: =NOW() -> 46088.852
A3: =Lookup!A3 -> KO | B3: =Lookup!B3 -> 46088 | C3: =Lookup!C3 -> 2023 | D3: =Lookup!D3 -> 13663 | E3: =Lookup!E3 -> 3410 | F3: =Lookup!F3 -> 4424 | G3: =Lookup!G3 -> 5235 | H3: =Lookup!H3 -> 0 | ... Z3: =Lookup!Z3 -> 97703 | AA3: {=MID(CELL("filename",D2),FIND("[",CELL("filename",D2))+1,FIND("]",CELL("filename",D2))-FIND("[",CELL("filename",D2))-1)} -> KO_BAL-SH_YR.xlsx | AB3: =_xlfn.CONCAT(LEFT(AA3,12),"-002") -> KO_BAL-SH_YR-002 | AC3: =NOW() -> 46088.852
A4: =Lookup!A4 -> KO | B4: =Lookup!B4 -> 46088 | C4: =Lookup!C4 -> 2022 | D4: =Lookup!D4 -> 11631 | E4: =Lookup!E4 -> 3487 | F4: =Lookup!F4 -> 4233 | G4: =Lookup!G4 -> 3240 | H4: =Lookup!H4 -> 0 | ... Z4: =Lookup!Z4 -> 92763 | AA4: {=MID(CELL("filename",D3),FIND("[",CELL("filename",D3))+1,FIND("]",CELL("filename",D3))-FIND("[",CELL("filename",D3))-1)} -> KO_BAL-SH_YR.xlsx | AB4: =_xlfn.CONCAT(LEFT(AA4,12),"-002") -> KO_BAL-SH_YR-002 | AC4: =NOW() -> 46088.852
A5: =Lookup!A5 -> KO | B5: =Lookup!B5 -> 46088 | C5: =Lookup!C5 -> 2021 | D5: =Lookup!D5 -> 12625 | E5: =Lookup!E5 -> 3512 | F5: =Lookup!F5 -> 3414 | G5: =Lookup!G5 -> 2994 | H5: =Lookup!H5 -> 0 | ... Z5: =Lookup!Z5 -> 94354 | AA5: {=MID(CELL("filename",D4),FIND("[",CELL("filename",D4))+1,FIND("]",CELL("filename",D4))-FIND("[",CELL("filename",D4))-1)} -> KO_BAL-SH_YR.xlsx | AB5: =_xlfn.CONCAT(LEFT(AA5,12),"-002") -> KO_BAL-SH_YR-002 | AC5: =NOW() -> 46088.852
A6: =Lookup!A6 -> KO | B6: =Lookup!B6 -> 46088 | C6: =Lookup!C6 -> 2020 | D6: =Lookup!D6 -> 10914 | E6: =Lookup!E6 -> 3144 | F6: =Lookup!F6 -> 3266 | G6: =Lookup!G6 -> 1916 | H6: =Lookup!H6 -> 0 | ... Z6: =Lookup!Z6 -> 87296 | AA6: {=MID(CELL("filename",D5),FIND("[",CELL("filename",D5))+1,FIND("]",CELL("filename",D5))-FIND("[",CELL("filename",D5))-1)} -> KO_BAL-SH_YR.xlsx | AB6: =_xlfn.CONCAT(LEFT(AA6,12),"-002") -> KO_BAL-SH_YR-002 | AC6: =NOW() -> 46088.852
A7: =Lookup!A7 -> KO | B7: =Lookup!B7 -> 46088 | C7: =Lookup!C7 -> 2019 | D7: =Lookup!D7 -> 11175 | E7: =Lookup!E7 -> 3971 | F7: =Lookup!F7 -> 3379 | G7: =Lookup!G7 -> 1886 | H7: =Lookup!H7 -> 0 | ... Z7: =Lookup!Z7 -> 86381 | AA7: {=MID(CELL("filename",D6),FIND("[",CELL("filename",D6))+1,FIND("]",CELL("filename",D6))-FIND("[",CELL("filename",D6))-1)} -> KO_BAL-SH_YR.xlsx | AB7: =_xlfn.CONCAT(LEFT(AA7,12),"-002") -> KO_BAL-SH_YR-002 | AC7: =NOW() -> 46088.852
A8: =Lookup!A8 -> KO | B8: =Lookup!B8 -> 46088 | C8: =Lookup!C8 -> 2018 | D8: =Lookup!D8 -> 16115 | E8: =Lookup!E8 -> 3685 | F8: =Lookup!F8 -> 3071 | G8: =Lookup!G8 -> 2059 | H8: =Lookup!H8 -> 0 | ... Z8: =Lookup!Z8 -> 83216 | AA8: {=MID(CELL("filename",D7),FIND("[",CELL("filename",D7))+1,FIND("]",CELL("filename",D7))-FIND("[",CELL("filename",D7))-1)} -> KO_BAL-SH_YR.xlsx | AB8: =_xlfn.CONCAT(LEFT(AA8,12),"-002") -> KO_BAL-SH_YR-002 | AC8: =NOW() -> 46088.852
A9: =Lookup!A9 -> KO | B9: =Lookup!B9 -> 46088 | C9: =Lookup!C9 -> 2017 | D9: =Lookup!D9 -> 20675 | E9: =Lookup!E9 -> 3667 | F9: =Lookup!F9 -> 2655 | G9: =Lookup!G9 -> 2000 | H9: =Lookup!H9 -> 219 | ... Z9: =Lookup!Z9 -> 87896 | AA9: {=MID(CELL("filename",D8),FIND("[",CELL("filename",D8))+1,FIND("]",CELL("filename",D8))-FIND("[",CELL("filename",D8))-1)} -> KO_BAL-SH_YR.xlsx | AB9: =_xlfn.CONCAT(LEFT(AA9,12),"-002") -> KO_BAL-SH_YR-002 | AC9: =NOW() -> 46088.852
A10: =Lookup!A10 -> KO | B10: =Lookup!B10 -> 46088 | C10: =Lookup!C10 -> 2016 | D10: =Lookup!D10 -> 22201 | E10: =Lookup!E10 -> 3856 | F10: =Lookup!F10 -> 2675 | G10: =Lookup!G10 -> 2481 | H10: =Lookup!H10 -> 2797 | ... Z10: =Lookup!Z10 -> 87270 | AA10: {=MID(CELL("filename",D9),FIND("[",CELL("filename",D9))+1,FIND("]",CELL("filename",D9))-FIND("[",CELL("filename",D9))-1)} -> KO_BAL-SH_YR.xlsx | AB10: =_xlfn.CONCAT(LEFT(AA10,12),"-002") -> KO_BAL-SH_YR-002 | AC10: =NOW() -> 46088.852
A11: =Lookup!A11 -> KO | B11: =Lookup!B11 -> 46088 | C11: =Lookup!C11 -> 2015 | D11: =Lookup!D11 -> 19900 | E11: =Lookup!E11 -> 3941 | F11: =Lookup!F11 -> 2902 | G11: =Lookup!G11 -> 2752 | H11: =Lookup!H11 -> 3900 | ... Z11: =Lookup!Z11 -> 89996 | AA11: {=MID(CELL("filename",D10),FIND("[",CELL("filename",D10))+1,FIND("]",CELL("filename",D10))-FIND("[",CELL("filename",D10))-1)} -> KO_BAL-SH_YR.xlsx | AB11: =_xlfn.CONCAT(LEFT(AA11,12),"-002") -> KO_BAL-SH_YR-002 | AC11: =NOW() -> 46088.852
A12: =Lookup!A12 -> KO | B12: =Lookup!B12 -> 46088 | C12: =Lookup!C12 -> 2014 | D12: =Lookup!D12 -> 21675 | E12: =Lookup!E12 -> 4466 | F12: =Lookup!F12 -> 3100 | G12: =Lookup!G12 -> 3066 | H12: =Lookup!H12 -> 679 | ... Z12: =Lookup!Z12 -> 92023 | AA12: {=MID(CELL("filename",D11),FIND("[",CELL("filename",D11))+1,FIND("]",CELL("filename",D11))-FIND("[",CELL("filename",D11))-1)} -> KO_BAL-SH_YR.xlsx | AB12: =_xlfn.CONCAT(LEFT(AA12,12),"-002") -> KO_BAL-SH_YR-002 | AC12: =NOW() -> 46088.852
A13: =Lookup!A13 -> KO | B13: =Lookup!B13 -> 46088 | C13: =Lookup!C13 -> 2013 | D13: =Lookup!D13 -> 20268 | E13: =Lookup!E13 -> 4873 | F13: =Lookup!F13 -> 3277 | G13: =Lookup!G13 -> 2886 | H13: =Lookup!H13 -> 0 | ... Z13: =Lookup!Z13 -> 90055 | AA13: {=MID(CELL("filename",D12),FIND("[",CELL("filename",D12))+1,FIND("]",CELL("filename",D12))-FIND("[",CELL("filename",D12))-1)} -> KO_BAL-SH_YR.xlsx | AB13: =_xlfn.CONCAT(LEFT(AA13,12),"-002") -> KO_BAL-SH_YR-002 | AC13: =NOW() -> 46088.852
... A40: =Lookup!A40 -> KO | B40: =Lookup!B40 -> 46088 | C40: =Lookup!C40 -> 1986 | D40: =Lookup!D40 -> 868.6331 | E40: =Lookup!E40 -> 672.568 | F40: =Lookup!F40 -> 695.437 | G40: =Lookup!G40 -> 0 | H40: =Lookup!H40 -> 837.512 | ... Z40: =Lookup!Z40 -> 8373.438 | AA40: {=MID(CELL("filename",D39),FIND("[",CELL("filename",D39))+1,FIND("]",CELL("filename",D39))-FIND("[",CELL("filename",D39))-1)} -> KO_BAL-SH_YR.xlsx | AB40: =_xlfn.CONCAT(LEFT(AA40,12),"-002") -> KO_BAL-SH_YR-002 | AC40: =NOW() -> 46088.852
