Workbook

Sheet Raw
B1: Q4 | C1: Q3 | D1: Q2 | E1: Q1 | F1: Q4 | G1: Q3 | H1: Q2 | I1: Q1 | J1: Q4 | K1: Q3 | L1: Q2 | M1: Q1 | N1: Q4 | O1: Q3 | P1: Q2 | Q1: Q1 | R1: Q4 | S1: Q3 | T1: Q2 | U1: Q1 | V1: Q4 | W1: Q3 | X1: Q2 | Y1: Q1 | Z1: Q4 | AA1: Q3 | AB1: Q2 | AC1: Q1 | AD1: Q4 | AE1: Q3 | AF1: Q2 | AG1: Q1 | AH1: Q4 | AI1: Q3 | AJ1: Q2 | AK1: Q1 | AL1: Q4 | AM1: Q3 | AN1: Q2 | AO1: Q1 | AP1: Q4 | AQ1: Q3 | AR1: Q2 | AS1: Q1 | AT1: Q4 | AU1: Q3 | AV1: Q2 | AW1: Q1 | AX1: Q4 | AY1: Q3 | AZ1: Q2 | BA1: Q1 | BB1: Q4 | BC1: Q3 | BD1: Q2 | BE1: Q1 | BF1: Q4 | BG1: Q3 | BH1: Q2 | BI1: Q1 | BJ1: Q4 | BK1: Q3 | BL1: Q2 | BM1: Q1 | BN1: Q4 | BO1: Q3 | BP1: Q2 | BQ1: Q1 | BR1: Q4 | BS1: Q3 | BT1: Q2 | BU1: Q1 | BV1: Q4 | BW1: Q3 | BX1: Q2 | BY1: Q1 | BZ1: Q4 | CA1: Q3 | CB1: Q2 | CC1: Q1 | CD1: Q4 | CE1: Q3 | CF1: Q2 | CG1: Q1 | CH1: Q4 | CI1: Q3 | CJ1: Q2 | CK1: Q1 | CL1: Q4 | CM1: Q3 | CN1: Q2 | CO1: Q1 | CP1: Q4 | CQ1: Q3 | CR1: Q2 | CS1: Q1 | CT1: Q4 | CU1: Q3 | CV1: Q2 | CW1: Q1 | CX1: Q4 | CY1: Q3 | CZ1: Q2 | DA1: Q1 | DB1: Q4 | DC1: Q3 | DD1: Q2 | DE1: Q1 | DF1: Q4 | DG1: Q3 | DH1: Q2 | DI1: Q1 | DJ1: Q4 | DK1: Q3 | DL1: Q2 | DM1: Q1 | DN1: Q4 | DO1: Q3 | DP1: Q2 | DQ1: Q1 | DR1: Q4 | DS1: Q3 | DT1: Q2 | DU1: Q1 | DV1: Q4 | DW1: Q3 | DX1: Q2 | DY1: Q1 | DZ1: Q4 | EA1: Q3 | EB1: Q2 | EC1: Q1 | ED1: Q4 | EE1: Q3 | EF1: Q2 | EG1: Q1 | EH1: Q4 | EI1: Q3 | EJ1: Q2 | EK1: Q1 | EL1: Q4 | EM1: Q3 | EN1: Q2 | EO1: Q1 | EP1: Q4 | EQ1: Q3 | ER1: Q2 | ES1: Q1 | ET1: Q4 | EU1: Q3 | EV1: Q2 | EW1: Q1 | EX1: Q4 | EY1: Q3 | EZ1: Q2 | FA1: Q1 | FB1: Q4
B2: 2025 | C2: 2025 | D2: 2025 | E2: 2025 | F2: 2024 | G2: 2024 | H2: 2024 | I2: 2024 | J2: 2023 | K2: 2023 | L2: 2023 | M2: 2023 | N2: 2022 | O2: 2022 | P2: 2022 | Q2: 2022 | R2: 2021 | S2: 2021 | T2: 2021 | U2: 2021 | V2: 2020 | W2: 2020 | X2: 2020 | Y2: 2020 | Z2: 2019 | AA2: 2019 | AB2: 2019 | AC2: 2019 | AD2: 2018 | AE2: 2018 | AF2: 2018 | AG2: 2018 | AH2: 2017 | AI2: 2017 | AJ2: 2017 | AK2: 2017 | AL2: 2016 | AM2: 2016 | AN2: 2016 | AO2: 2016 | AP2: 2015 | AQ2: 2015 | AR2: 2015 | AS2: 2015 | AT2: 2014 | AU2: 2014 | AV2: 2014 | AW2: 2014 | AX2: 2013 | AY2: 2013 | AZ2: 2013 | BA2: 2013 | BB2: 2012 | BC2: 2012 | BD2: 2012 | BE2: 2012 | BF2: 2011 | BG2: 2011 | BH2: 2011 | BI2: 2011 | BJ2: 2010 | BK2: 2010 | BL2: 2010 | BM2: 2010 | BN2: 2009 | BO2: 2009 | BP2: 2009 | BQ2: 2009 | BR2: 2008 | BS2: 2008 | BT2: 2008 | BU2: 2008 | BV2: 2007 | BW2: 2007 | BX2: 2007 | BY2: 2007 | BZ2: 2006 | CA2: 2006 | CB2: 2006 | CC2: 2006 | CD2: 2005 | CE2: 2005 | CF2: 2005 | CG2: 2005 | CH2: 2004 | CI2: 2004 | CJ2: 2004 | CK2: 2004 | CL2: 2003 | CM2: 2003 | CN2: 2003 | CO2: 2003 | CP2: 2002 | CQ2: 2002 | CR2: 2002 | CS2: 2002 | CT2: 2001 | CU2: 2001 | CV2: 2001 | CW2: 2001 | CX2: 2000 | CY2: 2000 | CZ2: 2000 | DA2: 2000 | DB2: 1999 | DC2: 1999 | DD2: 1999 | DE2: 1999 | DF2: 1998 | DG2: 1998 | DH2: 1998 | DI2: 1998 | DJ2: 1997 | DK2: 1997 | DL2: 1997 | DM2: 1997 | DN2: 1996 | DO2: 1996 | DP2: 1996 | DQ2: 1996 | DR2: 1995 | DS2: 1995 | DT2: 1995 | DU2: 1995 | DV2: 1994 | DW2: 1994 | DX2: 1994 | DY2: 1994 | DZ2: 1993 | EA2: 1993 | EB2: 1993 | EC2: 1993 | ED2: 1992 | EE2: 1992 | EF2: 1992 | EG2: 1992 | EH2: 1991 | EI2: 1991 | EJ2: 1991 | EK2: 1991 | EL2: 1990 | EM2: 1990 | EN2: 1990 | EO2: 1990 | EP2: 1989 | EQ2: 1989 | ER2: 1989 | ES2: 1989 | ET2: 1988 | EU2: 1988 | EV2: 1988 | EW2: 1988 | EX2: 1987 | EY2: 1987 | EZ2: 1987 | FA2: 1987 | FB2: 1986
B3: 46022 | C3: 45930 | D3: 45838 | E3: 45747 | F3: 45657 | G3: 45565 | H3: 45473 | I3: 45382 | J3: 45291 | K3: 45199 | L3: 45107 | M3: 45016 | N3: 44926 | O3: 44834 | P3: 44742 | Q3: 44651 | R3: 44561 | S3: 44469 | T3: 44377 | U3: 44286 | V3: 44196 | W3: 44104 | X3: 44012 | Y3: 43921 | Z3: 43830 | AA3: 43738 | AB3: 43646 | AC3: 43555 | AD3: 43465 | AE3: 43373 | AF3: 43281 | AG3: 43190 | AH3: 43100 | AI3: 43008 | AJ3: 42916 | AK3: 42825 | AL3: 42735 | AM3: 42643 | AN3: 42551 | AO3: 42460 | AP3: 42369 | AQ3: 42277 | AR3: 42185 | AS3: 42094 | AT3: 42004 | AU3: 41912 | AV3: 41820 | AW3: 41729 | AX3: 41639 | AY3: 41547 | AZ3: 41455 | BA3: 41364 | BB3: 41274 | BC3: 41182 | BD3: 41090 | BE3: 40999 | BF3: 40908 | BG3: 40816 | BH3: 40724 | BI3: 40633 | BJ3: 40543 | BK3: 40451 | BL3: 40359 | BM3: 40268 | BN3: 40178 | BO3: 40086 | BP3: 39994 | BQ3: 39903 | BR3: 39813 | BS3: 39721 | BT3: 39629 | BU3: 39538 | BV3: 39447 | BW3: 39355 | BX3: 39263 | BY3: 39172 | BZ3: 39082 | CA3: 38990 | CB3: 38898 | CC3: 38807 | CD3: 38717 | CE3: 38625 | CF3: 38533 | CG3: 38442 | CH3: 38352 | CI3: 38260 | CJ3: 38168 | CK3: 38077 | CL3: 37986 | CM3: 37894 | CN3: 37802 | CO3: 37711 | CP3: 37621 | CQ3: 37529 | CR3: 37437 | CS3: 37346 | CT3: 37256 | CU3: 37164 | CV3: 37072 | CW3: 36981 | CX3: 36891 | CY3: 36799 | CZ3: 36707 | DA3: 36616 | DB3: 36525 | DC3: 36433 | DD3: 36341 | DE3: 36250 | DF3: 36160 | DG3: 36068 | DH3: 35976 | DI3: 35885 | DJ3: 35795 | DK3: 35703 | DL3: 35611 | DM3: 35520 | DN3: 35430 | DO3: 35338 | DP3: 35246 | DQ3: 35155 | DR3: 35064 | DS3: 34972 | DT3: 34880 | DU3: 34789 | DV3: 34699 | DW3: 34607 | DX3: 34515 | DY3: 34424 | DZ3: 34334 | EA3: 34242 | EB3: 34150 | EC3: 34059 | ED3: 33969 | EE3: 33877 | EF3: 33785 | EG3: 33694 | EH3: 33603 | EI3: 33511 | EJ3: 33419 | EK3: 33328 | EL3: 33238 | EM3: 33146 | EN3: 33054 | EO3: 32963 | EP3: 32873 | EQ3: 32781 | ER3: 32689 | ES3: 32598 | ET3: 32508 | EU3: 32416 | EV3: 32324 | EW3: 32233 | EX3: 32142 | EY3: 32050 | EZ3: 31958 | FA3: 31867 | FB3: 31777
A5: Revenue | B5: 11822000000 | C5: 12455000000 | D5: 12535000000 | E5: 11129000000 | F5: 11544000000 | G5: 11854000000 | H5: 12363000000 | I5: 11300000000 | J5: 10849000000 | K5: 11953000000 | L5: 11972000000 | M5: 10980000000 | N5: 10125000000 | O5: 11063000000 | P5: 11325000000 | Q5: 10491000000 | R5: 9464000000 | S5: 10042000000 | T5: 10129000000 | U5: 9020000000 | V5: 8611000000 | W5: 8652000000 | X5: 7150000000 | Y5: 8601000000 | Z5: 9068000000 | AA5: 9507000000 | AB5: 9997000000 | AC5: 8694000000 | AD5: 8478000000 | AE5: 8775000000 | AF5: 9421000000 | AG5: 7626000000 | AH5: 8314000000 | AI5: 9078000000 | AJ5: 9702000000 | AK5: 9118000000 | AL5: 9409000000 | AM5: 10633000000 | AN5: 11539000000 | AO5: 10282000000 | AP5: 10000000000 | AQ5: 11427000000 | AR5: 12156000000 | AS5: 10711000000 | AT5: 10872000000 | AU5: 11976000000 | AV5: 12574000000 | AW5: 10576000000 | AX5: 11040000000 | AY5: 12030000000 | AZ5: 12749000000 | BA5: 11035000000 | BB5: 11455000000 | BC5: 12340000000 | BD5: 13085000000 | BE5: 11137000000 | BF5: 11040000000 | BG5: 12248000000 | BH5: 12737000000 | BI5: 10517000000 | BJ5: 10494000000 | BK5: 8426000000 | BL5: 8674000000 | BM5: 7525000000 | BN5: 7510000000 | BO5: 8044000000 | BP5: 8267000000 | BQ5: 7169000000 | BR5: 7126000000 | BS5: 8393000000 | BT5: 9046000000 | BU5: 7379000000 | BV5: 7331000000 | BW5: 7690000000 | BX5: 7733000000 | BY5: 6103000000 | BZ5: 5932000000 | CA5: 6454000000 | CB5: 6476000000 | CC5: 5226000000 | CD5: 5551000000 | CE5: 6037000000 | CF5: 6310000000 | CG5: 5206000000 | CH5: 5154000000 | CI5: 5596000000 | CJ5: 5914000000 | CK5: 5078000000 | CL5: 4989000000 | CM5: 5671000000 | CN5: 5695000000 | CO5: 4502000000 | CP5: 4795000000 | CQ5: 5322000000 | CR5: 5368000000 | CS5: 4079000000 | CT5: 4238000000 | CU5: 4695000000 | CV5: 4653000000 | CW5: 3959000000 | CX5: 4903000000 | CY5: 5413000000 | CZ5: 5487000000 | DA5: 4256000000 | DB5: 4931000000 | DC5: 5195000000 | DD5: 5379000000 | DE5: 4428000000 | DF5: 4458000000 | DG5: 4747000000 | DH5: 5151000000 | DI5: 4457000000 | DJ5: 4701000000 | DK5: 4954000000 | DL5: 5075000000 | DM5: 4138000000 | DN5: 4476000000 | DO5: 4687000000 | DP5: 5286000000 | DQ5: 4194000000 | DR5: 4333000000 | DS5: 4895000000 | DT5: 4936000000 | DU5: 3854000000 | DV5: 4017000000 | DW5: 4461000000 | DX5: 4342000000 | DY5: 3352000000 | DZ5: 3373000000 | EA5: 3629000000 | EB5: 3899000000 | EC5: 3056000000 | ED5: 3244091000 | EE5: 3507503000 | EF5: 3550373000 | EG5: 2772000000 | EH5: 2879001000 | EI5: 3172116000 | EJ5: 3039523000 | EK5: 2480974000 | EL5: 2556009000 | EM5: 2792754000 | EN5: 2739308000 | EO5: 2148278000 | EP5: 2248912000 | EQ5: 2302564000 | ER5: 2429122000 | ES5: 1985188000 | ET5: 2026829000 | EU5: 2.12832e+09 | EV5: 2313632000 | EW5: 1869050000 | EX5: 843924000 | EY5: 2483126000 | EZ5: 2435169000 | FA5: 1896122000
A6: Cost Of Goods Sold | B6: 4723000000 | C6: 4797000000 | D6: 4714000000 | E6: 4163000000 | F6: 4613000000 | G6: 4664000000 | H6: 4812000000 | I6: 4235000000 | J6: 4634000000 | K6: 4657000000 | L6: 4912000000 | M6: 4317000000 | N6: 4513000000 | O6: 4566000000 | P6: 4830000000 | Q6: 4091000000 | R6: 4088000000 | S6: 3977000000 | T6: 3787000000 | U6: 3505000000 | V6: 3578000000 | W6: 3471000000 | X6: 3013000000 | Y6: 3371000000 | Z6: 3566000000 | AA6: 3767000000 | AB6: 3921000000 | AC6: 3365000000 | AD6: 3440000000 | AE6: 3346000000 | AF6: 3543000000 | AG6: 2738000000 | AH6: 3155000000 | AI6: 3394000000 | AJ6: 3659000000 | AK6: 3513000000 | AL6: 3794000000 | AM6: 4131000000 | AN6: 4471000000 | AO6: 4069000000 | AP6: 4054000000 | AQ6: 4577000000 | AR6: 4748000000 | AS6: 4103000000 | AT6: 4357000000 | AU6: 4630000000 | AV6: 4819000000 | AW6: 4083000000 | AX6: 4315000000 | AY6: 4793000000 | AZ6: 4989000000 | BA6: 4324000000 | BB6: 4628000000 | BC6: 4853000000 | BD6: 5224000000 | BE6: 4348000000 | BF6: 4403000000 | BG6: 4875000000 | BH6: 4989000000 | BI6: 3948000000 | BJ6: 4279000000 | BK6: 2918000000 | BL6: 2955000000 | BM6: 2541000000 | BN6: 2651000000 | BO6: 2934000000 | BP6: 2913000000 | BQ6: 2590000000 | BR6: 2568000000 | BS6: 3020000000 | BT6: 3162000000 | BU6: 2624000000 | BV6: 2641000000 | BW6: 2884000000 | BX6: 2736000000 | BY6: 2145000000 | BZ6: 2063000000 | CA6: 2265000000 | CB6: 2110000000 | CC6: 1726000000 | CD6: 1996000000 | CE6: 2235000000 | CF6: 2146000000 | CG6: 1818000000 | CH6: 1821000000 | CI6: 2061000000 | CJ6: 2039000000 | CK6: 1753000000 | CL6: 1864000000 | CM6: 2168000000 | CN6: 2127000000 | CO6: 1617000000 | CP6: 1701000000 | CQ6: 2083000000 | CR6: 1927000000 | CS6: 1394000000 | CT6: 1428000000 | CU6: 1692000000 | CV6: 1579000000 | CW6: 1345000000 | CX6: 1393000000 | CY6: 1736000000 | CZ6: 1677000000 | DA6: 1398000000 | DB6: 1336000000 | DC6: 1706000000 | DD6: 1636000000 | DE6: 1331000000 | DF6: 1299000000 | DG6: 1446000000 | DH6: 1499000000 | DI6: 1318000000 | DJ6: 1452000000 | DK6: 1659000000 | DL6: 1609000000 | DM6: 1295000000 | DN6: 1488000000 | DO6: 1814000000 | DP6: 1906000000 | DQ6: 1530000000 | DR6: 1670000000 | DS6: 1949000000 | DT6: 1876000000 | DU6: 1445000000 | DV6: 1498000000 | DW6: 1760000000 | DX6: 1667000000 | DY6: 1242000000 | DZ6: 1260000000 | EA6: 1343000000 | EB6: 1464000000 | EC6: 1093000000 | ED6: 1263951000 | EE6: 1385344000 | EF6: 1373563000 | EG6: 1031519000 | EH6: 1191322000 | EI6: 1307256000 | EJ6: 1185758000 | EK6: 964049000 | EL6: 1075213000 | EM6: 1167285000 | EN6: 1099885000 | EO6: 866467000 | EP6: 1017185000 | EQ6: 995928000 | ER6: 1046412000 | ES6: 832544000 | ET6: 912758000 | EU6: 906477000 | EV6: 1020974000 | EW6: 861263000 | EX6: 191775000 | EY6: 1251933000 | EZ6: 1221200000 | FA6: 968251000
A7: Gross Profit | B7: 7099000000 | C7: 7658000000 | D7: 7821000000 | E7: 6966000000 | F7: 6931000000 | G7: 7190000000 | H7: 7551000000 | I7: 7065000000 | J7: 6215000000 | K7: 7296000000 | L7: 7060000000 | M7: 6663000000 | N7: 5612000000 | O7: 6497000000 | P7: 6495000000 | Q7: 6400000000 | R7: 5376000000 | S7: 6065000000 | T7: 6342000000 | U7: 5515000000 | V7: 5033000000 | W7: 5181000000 | X7: 4137000000 | Y7: 5230000000 | Z7: 5502000000 | AA7: 5740000000 | AB7: 6076000000 | AC7: 5329000000 | AD7: 5038000000 | AE7: 5429000000 | AF7: 5878000000 | AG7: 4888000000 | AH7: 5159000000 | AI7: 5684000000 | AJ7: 6043000000 | AK7: 5605000000 | AL7: 5615000000 | AM7: 6502000000 | AN7: 7068000000 | AO7: 6213000000 | AP7: 5946000000 | AQ7: 6850000000 | AR7: 7408000000 | AS7: 6608000000 | AT7: 6515000000 | AU7: 7346000000 | AV7: 7755000000 | AW7: 6493000000 | AX7: 6725000000 | AY7: 7237000000 | AZ7: 7760000000 | BA7: 6711000000 | BB7: 6827000000 | BC7: 7487000000 | BD7: 7861000000 | BE7: 6789000000 | BF7: 6637000000 | BG7: 7373000000 | BH7: 7748000000 | BI7: 6569000000 | BJ7: 6215000000 | BK7: 5508000000 | BL7: 5719000000 | BM7: 4984000000 | BN7: 4859000000 | BO7: 5110000000 | BP7: 5354000000 | BQ7: 4579000000 | BR7: 4558000000 | BS7: 5373000000 | BT7: 5884000000 | BU7: 4755000000 | BV7: 4690000000 | BW7: 4806000000 | BX7: 4997000000 | BY7: 3958000000 | BZ7: 3869000000 | CA7: 4189000000 | CB7: 4366000000 | CC7: 3500000000 | CD7: 3555000000 | CE7: 3802000000 | CF7: 4164000000 | CG7: 3388000000 | CH7: 3333000000 | CI7: 3535000000 | CJ7: 3875000000 | CK7: 3325000000 | CL7: 3125000000 | CM7: 3503000000 | CN7: 3568000000 | CO7: 2885000000 | CP7: 3094000000 | CQ7: 3239000000 | CR7: 3441000000 | CS7: 2685000000 | CT7: 2810000000 | CU7: 3003000000 | CV7: 3074000000 | CW7: 2614000000 | CX7: 3510000000 | CY7: 3677000000 | CZ7: 3810000000 | DA7: 2858000000 | DB7: 3595000000 | DC7: 3489000000 | DD7: 3743000000 | DE7: 3097000000 | DF7: 3159000000 | DG7: 3301000000 | DH7: 3652000000 | DI7: 3139000000 | DJ7: 3249000000 | DK7: 3295000000 | DL7: 3466000000 | DM7: 2843000000 | DN7: 2988000000 | DO7: 2873000000 | DP7: 3380000000 | DQ7: 2664000000 | DR7: 2663000000 | DS7: 2946000000 | DT7: 3060000000 | DU7: 2409000000 | DV7: 2519000000 | DW7: 2701000000 | DX7: 2675000000 | DY7: 2110000000 | DZ7: 2113000000 | EA7: 2286000000 | EB7: 2435000000 | EC7: 1963000000 | ED7: 1980140000 | EE7: 2122159000 | EF7: 2176810000 | EG7: 1740481000 | EH7: 1687679000 | EI7: 1864860000 | EJ7: 1853765000 | EK7: 1516925000 | EL7: 1480796000 | EM7: 1625469000 | EN7: 1639423000 | EO7: 1281811000 | EP7: 1231727000 | EQ7: 1306636000 | ER7: 1382710000 | ES7: 1152644000 | ET7: 1114071000 | EU7: 1221843000 | EV7: 1292658000 | EW7: 1007787000 | EX7: 652149000 | EY7: 1231193000 | EZ7: 1213969000 | FA7: 927871000
A9: Research And Development Expenses
A10: SG&A Expenses | B10: 4199000000 | C10: 3618000000 | D10: 3470000000 | E10: 3234000000 | F10: 4046000000 | G10: 3636000000 | H10: 3549000000 | I10: 3351000000 | J10: 3799000000 | K10: 3667000000 | L10: 3321000000 | M10: 3185000000 | N10: 3431000000 | O10: 3279000000 | P10: 3203000000 | Q10: 2967000000 | R10: 3336000000 | S10: 3122000000 | T10: 3017000000 | U10: 2669000000 | V10: 2589000000 | W10: 2511000000 | X10: 1983000000 | Y10: 2648000000 | Z10: 3224000000 | AA10: 3116000000 | AB10: 2996000000 | AC10: 2767000000 | AD10: 2914000000 | AE10: 2660000000 | AF10: 2887000000 | AG10: 2541000000 | AH10: 3057000000 | AI10: 3245000000 | AJ10: 3180000000 | AK10: 3352000000 | AL10: 3688000000 | AM10: 4009000000 | AN10: 3912000000 | AO10: 3761000000 | AP10: 3937000000 | AQ10: 4207000000 | AR10: 4204000000 | AS10: 4079000000 | AT10: 4338000000 | AU10: 4507000000 | AV10: 4384000000 | AW10: 3989000000 | AX10: 4319000000 | AY10: 4424000000 | AZ10: 4385000000 | BA10: 4182000000 | BB10: 4430000000 | BC10: 4630000000 | BD10: 4497000000 | BE10: 4181000000 | BF10: 4406000000 | BG10: 4523000000 | BH10: 4417000000 | BI10: 4076000000 | BJ10: 4547000000 | BK10: 3064000000 | BL10: 2878000000 | BM10: 2705000000 | BN10: 2978000000 | BO10: 2912000000 | BP10: 2844000000 | BQ10: 2624000000 | BR10: 2744000000 | BS10: 3139000000 | BT10: 3095000000 | BU10: 2796000000 | BV10: 3039000000 | BW10: 2896000000 | BX10: 2685000000 | BY10: 2325000000 | BZ10: 2587000000 | CA10: 2488000000 | CB10: 2296000000 | CC10: 2060000000 | CD10: 2293000000 | CE10: 2225000000 | CF10: 2192000000 | CG10: 2029000000 | CH10: 1986000000 | CI10: 2046000000 | CJ10: 1984000000 | CK10: 1874000000 | CL10: 1744000000 | CM10: 1997000000 | CN10: 1896000000 | CO10: 1650000000 | CP10: 1804000000 | CQ10: 1789000000 | CR10: 1881000000 | CS10: 1527000000 | CT10: 1562000000 | CU10: 1692000000 | CV10: 1561000000 | CW10: 1334000000 | CX10: 3351000000 | CY10: 2256000000 | CZ10: 2334000000 | DA10: 1938000000 | DB10: 3118000000 | DC10: 2390000000 | DD10: 2353000000 | DE10: 1953000000 | DF10: 2222000000 | DG10: 2064000000 | DH10: 2141000000 | DI10: 1857000000 | DJ10: 2076000000 | DK10: 2052000000 | DL10: 2023000000 | DM10: 1701000000 | DN10: 1909000000 | DO10: 2388000000 | DP10: 1965000000 | DQ10: 1631000000 | DR10: 1714000000 | DS10: 1940000000 | DT10: 1802000000 | DU10: 1530000000 | DV10: 1653000000 | DW10: 1701000000 | DX10: 1605000000 | DY10: 1338000000 | DZ10: 1476000000 | EA10: 1457000000 | EB10: 1476000000 | EC10: 1286000000 | ED10: 1396917000 | EE10: 1351203000 | EF10: 1340276000 | EG10: 1160996000 | EH10: 1200601000 | EI10: 1220156000 | EJ10: 1160498000 | EK10: 1022929000 | EL10: 1059328000 | EM10: 1113039000 | EN10: 1059741000 | EO10: 843828000 | EP10: 849972000 | EQ10: 848336000 | ER10: 883935000 | ES10: 765689000 | ET10: 773356000 | EU10: 790416000 | EV10: 827201000 | EW10: 647085000 | EX10: 469902000 | EY10: 837039000 | EZ10: 790695000 | FA10: 603756000
A11: Other Operating Income Or Expenses | B11: -1059000000 | C11: -58000000 | D11: -71000000 | E11: -73000000 | F11: -176000000 | G11: -1044000000 | H11: -1370000000 | I11: -1573000000 | J11: -143000000 | K11: -359000000 | L11: -1338000000 | M11: -111000000 | N11: -106000000 | O11: -130000000 | P11: -951000000 | Q11: -28000000 | R11: -368000000 | S11: -45000000 | T11: -309000000 | U11: -124000000 | V11: -106000000 | W11: -372000000 | X11: -173000000 | Y11: -202000000 | Z11: -114000000 | AA11: -125000000 | AB11: -92000000 | AC11: -127000000 | AD11: -163000000 | AE11: -155000000 | AF11: -225000000 | AG11: -536000000 | AH11: -592000000 | AI11: -194000000 | AJ11: -826000000 | AK11: -290000000 | AL11: -541000000 | AM11: -222000000 | AN11: -297000000 | AO11: -311000000 | AP11: -491000000 | AQ11: -264000000 | AR11: -669000000 | AS11: -233000000 | AT11: -726000000 | AU11: -128000000 | AV11: -201000000 | AW11: -128000000 | AX11: -301000000 | AY11: -341000000 | AZ11: -132000000 | BA11: -121000000 | BB11: -214000000 | BC11: -64000000 | BD11: -70000000 | BE11: -99000000 | BF11: -275000000 | BG11: -96000000 | BH11: -152000000 | BI11: -209000000 | BJ11: -545000000 | BK11: -100000000 | BL11: -78000000 | BM11: -96000000 | BN11: -101000000 | BO11: -48000000 | BP11: -72000000 | BQ11: -92000000 | BR11: -108000000 | BS11: -47000000 | BT11: -110000000 | BU11: -85000000 | BV11: -125000000 | BW11: -81000000 | BX11: -42000000 | BY11: -6000000 | BZ11: -70000000 | CA11: -39000000 | CB11: -31000000 | CC11: -45000000 | CD11: 0 | CE11: -85000000 | CF11: 0 | CG11: 0 | CH11: 0 | CI11: -392000000 | CJ11: -88000000 | CK11: 0 | CL11: -289000000 | CM11: -55000000 | CN11: -70000000 | CO11: -159000000 | CP11: 0 | CQ11: 0 | CR11: 0 | CS11: 0 | CT11: 0 | CU11: 0 | CV11: 0 | CW11: 0 | CX11: -478000000 | CY11: -94000000 | CZ11: -191000000 | DA11: -680000000 | DB11: 0 | DC11: 0 | DD11: 0 | DE11: 0 | DF11: 0 | DG11: 0 | DH11: 0 | DI11: 0 | DJ11: 0 | DK11: 0 | DL11: 0 | DM11: 0 | DN11: 0 | DO11: 0 | DP11: 0 | DQ11: 0 | DR11: 0 | DS11: 0 | DT11: 0 | DU11: 0 | DV11: 0 | DW11: 0 | DX11: 0 | DY11: 0 | DZ11: 0 | EA11: 0 | EB11: 0 | EC11: 0 | ED11: 0 | EE11: 0 | EF11: 0 | EG11: 0 | EH11: 0 | EI11: 0 | EJ11: 0 | EK11: 0 | EL11: 0 | EM11: 0 | EN11: 0 | EO11: 0 | EP11: 0 | EQ11: 0 | ER11: 0 | ES11: 0 | ET11: 0 | EU11: 0 | EV11: 0 | EW11: 0 | EX11: 0 | EY11: 0 | EZ11: 0 | FA11: 0
A12: Operating Expenses | B12: 5258000000 | C12: 3676000000 | D12: 3541000000 | E12: 3307000000 | F12: 4222000000 | G12: 4680000000 | H12: 4919000000 | I12: 4924000000 | J12: 3942000000 | K12: 4026000000 | L12: 4659000000 | M12: 3296000000 | N12: 3537000000 | O12: 3409000000 | P12: 4154000000 | Q12: 2995000000 | R12: 3704000000 | S12: 3167000000 | T12: 3326000000 | U12: 2793000000 | V12: 2695000000 | W12: 2883000000 | X12: 2156000000 | Y12: 2850000000 | Z12: 3338000000 | AA12: 3241000000 | AB12: 3088000000 | AC12: 2894000000 | AD12: 3077000000 | AE12: 2815000000 | AF12: 3112000000 | AG12: 3077000000 | AH12: 3649000000 | AI12: 3439000000 | AJ12: 4006000000 | AK12: 3642000000 | AL12: 4229000000 | AM12: 4231000000 | AN12: 4209000000 | AO12: 4072000000 | AP12: 4428000000 | AQ12: 4471000000 | AR12: 4873000000 | AS12: 4312000000 | AT12: 5064000000 | AU12: 4635000000 | AV12: 4585000000 | AW12: 4117000000 | AX12: 4620000000 | AY12: 4765000000 | AZ12: 4517000000 | BA12: 4303000000 | BB12: 4644000000 | BC12: 4694000000 | BD12: 4567000000 | BE12: 4280000000 | BF12: 4681000000 | BG12: 4619000000 | BH12: 4569000000 | BI12: 4285000000 | BJ12: 5092000000 | BK12: 3164000000 | BL12: 2956000000 | BM12: 2801000000 | BN12: 3079000000 | BO12: 2960000000 | BP12: 2916000000 | BQ12: 2716000000 | BR12: 2852000000 | BS12: 3186000000 | BT12: 3205000000 | BU12: 2881000000 | BV12: 3164000000 | BW12: 2977000000 | BX12: 2727000000 | BY12: 2331000000 | BZ12: 2657000000 | CA12: 2527000000 | CB12: 2327000000 | CC12: 2105000000 | CD12: 2293000000 | CE12: 2310000000 | CF12: 2192000000 | CG12: 2029000000 | CH12: 1986000000 | CI12: 2438000000 | CJ12: 2072000000 | CK12: 1874000000 | CL12: 2033000000 | CM12: 2052000000 | CN12: 1966000000 | CO12: 1809000000 | CP12: 1804000000 | CQ12: 1789000000 | CR12: 1881000000 | CS12: 1527000000 | CT12: 1562000000 | CU12: 1692000000 | CV12: 1561000000 | CW12: 1334000000 | CX12: 3351000000 | CY12: 2350000000 | CZ12: 2525000000 | DA12: 2618000000 | DB12: 3118000000 | DC12: 2390000000 | DD12: 2353000000 | DE12: 1953000000 | DF12: 2222000000 | DG12: 2064000000 | DH12: 2141000000 | DI12: 1857000000 | DJ12: 2076000000 | DK12: 2052000000 | DL12: 2023000000 | DM12: 1701000000 | DN12: 1909000000 | DO12: 2388000000 | DP12: 1965000000 | DQ12: 1631000000 | DR12: 1714000000 | DS12: 1940000000 | DT12: 1802000000 | DU12: 1530000000 | DV12: 1653000000 | DW12: 1701000000 | DX12: 1605000000 | DY12: 1338000000 | DZ12: 1476000000 | EA12: 1457000000 | EB12: 1476000000 | EC12: 1286000000 | ED12: 1396917000 | EE12: 1351203000 | EF12: 1340276000 | EG12: 1160996000 | EH12: 1200601000 | EI12: 1220156000 | EJ12: 1160498000 | EK12: 1022929000 | EL12: 1059328000 | EM12: 1113039000 | EN12: 1059741000 | EO12: 843828000 | EP12: 849972000 | EQ12: 848336000 | ER12: 883935000 | ES12: 765689000 | ET12: 773356000 | EU12: 790416000 | EV12: 827201000 | EW12: 647085000 | EX12: 469902000 | EY12: 837039000 | EZ12: 790695000 | FA12: 603756000
A13: Operating Income | B13: 1841000000 | C13: 3982000000 | D13: 4280000000 | E13: 3659000000 | F13: 2709000000 | G13: 2510000000 | H13: 2632000000 | I13: 2141000000 | J13: 2273000000 | K13: 3270000000 | L13: 2401000000 | M13: 3367000000 | N13: 2075000000 | O13: 3088000000 | P13: 2341000000 | Q13: 3405000000 | R13: 1672000000 | S13: 2898000000 | T13: 3016000000 | U13: 2722000000 | V13: 2338000000 | W13: 2298000000 | X13: 1981000000 | Y13: 2380000000 | Z13: 2164000000 | AA13: 2499000000 | AB13: 2988000000 | AC13: 2435000000 | AD13: 1961000000 | AE13: 2614000000 | AF13: 2766000000 | AG13: 1811000000 | AH13: 1510000000 | AI13: 2245000000 | AJ13: 2037000000 | AK13: 1963000000 | AL13: 1386000000 | AM13: 2271000000 | AN13: 2859000000 | AO13: 2141000000 | AP13: 1518000000 | AQ13: 2379000000 | AR13: 2535000000 | AS13: 2296000000 | AT13: 1451000000 | AU13: 2711000000 | AV13: 3170000000 | AW13: 2376000000 | AX13: 2105000000 | AY13: 2472000000 | AZ13: 3243000000 | BA13: 2408000000 | BB13: 2183000000 | BC13: 2793000000 | BD13: 3294000000 | BE13: 2509000000 | BF13: 1956000000 | BG13: 2754000000 | BH13: 3179000000 | BI13: 2284000000 | BJ13: 1123000000 | BK13: 2344000000 | BL13: 2763000000 | BM13: 2183000000 | BN13: 1780000000 | BO13: 2150000000 | BP13: 2438000000 | BQ13: 1863000000 | BR13: 1706000000 | BS13: 2187000000 | BT13: 2679000000 | BU13: 1874000000 | BV13: 1526000000 | BW13: 1829000000 | BX13: 2270000000 | BY13: 1627000000 | BZ13: 1212000000 | CA13: 1662000000 | CB13: 2039000000 | CC13: 1395000000 | CD13: 1262000000 | CE13: 1492000000 | CF13: 1972000000 | CG13: 1359000000 | CH13: 1347000000 | CI13: 1097000000 | CJ13: 1803000000 | CK13: 1451000000 | CL13: 1092000000 | CM13: 1451000000 | CN13: 1602000000 | CO13: 1076000000 | CP13: 1290000000 | CQ13: 1450000000 | CR13: 1560000000 | CS13: 1158000000 | CT13: 1248000000 | CU13: 1311000000 | CV13: 1513000000 | CW13: 1280000000 | CX13: 159000000 | CY13: 1327000000 | CZ13: 1285000000 | DA13: 240000000 | DB13: 477000000 | DC13: 1099000000 | DD13: 1390000000 | DE13: 1144000000 | DF13: 937000000 | DG13: 1237000000 | DH13: 1511000000 | DI13: 1282000000 | DJ13: 1173000000 | DK13: 1243000000 | DL13: 1443000000 | DM13: 1142000000 | DN13: 1079000000 | DO13: 485000000 | DP13: 1415000000 | DQ13: 1033000000 | DR13: 949000000 | DS13: 1006000000 | DT13: 1258000000 | DU13: 879000000 | DV13: 866000000 | DW13: 1000000000 | DX13: 1070000000 | DY13: 772000000 | DZ13: 637000000 | EA13: 829000000 | EB13: 959000000 | EC13: 677000000 | ED13: 583222900 | EE13: 770956100 | EF13: 836534200 | EG13: 579484900 | EH13: 487078100 | EI13: 644703900 | EJ13: 693266800 | EK13: 493996100 | EL13: 421468000 | EM13: 512429900 | EN13: 579682100 | EO13: 437983200 | EP13: 381755100 | EQ13: 458300000 | ER13: 498775100 | ES13: 386955000 | ET13: 340715000 | EU13: 431427000 | EV13: 465457000 | EW13: 360702000 | EX13: 182247000 | EY13: 394154100 | EZ13: 423273900 | FA13: 324115000
A14: Total Non-Operating Income/Expense | B14: 1121000000 | C14: 201000000 | D14: 516000000 | E14: 398000000 | F14: 97000000 | G14: 870000000 | H14: 396000000 | I14: 1731000000 | J14: 209000000 | K14: 267000000 | L14: 479000000 | M14: 686000000 | N14: 425000000 | O14: 356000000 | P14: -57000000 | Q14: 53000000 | R14: 1288000000 | S14: 186000000 | T14: 602000000 | U14: 41000000 | V14: 23000000 | W14: -117000000 | X14: 216000000 | Y14: 630000000 | Z14: 256000000 | AA14: 593000000 | AB14: 61000000 | AC14: -210000000 | AD14: -884000000 | AE14: -241000000 | AF14: 176000000 | AG14: 22000000 | AH14: -425000000 | AI14: -571000000 | AJ14: 587000000 | AK14: -456000000 | AL14: -871000000 | AM14: -843000000 | AN14: 1440000000 | AO14: -247000000 | AP14: 20000000 | AQ14: -654000000 | AR14: 1826000000 | AS14: -315000000 | AT14: -375000000 | AU14: -51000000 | AV14: 214000000 | AW14: -171000000 | AX14: 123000000 | AY14: 908000000 | AZ14: 282000000 | BA14: -64000000 | BB14: 194000000 | BC14: 291000000 | BD14: 329000000 | BE14: 216000000 | BF14: 260000000 | BG14: 173000000 | BH14: 620000000 | BI14: 232000000 | BJ14: 5082000000 | BK14: 356000000 | BL14: 360000000 | BM14: -4000000 | BN14: 180000000 | BO14: 293000000 | BP14: 290000000 | BQ14: -48000000 | BR14: -546000000 | BS14: 283000000 | BT14: -762000000 | BU14: 85000000 | BV14: 143000000 | BW14: 284000000 | BX14: 138000000 | BY14: 102000000 | BZ14: -326000000 | CA14: 164000000 | CB14: 352000000 | CC14: 80000000 | CD14: 111000000 | CE14: 161000000 | CF14: 244000000 | CG14: 89000000 | CH14: 75000000 | CI14: 138000000 | CJ14: 250000000 | CK14: 61000000 | CL14: 32000000 | CM14: 47000000 | CN14: 148000000 | CO14: 47000000 | CP14: -17000000 | CQ14: 45000000 | CR14: 115000000 | CS14: -102000000 | CT14: 44000000 | CU14: 223000000 | CV14: 84000000 | CW14: -33000000 | CX14: 318000000 | CY14: 156000000 | CZ14: 57000000 | DA14: -143000000 | DB14: -119000000 | DC14: 42000000 | DD14: -24000000 | DE14: -62000000 | DF14: -72000000 | DG14: 50000000 | DH14: 292000000 | DI14: -39000000 | DJ14: 11000000 | DK14: 262000000 | DL14: 492000000 | DM14: 289000000 | DN14: 58000000 | DO14: 483000000 | DP14: 140000000 | DQ14: 0 | DR14: -24000000 | DS14: 162000000 | DT14: 46000000 | DU14: 52000000 | DV14: -38000000 | DW14: 33000000 | DX14: 37000000 | DY14: -12000000 | DZ14: 42000000 | EA14: 41000000 | EB14: 21000000 | EC14: -21000000 | ED14: -30566000 | EE14: 17095000 | EF14: 10391000 | EG14: -20923000 | EH14: 60022000 | EI14: 20475000 | EJ14: 9928000 | EK14: -26191000 | EL14: 7591000 | EM14: 62164000 | EN14: 17887000 | EO14: -24770000 | EP14: -38910000 | EQ14: 72977000 | ER14: 9341000 | ES14: -4883000 | ET14: 9585000 | EU14: 18521000 | EV14: -644000 | EW14: -43626000 | EX14: 70268000 | EY14: 25132000 | EZ14: 13396000 | FA14: -20102000
A15: Pre-Tax Income | B15: 2962000000 | C15: 4183000000 | D15: 4796000000 | E15: 4057000000 | F15: 2806000000 | G15: 3380000000 | H15: 3028000000 | I15: 3872000000 | J15: 2482000000 | K15: 3537000000 | L15: 2880000000 | M15: 4053000000 | N15: 2500000000 | O15: 3444000000 | P15: 2284000000 | Q15: 3458000000 | R15: 2960000000 | S15: 3084000000 | T15: 3618000000 | U15: 2763000000 | V15: 2361000000 | W15: 2181000000 | X15: 2197000000 | Y15: 3010000000 | Z15: 2420000000 | AA15: 3092000000 | AB15: 3049000000 | AC15: 2225000000 | AD15: 1077000000 | AE15: 2373000000 | AF15: 2942000000 | AG15: 1833000000 | AH15: 1085000000 | AI15: 1674000000 | AJ15: 2624000000 | AK15: 1507000000 | AL15: 515000000 | AM15: 1428000000 | AN15: 4299000000 | AO15: 1894000000 | AP15: 1538000000 | AQ15: 1725000000 | AR15: 4361000000 | AS15: 1981000000 | AT15: 1076000000 | AU15: 2660000000 | AV15: 3384000000 | AW15: 2205000000 | AX15: 2228000000 | AY15: 3380000000 | AZ15: 3525000000 | BA15: 2344000000 | BB15: 2377000000 | BC15: 3084000000 | BD15: 3623000000 | BE15: 2725000000 | BF15: 2216000000 | BG15: 2927000000 | BH15: 3799000000 | BI15: 2516000000 | BJ15: 6205000000 | BK15: 2700000000 | BL15: 3123000000 | BM15: 2179000000 | BN15: 1960000000 | BO15: 2443000000 | BP15: 2728000000 | BQ15: 1815000000 | BR15: 1160000000 | BS15: 2470000000 | BT15: 1917000000 | BU15: 1959000000 | BV15: 1669000000 | BW15: 2113000000 | BX15: 2408000000 | BY15: 1729000000 | BZ15: 886000000 | CA15: 1826000000 | CB15: 2391000000 | CC15: 1475000000 | CD15: 1373000000 | CE15: 1653000000 | CF15: 2216000000 | CG15: 1448000000 | CH15: 1422000000 | CI15: 1235000000 | CJ15: 2053000000 | CK15: 1512000000 | CL15: 1124000000 | CM15: 1498000000 | CN15: 1750000000 | CO15: 1123000000 | CP15: 1273000000 | CQ15: 1495000000 | CR15: 1675000000 | CS15: 1056000000 | CT15: 1292000000 | CU15: 1534000000 | CV15: 1597000000 | CW15: 1247000000 | CX15: 477000000 | CY15: 1483000000 | CZ15: 1342000000 | DA15: 97000000 | DB15: 230000000 | DC15: 1141000000 | DD15: 1366000000 | DE15: 1082000000 | DF15: 865000000 | DG15: 1287000000 | DH15: 1803000000 | DI15: 1243000000 | DJ15: 1184000000 | DK15: 1505000000 | DL15: 1935000000 | DM15: 1431000000 | DN15: 1104000000 | DO15: 937000000 | DP15: 1522000000 | DQ15: 1033000000 | DR15: 925000000 | DS15: 1168000000 | DT15: 1304000000 | DU15: 931000000 | DV15: 828000000 | DW15: 1033000000 | DX15: 1107000000 | DY15: 760000000 | DZ15: 679000000 | EA15: 870000000 | EB15: 980000000 | EC15: 656000000 | ED15: 552657000 | EE15: 788051000 | EF15: 846925000 | EG15: 558455000 | EH15: 547100000 | EI15: 665179000 | EJ15: 703195000 | EK15: 467805000 | EL15: 429060000 | EM15: 574594000 | EN15: 597569000 | EO15: 413213000 | EP15: 342845000 | EQ15: 5.31277e+08 | ER15: 508116000 | ES15: 382072000 | ET15: 350300000 | EU15: 449948000 | EV15: 464813000 | EW15: 317076000 | EX15: 252515000 | EY15: 419286000 | EZ15: 436670000 | FA15: 304013000
A16: Income Taxes | B16: 646000000 | C16: 500000000 | D16: 993000000 | E16: 722000000 | F16: 593000000 | G16: 530000000 | H16: 627000000 | I16: 687000000 | J16: 496000000 | K16: 454000000 | L16: 359000000 | M16: 940000000 | N16: 444000000 | O16: 622000000 | P16: 384000000 | Q16: 665000000 | R16: 510000000 | S16: 609000000 | T16: 994000000 | U16: 508000000 | V16: 887000000 | W16: 441000000 | X16: 438000000 | Y16: 215000000 | Z16: 355000000 | AA16: 503000000 | AB16: 421000000 | AC16: 522000000 | AD16: 77000000 | AE16: 555000000 | AF16: 611000000 | AG16: 506000000 | AH16: 3802000000 | AI16: 230000000 | AJ16: 1252000000 | AK16: 323000000 | AL16: -32000000 | AM16: 378000000 | AN16: 839000000 | AO16: 401000000 | AP16: 302000000 | AQ16: 272000000 | AR16: 1250000000 | AS16: 415000000 | AT16: 305000000 | AU16: 538000000 | AV16: 779000000 | AW16: 579000000 | AX16: 520000000 | AY16: 925000000 | AZ16: 831000000 | BA16: 575000000 | BB16: 487000000 | BC16: 755000000 | BD16: 823000000 | BE16: 658000000 | BF16: 539000000 | BG16: 681000000 | BH16: 992000000 | BI16: 600000000 | BJ16: 443000000 | BK16: 633000000 | BL16: 741000000 | BM16: 553000000 | BN16: 382000000 | BO16: 523000000 | BP16: 679000000 | BQ16: 456000000 | BR16: 155000000 | BS16: 555000000 | BT16: 474000000 | BU16: 448000000 | BV16: 409000000 | BW16: 459000000 | BX16: 557000000 | BY16: 467000000 | BZ16: 208000000 | CA16: 366000000 | CB16: 555000000 | CC16: 369000000 | CD16: 509000000 | CE16: 370000000 | CF16: 493000000 | CG16: 446000000 | CH16: 221000000 | CI16: 300000000 | CJ16: 469000000 | CK16: 385000000 | CL16: 197000000 | CM16: 275000000 | CN16: 388000000 | CO16: 288000000 | CP16: 343000000 | CQ16: 404000000 | CR16: 452000000 | CS16: 324000000 | CT16: 378000000 | CU16: 460000000 | CV16: 479000000 | CW16: 374000000 | CX16: 235000000 | CY16: 416000000 | CZ16: 416000000 | DA16: 155000000 | DB16: 275000000 | DC16: 354000000 | DD16: 424000000 | DE16: 335000000 | DF16: 268000000 | DG16: 399000000 | DH16: 612000000 | DI16: 386000000 | DJ16: 367000000 | DK16: 494000000 | DL16: 621000000 | DM16: 444000000 | DN16: 342000000 | DO16: -30000000 | DP16: 472000000 | DQ16: 320000000 | DR16: 277000000 | DS16: 366000000 | DT16: 406000000 | DU16: 293000000 | DV16: 261000000 | DW16: 325000000 | DX16: 349000000 | DY16: 239000000 | DZ16: 213000000 | EA16: 280000000 | EB16: 302000000 | EC16: 202000000 | ED16: 173536000 | EE16: 247448000 | EF16: 2.65934e+08 | EG16: 175355000 | EH16: 188717000 | EI16: 208866000 | EJ16: 220803000 | EK16: 146891000 | EL16: 134725000 | EM16: 180422000 | EN16: 187637000 | EO16: 1.29748e+08 | EP16: 116602000 | EQ16: 170009000 | ER16: 162597000 | ES16: 122263000 | ET16: 114809000 | EU16: 154332000 | EV16: 161755000 | EW16: 106538000 | EX16: 59560000 | EY16: 147923000 | EZ16: 170300000 | FA16: 118565000
A17: Income After Taxes | B17: 2316000000 | C17: 3683000000 | D17: 3803000000 | E17: 3335000000 | F17: 2213000000 | G17: 2850000000 | H17: 2401000000 | I17: 3185000000 | J17: 1986000000 | K17: 3083000000 | L17: 2521000000 | M17: 3113000000 | N17: 2056000000 | O17: 2822000000 | P17: 1900000000 | Q17: 2793000000 | R17: 2450000000 | S17: 2475000000 | T17: 2624000000 | U17: 2255000000 | V17: 1474000000 | W17: 1740000000 | X17: 1759000000 | Y17: 2795000000 | Z17: 2065000000 | AA17: 2589000000 | AB17: 2628000000 | AC17: 1703000000 | AD17: 1000000000 | AE17: 1818000000 | AF17: 2331000000 | AG17: 1327000000 | AH17: -2717000000 | AI17: 1444000000 | AJ17: 1372000000 | AK17: 1184000000 | AL17: 547000000 | AM17: 1050000000 | AN17: 3460000000 | AO17: 1493000000 | AP17: 1236000000 | AQ17: 1453000000 | AR17: 3111000000 | AS17: 1566000000 | AT17: 771000000 | AU17: 2122000000 | AV17: 2605000000 | AW17: 1626000000 | AX17: 1708000000 | AY17: 2455000000 | AZ17: 2694000000 | BA17: 1769000000 | BB17: 1890000000 | BC17: 2329000000 | BD17: 2800000000 | BE17: 2067000000 | BF17: 1677000000 | BG17: 2246000000 | BH17: 2807000000 | BI17: 1916000000 | BJ17: 5762000000 | BK17: 2067000000 | BL17: 2382000000 | BM17: 1626000000 | BN17: 1578000000 | BO17: 1920000000 | BP17: 2049000000 | BQ17: 1359000000 | BR17: 1005000000 | BS17: 1915000000 | BT17: 1443000000 | BU17: 1511000000 | BV17: 1260000000 | BW17: 1654000000 | BX17: 1851000000 | BY17: 1262000000 | BZ17: 678000000 | CA17: 1460000000 | CB17: 1836000000 | CC17: 1106000000 | CD17: 864000000 | CE17: 1283000000 | CF17: 1723000000 | CG17: 1002000000 | CH17: 1201000000 | CI17: 935000000 | CJ17: 1584000000 | CK17: 1127000000 | CL17: 927000000 | CM17: 1223000000 | CN17: 1362000000 | CO17: 835000000 | CP17: 930000000 | CQ17: 1091000000 | CR17: 1223000000 | CS17: 732000000 | CT17: 914000000 | CU17: 1074000000 | CV17: 1118000000 | CW17: 873000000 | CX17: 242000000 | CY17: 1067000000 | CZ17: 926000000 | DA17: -58000000 | DB17: -45000000 | DC17: 787000000 | DD17: 942000000 | DE17: 747000000 | DF17: 597000000 | DG17: 888000000 | DH17: 1191000000 | DI17: 857000000 | DJ17: 817000000 | DK17: 1011000000 | DL17: 1314000000 | DM17: 987000000 | DN17: 762000000 | DO17: 967000000 | DP17: 1050000000 | DQ17: 713000000 | DR17: 648000000 | DS17: 802000000 | DT17: 898000000 | DU17: 638000000 | DV17: 567000000 | DW17: 708000000 | DX17: 758000000 | DY17: 521000000 | DZ17: 466000000 | EA17: 590000000 | EB17: 678000000 | EC17: 454000000 | ED17: 379121000 | EE17: 540603000 | EF17: 580991000 | EG17: 383100000 | EH17: 358383000 | EI17: 456313000 | EJ17: 482392000 | EK17: 320914000 | EL17: 294335000 | EM17: 394172000 | EN17: 409932000 | EO17: 283465000 | EP17: 226243000 | EQ17: 361268000 | ER17: 345519000 | ES17: 2.59809e+08 | ET17: 235491000 | EU17: 295616000 | EV17: 303058000 | EW17: 210538000 | EX17: 192955000 | EY17: 271363000 | EZ17: 266370000 | FA17: 185448000
A19: Other Income | CX19: 0 | DB19: 0 | DC19: 0 | DD19: 0 | DE19: 0 | DF19: 0 | DG19: 0 | DH19: 0 | DI19: 0 | DJ19: 0 | DK19: 0 | DL19: 0 | DM19: 0 | DN19: 0 | DO19: 0 | DP19: 0 | DQ19: 0 | DR19: 0 | DS19: 0 | DT19: 0 | DU19: 0 | DV19: 0 | DW19: 0 | DX19: 0 | DY19: 0 | DZ19: 0 | EA19: 0 | EB19: 0 | EC19: 0 | ED19: 0 | EE19: 0 | EF19: 0 | EG19: 0 | EH19: 0 | EI19: 0 | EJ19: 0 | EK19: 0 | EL19: 0 | EM19: 0 | EN19: 0 | EO19: 0 | EP19: 0 | EQ19: 0 | ER19: 0 | ES19: 0 | ET19: 0 | EU19: 0 | EV19: 0 | EW19: 0 | EX19: 0 | EY19: 0 | EZ19: 0 | FA19: 0 | FB19: 0
A20: Income From Continuous Operations | B20: 2316000000 | C20: 3683000000 | D20: 3803000000 | E20: 3335000000 | F20: 2213000000 | G20: 2850000000 | H20: 2401000000 | I20: 3185000000 | J20: 1986000000 | K20: 3083000000 | L20: 2521000000 | M20: 3113000000 | N20: 2056000000 | O20: 2822000000 | P20: 1900000000 | Q20: 2793000000 | R20: 2450000000 | S20: 2475000000 | T20: 2624000000 | U20: 2255000000 | V20: 1474000000 | W20: 1740000000 | X20: 1759000000 | Y20: 2795000000 | Z20: 2065000000 | AA20: 2589000000 | AB20: 2628000000 | AC20: 1703000000 | AD20: 1000000000 | AE20: 1818000000 | AF20: 2331000000 | AG20: 1327000000 | AH20: -2717000000 | AI20: 1444000000 | AJ20: 1372000000 | AK20: 1184000000 | AL20: 547000000 | AM20: 1050000000 | AN20: 3460000000 | AO20: 1493000000 | AP20: 1236000000 | AQ20: 1453000000 | AR20: 3111000000 | AS20: 1566000000 | AT20: 771000000 | AU20: 2122000000 | AV20: 2605000000 | AW20: 1626000000 | AX20: 1708000000 | AY20: 2455000000 | AZ20: 2694000000 | BA20: 1769000000 | BB20: 1890000000 | BC20: 2329000000 | BD20: 2800000000 | BE20: 2067000000 | BF20: 1677000000 | BG20: 2246000000 | BH20: 2807000000 | BI20: 1916000000 | BJ20: 5762000000 | BK20: 2067000000 | BL20: 2382000000 | BM20: 1626000000 | BN20: 1578000000 | BO20: 1920000000 | BP20: 2049000000 | BQ20: 1359000000 | BR20: 1005000000 | BS20: 1915000000 | BT20: 1443000000 | BU20: 1511000000 | BV20: 1260000000 | BW20: 1654000000 | BX20: 1851000000 | BY20: 1262000000 | BZ20: 678000000 | CA20: 1460000000 | CB20: 1836000000 | CC20: 1106000000 | CD20: 864000000 | CE20: 1283000000 | CF20: 1723000000 | CG20: 1002000000 | CH20: 1201000000 | CI20: 935000000 | CJ20: 1584000000 | CK20: 1127000000 | CL20: 927000000 | CM20: 1223000000 | CN20: 1362000000 | CO20: 835000000 | CP20: 930000000 | CQ20: 1091000000 | CR20: 1223000000 | CS20: 732000000 | CT20: 914000000 | CU20: 1074000000 | CV20: 1118000000 | CW20: 873000000 | CX20: 242000000 | CY20: 1067000000 | CZ20: 926000000 | DA20: -58000000 | DB20: -45000000 | DC20: 787000000 | DD20: 942000000 | DE20: 747000000 | DF20: 597000000 | DG20: 888000000 | DH20: 1191000000 | DI20: 857000000 | DJ20: 817000000 | DK20: 1011000000 | DL20: 1314000000 | DM20: 987000000 | DN20: 762000000 | DO20: 967000000 | DP20: 1050000000 | DQ20: 713000000 | DR20: 648000000 | DS20: 802000000 | DT20: 898000000 | DU20: 638000000 | DV20: 567000000 | DW20: 708000000 | DX20: 758000000 | DY20: 521000000 | DZ20: 473000000 | EA20: 576000000 | EB20: 678000000 | EC20: 442000000 | ED20: 392579000 | EE20: 540603000 | EF20: 565000000 | EG20: 386000000 | EH20: 358383000 | EI20: 456313000 | EJ20: 482392000 | EK20: 320914000 | EL20: 294335000 | EM20: 394172000 | EN20: 409932000 | EO20: 283465000 | EP20: 226243000 | EQ20: 361268000 | ER20: 345519000 | ES20: 2.59809e+08 | ET20: 235491000 | EU20: 295616000 | EV20: 303058000 | EW20: 210538000 | EX20: 192955000 | EY20: 271363000 | EZ20: 266370000 | FA20: 185448000
A21: Income From Discontinued Operations | B21: 0 | C21: 0 | D21: 0 | E21: 0 | F21: 0 | G21: 0 | H21: 0 | I21: 0 | J21: 0 | K21: 0 | L21: 0 | M21: 0 | N21: 0 | O21: 0 | P21: 0 | Q21: 0 | R21: 0 | S21: 0 | T21: 0 | U21: 0 | V21: 0 | W21: 0 | X21: 0 | Y21: 0 | Z21: 0 | AA21: 0 | AB21: 0 | AC21: 0 | AD21: 0 | AE21: 0 | AF21: 0 | AG21: 73000000 | AH21: 0 | AI21: 0 | AJ21: 0 | AK21: 0 | AL21: 0 | AM21: 0 | AN21: 0 | AO21: 0 | AP21: 0 | AQ21: 0 | AR21: 0 | AS21: 0 | AT21: 0 | AU21: 0 | AV21: 0 | AW21: 0 | AX21: 0 | AY21: 0 | AZ21: 0 | BA21: 0 | BB21: 0 | BC21: 0 | BD21: 0 | BE21: 0 | BF21: 0 | BG21: 0 | BH21: 0 | BI21: 0 | BJ21: 0 | BK21: 0 | BL21: 0 | BM21: 0 | BN21: 0 | BO21: 0 | BP21: 0 | BQ21: 0 | BR21: 0 | BS21: 0 | BT21: 0 | BU21: 0 | BV21: 0 | BW21: 0 | BX21: 0 | BY21: 0 | BZ21: 0 | CA21: 0 | CB21: 0 | CC21: 0 | CD21: 0 | CE21: 0 | CF21: 0 | CG21: 0 | CH21: 0 | CI21: 0 | CJ21: 0 | CK21: 0 | CL21: 0 | CM21: 0 | CN21: 0 | CO21: 0 | CP21: 0 | CQ21: 0 | CR21: 0 | CS21: 0 | CT21: 0 | CU21: 0 | CV21: 0 | CW21: 0 | CX21: 0 | CY21: 0 | CZ21: 0 | DA21: 0 | DB21: 0 | DC21: 0 | DD21: 0 | DE21: 0 | DF21: 0 | DG21: 0 | DH21: 0 | DI21: 0 | DJ21: 0 | DK21: 0 | DL21: 0 | DM21: 0 | DN21: 0 | DO21: 0 | DP21: 0 | DQ21: 0 | DR21: 0 | DS21: 0 | DT21: 0 | DU21: 0 | DV21: 0 | DW21: 0 | DX21: 0 | DY21: 0 | DZ21: 0 | EA21: 0 | EB21: 0 | EC21: 0 | ED21: -1998000000 | EE21: -1998000000 | EF21: 0 | EG21: -219000000 | EH21: 0 | EI21: 0 | EJ21: 0 | EK21: 0 | EL21: 0 | EM21: 0 | EN21: 0 | EO21: 0 | EP21: 530986000 | EQ21: 0 | ER21: 0 | ES21: 0 | ET21: 0 | EU21: 0 | EV21: 0 | EW21: 0 | EX21: 0 | EY21: 0 | EZ21: 0 | FA21: 0
A23: Net Income | B23: 2271000000 | C23: 3696000000 | D23: 3810000000 | E23: 3330000000 | F23: 2195000000 | G23: 2848000000 | H23: 2411000000 | I23: 3177000000 | J23: 1973000000 | K23: 3087000000 | L23: 2547000000 | M23: 3107000000 | N23: 2031000000 | O23: 2825000000 | P23: 1905000000 | Q23: 2781000000 | R23: 2414000000 | S23: 2471000000 | T23: 2641000000 | U23: 2245000000 | V23: 1456000000 | W23: 1737000000 | X23: 1779000000 | Y23: 2775000000 | Z23: 2042000000 | AA23: 2593000000 | AB23: 2607000000 | AC23: 1678000000 | AD23: 870000000 | AE23: 1880000000 | AF23: 2316000000 | AG23: 1368000000 | AH23: -2752000000 | AI23: 1447000000 | AJ23: 1371000000 | AK23: 1182000000 | AL23: 550000000 | AM23: 1046000000 | AN23: 3448000000 | AO23: 1483000000 | AP23: 1237000000 | AQ23: 1449000000 | AR23: 3108000000 | AS23: 1557000000 | AT23: 770000000 | AU23: 2114000000 | AV23: 2595000000 | AW23: 1619000000 | AX23: 1710000000 | AY23: 2447000000 | AZ23: 2676000000 | BA23: 1751000000 | BB23: 1866000000 | BC23: 2311000000 | BD23: 2788000000 | BE23: 2054000000 | BF23: 1657000000 | BG23: 2224000000 | BH23: 2800000000 | BI23: 1903000000 | BJ23: 5749000000 | BK23: 2055000000 | BL23: 2369000000 | BM23: 1614000000 | BN23: 1543000000 | BO23: 1896000000 | BP23: 2037000000 | BQ23: 1348000000 | BR23: 995000000 | BS23: 1890000000 | BT23: 1422000000 | BU23: 1500000000 | BV23: 1214000000 | BW23: 1654000000 | BX23: 1851000000 | BY23: 1262000000 | BZ23: 678000000 | CA23: 1460000000 | CB23: 1836000000 | CC23: 1106000000 | CD23: 864000000 | CE23: 1283000000 | CF23: 1723000000 | CG23: 1002000000 | CH23: 1201000000 | CI23: 935000000 | CJ23: 1584000000 | CK23: 1127000000 | CL23: 927000000 | CM23: 1223000000 | CN23: 1362000000 | CO23: 835000000 | CP23: 930000000 | CQ23: 1091000000 | CR23: 1223000000 | CS23: -194000000 | CT23: 914000000 | CU23: 1074000000 | CV23: 1118000000 | CW23: 863000000 | CX23: 242000000 | CY23: 1067000000 | CZ23: 926000000 | DA23: -58000000 | DB23: -45000000 | DC23: 787000000 | DD23: 942000000 | DE23: 747000000 | DF23: 597000000 | DG23: 888000000 | DH23: 1191000000 | DI23: 857000000 | DJ23: 817000000 | DK23: 1011000000 | DL23: 1314000000 | DM23: 987000000 | DN23: 762000000 | DO23: 967000000 | DP23: 1050000000 | DQ23: 713000000 | DR23: 648000000 | DS23: 802000000 | DT23: 898000000 | DU23: 638000000 | DV23: 567000000 | DW23: 708000000 | DX23: 758000000 | DY23: 521000000 | DZ23: 473000000 | EA23: 576000000 | EB23: 678000000 | EC23: 442000000 | ED23: 392579000 | EE23: 540603000 | EF23: 565000000 | EG23: 167000000 | EH23: 358383000 | EI23: 456313000 | EJ23: 482392000 | EK23: 320914000 | EL23: 294335000 | EM23: 394172000 | EN23: 409932000 | EO23: 283465000 | EP23: 757229000 | EQ23: 361268000 | ER23: 345519000 | ES23: 2.59809e+08 | ET23: 235491000 | EU23: 295616000 | EV23: 303058000 | EW23: 210538000 | EX23: 192955000 | EY23: 271363000 | EZ23: 266370000 | FA23: 185448000 | FB23: 0
A25: EBITDA | B25: 1538000000 | C25: 1145000000 | D25: 949000000 | E25: 1006000000 | F25: 1258000000 | G25: 879000000 | H25: 866000000 | I25: 1000000000 | J25: 1172000000 | K25: 863000000 | L25: 637000000 | M25: 829000000 | N25: 959000000 | O25: 677000000 | P25: 583222900 | Q25: 770956100 | R25: 836534200 | S25: 579484900 | T25: 487078100 | U25: 644703900 | V25: 693266800 | W25: 493996100 | X25: 421468000 | Y25: 512429900 | Z25: 579682100 | AA25: 437983200 | AB25: 381755100 | AC25: 458300000 | AD25: 498775100 | AE25: 386955000 | AF25: 340715000 | AG25: 431427000 | AH25: 465457000 | AI25: 360702000 | AJ25: 182247000 | AK25: 394154100 | AL25: 423273900 | AM25: 324115000
A26: EBIT | B26: 1415000000 | C26: 1033000000 | D26: 949000000 | E26: 1006000000 | F26: 1258000000 | G26: 879000000 | H26: 866000000 | I26: 1000000000 | J26: 1070000000 | K26: 772000000 | L26: 637000000 | M26: 829000000 | N26: 959000000 | O26: 677000000 | P26: 583222900 | Q26: 770956100 | R26: 836534200 | S26: 579484900 | T26: 487078100 | U26: 644703900 | V26: 693266800 | W26: 493996100 | X26: 421468000 | Y26: 512429900 | Z26: 579682100 | AA26: 437983200 | AB26: 381755100 | AC26: 458300000 | AD26: 498775100 | AE26: 386955000 | AF26: 340715000 | AG26: 431427000 | AH26: 465457000 | AI26: 360702000 | AJ26: 182247000 | AK26: 394154100 | AL26: 423273900 | AM26: 324115000
A27: Basic Shares Outstanding | B27: 4992000000 | C27: 5008000000 | D27: 5012000000 | E27: 5036000000 | F27: 5060000000 | G27: 5088000000 | H27: 5132000000 | I27: 5156000000 | J27: 5168000000 | K27: 5184000000 | L27: 5192000000 | M27: 5200000000 | N27: 5212000000 | O27: 5224000000 | P27: 5238836000 | Q27: 5254584000 | R27: 5271056000 | S27: 5307288000 | T27: 5315840000 | U27: 5321094000 | V27: 5331362000 | W27: 5335388000 | X27: 5345914000 | Y27: 5341026000 | Z27: 5339712000 | AA27: 5340552000 | AB27: 5392238000 | AC27: 5461042000 | AD27: 5534418000 | AE27: 5602486000 | AF27: 5676616000 | AG27: 0 | AH27: 5845220000 | AI27: 591044000 | AJ27: 5957698000 | AK27: 6006550000 | AL27: 6031696000 | AM27: 6049004000
A28: Shares Outstanding | B28: 4988124000 | C28: 5008000000 | D28: 5012000000 | E28: 5036000000 | F28: 5060000000 | G28: 5088000000 | H28: 5132000000 | I28: 5156000000 | J28: 5168000000 | K28: 5184000000 | L28: 5192000000 | M28: 5196142000 | N28: 5204396000 | O28: 5220280000 | P28: 5227084000 | Q28: 5254584000 | R28: 5271056000 | S28: 10631680000 | T28: 10631680000 | U28: 5321094000 | V28: 5331362000 | W28: 5335388000 | X28: 5345914000 | Y28: 5341026000 | Z28: 5339712000 | AA28: 5340552000 | AB28: 5392238000 | AC28: 5461042000 | AD28: 5534418000 | AE28: 5602486000 | AF28: 5676616000 | AG28: 0 | AH28: 5845220000 | AI28: 591044000 | AJ28: 5957698000 | AK28: 6006550000 | AL28: 6031696000 | AM28: 6049004000
A29: Basic EPS | B29: 0.53 | C29: 0.86 | D29: 0.89 | E29: 0.77 | F29: 0.51 | G29: 0.66 | H29: 0.56 | I29: 0.74 | J29: 0.46 | K29: 0.71 | L29: 0.59 | M29: 0.72 | N29: 0.47 | O29: 0.65 | P29: 0.44 | Q29: 0.64 | R29: 0.56 | S29: 0.57 | T29: 0.61 | U29: 0.52 | V29: 0.34 | W29: 0.4 | X29: 0.41 | Y29: 0.65 | Z29: 0.48 | AA29: 0.61 | AB29: 0.61 | AC29: 0.39 | AD29: 0.21 | AE29: 0.44 | AF29: 0.54 | AG29: 0.32 | AH29: -0.65 | AI29: 0.34 | AJ29: 0.32 | AK29: 0.28 | AL29: 0.13 | AM29: 0.24 | AN29: 0.8 | AO29: 0.34 | AP29: 0.29 | AQ29: 0.33 | AR29: 0.71 | AS29: 0.36 | AT29: 0.18 | AU29: 0.48 | AV29: 0.59 | AW29: 0.37 | AX29: 0.4 | AY29: 0.55 | AZ29: 0.6 | BA29: 0.39 | BB29: 0.42 | BC29: 0.51 | BD29: 0.62 | BE29: 0.45 | BF29: 0.365 | BG29: 0.49 | BH29: 0.61 | BI29: 0.415 | BJ29: 1.24 | BK29: 0.445 | BL29: 0.515 | BM29: 0.35 | BN29: 0.335 | BO29: 0.41 | BP29: 0.44 | BQ29: 0.29 | BR29: 0.215 | BS29: 0.41 | BT29: 0.305 | BU29: 0.325 | BV29: 0.26 | BW29: 0.36 | BX29: 0.4 | BY29: 0.275 | BZ29: 0.145 | CA29: 0.31 | CB29: 0.39 | CC29: 0.235 | CD29: 0.18 | CE29: 0.27 | CF29: 0.36 | CG29: 0.21 | CH29: 0.25 | CI29: 0.195 | CJ29: 0.325 | CK29: 0.23 | CL29: 0.19 | CM29: 0.25 | CN29: 0.275 | CO29: 0.17 | CP29: 0.19 | CQ29: 0.22 | CR29: 0.245 | CS29: -0.04 | CT29: 0.185 | CU29: 0.215 | CV29: 0.225 | CW29: 0.175 | CX29: 0.05 | CY29: 0.215 | CZ29: 0.185 | DA29: -0.01 | DB29: -0.01 | DC29: 0.16 | DD29: 0.19 | DE29: 0.15 | DF29: 0.12 | DG29: 0.18 | DH29: 0.24 | DI29: 0.175 | DJ29: 0.165 | DK29: 0.205 | DL29: 0.265 | DM29: 0.2 | DN29: 0.155 | DO29: 0.195 | DP29: 0.21 | DQ29: 0.1425 | DR29: 0.13 | DS29: 0.16 | DT29: 0.175 | DU29: 0.125 | DV29: 0.11 | DW29: 0.1375 | DX29: 0.1475 | DY29: 0.1 | DZ29: 0.09 | EA29: 0.11 | EB29: 0.13 | EC29: 0.085 | ED29: 0.075 | EE29: 0.1025 | EF29: 0.11 | EG29: 0.0725 | EH29: 0.0674 | EI29: 0.0858 | EJ29: 0.0905 | EK29: 0.0601 | EL29: 0.0551 | EM29: 0.0738 | EN29: 0.0768 | EO29: 0.0531 | EP29: 0.1404 | EQ29: 0.0662 | ER29: 0.0624 | ES29: 0.0464 | ET29: 0.0415 | EU29: 0 | EV29: 51800 | EW29: 356200 | EX29: 32400 | EY29: 45200 | EZ29: 44200 | FA29: 30700 | FB29: 0
A30: EPS | B30: 0.53 | C30: 0.86 | D30: 0.88 | E30: 0.77 | F30: 0.5 | G30: 0.66 | H30: 0.56 | I30: 0.74 | J30: 0.45 | K30: 0.71 | L30: 0.59 | M30: 0.72 | N30: 0.46 | O30: 0.65 | P30: 0.44 | Q30: 0.64 | R30: 0.55 | S30: 0.57 | T30: 0.61 | U30: 0.52 | V30: 0.34 | W30: 0.4 | X30: 0.41 | Y30: 0.64 | Z30: 0.47 | AA30: 0.6 | AB30: 0.61 | AC30: 0.39 | AD30: 0.2 | AE30: 0.44 | AF30: 0.54 | AG30: 0.32 | AH30: -0.63 | AI30: 0.33 | AJ30: 0.32 | AK30: 0.27 | AL30: 0.12 | AM30: 0.24 | AN30: 0.79 | AO30: 0.34 | AP30: 0.28 | AQ30: 0.33 | AR30: 0.71 | AS30: 0.35 | AT30: 0.18 | AU30: 0.48 | AV30: 0.58 | AW30: 0.36 | AX30: 0.38 | AY30: 0.54 | AZ30: 0.59 | BA30: 0.39 | BB30: 0.41 | BC30: 0.5 | BD30: 0.61 | BE30: 0.45 | BF30: 0.36 | BG30: 0.48 | BH30: 0.6 | BI30: 0.41 | BJ30: 1.235 | BK30: 0.44 | BL30: 0.51 | BM30: 0.345 | BN30: 0.33 | BO30: 0.405 | BP30: 0.44 | BQ30: 0.29 | BR30: 0.215 | BS30: 0.405 | BT30: 0.305 | BU30: 0.32 | BV30: 0.26 | BW30: 0.355 | BX30: 0.4 | BY30: 0.27 | BZ30: 0.145 | CA30: 0.31 | CB30: 0.39 | CC30: 0.235 | CD30: 0.18 | CE30: 0.27 | CF30: 0.36 | CG30: 0.21 | CH30: 0.25 | CI30: 0.195 | CJ30: 0.325 | CK30: 0.23 | CL30: 0.19 | CM30: 0.25 | CN30: 0.275 | CO30: 0.17 | CP30: 0.19 | CQ30: 0.22 | CR30: 0.245 | CS30: -0.04 | CT30: 0.185 | CU30: 0.215 | CV30: 0.225 | CW30: 0.175 | CX30: 0.05 | CY30: 0.215 | CZ30: 0.185 | DA30: -0.01 | DB30: -0.01 | DC30: 0.16 | DD30: 0.19 | DE30: 0.15 | DF30: 0.12 | DG30: 0.18 | DH30: 0.24 | DI30: 0.17 | DJ30: 0.165 | DK30: 0.205 | DL30: 0.265 | DM30: 0.2 | DN30: 0.155 | DO30: 0.195 | DP30: 0.21 | DQ30: 0.1425 | DR30: 0.13 | DS30: 0.16 | DT30: 0.175 | DU30: 0.125 | DV30: 0.11 | DW30: 0.1375 | DX30: 0.1475 | DY30: 0.1 | DZ30: 0.09 | EA30: 0.11 | EB30: 0.13 | EC30: 0.085 | ED30: 0.075 | EE30: 0.1025 | EF30: 0.1075 | EG30: 0.0325 | EH30: 0.0337 | EI30: 0.0858 | EJ30: 0.0905 | EK30: 0.0601 | EL30: 0.0551 | EM30: 0.0738 | EN30: 0.0768 | EO30: 0.0531 | EP30: 0.1404 | EQ30: 0.0662 | ER30: 0.0624 | ES30: 0.0464 | ET30: 0.0415 | EU30: 0 | EV30: 51800 | EW30: 356200 | EX30: 32400 | EY30: 45200 | EZ30: 44200 | FA30: 30700 | FB30: 0

Sheet Lookup
C4: Year: | D4: Account: | F4: TICKER | G4: ASOF_DATE | H4: YR | I4: QRT_NUM | J4: Revenue | K4: Cost Of Goods Sold | L4: Gross Profit | M4: SG&A Expenses | N4: Other Operating Income Or Expenses | O4: Operating Expenses | P4: Operating Income | Q4: Total Non-Operating Income/Expense | R4: Pre-Tax Income | S4: Income Taxes | T4: Income After Taxes | U4: Other Income | V4: Income From Continuous Operations | W4: Income From Discontinued Operations | X4: Net Income | Y4: EBITDA | Z4: EBIT | AA4: Basic Shares Outstanding | AB4: Shares Outstanding | AC4: Basic EPS | AD4: EPS
C5: 2024 | D5: Revenue | F5: KO | G5: =TODAY() -> 46088 | H5: 2025 | I5: Q4 | J5: {=INDEX(Raw!B:FB, MATCH(J$4, Raw!$A:$A, 0), MATCH(1, (Raw!$B$1:$FB$1=$I5)*(Raw!$B$2:$FB$2=$H5), 0))} -> 11822000000 | K5: {=INDEX(Raw!C:FC, MATCH(K$4, Raw!$A:$A, 0), MATCH(1, (Raw!$B$1:$FB$1=$I5)*(Raw!$B$2:$FB$2=$H5), 0))} -> 4797000000 | L5: {=INDEX(Raw!D:FD, MATCH(L$4, Raw!$A:$A, 0), MATCH(1, (Raw!$B$1:$FB$1=$I5)*(Raw!$B$2:$FB$2=$H5), 0))} -> 7821000000 | M5: {=INDEX(Raw!E:FE, MATCH(M$4, Raw!$A:$A, 0), MATCH(1, (Raw!$B$1:$FB$1=$I5)*(Raw!$B$2:$FB$2=$H5), 0))} -> 3234000000 | N5: {=INDEX(Raw!F:FF, MATCH(N$4, Raw!$A:$A, 0), MATCH(1, (Raw!$B$1:$FB$1=$I5)*(Raw!$B$2:$FB$2=$H5), 0))} -> -176000000 | O5: {=INDEX(Raw!G:FG, MATCH(O$4, Raw!$A:$A, 0), MATCH(1, (Raw!$B$1:$FB$1=$I5)*(Raw!$B$2:$FB$2=$H5), 0))} -> 4680000000 | P5: {=INDEX(Raw!H:FH, MATCH(P$4, Raw!$A:$A, 0), MATCH(1, (Raw!$B$1:$FB$1=$I5)*(Raw!$B$2:$FB$2=$H5), 0))} -> 2632000000 | Q5: {=INDEX(Raw!I:FI, MATCH(Q$4, Raw!$A:$A, 0), MATCH(1, (Raw!$B$1:$FB$1=$I5)*(Raw!$B$2:$FB$2=$H5), 0))} -> 1731000000 | R5: {=INDEX(Raw!J:FJ, MATCH(R$4, Raw!$A:$A, 0), MATCH(1, (Raw!$B$1:$FB$1=$I5)*(Raw!$B$2:$FB$2=$H5), 0))} -> 2482000000 | S5: {=INDEX(Raw!K:FK, MATCH(S$4, Raw!$A:$A, 0), MATCH(1, (Raw!$B$1:$FB$1=$I5)*(Raw!$B$2:$FB$2=$H5), 0))} -> 454000000 | T5: {=INDEX(Raw!L:FL, MATCH(T$4, Raw!$A:$A, 0), MATCH(1, (Raw!$B$1:$FB$1=$I5)*(Raw!$B$2:$FB$2=$H5), 0))} -> 2521000000 | U5: {=INDEX(Raw!M:FM, MATCH(U$4, Raw!$A:$A, 0), MATCH(1, (Raw!$B$1:$FB$1=$I5)*(Raw!$B$2:$FB$2=$H5), 0))} -> 0 | V5: {=INDEX(Raw!N:FN, MATCH(V$4, Raw!$A:$A, 0), MATCH(1, (Raw!$B$1:$FB$1=$I5)*(Raw!$B$2:$FB$2=$H5), 0))} -> 2056000000 | W5: {=INDEX(Raw!O:FO, MATCH(W$4, Raw!$A:$A, 0), MATCH(1, (Raw!$B$1:$FB$1=$I5)*(Raw!$B$2:$FB$2=$H5), 0))} -> 0 | X5: {=INDEX(Raw!P:FP, MATCH(X$4, Raw!$A:$A, 0), MATCH(1, (Raw!$B$1:$FB$1=$I5)*(Raw!$B$2:$FB$2=$H5), 0))} -> 1905000000 | Y5: {=INDEX(Raw!Q:FQ, MATCH(Y$4, Raw!$A:$A, 0), MATCH(1, (Raw!$B$1:$FB$1=$I5)*(Raw!$B$2:$FB$2=$H5), 0))} -> 770956100 | Z5: {=INDEX(Raw!R:FR, MATCH(Z$4, Raw!$A:$A, 0), MATCH(1, (Raw!$B$1:$FB$1=$I5)*(Raw!$B$2:$FB$2=$H5), 0))} -> 836534200 | AA5: {=INDEX(Raw!S:FS, MATCH(AA$4, Raw!$A:$A, 0), MATCH(1, (Raw!$B$1:$FB$1=$I5)*(Raw!$B$2:$FB$2=$H5), 0))} -> 5307288000 | AB5: {=INDEX(Raw!T:FT, MATCH(AB$4, Raw!$A:$A, 0), MATCH(1, (Raw!$B$1:$FB$1=$I5)*(Raw!$B$2:$FB$2=$H5), 0))} -> 10631680000 | AC5: {=INDEX(Raw!U:FU, MATCH(AC$4, Raw!$A:$A, 0), MATCH(1, (Raw!$B$1:$FB$1=$I5)*(Raw!$B$2:$FB$2=$H5), 0))} -> 0.52 | AD5: {=INDEX(Raw!V:FV, MATCH(AD$4, Raw!$A:$A, 0), MATCH(1, (Raw!$B$1:$FB$1=$I5)*(Raw!$B$2:$FB$2=$H5), 0))} -> 0.34
F6: KO | G6: =TODAY() -> 46088 | H6: 2025 | I6: Q3 | J6: {=INDEX(Raw!B:FB, MATCH(J$4, Raw!$A:$A, 0), MATCH(1, (Raw!$B$1:$FB$1=$I6)*(Raw!$B$2:$FB$2=$H6), 0))} -> 12455000000 | K6: {=INDEX(Raw!C:FC, MATCH(K$4, Raw!$A:$A, 0), MATCH(1, (Raw!$B$1:$FB$1=$I6)*(Raw!$B$2:$FB$2=$H6), 0))} -> 4714000000 | L6: {=INDEX(Raw!D:FD, MATCH(L$4, Raw!$A:$A, 0), MATCH(1, (Raw!$B$1:$FB$1=$I6)*(Raw!$B$2:$FB$2=$H6), 0))} -> 6966000000 | M6: {=INDEX(Raw!E:FE, MATCH(M$4, Raw!$A:$A, 0), MATCH(1, (Raw!$B$1:$FB$1=$I6)*(Raw!$B$2:$FB$2=$H6), 0))} -> 4046000000 | N6: {=INDEX(Raw!F:FF, MATCH(N$4, Raw!$A:$A, 0), MATCH(1, (Raw!$B$1:$FB$1=$I6)*(Raw!$B$2:$FB$2=$H6), 0))} -> -1044000000 | O6: {=INDEX(Raw!G:FG, MATCH(O$4, Raw!$A:$A, 0), MATCH(1, (Raw!$B$1:$FB$1=$I6)*(Raw!$B$2:$FB$2=$H6), 0))} -> 4919000000 | P6: {=INDEX(Raw!H:FH, MATCH(P$4, Raw!$A:$A, 0), MATCH(1, (Raw!$B$1:$FB$1=$I6)*(Raw!$B$2:$FB$2=$H6), 0))} -> 2141000000 | Q6: {=INDEX(Raw!I:FI, MATCH(Q$4, Raw!$A:$A, 0), MATCH(1, (Raw!$B$1:$FB$1=$I6)*(Raw!$B$2:$FB$2=$H6), 0))} -> 209000000 | R6: {=INDEX(Raw!J:FJ, MATCH(R$4, Raw!$A:$A, 0), MATCH(1, (Raw!$B$1:$FB$1=$I6)*(Raw!$B$2:$FB$2=$H6), 0))} -> 3537000000 | S6: {=INDEX(Raw!K:FK, MATCH(S$4, Raw!$A:$A, 0), MATCH(1, (Raw!$B$1:$FB$1=$I6)*(Raw!$B$2:$FB$2=$H6), 0))} -> 359000000 | T6: {=INDEX(Raw!L:FL, MATCH(T$4, Raw!$A:$A, 0), MATCH(1, (Raw!$B$1:$FB$1=$I6)*(Raw!$B$2:$FB$2=$H6), 0))} -> 3113000000 | U6: {=INDEX(Raw!M:FM, MATCH(U$4, Raw!$A:$A, 0), MATCH(1, (Raw!$B$1:$FB$1=$I6)*(Raw!$B$2:$FB$2=$H6), 0))} -> 0 | V6: {=INDEX(Raw!N:FN, MATCH(V$4, Raw!$A:$A, 0), MATCH(1, (Raw!$B$1:$FB$1=$I6)*(Raw!$B$2:$FB$2=$H6), 0))} -> 2822000000 | W6: {=INDEX(Raw!O:FO, MATCH(W$4, Raw!$A:$A, 0), MATCH(1, (Raw!$B$1:$FB$1=$I6)*(Raw!$B$2:$FB$2=$H6), 0))} -> 0 | X6: {=INDEX(Raw!P:FP, MATCH(X$4, Raw!$A:$A, 0), MATCH(1, (Raw!$B$1:$FB$1=$I6)*(Raw!$B$2:$FB$2=$H6), 0))} -> 2781000000 | Y6: {=INDEX(Raw!Q:FQ, MATCH(Y$4, Raw!$A:$A, 0), MATCH(1, (Raw!$B$1:$FB$1=$I6)*(Raw!$B$2:$FB$2=$H6), 0))} -> 836534200 | Z6: {=INDEX(Raw!R:FR, MATCH(Z$4, Raw!$A:$A, 0), MATCH(1, (Raw!$B$1:$FB$1=$I6)*(Raw!$B$2:$FB$2=$H6), 0))} -> 579484900 | AA6: {=INDEX(Raw!S:FS, MATCH(AA$4, Raw!$A:$A, 0), MATCH(1, (Raw!$B$1:$FB$1=$I6)*(Raw!$B$2:$FB$2=$H6), 0))} -> 5315840000 | AB6: {=INDEX(Raw!T:FT, MATCH(AB$4, Raw!$A:$A, 0), MATCH(1, (Raw!$B$1:$FB$1=$I6)*(Raw!$B$2:$FB$2=$H6), 0))} -> 5321094000 | AC6: {=INDEX(Raw!U:FU, MATCH(AC$4, Raw!$A:$A, 0), MATCH(1, (Raw!$B$1:$FB$1=$I6)*(Raw!$B$2:$FB$2=$H6), 0))} -> 0.34 | AD6: {=INDEX(Raw!V:FV, MATCH(AD$4, Raw!$A:$A, 0), MATCH(1, (Raw!$B$1:$FB$1=$I6)*(Raw!$B$2:$FB$2=$H6), 0))} -> 0.4
F7: KO | G7: =TODAY() -> 46088 | H7: 2025 | I7: Q2 | J7: {=INDEX(Raw!B:FB, MATCH(J$4, Raw!$A:$A, 0), MATCH(1, (Raw!$B$1:$FB$1=$I7)*(Raw!$B$2:$FB$2=$H7), 0))} -> 12535000000 | K7: {=INDEX(Raw!C:FC, MATCH(K$4, Raw!$A:$A, 0), MATCH(1, (Raw!$B$1:$FB$1=$I7)*(Raw!$B$2:$FB$2=$H7), 0))} -> 4163000000 | L7: {=INDEX(Raw!D:FD, MATCH(L$4, Raw!$A:$A, 0), MATCH(1, (Raw!$B$1:$FB$1=$I7)*(Raw!$B$2:$FB$2=$H7), 0))} -> 6931000000 | M7: {=INDEX(Raw!E:FE, MATCH(M$4, Raw!$A:$A, 0), MATCH(1, (Raw!$B$1:$FB$1=$I7)*(Raw!$B$2:$FB$2=$H7), 0))} -> 3636000000 | N7: {=INDEX(Raw!F:FF, MATCH(N$4, Raw!$A:$A, 0), MATCH(1, (Raw!$B$1:$FB$1=$I7)*(Raw!$B$2:$FB$2=$H7), 0))} -> -1370000000 | O7: {=INDEX(Raw!G:FG, MATCH(O$4, Raw!$A:$A, 0), MATCH(1, (Raw!$B$1:$FB$1=$I7)*(Raw!$B$2:$FB$2=$H7), 0))} -> 4924000000 | P7: {=INDEX(Raw!H:FH, MATCH(P$4, Raw!$A:$A, 0), MATCH(1, (Raw!$B$1:$FB$1=$I7)*(Raw!$B$2:$FB$2=$H7), 0))} -> 2273000000 | Q7: {=INDEX(Raw!I:FI, MATCH(Q$4, Raw!$A:$A, 0), MATCH(1, (Raw!$B$1:$FB$1=$I7)*(Raw!$B$2:$FB$2=$H7), 0))} -> 267000000 | R7: {=INDEX(Raw!J:FJ, MATCH(R$4, Raw!$A:$A, 0), MATCH(1, (Raw!$B$1:$FB$1=$I7)*(Raw!$B$2:$FB$2=$H7), 0))} -> 2880000000 | S7: {=INDEX(Raw!K:FK, MATCH(S$4, Raw!$A:$A, 0), MATCH(1, (Raw!$B$1:$FB$1=$I7)*(Raw!$B$2:$FB$2=$H7), 0))} -> 940000000 | T7: {=INDEX(Raw!L:FL, MATCH(T$4, Raw!$A:$A, 0), MATCH(1, (Raw!$B$1:$FB$1=$I7)*(Raw!$B$2:$FB$2=$H7), 0))} -> 2056000000 | U7: {=INDEX(Raw!M:FM, MATCH(U$4, Raw!$A:$A, 0), MATCH(1, (Raw!$B$1:$FB$1=$I7)*(Raw!$B$2:$FB$2=$H7), 0))} -> 0 | V7: {=INDEX(Raw!N:FN, MATCH(V$4, Raw!$A:$A, 0), MATCH(1, (Raw!$B$1:$FB$1=$I7)*(Raw!$B$2:$FB$2=$H7), 0))} -> 1900000000 | W7: {=INDEX(Raw!O:FO, MATCH(W$4, Raw!$A:$A, 0), MATCH(1, (Raw!$B$1:$FB$1=$I7)*(Raw!$B$2:$FB$2=$H7), 0))} -> 0 | X7: {=INDEX(Raw!P:FP, MATCH(X$4, Raw!$A:$A, 0), MATCH(1, (Raw!$B$1:$FB$1=$I7)*(Raw!$B$2:$FB$2=$H7), 0))} -> 2414000000 | Y7: {=INDEX(Raw!Q:FQ, MATCH(Y$4, Raw!$A:$A, 0), MATCH(1, (Raw!$B$1:$FB$1=$I7)*(Raw!$B$2:$FB$2=$H7), 0))} -> 579484900 | Z7: {=INDEX(Raw!R:FR, MATCH(Z$4, Raw!$A:$A, 0), MATCH(1, (Raw!$B$1:$FB$1=$I7)*(Raw!$B$2:$FB$2=$H7), 0))} -> 487078100 | AA7: {=INDEX(Raw!S:FS, MATCH(AA$4, Raw!$A:$A, 0), MATCH(1, (Raw!$B$1:$FB$1=$I7)*(Raw!$B$2:$FB$2=$H7), 0))} -> 5321094000 | AB7: {=INDEX(Raw!T:FT, MATCH(AB$4, Raw!$A:$A, 0), MATCH(1, (Raw!$B$1:$FB$1=$I7)*(Raw!$B$2:$FB$2=$H7), 0))} -> 5331362000 | AC7: {=INDEX(Raw!U:FU, MATCH(AC$4, Raw!$A:$A, 0), MATCH(1, (Raw!$B$1:$FB$1=$I7)*(Raw!$B$2:$FB$2=$H7), 0))} -> 0.4 | AD7: {=INDEX(Raw!V:FV, MATCH(AD$4, Raw!$A:$A, 0), MATCH(1, (Raw!$B$1:$FB$1=$I7)*(Raw!$B$2:$FB$2=$H7), 0))} -> 0.41
F8: KO | G8: =TODAY() -> 46088 | H8: 2025 | I8: Q1 | J8: {=INDEX(Raw!B:FB, MATCH(J$4, Raw!$A:$A, 0), MATCH(1, (Raw!$B$1:$FB$1=$I8)*(Raw!$B$2:$FB$2=$H8), 0))} -> 11129000000 | K8: {=INDEX(Raw!C:FC, MATCH(K$4, Raw!$A:$A, 0), MATCH(1, (Raw!$B$1:$FB$1=$I8)*(Raw!$B$2:$FB$2=$H8), 0))} -> 4613000000 | L8: {=INDEX(Raw!D:FD, MATCH(L$4, Raw!$A:$A, 0), MATCH(1, (Raw!$B$1:$FB$1=$I8)*(Raw!$B$2:$FB$2=$H8), 0))} -> 7190000000 | M8: {=INDEX(Raw!E:FE, MATCH(M$4, Raw!$A:$A, 0), MATCH(1, (Raw!$B$1:$FB$1=$I8)*(Raw!$B$2:$FB$2=$H8), 0))} -> 3549000000 | N8: {=INDEX(Raw!F:FF, MATCH(N$4, Raw!$A:$A, 0), MATCH(1, (Raw!$B$1:$FB$1=$I8)*(Raw!$B$2:$FB$2=$H8), 0))} -> -1573000000 | O8: {=INDEX(Raw!G:FG, MATCH(O$4, Raw!$A:$A, 0), MATCH(1, (Raw!$B$1:$FB$1=$I8)*(Raw!$B$2:$FB$2=$H8), 0))} -> 3942000000 | P8: {=INDEX(Raw!H:FH, MATCH(P$4, Raw!$A:$A, 0), MATCH(1, (Raw!$B$1:$FB$1=$I8)*(Raw!$B$2:$FB$2=$H8), 0))} -> 3270000000 | Q8: {=INDEX(Raw!I:FI, MATCH(Q$4, Raw!$A:$A, 0), MATCH(1, (Raw!$B$1:$FB$1=$I8)*(Raw!$B$2:$FB$2=$H8), 0))} -> 479000000 | R8: {=INDEX(Raw!J:FJ, MATCH(R$4, Raw!$A:$A, 0), MATCH(1, (Raw!$B$1:$FB$1=$I8)*(Raw!$B$2:$FB$2=$H8), 0))} -> 4053000000 | S8: {=INDEX(Raw!K:FK, MATCH(S$4, Raw!$A:$A, 0), MATCH(1, (Raw!$B$1:$FB$1=$I8)*(Raw!$B$2:$FB$2=$H8), 0))} -> 444000000 | T8: {=INDEX(Raw!L:FL, MATCH(T$4, Raw!$A:$A, 0), MATCH(1, (Raw!$B$1:$FB$1=$I8)*(Raw!$B$2:$FB$2=$H8), 0))} -> 2822000000 | U8: {=INDEX(Raw!M:FM, MATCH(U$4, Raw!$A:$A, 0), MATCH(1, (Raw!$B$1:$FB$1=$I8)*(Raw!$B$2:$FB$2=$H8), 0))} -> 0 | V8: {=INDEX(Raw!N:FN, MATCH(V$4, Raw!$A:$A, 0), MATCH(1, (Raw!$B$1:$FB$1=$I8)*(Raw!$B$2:$FB$2=$H8), 0))} -> 2793000000 | W8: {=INDEX(Raw!O:FO, MATCH(W$4, Raw!$A:$A, 0), MATCH(1, (Raw!$B$1:$FB$1=$I8)*(Raw!$B$2:$FB$2=$H8), 0))} -> 0 | X8: {=INDEX(Raw!P:FP, MATCH(X$4, Raw!$A:$A, 0), MATCH(1, (Raw!$B$1:$FB$1=$I8)*(Raw!$B$2:$FB$2=$H8), 0))} -> 2471000000 | Y8: {=INDEX(Raw!Q:FQ, MATCH(Y$4, Raw!$A:$A, 0), MATCH(1, (Raw!$B$1:$FB$1=$I8)*(Raw!$B$2:$FB$2=$H8), 0))} -> 487078100 | Z8: {=INDEX(Raw!R:FR, MATCH(Z$4, Raw!$A:$A, 0), MATCH(1, (Raw!$B$1:$FB$1=$I8)*(Raw!$B$2:$FB$2=$H8), 0))} -> 644703900 | AA8: {=INDEX(Raw!S:FS, MATCH(AA$4, Raw!$A:$A, 0), MATCH(1, (Raw!$B$1:$FB$1=$I8)*(Raw!$B$2:$FB$2=$H8), 0))} -> 5331362000 | AB8: {=INDEX(Raw!T:FT, MATCH(AB$4, Raw!$A:$A, 0), MATCH(1, (Raw!$B$1:$FB$1=$I8)*(Raw!$B$2:$FB$2=$H8), 0))} -> 5335388000 | AC8: {=INDEX(Raw!U:FU, MATCH(AC$4, Raw!$A:$A, 0), MATCH(1, (Raw!$B$1:$FB$1=$I8)*(Raw!$B$2:$FB$2=$H8), 0))} -> 0.41 | AD8: {=INDEX(Raw!V:FV, MATCH(AD$4, Raw!$A:$A, 0), MATCH(1, (Raw!$B$1:$FB$1=$I8)*(Raw!$B$2:$FB$2=$H8), 0))} -> 0.64
F9: KO | G9: =TODAY() -> 46088 | H9: =$C$5 -> 2024 | I9: Q4 | J9: {=INDEX(Raw!B:FB, MATCH(J$4, Raw!$A:$A, 0), MATCH(1, (Raw!$B$1:$FB$1=$I9)*(Raw!$B$2:$FB$2=$H9), 0))} -> 11544000000 | K9: {=INDEX(Raw!C:FC, MATCH(K$4, Raw!$A:$A, 0), MATCH(1, (Raw!$B$1:$FB$1=$I9)*(Raw!$B$2:$FB$2=$H9), 0))} -> 4664000000 | L9: {=INDEX(Raw!D:FD, MATCH(L$4, Raw!$A:$A, 0), MATCH(1, (Raw!$B$1:$FB$1=$I9)*(Raw!$B$2:$FB$2=$H9), 0))} -> 7551000000 | M9: {=INDEX(Raw!E:FE, MATCH(M$4, Raw!$A:$A, 0), MATCH(1, (Raw!$B$1:$FB$1=$I9)*(Raw!$B$2:$FB$2=$H9), 0))} -> 3351000000 | N9: {=INDEX(Raw!F:FF, MATCH(N$4, Raw!$A:$A, 0), MATCH(1, (Raw!$B$1:$FB$1=$I9)*(Raw!$B$2:$FB$2=$H9), 0))} -> -143000000 | O9: {=INDEX(Raw!G:FG, MATCH(O$4, Raw!$A:$A, 0), MATCH(1, (Raw!$B$1:$FB$1=$I9)*(Raw!$B$2:$FB$2=$H9), 0))} -> 4026000000 | P9: {=INDEX(Raw!H:FH, MATCH(P$4, Raw!$A:$A, 0), MATCH(1, (Raw!$B$1:$FB$1=$I9)*(Raw!$B$2:$FB$2=$H9), 0))} -> 2401000000 | Q9: {=INDEX(Raw!I:FI, MATCH(Q$4, Raw!$A:$A, 0), MATCH(1, (Raw!$B$1:$FB$1=$I9)*(Raw!$B$2:$FB$2=$H9), 0))} -> 686000000 | R9: {=INDEX(Raw!J:FJ, MATCH(R$4, Raw!$A:$A, 0), MATCH(1, (Raw!$B$1:$FB$1=$I9)*(Raw!$B$2:$FB$2=$H9), 0))} -> 2500000000 | S9: {=INDEX(Raw!K:FK, MATCH(S$4, Raw!$A:$A, 0), MATCH(1, (Raw!$B$1:$FB$1=$I9)*(Raw!$B$2:$FB$2=$H9), 0))} -> 622000000 | T9: {=INDEX(Raw!L:FL, MATCH(T$4, Raw!$A:$A, 0), MATCH(1, (Raw!$B$1:$FB$1=$I9)*(Raw!$B$2:$FB$2=$H9), 0))} -> 1900000000 | U9: {=INDEX(Raw!M:FM, MATCH(U$4, Raw!$A:$A, 0), MATCH(1, (Raw!$B$1:$FB$1=$I9)*(Raw!$B$2:$FB$2=$H9), 0))} -> 0 | V9: {=INDEX(Raw!N:FN, MATCH(V$4, Raw!$A:$A, 0), MATCH(1, (Raw!$B$1:$FB$1=$I9)*(Raw!$B$2:$FB$2=$H9), 0))} -> 2450000000 | W9: {=INDEX(Raw!O:FO, MATCH(W$4, Raw!$A:$A, 0), MATCH(1, (Raw!$B$1:$FB$1=$I9)*(Raw!$B$2:$FB$2=$H9), 0))} -> 0 | X9: {=INDEX(Raw!P:FP, MATCH(X$4, Raw!$A:$A, 0), MATCH(1, (Raw!$B$1:$FB$1=$I9)*(Raw!$B$2:$FB$2=$H9), 0))} -> 2641000000 | Y9: {=INDEX(Raw!Q:FQ, MATCH(Y$4, Raw!$A:$A, 0), MATCH(1, (Raw!$B$1:$FB$1=$I9)*(Raw!$B$2:$FB$2=$H9), 0))} -> 644703900 | Z9: {=INDEX(Raw!R:FR, MATCH(Z$4, Raw!$A:$A, 0), MATCH(1, (Raw!$B$1:$FB$1=$I9)*(Raw!$B$2:$FB$2=$H9), 0))} -> 693266800 | AA9: {=INDEX(Raw!S:FS, MATCH(AA$4, Raw!$A:$A, 0), MATCH(1, (Raw!$B$1:$FB$1=$I9)*(Raw!$B$2:$FB$2=$H9), 0))} -> 5335388000 | AB9: {=INDEX(Raw!T:FT, MATCH(AB$4, Raw!$A:$A, 0), MATCH(1, (Raw!$B$1:$FB$1=$I9)*(Raw!$B$2:$FB$2=$H9), 0))} -> 5345914000 | AC9: {=INDEX(Raw!U:FU, MATCH(AC$4, Raw!$A:$A, 0), MATCH(1, (Raw!$B$1:$FB$1=$I9)*(Raw!$B$2:$FB$2=$H9), 0))} -> 0.65 | AD9: {=INDEX(Raw!V:FV, MATCH(AD$4, Raw!$A:$A, 0), MATCH(1, (Raw!$B$1:$FB$1=$I9)*(Raw!$B$2:$FB$2=$H9), 0))} -> 0.47
F10: KO | G10: =TODAY() -> 46088 | H10: =H9 -> 2024 | I10: Q3 | J10: {=INDEX(Raw!B:FB, MATCH(J$4, Raw!$A:$A, 0), MATCH(1, (Raw!$B$1:$FB$1=$I10)*(Raw!$B$2:$FB$2=$H10), 0))} -> 11854000000 | K10: {=INDEX(Raw!C:FC, MATCH(K$4, Raw!$A:$A, 0), MATCH(1, (Raw!$B$1:$FB$1=$I10)*(Raw!$B$2:$FB$2=$H10), 0))} -> 4812000000 | L10: {=INDEX(Raw!D:FD, MATCH(L$4, Raw!$A:$A, 0), MATCH(1, (Raw!$B$1:$FB$1=$I10)*(Raw!$B$2:$FB$2=$H10), 0))} -> 7065000000 | M10: {=INDEX(Raw!E:FE, MATCH(M$4, Raw!$A:$A, 0), MATCH(1, (Raw!$B$1:$FB$1=$I10)*(Raw!$B$2:$FB$2=$H10), 0))} -> 3799000000 | N10: {=INDEX(Raw!F:FF, MATCH(N$4, Raw!$A:$A, 0), MATCH(1, (Raw!$B$1:$FB$1=$I10)*(Raw!$B$2:$FB$2=$H10), 0))} -> -359000000 | O10: {=INDEX(Raw!G:FG, MATCH(O$4, Raw!$A:$A, 0), MATCH(1, (Raw!$B$1:$FB$1=$I10)*(Raw!$B$2:$FB$2=$H10), 0))} -> 4659000000 | P10: {=INDEX(Raw!H:FH, MATCH(P$4, Raw!$A:$A, 0), MATCH(1, (Raw!$B$1:$FB$1=$I10)*(Raw!$B$2:$FB$2=$H10), 0))} -> 3367000000 | Q10: {=INDEX(Raw!I:FI, MATCH(Q$4, Raw!$A:$A, 0), MATCH(1, (Raw!$B$1:$FB$1=$I10)*(Raw!$B$2:$FB$2=$H10), 0))} -> 425000000 | R10: {=INDEX(Raw!J:FJ, MATCH(R$4, Raw!$A:$A, 0), MATCH(1, (Raw!$B$1:$FB$1=$I10)*(Raw!$B$2:$FB$2=$H10), 0))} -> 3444000000 | S10: {=INDEX(Raw!K:FK, MATCH(S$4, Raw!$A:$A, 0), MATCH(1, (Raw!$B$1:$FB$1=$I10)*(Raw!$B$2:$FB$2=$H10), 0))} -> 384000000 | T10: {=INDEX(Raw!L:FL, MATCH(T$4, Raw!$A:$A, 0), MATCH(1, (Raw!$B$1:$FB$1=$I10)*(Raw!$B$2:$FB$2=$H10), 0))} -> 2793000000 | U10: {=INDEX(Raw!M:FM, MATCH(U$4, Raw!$A:$A, 0), MATCH(1, (Raw!$B$1:$FB$1=$I10)*(Raw!$B$2:$FB$2=$H10), 0))} -> 0 | V10: {=INDEX(Raw!N:FN, MATCH(V$4, Raw!$A:$A, 0), MATCH(1, (Raw!$B$1:$FB$1=$I10)*(Raw!$B$2:$FB$2=$H10), 0))} -> 2475000000 | W10: {=INDEX(Raw!O:FO, MATCH(W$4, Raw!$A:$A, 0), MATCH(1, (Raw!$B$1:$FB$1=$I10)*(Raw!$B$2:$FB$2=$H10), 0))} -> 0 | X10: {=INDEX(Raw!P:FP, MATCH(X$4, Raw!$A:$A, 0), MATCH(1, (Raw!$B$1:$FB$1=$I10)*(Raw!$B$2:$FB$2=$H10), 0))} -> 2245000000 | Y10: {=INDEX(Raw!Q:FQ, MATCH(Y$4, Raw!$A:$A, 0), MATCH(1, (Raw!$B$1:$FB$1=$I10)*(Raw!$B$2:$FB$2=$H10), 0))} -> 693266800 | Z10: {=INDEX(Raw!R:FR, MATCH(Z$4, Raw!$A:$A, 0), MATCH(1, (Raw!$B$1:$FB$1=$I10)*(Raw!$B$2:$FB$2=$H10), 0))} -> 493996100 | AA10: {=INDEX(Raw!S:FS, MATCH(AA$4, Raw!$A:$A, 0), MATCH(1, (Raw!$B$1:$FB$1=$I10)*(Raw!$B$2:$FB$2=$H10), 0))} -> 5345914000 | AB10: {=INDEX(Raw!T:FT, MATCH(AB$4, Raw!$A:$A, 0), MATCH(1, (Raw!$B$1:$FB$1=$I10)*(Raw!$B$2:$FB$2=$H10), 0))} -> 5341026000 | AC10: {=INDEX(Raw!U:FU, MATCH(AC$4, Raw!$A:$A, 0), MATCH(1, (Raw!$B$1:$FB$1=$I10)*(Raw!$B$2:$FB$2=$H10), 0))} -> 0.48 | AD10: {=INDEX(Raw!V:FV, MATCH(AD$4, Raw!$A:$A, 0), MATCH(1, (Raw!$B$1:$FB$1=$I10)*(Raw!$B$2:$FB$2=$H10), 0))} -> 0.6
F11: KO | G11: =TODAY() -> 46088 | H11: =H10 -> 2024 | I11: Q2 | J11: {=INDEX(Raw!B:FB, MATCH(J$4, Raw!$A:$A, 0), MATCH(1, (Raw!$B$1:$FB$1=$I11)*(Raw!$B$2:$FB$2=$H11), 0))} -> 12363000000 | K11: {=INDEX(Raw!C:FC, MATCH(K$4, Raw!$A:$A, 0), MATCH(1, (Raw!$B$1:$FB$1=$I11)*(Raw!$B$2:$FB$2=$H11), 0))} -> 4235000000 | L11: {=INDEX(Raw!D:FD, MATCH(L$4, Raw!$A:$A, 0), MATCH(1, (Raw!$B$1:$FB$1=$I11)*(Raw!$B$2:$FB$2=$H11), 0))} -> 6215000000 | M11: {=INDEX(Raw!E:FE, MATCH(M$4, Raw!$A:$A, 0), MATCH(1, (Raw!$B$1:$FB$1=$I11)*(Raw!$B$2:$FB$2=$H11), 0))} -> 3667000000 | N11: {=INDEX(Raw!F:FF, MATCH(N$4, Raw!$A:$A, 0), MATCH(1, (Raw!$B$1:$FB$1=$I11)*(Raw!$B$2:$FB$2=$H11), 0))} -> -1338000000 | O11: {=INDEX(Raw!G:FG, MATCH(O$4, Raw!$A:$A, 0), MATCH(1, (Raw!$B$1:$FB$1=$I11)*(Raw!$B$2:$FB$2=$H11), 0))} -> 3296000000 | P11: {=INDEX(Raw!H:FH, MATCH(P$4, Raw!$A:$A, 0), MATCH(1, (Raw!$B$1:$FB$1=$I11)*(Raw!$B$2:$FB$2=$H11), 0))} -> 2075000000 | Q11: {=INDEX(Raw!I:FI, MATCH(Q$4, Raw!$A:$A, 0), MATCH(1, (Raw!$B$1:$FB$1=$I11)*(Raw!$B$2:$FB$2=$H11), 0))} -> 356000000 | R11: {=INDEX(Raw!J:FJ, MATCH(R$4, Raw!$A:$A, 0), MATCH(1, (Raw!$B$1:$FB$1=$I11)*(Raw!$B$2:$FB$2=$H11), 0))} -> 2284000000 | S11: {=INDEX(Raw!K:FK, MATCH(S$4, Raw!$A:$A, 0), MATCH(1, (Raw!$B$1:$FB$1=$I11)*(Raw!$B$2:$FB$2=$H11), 0))} -> 665000000 | T11: {=INDEX(Raw!L:FL, MATCH(T$4, Raw!$A:$A, 0), MATCH(1, (Raw!$B$1:$FB$1=$I11)*(Raw!$B$2:$FB$2=$H11), 0))} -> 2450000000 | U11: {=INDEX(Raw!M:FM, MATCH(U$4, Raw!$A:$A, 0), MATCH(1, (Raw!$B$1:$FB$1=$I11)*(Raw!$B$2:$FB$2=$H11), 0))} -> 0 | V11: {=INDEX(Raw!N:FN, MATCH(V$4, Raw!$A:$A, 0), MATCH(1, (Raw!$B$1:$FB$1=$I11)*(Raw!$B$2:$FB$2=$H11), 0))} -> 2624000000 | W11: {=INDEX(Raw!O:FO, MATCH(W$4, Raw!$A:$A, 0), MATCH(1, (Raw!$B$1:$FB$1=$I11)*(Raw!$B$2:$FB$2=$H11), 0))} -> 0 | X11: {=INDEX(Raw!P:FP, MATCH(X$4, Raw!$A:$A, 0), MATCH(1, (Raw!$B$1:$FB$1=$I11)*(Raw!$B$2:$FB$2=$H11), 0))} -> 1456000000 | Y11: {=INDEX(Raw!Q:FQ, MATCH(Y$4, Raw!$A:$A, 0), MATCH(1, (Raw!$B$1:$FB$1=$I11)*(Raw!$B$2:$FB$2=$H11), 0))} -> 493996100 | Z11: {=INDEX(Raw!R:FR, MATCH(Z$4, Raw!$A:$A, 0), MATCH(1, (Raw!$B$1:$FB$1=$I11)*(Raw!$B$2:$FB$2=$H11), 0))} -> 421468000 | AA11: {=INDEX(Raw!S:FS, MATCH(AA$4, Raw!$A:$A, 0), MATCH(1, (Raw!$B$1:$FB$1=$I11)*(Raw!$B$2:$FB$2=$H11), 0))} -> 5341026000 | AB11: {=INDEX(Raw!T:FT, MATCH(AB$4, Raw!$A:$A, 0), MATCH(1, (Raw!$B$1:$FB$1=$I11)*(Raw!$B$2:$FB$2=$H11), 0))} -> 5339712000 | AC11: {=INDEX(Raw!U:FU, MATCH(AC$4, Raw!$A:$A, 0), MATCH(1, (Raw!$B$1:$FB$1=$I11)*(Raw!$B$2:$FB$2=$H11), 0))} -> 0.61 | AD11: {=INDEX(Raw!V:FV, MATCH(AD$4, Raw!$A:$A, 0), MATCH(1, (Raw!$B$1:$FB$1=$I11)*(Raw!$B$2:$FB$2=$H11), 0))} -> 0.61
F12: KO | G12: =TODAY() -> 46088 | H12: =H11 -> 2024 | I12: Q1 | J12: {=INDEX(Raw!B:FB, MATCH(J$4, Raw!$A:$A, 0), MATCH(1, (Raw!$B$1:$FB$1=$I12)*(Raw!$B$2:$FB$2=$H12), 0))} -> 11300000000 | K12: {=INDEX(Raw!C:FC, MATCH(K$4, Raw!$A:$A, 0), MATCH(1, (Raw!$B$1:$FB$1=$I12)*(Raw!$B$2:$FB$2=$H12), 0))} -> 4634000000 | L12: {=INDEX(Raw!D:FD, MATCH(L$4, Raw!$A:$A, 0), MATCH(1, (Raw!$B$1:$FB$1=$I12)*(Raw!$B$2:$FB$2=$H12), 0))} -> 7296000000 | M12: {=INDEX(Raw!E:FE, MATCH(M$4, Raw!$A:$A, 0), MATCH(1, (Raw!$B$1:$FB$1=$I12)*(Raw!$B$2:$FB$2=$H12), 0))} -> 3321000000 | N12: {=INDEX(Raw!F:FF, MATCH(N$4, Raw!$A:$A, 0), MATCH(1, (Raw!$B$1:$FB$1=$I12)*(Raw!$B$2:$FB$2=$H12), 0))} -> -111000000 | O12: {=INDEX(Raw!G:FG, MATCH(O$4, Raw!$A:$A, 0), MATCH(1, (Raw!$B$1:$FB$1=$I12)*(Raw!$B$2:$FB$2=$H12), 0))} -> 3537000000 | P12: {=INDEX(Raw!H:FH, MATCH(P$4, Raw!$A:$A, 0), MATCH(1, (Raw!$B$1:$FB$1=$I12)*(Raw!$B$2:$FB$2=$H12), 0))} -> 3088000000 | Q12: {=INDEX(Raw!I:FI, MATCH(Q$4, Raw!$A:$A, 0), MATCH(1, (Raw!$B$1:$FB$1=$I12)*(Raw!$B$2:$FB$2=$H12), 0))} -> -57000000 | R12: {=INDEX(Raw!J:FJ, MATCH(R$4, Raw!$A:$A, 0), MATCH(1, (Raw!$B$1:$FB$1=$I12)*(Raw!$B$2:$FB$2=$H12), 0))} -> 3458000000 | S12: {=INDEX(Raw!K:FK, MATCH(S$4, Raw!$A:$A, 0), MATCH(1, (Raw!$B$1:$FB$1=$I12)*(Raw!$B$2:$FB$2=$H12), 0))} -> 510000000 | T12: {=INDEX(Raw!L:FL, MATCH(T$4, Raw!$A:$A, 0), MATCH(1, (Raw!$B$1:$FB$1=$I12)*(Raw!$B$2:$FB$2=$H12), 0))} -> 2475000000 | U12: {=INDEX(Raw!M:FM, MATCH(U$4, Raw!$A:$A, 0), MATCH(1, (Raw!$B$1:$FB$1=$I12)*(Raw!$B$2:$FB$2=$H12), 0))} -> 0 | V12: {=INDEX(Raw!N:FN, MATCH(V$4, Raw!$A:$A, 0), MATCH(1, (Raw!$B$1:$FB$1=$I12)*(Raw!$B$2:$FB$2=$H12), 0))} -> 2255000000 | W12: {=INDEX(Raw!O:FO, MATCH(W$4, Raw!$A:$A, 0), MATCH(1, (Raw!$B$1:$FB$1=$I12)*(Raw!$B$2:$FB$2=$H12), 0))} -> 0 | X12: {=INDEX(Raw!P:FP, MATCH(X$4, Raw!$A:$A, 0), MATCH(1, (Raw!$B$1:$FB$1=$I12)*(Raw!$B$2:$FB$2=$H12), 0))} -> 1737000000 | Y12: {=INDEX(Raw!Q:FQ, MATCH(Y$4, Raw!$A:$A, 0), MATCH(1, (Raw!$B$1:$FB$1=$I12)*(Raw!$B$2:$FB$2=$H12), 0))} -> 421468000 | Z12: {=INDEX(Raw!R:FR, MATCH(Z$4, Raw!$A:$A, 0), MATCH(1, (Raw!$B$1:$FB$1=$I12)*(Raw!$B$2:$FB$2=$H12), 0))} -> 512429900 | AA12: {=INDEX(Raw!S:FS, MATCH(AA$4, Raw!$A:$A, 0), MATCH(1, (Raw!$B$1:$FB$1=$I12)*(Raw!$B$2:$FB$2=$H12), 0))} -> 5339712000 | AB12: {=INDEX(Raw!T:FT, MATCH(AB$4, Raw!$A:$A, 0), MATCH(1, (Raw!$B$1:$FB$1=$I12)*(Raw!$B$2:$FB$2=$H12), 0))} -> 5340552000 | AC12: {=INDEX(Raw!U:FU, MATCH(AC$4, Raw!$A:$A, 0), MATCH(1, (Raw!$B$1:$FB$1=$I12)*(Raw!$B$2:$FB$2=$H12), 0))} -> 0.61 | AD12: {=INDEX(Raw!V:FV, MATCH(AD$4, Raw!$A:$A, 0), MATCH(1, (Raw!$B$1:$FB$1=$I12)*(Raw!$B$2:$FB$2=$H12), 0))} -> 0.39
F13: KO | G13: =TODAY() -> 46088 | H13: =H9-1 -> 2023 | I13: Q4 | J13: {=INDEX(Raw!B:FB, MATCH(J$4, Raw!$A:$A, 0), MATCH(1, (Raw!$B$1:$FB$1=$I13)*(Raw!$B$2:$FB$2=$H13), 0))} -> 10849000000 | K13: {=INDEX(Raw!C:FC, MATCH(K$4, Raw!$A:$A, 0), MATCH(1, (Raw!$B$1:$FB$1=$I13)*(Raw!$B$2:$FB$2=$H13), 0))} -> 4657000000 | L13: {=INDEX(Raw!D:FD, MATCH(L$4, Raw!$A:$A, 0), MATCH(1, (Raw!$B$1:$FB$1=$I13)*(Raw!$B$2:$FB$2=$H13), 0))} -> 7060000000 | M13: {=INDEX(Raw!E:FE, MATCH(M$4, Raw!$A:$A, 0), MATCH(1, (Raw!$B$1:$FB$1=$I13)*(Raw!$B$2:$FB$2=$H13), 0))} -> 3185000000 | N13: {=INDEX(Raw!F:FF, MATCH(N$4, Raw!$A:$A, 0), MATCH(1, (Raw!$B$1:$FB$1=$I13)*(Raw!$B$2:$FB$2=$H13), 0))} -> -106000000 | O13: {=INDEX(Raw!G:FG, MATCH(O$4, Raw!$A:$A, 0), MATCH(1, (Raw!$B$1:$FB$1=$I13)*(Raw!$B$2:$FB$2=$H13), 0))} -> 3409000000 | P13: {=INDEX(Raw!H:FH, MATCH(P$4, Raw!$A:$A, 0), MATCH(1, (Raw!$B$1:$FB$1=$I13)*(Raw!$B$2:$FB$2=$H13), 0))} -> 2341000000 | Q13: {=INDEX(Raw!I:FI, MATCH(Q$4, Raw!$A:$A, 0), MATCH(1, (Raw!$B$1:$FB$1=$I13)*(Raw!$B$2:$FB$2=$H13), 0))} -> 53000000 | R13: {=INDEX(Raw!J:FJ, MATCH(R$4, Raw!$A:$A, 0), MATCH(1, (Raw!$B$1:$FB$1=$I13)*(Raw!$B$2:$FB$2=$H13), 0))} -> 2960000000 | S13: {=INDEX(Raw!K:FK, MATCH(S$4, Raw!$A:$A, 0), MATCH(1, (Raw!$B$1:$FB$1=$I13)*(Raw!$B$2:$FB$2=$H13), 0))} -> 609000000 | T13: {=INDEX(Raw!L:FL, MATCH(T$4, Raw!$A:$A, 0), MATCH(1, (Raw!$B$1:$FB$1=$I13)*(Raw!$B$2:$FB$2=$H13), 0))} -> 2624000000 | U13: {=INDEX(Raw!M:FM, MATCH(U$4, Raw!$A:$A, 0), MATCH(1, (Raw!$B$1:$FB$1=$I13)*(Raw!$B$2:$FB$2=$H13), 0))} -> 0 | V13: {=INDEX(Raw!N:FN, MATCH(V$4, Raw!$A:$A, 0), MATCH(1, (Raw!$B$1:$FB$1=$I13)*(Raw!$B$2:$FB$2=$H13), 0))} -> 1474000000 | W13: {=INDEX(Raw!O:FO, MATCH(W$4, Raw!$A:$A, 0), MATCH(1, (Raw!$B$1:$FB$1=$I13)*(Raw!$B$2:$FB$2=$H13), 0))} -> 0 | X13: {=INDEX(Raw!P:FP, MATCH(X$4, Raw!$A:$A, 0), MATCH(1, (Raw!$B$1:$FB$1=$I13)*(Raw!$B$2:$FB$2=$H13), 0))} -> 1779000000 | Y13: {=INDEX(Raw!Q:FQ, MATCH(Y$4, Raw!$A:$A, 0), MATCH(1, (Raw!$B$1:$FB$1=$I13)*(Raw!$B$2:$FB$2=$H13), 0))} -> 512429900 | Z13: {=INDEX(Raw!R:FR, MATCH(Z$4, Raw!$A:$A, 0), MATCH(1, (Raw!$B$1:$FB$1=$I13)*(Raw!$B$2:$FB$2=$H13), 0))} -> 579682100 | AA13: {=INDEX(Raw!S:FS, MATCH(AA$4, Raw!$A:$A, 0), MATCH(1, (Raw!$B$1:$FB$1=$I13)*(Raw!$B$2:$FB$2=$H13), 0))} -> 5340552000 | AB13: {=INDEX(Raw!T:FT, MATCH(AB$4, Raw!$A:$A, 0), MATCH(1, (Raw!$B$1:$FB$1=$I13)*(Raw!$B$2:$FB$2=$H13), 0))} -> 5392238000 | AC13: {=INDEX(Raw!U:FU, MATCH(AC$4, Raw!$A:$A, 0), MATCH(1, (Raw!$B$1:$FB$1=$I13)*(Raw!$B$2:$FB$2=$H13), 0))} -> 0.39 | AD13: {=INDEX(Raw!V:FV, MATCH(AD$4, Raw!$A:$A, 0), MATCH(1, (Raw!$B$1:$FB$1=$I13)*(Raw!$B$2:$FB$2=$H13), 0))} -> 0.2
F14: KO | G14: =TODAY() -> 46088 | H14: =H13 -> 2023 | I14: Q3 | J14: {=INDEX(Raw!B:FB, MATCH(J$4, Raw!$A:$A, 0), MATCH(1, (Raw!$B$1:$FB$1=$I14)*(Raw!$B$2:$FB$2=$H14), 0))} -> 11953000000 | K14: {=INDEX(Raw!C:FC, MATCH(K$4, Raw!$A:$A, 0), MATCH(1, (Raw!$B$1:$FB$1=$I14)*(Raw!$B$2:$FB$2=$H14), 0))} -> 4912000000 | L14: {=INDEX(Raw!D:FD, MATCH(L$4, Raw!$A:$A, 0), MATCH(1, (Raw!$B$1:$FB$1=$I14)*(Raw!$B$2:$FB$2=$H14), 0))} -> 6663000000 | M14: {=INDEX(Raw!E:FE, MATCH(M$4, Raw!$A:$A, 0), MATCH(1, (Raw!$B$1:$FB$1=$I14)*(Raw!$B$2:$FB$2=$H14), 0))} -> 3431000000 | N14: {=INDEX(Raw!F:FF, MATCH(N$4, Raw!$A:$A, 0), MATCH(1, (Raw!$B$1:$FB$1=$I14)*(Raw!$B$2:$FB$2=$H14), 0))} -> -130000000 | O14: {=INDEX(Raw!G:FG, MATCH(O$4, Raw!$A:$A, 0), MATCH(1, (Raw!$B$1:$FB$1=$I14)*(Raw!$B$2:$FB$2=$H14), 0))} -> 4154000000 | P14: {=INDEX(Raw!H:FH, MATCH(P$4, Raw!$A:$A, 0), MATCH(1, (Raw!$B$1:$FB$1=$I14)*(Raw!$B$2:$FB$2=$H14), 0))} -> 3405000000 | Q14: {=INDEX(Raw!I:FI, MATCH(Q$4, Raw!$A:$A, 0), MATCH(1, (Raw!$B$1:$FB$1=$I14)*(Raw!$B$2:$FB$2=$H14), 0))} -> 1288000000 | R14: {=INDEX(Raw!J:FJ, MATCH(R$4, Raw!$A:$A, 0), MATCH(1, (Raw!$B$1:$FB$1=$I14)*(Raw!$B$2:$FB$2=$H14), 0))} -> 3084000000 | S14: {=INDEX(Raw!K:FK, MATCH(S$4, Raw!$A:$A, 0), MATCH(1, (Raw!$B$1:$FB$1=$I14)*(Raw!$B$2:$FB$2=$H14), 0))} -> 994000000 | T14: {=INDEX(Raw!L:FL, MATCH(T$4, Raw!$A:$A, 0), MATCH(1, (Raw!$B$1:$FB$1=$I14)*(Raw!$B$2:$FB$2=$H14), 0))} -> 2255000000 | U14: {=INDEX(Raw!M:FM, MATCH(U$4, Raw!$A:$A, 0), MATCH(1, (Raw!$B$1:$FB$1=$I14)*(Raw!$B$2:$FB$2=$H14), 0))} -> 0 | V14: {=INDEX(Raw!N:FN, MATCH(V$4, Raw!$A:$A, 0), MATCH(1, (Raw!$B$1:$FB$1=$I14)*(Raw!$B$2:$FB$2=$H14), 0))} -> 1740000000 | W14: {=INDEX(Raw!O:FO, MATCH(W$4, Raw!$A:$A, 0), MATCH(1, (Raw!$B$1:$FB$1=$I14)*(Raw!$B$2:$FB$2=$H14), 0))} -> 0 | X14: {=INDEX(Raw!P:FP, MATCH(X$4, Raw!$A:$A, 0), MATCH(1, (Raw!$B$1:$FB$1=$I14)*(Raw!$B$2:$FB$2=$H14), 0))} -> 2775000000 | Y14: {=INDEX(Raw!Q:FQ, MATCH(Y$4, Raw!$A:$A, 0), MATCH(1, (Raw!$B$1:$FB$1=$I14)*(Raw!$B$2:$FB$2=$H14), 0))} -> 579682100 | Z14: {=INDEX(Raw!R:FR, MATCH(Z$4, Raw!$A:$A, 0), MATCH(1, (Raw!$B$1:$FB$1=$I14)*(Raw!$B$2:$FB$2=$H14), 0))} -> 437983200 | AA14: {=INDEX(Raw!S:FS, MATCH(AA$4, Raw!$A:$A, 0), MATCH(1, (Raw!$B$1:$FB$1=$I14)*(Raw!$B$2:$FB$2=$H14), 0))} -> 5392238000 | AB14: {=INDEX(Raw!T:FT, MATCH(AB$4, Raw!$A:$A, 0), MATCH(1, (Raw!$B$1:$FB$1=$I14)*(Raw!$B$2:$FB$2=$H14), 0))} -> 5461042000 | AC14: {=INDEX(Raw!U:FU, MATCH(AC$4, Raw!$A:$A, 0), MATCH(1, (Raw!$B$1:$FB$1=$I14)*(Raw!$B$2:$FB$2=$H14), 0))} -> 0.21 | AD14: {=INDEX(Raw!V:FV, MATCH(AD$4, Raw!$A:$A, 0), MATCH(1, (Raw!$B$1:$FB$1=$I14)*(Raw!$B$2:$FB$2=$H14), 0))} -> 0.44
F15: KO | G15: =TODAY() -> 46088 | H15: =H14 -> 2023 | I15: Q2 | J15: {=INDEX(Raw!B:FB, MATCH(J$4, Raw!$A:$A, 0), MATCH(1, (Raw!$B$1:$FB$1=$I15)*(Raw!$B$2:$FB$2=$H15), 0))} -> 11972000000 | K15: {=INDEX(Raw!C:FC, MATCH(K$4, Raw!$A:$A, 0), MATCH(1, (Raw!$B$1:$FB$1=$I15)*(Raw!$B$2:$FB$2=$H15), 0))} -> 4317000000 | L15: {=INDEX(Raw!D:FD, MATCH(L$4, Raw!$A:$A, 0), MATCH(1, (Raw!$B$1:$FB$1=$I15)*(Raw!$B$2:$FB$2=$H15), 0))} -> 5612000000 | M15: {=INDEX(Raw!E:FE, MATCH(M$4, Raw!$A:$A, 0), MATCH(1, (Raw!$B$1:$FB$1=$I15)*(Raw!$B$2:$FB$2=$H15), 0))} -> 3279000000 | N15: {=INDEX(Raw!F:FF, MATCH(N$4, Raw!$A:$A, 0), MATCH(1, (Raw!$B$1:$FB$1=$I15)*(Raw!$B$2:$FB$2=$H15), 0))} -> -951000000 | O15: {=INDEX(Raw!G:FG, MATCH(O$4, Raw!$A:$A, 0), MATCH(1, (Raw!$B$1:$FB$1=$I15)*(Raw!$B$2:$FB$2=$H15), 0))} -> 2995000000 | P15: {=INDEX(Raw!H:FH, MATCH(P$4, Raw!$A:$A, 0), MATCH(1, (Raw!$B$1:$FB$1=$I15)*(Raw!$B$2:$FB$2=$H15), 0))} -> 1672000000 | Q15: {=INDEX(Raw!I:FI, MATCH(Q$4, Raw!$A:$A, 0), MATCH(1, (Raw!$B$1:$FB$1=$I15)*(Raw!$B$2:$FB$2=$H15), 0))} -> 186000000 | R15: {=INDEX(Raw!J:FJ, MATCH(R$4, Raw!$A:$A, 0), MATCH(1, (Raw!$B$1:$FB$1=$I15)*(Raw!$B$2:$FB$2=$H15), 0))} -> 3618000000 | S15: {=INDEX(Raw!K:FK, MATCH(S$4, Raw!$A:$A, 0), MATCH(1, (Raw!$B$1:$FB$1=$I15)*(Raw!$B$2:$FB$2=$H15), 0))} -> 508000000 | T15: {=INDEX(Raw!L:FL, MATCH(T$4, Raw!$A:$A, 0), MATCH(1, (Raw!$B$1:$FB$1=$I15)*(Raw!$B$2:$FB$2=$H15), 0))} -> 1474000000 | U15: {=INDEX(Raw!M:FM, MATCH(U$4, Raw!$A:$A, 0), MATCH(1, (Raw!$B$1:$FB$1=$I15)*(Raw!$B$2:$FB$2=$H15), 0))} -> 0 | V15: {=INDEX(Raw!N:FN, MATCH(V$4, Raw!$A:$A, 0), MATCH(1, (Raw!$B$1:$FB$1=$I15)*(Raw!$B$2:$FB$2=$H15), 0))} -> 1759000000 | W15: {=INDEX(Raw!O:FO, MATCH(W$4, Raw!$A:$A, 0), MATCH(1, (Raw!$B$1:$FB$1=$I15)*(Raw!$B$2:$FB$2=$H15), 0))} -> 0 | X15: {=INDEX(Raw!P:FP, MATCH(X$4, Raw!$A:$A, 0), MATCH(1, (Raw!$B$1:$FB$1=$I15)*(Raw!$B$2:$FB$2=$H15), 0))} -> 2042000000 | Y15: {=INDEX(Raw!Q:FQ, MATCH(Y$4, Raw!$A:$A, 0), MATCH(1, (Raw!$B$1:$FB$1=$I15)*(Raw!$B$2:$FB$2=$H15), 0))} -> 437983200 | Z15: {=INDEX(Raw!R:FR, MATCH(Z$4, Raw!$A:$A, 0), MATCH(1, (Raw!$B$1:$FB$1=$I15)*(Raw!$B$2:$FB$2=$H15), 0))} -> 381755100 | AA15: {=INDEX(Raw!S:FS, MATCH(AA$4, Raw!$A:$A, 0), MATCH(1, (Raw!$B$1:$FB$1=$I15)*(Raw!$B$2:$FB$2=$H15), 0))} -> 5461042000 | AB15: {=INDEX(Raw!T:FT, MATCH(AB$4, Raw!$A:$A, 0), MATCH(1, (Raw!$B$1:$FB$1=$I15)*(Raw!$B$2:$FB$2=$H15), 0))} -> 5534418000 | AC15: {=INDEX(Raw!U:FU, MATCH(AC$4, Raw!$A:$A, 0), MATCH(1, (Raw!$B$1:$FB$1=$I15)*(Raw!$B$2:$FB$2=$H15), 0))} -> 0.44 | AD15: {=INDEX(Raw!V:FV, MATCH(AD$4, Raw!$A:$A, 0), MATCH(1, (Raw!$B$1:$FB$1=$I15)*(Raw!$B$2:$FB$2=$H15), 0))} -> 0.54
F16: KO | G16: =TODAY() -> 46088 | H16: =H15 -> 2023 | I16: Q1 | J16: {=INDEX(Raw!B:FB, MATCH(J$4, Raw!$A:$A, 0), MATCH(1, (Raw!$B$1:$FB$1=$I16)*(Raw!$B$2:$FB$2=$H16), 0))} -> 10980000000 | K16: {=INDEX(Raw!C:FC, MATCH(K$4, Raw!$A:$A, 0), MATCH(1, (Raw!$B$1:$FB$1=$I16)*(Raw!$B$2:$FB$2=$H16), 0))} -> 4513000000 | L16: {=INDEX(Raw!D:FD, MATCH(L$4, Raw!$A:$A, 0), MATCH(1, (Raw!$B$1:$FB$1=$I16)*(Raw!$B$2:$FB$2=$H16), 0))} -> 6497000000 | M16: {=INDEX(Raw!E:FE, MATCH(M$4, Raw!$A:$A, 0), MATCH(1, (Raw!$B$1:$FB$1=$I16)*(Raw!$B$2:$FB$2=$H16), 0))} -> 3203000000 | N16: {=INDEX(Raw!F:FF, MATCH(N$4, Raw!$A:$A, 0), MATCH(1, (Raw!$B$1:$FB$1=$I16)*(Raw!$B$2:$FB$2=$H16), 0))} -> -28000000 | O16: {=INDEX(Raw!G:FG, MATCH(O$4, Raw!$A:$A, 0), MATCH(1, (Raw!$B$1:$FB$1=$I16)*(Raw!$B$2:$FB$2=$H16), 0))} -> 3704000000 | P16: {=INDEX(Raw!H:FH, MATCH(P$4, Raw!$A:$A, 0), MATCH(1, (Raw!$B$1:$FB$1=$I16)*(Raw!$B$2:$FB$2=$H16), 0))} -> 2898000000 | Q16: {=INDEX(Raw!I:FI, MATCH(Q$4, Raw!$A:$A, 0), MATCH(1, (Raw!$B$1:$FB$1=$I16)*(Raw!$B$2:$FB$2=$H16), 0))} -> 602000000 | R16: {=INDEX(Raw!J:FJ, MATCH(R$4, Raw!$A:$A, 0), MATCH(1, (Raw!$B$1:$FB$1=$I16)*(Raw!$B$2:$FB$2=$H16), 0))} -> 2763000000 | S16: {=INDEX(Raw!K:FK, MATCH(S$4, Raw!$A:$A, 0), MATCH(1, (Raw!$B$1:$FB$1=$I16)*(Raw!$B$2:$FB$2=$H16), 0))} -> 887000000 | T16: {=INDEX(Raw!L:FL, MATCH(T$4, Raw!$A:$A, 0), MATCH(1, (Raw!$B$1:$FB$1=$I16)*(Raw!$B$2:$FB$2=$H16), 0))} -> 1740000000 | U16: {=INDEX(Raw!M:FM, MATCH(U$4, Raw!$A:$A, 0), MATCH(1, (Raw!$B$1:$FB$1=$I16)*(Raw!$B$2:$FB$2=$H16), 0))} -> 0 | V16: {=INDEX(Raw!N:FN, MATCH(V$4, Raw!$A:$A, 0), MATCH(1, (Raw!$B$1:$FB$1=$I16)*(Raw!$B$2:$FB$2=$H16), 0))} -> 2795000000 | W16: {=INDEX(Raw!O:FO, MATCH(W$4, Raw!$A:$A, 0), MATCH(1, (Raw!$B$1:$FB$1=$I16)*(Raw!$B$2:$FB$2=$H16), 0))} -> 0 | X16: {=INDEX(Raw!P:FP, MATCH(X$4, Raw!$A:$A, 0), MATCH(1, (Raw!$B$1:$FB$1=$I16)*(Raw!$B$2:$FB$2=$H16), 0))} -> 2593000000 | Y16: {=INDEX(Raw!Q:FQ, MATCH(Y$4, Raw!$A:$A, 0), MATCH(1, (Raw!$B$1:$FB$1=$I16)*(Raw!$B$2:$FB$2=$H16), 0))} -> 381755100 | Z16: {=INDEX(Raw!R:FR, MATCH(Z$4, Raw!$A:$A, 0), MATCH(1, (Raw!$B$1:$FB$1=$I16)*(Raw!$B$2:$FB$2=$H16), 0))} -> 458300000 | AA16: {=INDEX(Raw!S:FS, MATCH(AA$4, Raw!$A:$A, 0), MATCH(1, (Raw!$B$1:$FB$1=$I16)*(Raw!$B$2:$FB$2=$H16), 0))} -> 5534418000 | AB16: {=INDEX(Raw!T:FT, MATCH(AB$4, Raw!$A:$A, 0), MATCH(1, (Raw!$B$1:$FB$1=$I16)*(Raw!$B$2:$FB$2=$H16), 0))} -> 5602486000 | AC16: {=INDEX(Raw!U:FU, MATCH(AC$4, Raw!$A:$A, 0), MATCH(1, (Raw!$B$1:$FB$1=$I16)*(Raw!$B$2:$FB$2=$H16), 0))} -> 0.54 | AD16: {=INDEX(Raw!V:FV, MATCH(AD$4, Raw!$A:$A, 0), MATCH(1, (Raw!$B$1:$FB$1=$I16)*(Raw!$B$2:$FB$2=$H16), 0))} -> 0.32
F17: KO | G17: =TODAY() -> 46088 | H17: =H13-1 -> 2022 | I17: Q4 | J17: {=INDEX(Raw!B:FB, MATCH(J$4, Raw!$A:$A, 0), MATCH(1, (Raw!$B$1:$FB$1=$I17)*(Raw!$B$2:$FB$2=$H17), 0))} -> 10125000000 | K17: {=INDEX(Raw!C:FC, MATCH(K$4, Raw!$A:$A, 0), MATCH(1, (Raw!$B$1:$FB$1=$I17)*(Raw!$B$2:$FB$2=$H17), 0))} -> 4566000000 | L17: {=INDEX(Raw!D:FD, MATCH(L$4, Raw!$A:$A, 0), MATCH(1, (Raw!$B$1:$FB$1=$I17)*(Raw!$B$2:$FB$2=$H17), 0))} -> 6495000000 | M17: {=INDEX(Raw!E:FE, MATCH(M$4, Raw!$A:$A, 0), MATCH(1, (Raw!$B$1:$FB$1=$I17)*(Raw!$B$2:$FB$2=$H17), 0))} -> 2967000000 | N17: {=INDEX(Raw!F:FF, MATCH(N$4, Raw!$A:$A, 0), MATCH(1, (Raw!$B$1:$FB$1=$I17)*(Raw!$B$2:$FB$2=$H17), 0))} -> -368000000 | O17: {=INDEX(Raw!G:FG, MATCH(O$4, Raw!$A:$A, 0), MATCH(1, (Raw!$B$1:$FB$1=$I17)*(Raw!$B$2:$FB$2=$H17), 0))} -> 3167000000 | P17: {=INDEX(Raw!H:FH, MATCH(P$4, Raw!$A:$A, 0), MATCH(1, (Raw!$B$1:$FB$1=$I17)*(Raw!$B$2:$FB$2=$H17), 0))} -> 3016000000 | Q17: {=INDEX(Raw!I:FI, MATCH(Q$4, Raw!$A:$A, 0), MATCH(1, (Raw!$B$1:$FB$1=$I17)*(Raw!$B$2:$FB$2=$H17), 0))} -> 41000000 | R17: {=INDEX(Raw!J:FJ, MATCH(R$4, Raw!$A:$A, 0), MATCH(1, (Raw!$B$1:$FB$1=$I17)*(Raw!$B$2:$FB$2=$H17), 0))} -> 2361000000 | S17: {=INDEX(Raw!K:FK, MATCH(S$4, Raw!$A:$A, 0), MATCH(1, (Raw!$B$1:$FB$1=$I17)*(Raw!$B$2:$FB$2=$H17), 0))} -> 441000000 | T17: {=INDEX(Raw!L:FL, MATCH(T$4, Raw!$A:$A, 0), MATCH(1, (Raw!$B$1:$FB$1=$I17)*(Raw!$B$2:$FB$2=$H17), 0))} -> 1759000000 | U17: {=INDEX(Raw!M:FM, MATCH(U$4, Raw!$A:$A, 0), MATCH(1, (Raw!$B$1:$FB$1=$I17)*(Raw!$B$2:$FB$2=$H17), 0))} -> 0 | V17: {=INDEX(Raw!N:FN, MATCH(V$4, Raw!$A:$A, 0), MATCH(1, (Raw!$B$1:$FB$1=$I17)*(Raw!$B$2:$FB$2=$H17), 0))} -> 2065000000 | W17: {=INDEX(Raw!O:FO, MATCH(W$4, Raw!$A:$A, 0), MATCH(1, (Raw!$B$1:$FB$1=$I17)*(Raw!$B$2:$FB$2=$H17), 0))} -> 0 | X17: {=INDEX(Raw!P:FP, MATCH(X$4, Raw!$A:$A, 0), MATCH(1, (Raw!$B$1:$FB$1=$I17)*(Raw!$B$2:$FB$2=$H17), 0))} -> 2607000000 | Y17: {=INDEX(Raw!Q:FQ, MATCH(Y$4, Raw!$A:$A, 0), MATCH(1, (Raw!$B$1:$FB$1=$I17)*(Raw!$B$2:$FB$2=$H17), 0))} -> 458300000 | Z17: {=INDEX(Raw!R:FR, MATCH(Z$4, Raw!$A:$A, 0), MATCH(1, (Raw!$B$1:$FB$1=$I17)*(Raw!$B$2:$FB$2=$H17), 0))} -> 498775100 | AA17: {=INDEX(Raw!S:FS, MATCH(AA$4, Raw!$A:$A, 0), MATCH(1, (Raw!$B$1:$FB$1=$I17)*(Raw!$B$2:$FB$2=$H17), 0))} -> 5602486000 | AB17: {=INDEX(Raw!T:FT, MATCH(AB$4, Raw!$A:$A, 0), MATCH(1, (Raw!$B$1:$FB$1=$I17)*(Raw!$B$2:$FB$2=$H17), 0))} -> 5676616000 | AC17: {=INDEX(Raw!U:FU, MATCH(AC$4, Raw!$A:$A, 0), MATCH(1, (Raw!$B$1:$FB$1=$I17)*(Raw!$B$2:$FB$2=$H17), 0))} -> 0.32 | AD17: {=INDEX(Raw!V:FV, MATCH(AD$4, Raw!$A:$A, 0), MATCH(1, (Raw!$B$1:$FB$1=$I17)*(Raw!$B$2:$FB$2=$H17), 0))} -> -0.63
F18: KO | G18: =TODAY() -> 46088 | H18: =H17 -> 2022 | I18: Q3 | J18: {=INDEX(Raw!B:FB, MATCH(J$4, Raw!$A:$A, 0), MATCH(1, (Raw!$B$1:$FB$1=$I18)*(Raw!$B$2:$FB$2=$H18), 0))} -> 11063000000 | K18: {=INDEX(Raw!C:FC, MATCH(K$4, Raw!$A:$A, 0), MATCH(1, (Raw!$B$1:$FB$1=$I18)*(Raw!$B$2:$FB$2=$H18), 0))} -> 4830000000 | L18: {=INDEX(Raw!D:FD, MATCH(L$4, Raw!$A:$A, 0), MATCH(1, (Raw!$B$1:$FB$1=$I18)*(Raw!$B$2:$FB$2=$H18), 0))} -> 6400000000 | M18: {=INDEX(Raw!E:FE, MATCH(M$4, Raw!$A:$A, 0), MATCH(1, (Raw!$B$1:$FB$1=$I18)*(Raw!$B$2:$FB$2=$H18), 0))} -> 3336000000 | N18: {=INDEX(Raw!F:FF, MATCH(N$4, Raw!$A:$A, 0), MATCH(1, (Raw!$B$1:$FB$1=$I18)*(Raw!$B$2:$FB$2=$H18), 0))} -> -45000000 | O18: {=INDEX(Raw!G:FG, MATCH(O$4, Raw!$A:$A, 0), MATCH(1, (Raw!$B$1:$FB$1=$I18)*(Raw!$B$2:$FB$2=$H18), 0))} -> 3326000000 | P18: {=INDEX(Raw!H:FH, MATCH(P$4, Raw!$A:$A, 0), MATCH(1, (Raw!$B$1:$FB$1=$I18)*(Raw!$B$2:$FB$2=$H18), 0))} -> 2722000000 | Q18: {=INDEX(Raw!I:FI, MATCH(Q$4, Raw!$A:$A, 0), MATCH(1, (Raw!$B$1:$FB$1=$I18)*(Raw!$B$2:$FB$2=$H18), 0))} -> 23000000 | R18: {=INDEX(Raw!J:FJ, MATCH(R$4, Raw!$A:$A, 0), MATCH(1, (Raw!$B$1:$FB$1=$I18)*(Raw!$B$2:$FB$2=$H18), 0))} -> 2181000000 | S18: {=INDEX(Raw!K:FK, MATCH(S$4, Raw!$A:$A, 0), MATCH(1, (Raw!$B$1:$FB$1=$I18)*(Raw!$B$2:$FB$2=$H18), 0))} -> 438000000 | T18: {=INDEX(Raw!L:FL, MATCH(T$4, Raw!$A:$A, 0), MATCH(1, (Raw!$B$1:$FB$1=$I18)*(Raw!$B$2:$FB$2=$H18), 0))} -> 2795000000 | U18: {=INDEX(Raw!M:FM, MATCH(U$4, Raw!$A:$A, 0), MATCH(1, (Raw!$B$1:$FB$1=$I18)*(Raw!$B$2:$FB$2=$H18), 0))} -> 0 | V18: {=INDEX(Raw!N:FN, MATCH(V$4, Raw!$A:$A, 0), MATCH(1, (Raw!$B$1:$FB$1=$I18)*(Raw!$B$2:$FB$2=$H18), 0))} -> 2589000000 | W18: {=INDEX(Raw!O:FO, MATCH(W$4, Raw!$A:$A, 0), MATCH(1, (Raw!$B$1:$FB$1=$I18)*(Raw!$B$2:$FB$2=$H18), 0))} -> 0 | X18: {=INDEX(Raw!P:FP, MATCH(X$4, Raw!$A:$A, 0), MATCH(1, (Raw!$B$1:$FB$1=$I18)*(Raw!$B$2:$FB$2=$H18), 0))} -> 1678000000 | Y18: {=INDEX(Raw!Q:FQ, MATCH(Y$4, Raw!$A:$A, 0), MATCH(1, (Raw!$B$1:$FB$1=$I18)*(Raw!$B$2:$FB$2=$H18), 0))} -> 498775100 | Z18: {=INDEX(Raw!R:FR, MATCH(Z$4, Raw!$A:$A, 0), MATCH(1, (Raw!$B$1:$FB$1=$I18)*(Raw!$B$2:$FB$2=$H18), 0))} -> 386955000 | AA18: {=INDEX(Raw!S:FS, MATCH(AA$4, Raw!$A:$A, 0), MATCH(1, (Raw!$B$1:$FB$1=$I18)*(Raw!$B$2:$FB$2=$H18), 0))} -> 5676616000 | AB18: {=INDEX(Raw!T:FT, MATCH(AB$4, Raw!$A:$A, 0), MATCH(1, (Raw!$B$1:$FB$1=$I18)*(Raw!$B$2:$FB$2=$H18), 0))} -> 0 | AC18: {=INDEX(Raw!U:FU, MATCH(AC$4, Raw!$A:$A, 0), MATCH(1, (Raw!$B$1:$FB$1=$I18)*(Raw!$B$2:$FB$2=$H18), 0))} -> -0.65 | AD18: {=INDEX(Raw!V:FV, MATCH(AD$4, Raw!$A:$A, 0), MATCH(1, (Raw!$B$1:$FB$1=$I18)*(Raw!$B$2:$FB$2=$H18), 0))} -> 0.33
F19: KO | G19: =TODAY() -> 46088 | H19: =H18 -> 2022 | I19: Q2 | J19: {=INDEX(Raw!B:FB, MATCH(J$4, Raw!$A:$A, 0), MATCH(1, (Raw!$B$1:$FB$1=$I19)*(Raw!$B$2:$FB$2=$H19), 0))} -> 11325000000 | K19: {=INDEX(Raw!C:FC, MATCH(K$4, Raw!$A:$A, 0), MATCH(1, (Raw!$B$1:$FB$1=$I19)*(Raw!$B$2:$FB$2=$H19), 0))} -> 4091000000 | L19: {=INDEX(Raw!D:FD, MATCH(L$4, Raw!$A:$A, 0), MATCH(1, (Raw!$B$1:$FB$1=$I19)*(Raw!$B$2:$FB$2=$H19), 0))} -> 5376000000 | M19: {=INDEX(Raw!E:FE, MATCH(M$4, Raw!$A:$A, 0), MATCH(1, (Raw!$B$1:$FB$1=$I19)*(Raw!$B$2:$FB$2=$H19), 0))} -> 3122000000 | N19: {=INDEX(Raw!F:FF, MATCH(N$4, Raw!$A:$A, 0), MATCH(1, (Raw!$B$1:$FB$1=$I19)*(Raw!$B$2:$FB$2=$H19), 0))} -> -309000000 | O19: {=INDEX(Raw!G:FG, MATCH(O$4, Raw!$A:$A, 0), MATCH(1, (Raw!$B$1:$FB$1=$I19)*(Raw!$B$2:$FB$2=$H19), 0))} -> 2793000000 | P19: {=INDEX(Raw!H:FH, MATCH(P$4, Raw!$A:$A, 0), MATCH(1, (Raw!$B$1:$FB$1=$I19)*(Raw!$B$2:$FB$2=$H19), 0))} -> 2338000000 | Q19: {=INDEX(Raw!I:FI, MATCH(Q$4, Raw!$A:$A, 0), MATCH(1, (Raw!$B$1:$FB$1=$I19)*(Raw!$B$2:$FB$2=$H19), 0))} -> -117000000 | R19: {=INDEX(Raw!J:FJ, MATCH(R$4, Raw!$A:$A, 0), MATCH(1, (Raw!$B$1:$FB$1=$I19)*(Raw!$B$2:$FB$2=$H19), 0))} -> 2197000000 | S19: {=INDEX(Raw!K:FK, MATCH(S$4, Raw!$A:$A, 0), MATCH(1, (Raw!$B$1:$FB$1=$I19)*(Raw!$B$2:$FB$2=$H19), 0))} -> 215000000 | T19: {=INDEX(Raw!L:FL, MATCH(T$4, Raw!$A:$A, 0), MATCH(1, (Raw!$B$1:$FB$1=$I19)*(Raw!$B$2:$FB$2=$H19), 0))} -> 2065000000 | U19: {=INDEX(Raw!M:FM, MATCH(U$4, Raw!$A:$A, 0), MATCH(1, (Raw!$B$1:$FB$1=$I19)*(Raw!$B$2:$FB$2=$H19), 0))} -> 0 | V19: {=INDEX(Raw!N:FN, MATCH(V$4, Raw!$A:$A, 0), MATCH(1, (Raw!$B$1:$FB$1=$I19)*(Raw!$B$2:$FB$2=$H19), 0))} -> 2628000000 | W19: {=INDEX(Raw!O:FO, MATCH(W$4, Raw!$A:$A, 0), MATCH(1, (Raw!$B$1:$FB$1=$I19)*(Raw!$B$2:$FB$2=$H19), 0))} -> 0 | X19: {=INDEX(Raw!P:FP, MATCH(X$4, Raw!$A:$A, 0), MATCH(1, (Raw!$B$1:$FB$1=$I19)*(Raw!$B$2:$FB$2=$H19), 0))} -> 870000000 | Y19: {=INDEX(Raw!Q:FQ, MATCH(Y$4, Raw!$A:$A, 0), MATCH(1, (Raw!$B$1:$FB$1=$I19)*(Raw!$B$2:$FB$2=$H19), 0))} -> 386955000 | Z19: {=INDEX(Raw!R:FR, MATCH(Z$4, Raw!$A:$A, 0), MATCH(1, (Raw!$B$1:$FB$1=$I19)*(Raw!$B$2:$FB$2=$H19), 0))} -> 340715000 | AA19: {=INDEX(Raw!S:FS, MATCH(AA$4, Raw!$A:$A, 0), MATCH(1, (Raw!$B$1:$FB$1=$I19)*(Raw!$B$2:$FB$2=$H19), 0))} -> 0 | AB19: {=INDEX(Raw!T:FT, MATCH(AB$4, Raw!$A:$A, 0), MATCH(1, (Raw!$B$1:$FB$1=$I19)*(Raw!$B$2:$FB$2=$H19), 0))} -> 5845220000 | AC19: {=INDEX(Raw!U:FU, MATCH(AC$4, Raw!$A:$A, 0), MATCH(1, (Raw!$B$1:$FB$1=$I19)*(Raw!$B$2:$FB$2=$H19), 0))} -> 0.34 | AD19: {=INDEX(Raw!V:FV, MATCH(AD$4, Raw!$A:$A, 0), MATCH(1, (Raw!$B$1:$FB$1=$I19)*(Raw!$B$2:$FB$2=$H19), 0))} -> 0.32
F20: KO | G20: =TODAY() -> 46088 | H20: =H19 -> 2022 | I20: Q1 | J20: {=INDEX(Raw!B:FB, MATCH(J$4, Raw!$A:$A, 0), MATCH(1, (Raw!$B$1:$FB$1=$I20)*(Raw!$B$2:$FB$2=$H20), 0))} -> 10491000000 | K20: {=INDEX(Raw!C:FC, MATCH(K$4, Raw!$A:$A, 0), MATCH(1, (Raw!$B$1:$FB$1=$I20)*(Raw!$B$2:$FB$2=$H20), 0))} -> 4088000000 | L20: {=INDEX(Raw!D:FD, MATCH(L$4, Raw!$A:$A, 0), MATCH(1, (Raw!$B$1:$FB$1=$I20)*(Raw!$B$2:$FB$2=$H20), 0))} -> 6065000000 | M20: {=INDEX(Raw!E:FE, MATCH(M$4, Raw!$A:$A, 0), MATCH(1, (Raw!$B$1:$FB$1=$I20)*(Raw!$B$2:$FB$2=$H20), 0))} -> 3017000000 | N20: {=INDEX(Raw!F:FF, MATCH(N$4, Raw!$A:$A, 0), MATCH(1, (Raw!$B$1:$FB$1=$I20)*(Raw!$B$2:$FB$2=$H20), 0))} -> -124000000 | O20: {=INDEX(Raw!G:FG, MATCH(O$4, Raw!$A:$A, 0), MATCH(1, (Raw!$B$1:$FB$1=$I20)*(Raw!$B$2:$FB$2=$H20), 0))} -> 2695000000 | P20: {=INDEX(Raw!H:FH, MATCH(P$4, Raw!$A:$A, 0), MATCH(1, (Raw!$B$1:$FB$1=$I20)*(Raw!$B$2:$FB$2=$H20), 0))} -> 2298000000 | Q20: {=INDEX(Raw!I:FI, MATCH(Q$4, Raw!$A:$A, 0), MATCH(1, (Raw!$B$1:$FB$1=$I20)*(Raw!$B$2:$FB$2=$H20), 0))} -> 216000000 | R20: {=INDEX(Raw!J:FJ, MATCH(R$4, Raw!$A:$A, 0), MATCH(1, (Raw!$B$1:$FB$1=$I20)*(Raw!$B$2:$FB$2=$H20), 0))} -> 3010000000 | S20: {=INDEX(Raw!K:FK, MATCH(S$4, Raw!$A:$A, 0), MATCH(1, (Raw!$B$1:$FB$1=$I20)*(Raw!$B$2:$FB$2=$H20), 0))} -> 355000000 | T20: {=INDEX(Raw!L:FL, MATCH(T$4, Raw!$A:$A, 0), MATCH(1, (Raw!$B$1:$FB$1=$I20)*(Raw!$B$2:$FB$2=$H20), 0))} -> 2589000000 | U20: {=INDEX(Raw!M:FM, MATCH(U$4, Raw!$A:$A, 0), MATCH(1, (Raw!$B$1:$FB$1=$I20)*(Raw!$B$2:$FB$2=$H20), 0))} -> 0 | V20: {=INDEX(Raw!N:FN, MATCH(V$4, Raw!$A:$A, 0), MATCH(1, (Raw!$B$1:$FB$1=$I20)*(Raw!$B$2:$FB$2=$H20), 0))} -> 1703000000 | W20: {=INDEX(Raw!O:FO, MATCH(W$4, Raw!$A:$A, 0), MATCH(1, (Raw!$B$1:$FB$1=$I20)*(Raw!$B$2:$FB$2=$H20), 0))} -> 0 | X20: {=INDEX(Raw!P:FP, MATCH(X$4, Raw!$A:$A, 0), MATCH(1, (Raw!$B$1:$FB$1=$I20)*(Raw!$B$2:$FB$2=$H20), 0))} -> 1880000000 | Y20: {=INDEX(Raw!Q:FQ, MATCH(Y$4, Raw!$A:$A, 0), MATCH(1, (Raw!$B$1:$FB$1=$I20)*(Raw!$B$2:$FB$2=$H20), 0))} -> 340715000 | Z20: {=INDEX(Raw!R:FR, MATCH(Z$4, Raw!$A:$A, 0), MATCH(1, (Raw!$B$1:$FB$1=$I20)*(Raw!$B$2:$FB$2=$H20), 0))} -> 431427000 | AA20: {=INDEX(Raw!S:FS, MATCH(AA$4, Raw!$A:$A, 0), MATCH(1, (Raw!$B$1:$FB$1=$I20)*(Raw!$B$2:$FB$2=$H20), 0))} -> 5845220000 | AB20: {=INDEX(Raw!T:FT, MATCH(AB$4, Raw!$A:$A, 0), MATCH(1, (Raw!$B$1:$FB$1=$I20)*(Raw!$B$2:$FB$2=$H20), 0))} -> 591044000 | AC20: {=INDEX(Raw!U:FU, MATCH(AC$4, Raw!$A:$A, 0), MATCH(1, (Raw!$B$1:$FB$1=$I20)*(Raw!$B$2:$FB$2=$H20), 0))} -> 0.32 | AD20: {=INDEX(Raw!V:FV, MATCH(AD$4, Raw!$A:$A, 0), MATCH(1, (Raw!$B$1:$FB$1=$I20)*(Raw!$B$2:$FB$2=$H20), 0))} -> 0.27
F21: KO | G21: =TODAY() -> 46088 | H21: =H17-1 -> 2021 | I21: Q4 | J21: {=INDEX(Raw!B:FB, MATCH(J$4, Raw!$A:$A, 0), MATCH(1, (Raw!$B$1:$FB$1=$I21)*(Raw!$B$2:$FB$2=$H21), 0))} -> 9464000000 | K21: {=INDEX(Raw!C:FC, MATCH(K$4, Raw!$A:$A, 0), MATCH(1, (Raw!$B$1:$FB$1=$I21)*(Raw!$B$2:$FB$2=$H21), 0))} -> 3977000000 | L21: {=INDEX(Raw!D:FD, MATCH(L$4, Raw!$A:$A, 0), MATCH(1, (Raw!$B$1:$FB$1=$I21)*(Raw!$B$2:$FB$2=$H21), 0))} -> 6342000000 | M21: {=INDEX(Raw!E:FE, MATCH(M$4, Raw!$A:$A, 0), MATCH(1, (Raw!$B$1:$FB$1=$I21)*(Raw!$B$2:$FB$2=$H21), 0))} -> 2669000000 | N21: {=INDEX(Raw!F:FF, MATCH(N$4, Raw!$A:$A, 0), MATCH(1, (Raw!$B$1:$FB$1=$I21)*(Raw!$B$2:$FB$2=$H21), 0))} -> -106000000 | O21: {=INDEX(Raw!G:FG, MATCH(O$4, Raw!$A:$A, 0), MATCH(1, (Raw!$B$1:$FB$1=$I21)*(Raw!$B$2:$FB$2=$H21), 0))} -> 2883000000 | P21: {=INDEX(Raw!H:FH, MATCH(P$4, Raw!$A:$A, 0), MATCH(1, (Raw!$B$1:$FB$1=$I21)*(Raw!$B$2:$FB$2=$H21), 0))} -> 1981000000 | Q21: {=INDEX(Raw!I:FI, MATCH(Q$4, Raw!$A:$A, 0), MATCH(1, (Raw!$B$1:$FB$1=$I21)*(Raw!$B$2:$FB$2=$H21), 0))} -> 630000000 | R21: {=INDEX(Raw!J:FJ, MATCH(R$4, Raw!$A:$A, 0), MATCH(1, (Raw!$B$1:$FB$1=$I21)*(Raw!$B$2:$FB$2=$H21), 0))} -> 2420000000 | S21: {=INDEX(Raw!K:FK, MATCH(S$4, Raw!$A:$A, 0), MATCH(1, (Raw!$B$1:$FB$1=$I21)*(Raw!$B$2:$FB$2=$H21), 0))} -> 503000000 | T21: {=INDEX(Raw!L:FL, MATCH(T$4, Raw!$A:$A, 0), MATCH(1, (Raw!$B$1:$FB$1=$I21)*(Raw!$B$2:$FB$2=$H21), 0))} -> 2628000000 | U21: {=INDEX(Raw!M:FM, MATCH(U$4, Raw!$A:$A, 0), MATCH(1, (Raw!$B$1:$FB$1=$I21)*(Raw!$B$2:$FB$2=$H21), 0))} -> 0 | V21: {=INDEX(Raw!N:FN, MATCH(V$4, Raw!$A:$A, 0), MATCH(1, (Raw!$B$1:$FB$1=$I21)*(Raw!$B$2:$FB$2=$H21), 0))} -> 1000000000 | W21: {=INDEX(Raw!O:FO, MATCH(W$4, Raw!$A:$A, 0), MATCH(1, (Raw!$B$1:$FB$1=$I21)*(Raw!$B$2:$FB$2=$H21), 0))} -> 0 | X21: {=INDEX(Raw!P:FP, MATCH(X$4, Raw!$A:$A, 0), MATCH(1, (Raw!$B$1:$FB$1=$I21)*(Raw!$B$2:$FB$2=$H21), 0))} -> 2316000000 | Y21: {=INDEX(Raw!Q:FQ, MATCH(Y$4, Raw!$A:$A, 0), MATCH(1, (Raw!$B$1:$FB$1=$I21)*(Raw!$B$2:$FB$2=$H21), 0))} -> 431427000 | Z21: {=INDEX(Raw!R:FR, MATCH(Z$4, Raw!$A:$A, 0), MATCH(1, (Raw!$B$1:$FB$1=$I21)*(Raw!$B$2:$FB$2=$H21), 0))} -> 465457000 | AA21: {=INDEX(Raw!S:FS, MATCH(AA$4, Raw!$A:$A, 0), MATCH(1, (Raw!$B$1:$FB$1=$I21)*(Raw!$B$2:$FB$2=$H21), 0))} -> 591044000 | AB21: {=INDEX(Raw!T:FT, MATCH(AB$4, Raw!$A:$A, 0), MATCH(1, (Raw!$B$1:$FB$1=$I21)*(Raw!$B$2:$FB$2=$H21), 0))} -> 5957698000 | AC21: {=INDEX(Raw!U:FU, MATCH(AC$4, Raw!$A:$A, 0), MATCH(1, (Raw!$B$1:$FB$1=$I21)*(Raw!$B$2:$FB$2=$H21), 0))} -> 0.28 | AD21: {=INDEX(Raw!V:FV, MATCH(AD$4, Raw!$A:$A, 0), MATCH(1, (Raw!$B$1:$FB$1=$I21)*(Raw!$B$2:$FB$2=$H21), 0))} -> 0.12
F22: KO | G22: =TODAY() -> 46088 | H22: =H21 -> 2021 | I22: Q3 | J22: {=INDEX(Raw!B:FB, MATCH(J$4, Raw!$A:$A, 0), MATCH(1, (Raw!$B$1:$FB$1=$I22)*(Raw!$B$2:$FB$2=$H22), 0))} -> 10042000000 | K22: {=INDEX(Raw!C:FC, MATCH(K$4, Raw!$A:$A, 0), MATCH(1, (Raw!$B$1:$FB$1=$I22)*(Raw!$B$2:$FB$2=$H22), 0))} -> 3787000000 | L22: {=INDEX(Raw!D:FD, MATCH(L$4, Raw!$A:$A, 0), MATCH(1, (Raw!$B$1:$FB$1=$I22)*(Raw!$B$2:$FB$2=$H22), 0))} -> 5515000000 | M22: {=INDEX(Raw!E:FE, MATCH(M$4, Raw!$A:$A, 0), MATCH(1, (Raw!$B$1:$FB$1=$I22)*(Raw!$B$2:$FB$2=$H22), 0))} -> 2589000000 | N22: {=INDEX(Raw!F:FF, MATCH(N$4, Raw!$A:$A, 0), MATCH(1, (Raw!$B$1:$FB$1=$I22)*(Raw!$B$2:$FB$2=$H22), 0))} -> -372000000 | O22: {=INDEX(Raw!G:FG, MATCH(O$4, Raw!$A:$A, 0), MATCH(1, (Raw!$B$1:$FB$1=$I22)*(Raw!$B$2:$FB$2=$H22), 0))} -> 2156000000 | P22: {=INDEX(Raw!H:FH, MATCH(P$4, Raw!$A:$A, 0), MATCH(1, (Raw!$B$1:$FB$1=$I22)*(Raw!$B$2:$FB$2=$H22), 0))} -> 2380000000 | Q22: {=INDEX(Raw!I:FI, MATCH(Q$4, Raw!$A:$A, 0), MATCH(1, (Raw!$B$1:$FB$1=$I22)*(Raw!$B$2:$FB$2=$H22), 0))} -> 256000000 | R22: {=INDEX(Raw!J:FJ, MATCH(R$4, Raw!$A:$A, 0), MATCH(1, (Raw!$B$1:$FB$1=$I22)*(Raw!$B$2:$FB$2=$H22), 0))} -> 3092000000 | S22: {=INDEX(Raw!K:FK, MATCH(S$4, Raw!$A:$A, 0), MATCH(1, (Raw!$B$1:$FB$1=$I22)*(Raw!$B$2:$FB$2=$H22), 0))} -> 421000000 | T22: {=INDEX(Raw!L:FL, MATCH(T$4, Raw!$A:$A, 0), MATCH(1, (Raw!$B$1:$FB$1=$I22)*(Raw!$B$2:$FB$2=$H22), 0))} -> 1703000000 | U22: {=INDEX(Raw!M:FM, MATCH(U$4, Raw!$A:$A, 0), MATCH(1, (Raw!$B$1:$FB$1=$I22)*(Raw!$B$2:$FB$2=$H22), 0))} -> 0 | V22: {=INDEX(Raw!N:FN, MATCH(V$4, Raw!$A:$A, 0), MATCH(1, (Raw!$B$1:$FB$1=$I22)*(Raw!$B$2:$FB$2=$H22), 0))} -> 1818000000 | W22: {=INDEX(Raw!O:FO, MATCH(W$4, Raw!$A:$A, 0), MATCH(1, (Raw!$B$1:$FB$1=$I22)*(Raw!$B$2:$FB$2=$H22), 0))} -> 0 | X22: {=INDEX(Raw!P:FP, MATCH(X$4, Raw!$A:$A, 0), MATCH(1, (Raw!$B$1:$FB$1=$I22)*(Raw!$B$2:$FB$2=$H22), 0))} -> 1368000000 | Y22: {=INDEX(Raw!Q:FQ, MATCH(Y$4, Raw!$A:$A, 0), MATCH(1, (Raw!$B$1:$FB$1=$I22)*(Raw!$B$2:$FB$2=$H22), 0))} -> 465457000 | Z22: {=INDEX(Raw!R:FR, MATCH(Z$4, Raw!$A:$A, 0), MATCH(1, (Raw!$B$1:$FB$1=$I22)*(Raw!$B$2:$FB$2=$H22), 0))} -> 360702000 | AA22: {=INDEX(Raw!S:FS, MATCH(AA$4, Raw!$A:$A, 0), MATCH(1, (Raw!$B$1:$FB$1=$I22)*(Raw!$B$2:$FB$2=$H22), 0))} -> 5957698000 | AB22: {=INDEX(Raw!T:FT, MATCH(AB$4, Raw!$A:$A, 0), MATCH(1, (Raw!$B$1:$FB$1=$I22)*(Raw!$B$2:$FB$2=$H22), 0))} -> 6006550000 | AC22: {=INDEX(Raw!U:FU, MATCH(AC$4, Raw!$A:$A, 0), MATCH(1, (Raw!$B$1:$FB$1=$I22)*(Raw!$B$2:$FB$2=$H22), 0))} -> 0.13 | AD22: {=INDEX(Raw!V:FV, MATCH(AD$4, Raw!$A:$A, 0), MATCH(1, (Raw!$B$1:$FB$1=$I22)*(Raw!$B$2:$FB$2=$H22), 0))} -> 0.24
F23: KO | G23: =TODAY() -> 46088 | H23: =H22 -> 2021 | I23: Q2 | J23: {=INDEX(Raw!B:FB, MATCH(J$4, Raw!$A:$A, 0), MATCH(1, (Raw!$B$1:$FB$1=$I23)*(Raw!$B$2:$FB$2=$H23), 0))} -> 10129000000 | K23: {=INDEX(Raw!C:FC, MATCH(K$4, Raw!$A:$A, 0), MATCH(1, (Raw!$B$1:$FB$1=$I23)*(Raw!$B$2:$FB$2=$H23), 0))} -> 3505000000 | L23: {=INDEX(Raw!D:FD, MATCH(L$4, Raw!$A:$A, 0), MATCH(1, (Raw!$B$1:$FB$1=$I23)*(Raw!$B$2:$FB$2=$H23), 0))} -> 5033000000 | M23: {=INDEX(Raw!E:FE, MATCH(M$4, Raw!$A:$A, 0), MATCH(1, (Raw!$B$1:$FB$1=$I23)*(Raw!$B$2:$FB$2=$H23), 0))} -> 2511000000 | N23: {=INDEX(Raw!F:FF, MATCH(N$4, Raw!$A:$A, 0), MATCH(1, (Raw!$B$1:$FB$1=$I23)*(Raw!$B$2:$FB$2=$H23), 0))} -> -173000000 | O23: {=INDEX(Raw!G:FG, MATCH(O$4, Raw!$A:$A, 0), MATCH(1, (Raw!$B$1:$FB$1=$I23)*(Raw!$B$2:$FB$2=$H23), 0))} -> 2850000000 | P23: {=INDEX(Raw!H:FH, MATCH(P$4, Raw!$A:$A, 0), MATCH(1, (Raw!$B$1:$FB$1=$I23)*(Raw!$B$2:$FB$2=$H23), 0))} -> 2164000000 | Q23: {=INDEX(Raw!I:FI, MATCH(Q$4, Raw!$A:$A, 0), MATCH(1, (Raw!$B$1:$FB$1=$I23)*(Raw!$B$2:$FB$2=$H23), 0))} -> 593000000 | R23: {=INDEX(Raw!J:FJ, MATCH(R$4, Raw!$A:$A, 0), MATCH(1, (Raw!$B$1:$FB$1=$I23)*(Raw!$B$2:$FB$2=$H23), 0))} -> 3049000000 | S23: {=INDEX(Raw!K:FK, MATCH(S$4, Raw!$A:$A, 0), MATCH(1, (Raw!$B$1:$FB$1=$I23)*(Raw!$B$2:$FB$2=$H23), 0))} -> 522000000 | T23: {=INDEX(Raw!L:FL, MATCH(T$4, Raw!$A:$A, 0), MATCH(1, (Raw!$B$1:$FB$1=$I23)*(Raw!$B$2:$FB$2=$H23), 0))} -> 1000000000 | U23: {=INDEX(Raw!M:FM, MATCH(U$4, Raw!$A:$A, 0), MATCH(1, (Raw!$B$1:$FB$1=$I23)*(Raw!$B$2:$FB$2=$H23), 0))} -> 0 | V23: {=INDEX(Raw!N:FN, MATCH(V$4, Raw!$A:$A, 0), MATCH(1, (Raw!$B$1:$FB$1=$I23)*(Raw!$B$2:$FB$2=$H23), 0))} -> 2331000000 | W23: {=INDEX(Raw!O:FO, MATCH(W$4, Raw!$A:$A, 0), MATCH(1, (Raw!$B$1:$FB$1=$I23)*(Raw!$B$2:$FB$2=$H23), 0))} -> 73000000 | X23: {=INDEX(Raw!P:FP, MATCH(X$4, Raw!$A:$A, 0), MATCH(1, (Raw!$B$1:$FB$1=$I23)*(Raw!$B$2:$FB$2=$H23), 0))} -> -2752000000 | Y23: {=INDEX(Raw!Q:FQ, MATCH(Y$4, Raw!$A:$A, 0), MATCH(1, (Raw!$B$1:$FB$1=$I23)*(Raw!$B$2:$FB$2=$H23), 0))} -> 360702000 | Z23: {=INDEX(Raw!R:FR, MATCH(Z$4, Raw!$A:$A, 0), MATCH(1, (Raw!$B$1:$FB$1=$I23)*(Raw!$B$2:$FB$2=$H23), 0))} -> 182247000 | AA23: {=INDEX(Raw!S:FS, MATCH(AA$4, Raw!$A:$A, 0), MATCH(1, (Raw!$B$1:$FB$1=$I23)*(Raw!$B$2:$FB$2=$H23), 0))} -> 6006550000 | AB23: {=INDEX(Raw!T:FT, MATCH(AB$4, Raw!$A:$A, 0), MATCH(1, (Raw!$B$1:$FB$1=$I23)*(Raw!$B$2:$FB$2=$H23), 0))} -> 6031696000 | AC23: {=INDEX(Raw!U:FU, MATCH(AC$4, Raw!$A:$A, 0), MATCH(1, (Raw!$B$1:$FB$1=$I23)*(Raw!$B$2:$FB$2=$H23), 0))} -> 0.24 | AD23: {=INDEX(Raw!V:FV, MATCH(AD$4, Raw!$A:$A, 0), MATCH(1, (Raw!$B$1:$FB$1=$I23)*(Raw!$B$2:$FB$2=$H23), 0))} -> 0.79
F24: KO | G24: =TODAY() -> 46088 | H24: =H23 -> 2021 | I24: Q1 | J24: {=INDEX(Raw!B:FB, MATCH(J$4, Raw!$A:$A, 0), MATCH(1, (Raw!$B$1:$FB$1=$I24)*(Raw!$B$2:$FB$2=$H24), 0))} -> 9020000000 | K24: {=INDEX(Raw!C:FC, MATCH(K$4, Raw!$A:$A, 0), MATCH(1, (Raw!$B$1:$FB$1=$I24)*(Raw!$B$2:$FB$2=$H24), 0))} -> 3578000000 | L24: {=INDEX(Raw!D:FD, MATCH(L$4, Raw!$A:$A, 0), MATCH(1, (Raw!$B$1:$FB$1=$I24)*(Raw!$B$2:$FB$2=$H24), 0))} -> 5181000000 | M24: {=INDEX(Raw!E:FE, MATCH(M$4, Raw!$A:$A, 0), MATCH(1, (Raw!$B$1:$FB$1=$I24)*(Raw!$B$2:$FB$2=$H24), 0))} -> 1983000000 | N24: {=INDEX(Raw!F:FF, MATCH(N$4, Raw!$A:$A, 0), MATCH(1, (Raw!$B$1:$FB$1=$I24)*(Raw!$B$2:$FB$2=$H24), 0))} -> -202000000 | O24: {=INDEX(Raw!G:FG, MATCH(O$4, Raw!$A:$A, 0), MATCH(1, (Raw!$B$1:$FB$1=$I24)*(Raw!$B$2:$FB$2=$H24), 0))} -> 3338000000 | P24: {=INDEX(Raw!H:FH, MATCH(P$4, Raw!$A:$A, 0), MATCH(1, (Raw!$B$1:$FB$1=$I24)*(Raw!$B$2:$FB$2=$H24), 0))} -> 2499000000 | Q24: {=INDEX(Raw!I:FI, MATCH(Q$4, Raw!$A:$A, 0), MATCH(1, (Raw!$B$1:$FB$1=$I24)*(Raw!$B$2:$FB$2=$H24), 0))} -> 61000000 | R24: {=INDEX(Raw!J:FJ, MATCH(R$4, Raw!$A:$A, 0), MATCH(1, (Raw!$B$1:$FB$1=$I24)*(Raw!$B$2:$FB$2=$H24), 0))} -> 2225000000 | S24: {=INDEX(Raw!K:FK, MATCH(S$4, Raw!$A:$A, 0), MATCH(1, (Raw!$B$1:$FB$1=$I24)*(Raw!$B$2:$FB$2=$H24), 0))} -> 77000000 | T24: {=INDEX(Raw!L:FL, MATCH(T$4, Raw!$A:$A, 0), MATCH(1, (Raw!$B$1:$FB$1=$I24)*(Raw!$B$2:$FB$2=$H24), 0))} -> 1818000000 | U24: {=INDEX(Raw!M:FM, MATCH(U$4, Raw!$A:$A, 0), MATCH(1, (Raw!$B$1:$FB$1=$I24)*(Raw!$B$2:$FB$2=$H24), 0))} -> 0 | V24: {=INDEX(Raw!N:FN, MATCH(V$4, Raw!$A:$A, 0), MATCH(1, (Raw!$B$1:$FB$1=$I24)*(Raw!$B$2:$FB$2=$H24), 0))} -> 1327000000 | W24: {=INDEX(Raw!O:FO, MATCH(W$4, Raw!$A:$A, 0), MATCH(1, (Raw!$B$1:$FB$1=$I24)*(Raw!$B$2:$FB$2=$H24), 0))} -> 0 | X24: {=INDEX(Raw!P:FP, MATCH(X$4, Raw!$A:$A, 0), MATCH(1, (Raw!$B$1:$FB$1=$I24)*(Raw!$B$2:$FB$2=$H24), 0))} -> 1447000000 | Y24: {=INDEX(Raw!Q:FQ, MATCH(Y$4, Raw!$A:$A, 0), MATCH(1, (Raw!$B$1:$FB$1=$I24)*(Raw!$B$2:$FB$2=$H24), 0))} -> 182247000 | Z24: {=INDEX(Raw!R:FR, MATCH(Z$4, Raw!$A:$A, 0), MATCH(1, (Raw!$B$1:$FB$1=$I24)*(Raw!$B$2:$FB$2=$H24), 0))} -> 394154100 | AA24: {=INDEX(Raw!S:FS, MATCH(AA$4, Raw!$A:$A, 0), MATCH(1, (Raw!$B$1:$FB$1=$I24)*(Raw!$B$2:$FB$2=$H24), 0))} -> 6031696000 | AB24: {=INDEX(Raw!T:FT, MATCH(AB$4, Raw!$A:$A, 0), MATCH(1, (Raw!$B$1:$FB$1=$I24)*(Raw!$B$2:$FB$2=$H24), 0))} -> 6049004000 | AC24: {=INDEX(Raw!U:FU, MATCH(AC$4, Raw!$A:$A, 0), MATCH(1, (Raw!$B$1:$FB$1=$I24)*(Raw!$B$2:$FB$2=$H24), 0))} -> 0.8 | AD24: {=INDEX(Raw!V:FV, MATCH(AD$4, Raw!$A:$A, 0), MATCH(1, (Raw!$B$1:$FB$1=$I24)*(Raw!$B$2:$FB$2=$H24), 0))} -> 0.34
F25: KO | G25: =TODAY() -> 46088 | H25: =H21-1 -> 2020 | I25: Q4 | J25: {=INDEX(Raw!B:FB, MATCH(J$4, Raw!$A:$A, 0), MATCH(1, (Raw!$B$1:$FB$1=$I25)*(Raw!$B$2:$FB$2=$H25), 0))} -> 8611000000 | K25: {=INDEX(Raw!C:FC, MATCH(K$4, Raw!$A:$A, 0), MATCH(1, (Raw!$B$1:$FB$1=$I25)*(Raw!$B$2:$FB$2=$H25), 0))} -> 3471000000 | L25: {=INDEX(Raw!D:FD, MATCH(L$4, Raw!$A:$A, 0), MATCH(1, (Raw!$B$1:$FB$1=$I25)*(Raw!$B$2:$FB$2=$H25), 0))} -> 4137000000 | M25: {=INDEX(Raw!E:FE, MATCH(M$4, Raw!$A:$A, 0), MATCH(1, (Raw!$B$1:$FB$1=$I25)*(Raw!$B$2:$FB$2=$H25), 0))} -> 2648000000 | N25: {=INDEX(Raw!F:FF, MATCH(N$4, Raw!$A:$A, 0), MATCH(1, (Raw!$B$1:$FB$1=$I25)*(Raw!$B$2:$FB$2=$H25), 0))} -> -114000000 | O25: {=INDEX(Raw!G:FG, MATCH(O$4, Raw!$A:$A, 0), MATCH(1, (Raw!$B$1:$FB$1=$I25)*(Raw!$B$2:$FB$2=$H25), 0))} -> 3241000000 | P25: {=INDEX(Raw!H:FH, MATCH(P$4, Raw!$A:$A, 0), MATCH(1, (Raw!$B$1:$FB$1=$I25)*(Raw!$B$2:$FB$2=$H25), 0))} -> 2988000000 | Q25: {=INDEX(Raw!I:FI, MATCH(Q$4, Raw!$A:$A, 0), MATCH(1, (Raw!$B$1:$FB$1=$I25)*(Raw!$B$2:$FB$2=$H25), 0))} -> -210000000 | R25: {=INDEX(Raw!J:FJ, MATCH(R$4, Raw!$A:$A, 0), MATCH(1, (Raw!$B$1:$FB$1=$I25)*(Raw!$B$2:$FB$2=$H25), 0))} -> 1077000000 | S25: {=INDEX(Raw!K:FK, MATCH(S$4, Raw!$A:$A, 0), MATCH(1, (Raw!$B$1:$FB$1=$I25)*(Raw!$B$2:$FB$2=$H25), 0))} -> 555000000 | T25: {=INDEX(Raw!L:FL, MATCH(T$4, Raw!$A:$A, 0), MATCH(1, (Raw!$B$1:$FB$1=$I25)*(Raw!$B$2:$FB$2=$H25), 0))} -> 2331000000 | U25: {=INDEX(Raw!M:FM, MATCH(U$4, Raw!$A:$A, 0), MATCH(1, (Raw!$B$1:$FB$1=$I25)*(Raw!$B$2:$FB$2=$H25), 0))} -> 0 | V25: {=INDEX(Raw!N:FN, MATCH(V$4, Raw!$A:$A, 0), MATCH(1, (Raw!$B$1:$FB$1=$I25)*(Raw!$B$2:$FB$2=$H25), 0))} -> -2717000000 | W25: {=INDEX(Raw!O:FO, MATCH(W$4, Raw!$A:$A, 0), MATCH(1, (Raw!$B$1:$FB$1=$I25)*(Raw!$B$2:$FB$2=$H25), 0))} -> 0 | X25: {=INDEX(Raw!P:FP, MATCH(X$4, Raw!$A:$A, 0), MATCH(1, (Raw!$B$1:$FB$1=$I25)*(Raw!$B$2:$FB$2=$H25), 0))} -> 1371000000 | Y25: {=INDEX(Raw!Q:FQ, MATCH(Y$4, Raw!$A:$A, 0), MATCH(1, (Raw!$B$1:$FB$1=$I25)*(Raw!$B$2:$FB$2=$H25), 0))} -> 394154100 | Z25: {=INDEX(Raw!R:FR, MATCH(Z$4, Raw!$A:$A, 0), MATCH(1, (Raw!$B$1:$FB$1=$I25)*(Raw!$B$2:$FB$2=$H25), 0))} -> 423273900 | AA25: {=INDEX(Raw!S:FS, MATCH(AA$4, Raw!$A:$A, 0), MATCH(1, (Raw!$B$1:$FB$1=$I25)*(Raw!$B$2:$FB$2=$H25), 0))} -> 6049004000 | AB25: {=INDEX(Raw!T:FT, MATCH(AB$4, Raw!$A:$A, 0), MATCH(1, (Raw!$B$1:$FB$1=$I25)*(Raw!$B$2:$FB$2=$H25), 0))} -> 0 | AC25: {=INDEX(Raw!U:FU, MATCH(AC$4, Raw!$A:$A, 0), MATCH(1, (Raw!$B$1:$FB$1=$I25)*(Raw!$B$2:$FB$2=$H25), 0))} -> 0.34 | AD25: {=INDEX(Raw!V:FV, MATCH(AD$4, Raw!$A:$A, 0), MATCH(1, (Raw!$B$1:$FB$1=$I25)*(Raw!$B$2:$FB$2=$H25), 0))} -> 0.28
F26: KO | G26: =TODAY() -> 46088 | H26: =H25 -> 2020 | I26: Q3 | J26: {=INDEX(Raw!B:FB, MATCH(J$4, Raw!$A:$A, 0), MATCH(1, (Raw!$B$1:$FB$1=$I26)*(Raw!$B$2:$FB$2=$H26), 0))} -> 8652000000 | K26: {=INDEX(Raw!C:FC, MATCH(K$4, Raw!$A:$A, 0), MATCH(1, (Raw!$B$1:$FB$1=$I26)*(Raw!$B$2:$FB$2=$H26), 0))} -> 3013000000 | L26: {=INDEX(Raw!D:FD, MATCH(L$4, Raw!$A:$A, 0), MATCH(1, (Raw!$B$1:$FB$1=$I26)*(Raw!$B$2:$FB$2=$H26), 0))} -> 5230000000 | M26: {=INDEX(Raw!E:FE, MATCH(M$4, Raw!$A:$A, 0), MATCH(1, (Raw!$B$1:$FB$1=$I26)*(Raw!$B$2:$FB$2=$H26), 0))} -> 3224000000 | N26: {=INDEX(Raw!F:FF, MATCH(N$4, Raw!$A:$A, 0), MATCH(1, (Raw!$B$1:$FB$1=$I26)*(Raw!$B$2:$FB$2=$H26), 0))} -> -125000000 | O26: {=INDEX(Raw!G:FG, MATCH(O$4, Raw!$A:$A, 0), MATCH(1, (Raw!$B$1:$FB$1=$I26)*(Raw!$B$2:$FB$2=$H26), 0))} -> 3088000000 | P26: {=INDEX(Raw!H:FH, MATCH(P$4, Raw!$A:$A, 0), MATCH(1, (Raw!$B$1:$FB$1=$I26)*(Raw!$B$2:$FB$2=$H26), 0))} -> 2435000000 | Q26: {=INDEX(Raw!I:FI, MATCH(Q$4, Raw!$A:$A, 0), MATCH(1, (Raw!$B$1:$FB$1=$I26)*(Raw!$B$2:$FB$2=$H26), 0))} -> -884000000 | R26: {=INDEX(Raw!J:FJ, MATCH(R$4, Raw!$A:$A, 0), MATCH(1, (Raw!$B$1:$FB$1=$I26)*(Raw!$B$2:$FB$2=$H26), 0))} -> 2373000000 | S26: {=INDEX(Raw!K:FK, MATCH(S$4, Raw!$A:$A, 0), MATCH(1, (Raw!$B$1:$FB$1=$I26)*(Raw!$B$2:$FB$2=$H26), 0))} -> 611000000 | T26: {=INDEX(Raw!L:FL, MATCH(T$4, Raw!$A:$A, 0), MATCH(1, (Raw!$B$1:$FB$1=$I26)*(Raw!$B$2:$FB$2=$H26), 0))} -> 1327000000 | U26: {=INDEX(Raw!M:FM, MATCH(U$4, Raw!$A:$A, 0), MATCH(1, (Raw!$B$1:$FB$1=$I26)*(Raw!$B$2:$FB$2=$H26), 0))} -> 0 | V26: {=INDEX(Raw!N:FN, MATCH(V$4, Raw!$A:$A, 0), MATCH(1, (Raw!$B$1:$FB$1=$I26)*(Raw!$B$2:$FB$2=$H26), 0))} -> 1444000000 | W26: {=INDEX(Raw!O:FO, MATCH(W$4, Raw!$A:$A, 0), MATCH(1, (Raw!$B$1:$FB$1=$I26)*(Raw!$B$2:$FB$2=$H26), 0))} -> 0 | X26: {=INDEX(Raw!P:FP, MATCH(X$4, Raw!$A:$A, 0), MATCH(1, (Raw!$B$1:$FB$1=$I26)*(Raw!$B$2:$FB$2=$H26), 0))} -> 1182000000 | Y26: {=INDEX(Raw!Q:FQ, MATCH(Y$4, Raw!$A:$A, 0), MATCH(1, (Raw!$B$1:$FB$1=$I26)*(Raw!$B$2:$FB$2=$H26), 0))} -> 423273900 | Z26: {=INDEX(Raw!R:FR, MATCH(Z$4, Raw!$A:$A, 0), MATCH(1, (Raw!$B$1:$FB$1=$I26)*(Raw!$B$2:$FB$2=$H26), 0))} -> 324115000 | AA26: {=INDEX(Raw!S:FS, MATCH(AA$4, Raw!$A:$A, 0), MATCH(1, (Raw!$B$1:$FB$1=$I26)*(Raw!$B$2:$FB$2=$H26), 0))} -> 0 | AB26: {=INDEX(Raw!T:FT, MATCH(AB$4, Raw!$A:$A, 0), MATCH(1, (Raw!$B$1:$FB$1=$I26)*(Raw!$B$2:$FB$2=$H26), 0))} -> 0 | AC26: {=INDEX(Raw!U:FU, MATCH(AC$4, Raw!$A:$A, 0), MATCH(1, (Raw!$B$1:$FB$1=$I26)*(Raw!$B$2:$FB$2=$H26), 0))} -> 0.29 | AD26: {=INDEX(Raw!V:FV, MATCH(AD$4, Raw!$A:$A, 0), MATCH(1, (Raw!$B$1:$FB$1=$I26)*(Raw!$B$2:$FB$2=$H26), 0))} -> 0.33
F27: KO | G27: =TODAY() -> 46088 | H27: =H26 -> 2020 | I27: Q2 | J27: {=INDEX(Raw!B:FB, MATCH(J$4, Raw!$A:$A, 0), MATCH(1, (Raw!$B$1:$FB$1=$I27)*(Raw!$B$2:$FB$2=$H27), 0))} -> 7150000000 | K27: {=INDEX(Raw!C:FC, MATCH(K$4, Raw!$A:$A, 0), MATCH(1, (Raw!$B$1:$FB$1=$I27)*(Raw!$B$2:$FB$2=$H27), 0))} -> 3371000000 | L27: {=INDEX(Raw!D:FD, MATCH(L$4, Raw!$A:$A, 0), MATCH(1, (Raw!$B$1:$FB$1=$I27)*(Raw!$B$2:$FB$2=$H27), 0))} -> 5502000000 | M27: {=INDEX(Raw!E:FE, MATCH(M$4, Raw!$A:$A, 0), MATCH(1, (Raw!$B$1:$FB$1=$I27)*(Raw!$B$2:$FB$2=$H27), 0))} -> 3116000000 | N27: {=INDEX(Raw!F:FF, MATCH(N$4, Raw!$A:$A, 0), MATCH(1, (Raw!$B$1:$FB$1=$I27)*(Raw!$B$2:$FB$2=$H27), 0))} -> -92000000 | O27: {=INDEX(Raw!G:FG, MATCH(O$4, Raw!$A:$A, 0), MATCH(1, (Raw!$B$1:$FB$1=$I27)*(Raw!$B$2:$FB$2=$H27), 0))} -> 2894000000 | P27: {=INDEX(Raw!H:FH, MATCH(P$4, Raw!$A:$A, 0), MATCH(1, (Raw!$B$1:$FB$1=$I27)*(Raw!$B$2:$FB$2=$H27), 0))} -> 1961000000 | Q27: {=INDEX(Raw!I:FI, MATCH(Q$4, Raw!$A:$A, 0), MATCH(1, (Raw!$B$1:$FB$1=$I27)*(Raw!$B$2:$FB$2=$H27), 0))} -> -241000000 | R27: {=INDEX(Raw!J:FJ, MATCH(R$4, Raw!$A:$A, 0), MATCH(1, (Raw!$B$1:$FB$1=$I27)*(Raw!$B$2:$FB$2=$H27), 0))} -> 2942000000 | S27: {=INDEX(Raw!K:FK, MATCH(S$4, Raw!$A:$A, 0), MATCH(1, (Raw!$B$1:$FB$1=$I27)*(Raw!$B$2:$FB$2=$H27), 0))} -> 506000000 | T27: {=INDEX(Raw!L:FL, MATCH(T$4, Raw!$A:$A, 0), MATCH(1, (Raw!$B$1:$FB$1=$I27)*(Raw!$B$2:$FB$2=$H27), 0))} -> -2717000000 | U27: {=INDEX(Raw!M:FM, MATCH(U$4, Raw!$A:$A, 0), MATCH(1, (Raw!$B$1:$FB$1=$I27)*(Raw!$B$2:$FB$2=$H27), 0))} -> 0 | V27: {=INDEX(Raw!N:FN, MATCH(V$4, Raw!$A:$A, 0), MATCH(1, (Raw!$B$1:$FB$1=$I27)*(Raw!$B$2:$FB$2=$H27), 0))} -> 1372000000 | W27: {=INDEX(Raw!O:FO, MATCH(W$4, Raw!$A:$A, 0), MATCH(1, (Raw!$B$1:$FB$1=$I27)*(Raw!$B$2:$FB$2=$H27), 0))} -> 0 | X27: {=INDEX(Raw!P:FP, MATCH(X$4, Raw!$A:$A, 0), MATCH(1, (Raw!$B$1:$FB$1=$I27)*(Raw!$B$2:$FB$2=$H27), 0))} -> 550000000 | Y27: {=INDEX(Raw!Q:FQ, MATCH(Y$4, Raw!$A:$A, 0), MATCH(1, (Raw!$B$1:$FB$1=$I27)*(Raw!$B$2:$FB$2=$H27), 0))} -> 324115000 | Z27: {=INDEX(Raw!R:FR, MATCH(Z$4, Raw!$A:$A, 0), MATCH(1, (Raw!$B$1:$FB$1=$I27)*(Raw!$B$2:$FB$2=$H27), 0))} -> 0 | AA27: {=INDEX(Raw!S:FS, MATCH(AA$4, Raw!$A:$A, 0), MATCH(1, (Raw!$B$1:$FB$1=$I27)*(Raw!$B$2:$FB$2=$H27), 0))} -> 0 | AB27: {=INDEX(Raw!T:FT, MATCH(AB$4, Raw!$A:$A, 0), MATCH(1, (Raw!$B$1:$FB$1=$I27)*(Raw!$B$2:$FB$2=$H27), 0))} -> 0 | AC27: {=INDEX(Raw!U:FU, MATCH(AC$4, Raw!$A:$A, 0), MATCH(1, (Raw!$B$1:$FB$1=$I27)*(Raw!$B$2:$FB$2=$H27), 0))} -> 0.33 | AD27: {=INDEX(Raw!V:FV, MATCH(AD$4, Raw!$A:$A, 0), MATCH(1, (Raw!$B$1:$FB$1=$I27)*(Raw!$B$2:$FB$2=$H27), 0))} -> 0.71
F28: KO | G28: =TODAY() -> 46088 | H28: =H27 -> 2020 | I28: Q1 | J28: {=INDEX(Raw!B:FB, MATCH(J$4, Raw!$A:$A, 0), MATCH(1, (Raw!$B$1:$FB$1=$I28)*(Raw!$B$2:$FB$2=$H28), 0))} -> 8601000000 | K28: {=INDEX(Raw!C:FC, MATCH(K$4, Raw!$A:$A, 0), MATCH(1, (Raw!$B$1:$FB$1=$I28)*(Raw!$B$2:$FB$2=$H28), 0))} -> 3566000000 | L28: {=INDEX(Raw!D:FD, MATCH(L$4, Raw!$A:$A, 0), MATCH(1, (Raw!$B$1:$FB$1=$I28)*(Raw!$B$2:$FB$2=$H28), 0))} -> 5740000000 | M28: {=INDEX(Raw!E:FE, MATCH(M$4, Raw!$A:$A, 0), MATCH(1, (Raw!$B$1:$FB$1=$I28)*(Raw!$B$2:$FB$2=$H28), 0))} -> 2996000000 | N28: {=INDEX(Raw!F:FF, MATCH(N$4, Raw!$A:$A, 0), MATCH(1, (Raw!$B$1:$FB$1=$I28)*(Raw!$B$2:$FB$2=$H28), 0))} -> -127000000 | O28: {=INDEX(Raw!G:FG, MATCH(O$4, Raw!$A:$A, 0), MATCH(1, (Raw!$B$1:$FB$1=$I28)*(Raw!$B$2:$FB$2=$H28), 0))} -> 3077000000 | P28: {=INDEX(Raw!H:FH, MATCH(P$4, Raw!$A:$A, 0), MATCH(1, (Raw!$B$1:$FB$1=$I28)*(Raw!$B$2:$FB$2=$H28), 0))} -> 2614000000 | Q28: {=INDEX(Raw!I:FI, MATCH(Q$4, Raw!$A:$A, 0), MATCH(1, (Raw!$B$1:$FB$1=$I28)*(Raw!$B$2:$FB$2=$H28), 0))} -> 176000000 | R28: {=INDEX(Raw!J:FJ, MATCH(R$4, Raw!$A:$A, 0), MATCH(1, (Raw!$B$1:$FB$1=$I28)*(Raw!$B$2:$FB$2=$H28), 0))} -> 1833000000 | S28: {=INDEX(Raw!K:FK, MATCH(S$4, Raw!$A:$A, 0), MATCH(1, (Raw!$B$1:$FB$1=$I28)*(Raw!$B$2:$FB$2=$H28), 0))} -> 3802000000 | T28: {=INDEX(Raw!L:FL, MATCH(T$4, Raw!$A:$A, 0), MATCH(1, (Raw!$B$1:$FB$1=$I28)*(Raw!$B$2:$FB$2=$H28), 0))} -> 1444000000 | U28: {=INDEX(Raw!M:FM, MATCH(U$4, Raw!$A:$A, 0), MATCH(1, (Raw!$B$1:$FB$1=$I28)*(Raw!$B$2:$FB$2=$H28), 0))} -> 0 | V28: {=INDEX(Raw!N:FN, MATCH(V$4, Raw!$A:$A, 0), MATCH(1, (Raw!$B$1:$FB$1=$I28)*(Raw!$B$2:$FB$2=$H28), 0))} -> 1184000000 | W28: {=INDEX(Raw!O:FO, MATCH(W$4, Raw!$A:$A, 0), MATCH(1, (Raw!$B$1:$FB$1=$I28)*(Raw!$B$2:$FB$2=$H28), 0))} -> 0 | X28: {=INDEX(Raw!P:FP, MATCH(X$4, Raw!$A:$A, 0), MATCH(1, (Raw!$B$1:$FB$1=$I28)*(Raw!$B$2:$FB$2=$H28), 0))} -> 1046000000 | Y28: {=INDEX(Raw!Q:FQ, MATCH(Y$4, Raw!$A:$A, 0), MATCH(1, (Raw!$B$1:$FB$1=$I28)*(Raw!$B$2:$FB$2=$H28), 0))} -> 0 | Z28: {=INDEX(Raw!R:FR, MATCH(Z$4, Raw!$A:$A, 0), MATCH(1, (Raw!$B$1:$FB$1=$I28)*(Raw!$B$2:$FB$2=$H28), 0))} -> 0 | AA28: {=INDEX(Raw!S:FS, MATCH(AA$4, Raw!$A:$A, 0), MATCH(1, (Raw!$B$1:$FB$1=$I28)*(Raw!$B$2:$FB$2=$H28), 0))} -> 0 | AB28: {=INDEX(Raw!T:FT, MATCH(AB$4, Raw!$A:$A, 0), MATCH(1, (Raw!$B$1:$FB$1=$I28)*(Raw!$B$2:$FB$2=$H28), 0))} -> 0 | AC28: {=INDEX(Raw!U:FU, MATCH(AC$4, Raw!$A:$A, 0), MATCH(1, (Raw!$B$1:$FB$1=$I28)*(Raw!$B$2:$FB$2=$H28), 0))} -> 0.71 | AD28: {=INDEX(Raw!V:FV, MATCH(AD$4, Raw!$A:$A, 0), MATCH(1, (Raw!$B$1:$FB$1=$I28)*(Raw!$B$2:$FB$2=$H28), 0))} -> 0.35
F29: KO | G29: =TODAY() -> 46088 | H29: =H25-1 -> 2019 | I29: Q4 | J29: {=INDEX(Raw!B:FB, MATCH(J$4, Raw!$A:$A, 0), MATCH(1, (Raw!$B$1:$FB$1=$I29)*(Raw!$B$2:$FB$2=$H29), 0))} -> 9068000000 | K29: {=INDEX(Raw!C:FC, MATCH(K$4, Raw!$A:$A, 0), MATCH(1, (Raw!$B$1:$FB$1=$I29)*(Raw!$B$2:$FB$2=$H29), 0))} -> 3767000000 | L29: {=INDEX(Raw!D:FD, MATCH(L$4, Raw!$A:$A, 0), MATCH(1, (Raw!$B$1:$FB$1=$I29)*(Raw!$B$2:$FB$2=$H29), 0))} -> 6076000000 | M29: {=INDEX(Raw!E:FE, MATCH(M$4, Raw!$A:$A, 0), MATCH(1, (Raw!$B$1:$FB$1=$I29)*(Raw!$B$2:$FB$2=$H29), 0))} -> 2767000000 | N29: {=INDEX(Raw!F:FF, MATCH(N$4, Raw!$A:$A, 0), MATCH(1, (Raw!$B$1:$FB$1=$I29)*(Raw!$B$2:$FB$2=$H29), 0))} -> -163000000 | O29: {=INDEX(Raw!G:FG, MATCH(O$4, Raw!$A:$A, 0), MATCH(1, (Raw!$B$1:$FB$1=$I29)*(Raw!$B$2:$FB$2=$H29), 0))} -> 2815000000 | P29: {=INDEX(Raw!H:FH, MATCH(P$4, Raw!$A:$A, 0), MATCH(1, (Raw!$B$1:$FB$1=$I29)*(Raw!$B$2:$FB$2=$H29), 0))} -> 2766000000 | Q29: {=INDEX(Raw!I:FI, MATCH(Q$4, Raw!$A:$A, 0), MATCH(1, (Raw!$B$1:$FB$1=$I29)*(Raw!$B$2:$FB$2=$H29), 0))} -> 22000000 | R29: {=INDEX(Raw!J:FJ, MATCH(R$4, Raw!$A:$A, 0), MATCH(1, (Raw!$B$1:$FB$1=$I29)*(Raw!$B$2:$FB$2=$H29), 0))} -> 1085000000 | S29: {=INDEX(Raw!K:FK, MATCH(S$4, Raw!$A:$A, 0), MATCH(1, (Raw!$B$1:$FB$1=$I29)*(Raw!$B$2:$FB$2=$H29), 0))} -> 230000000 | T29: {=INDEX(Raw!L:FL, MATCH(T$4, Raw!$A:$A, 0), MATCH(1, (Raw!$B$1:$FB$1=$I29)*(Raw!$B$2:$FB$2=$H29), 0))} -> 1372000000 | U29: {=INDEX(Raw!M:FM, MATCH(U$4, Raw!$A:$A, 0), MATCH(1, (Raw!$B$1:$FB$1=$I29)*(Raw!$B$2:$FB$2=$H29), 0))} -> 0 | V29: {=INDEX(Raw!N:FN, MATCH(V$4, Raw!$A:$A, 0), MATCH(1, (Raw!$B$1:$FB$1=$I29)*(Raw!$B$2:$FB$2=$H29), 0))} -> 547000000 | W29: {=INDEX(Raw!O:FO, MATCH(W$4, Raw!$A:$A, 0), MATCH(1, (Raw!$B$1:$FB$1=$I29)*(Raw!$B$2:$FB$2=$H29), 0))} -> 0 | X29: {=INDEX(Raw!P:FP, MATCH(X$4, Raw!$A:$A, 0), MATCH(1, (Raw!$B$1:$FB$1=$I29)*(Raw!$B$2:$FB$2=$H29), 0))} -> 3448000000 | Y29: {=INDEX(Raw!Q:FQ, MATCH(Y$4, Raw!$A:$A, 0), MATCH(1, (Raw!$B$1:$FB$1=$I29)*(Raw!$B$2:$FB$2=$H29), 0))} -> 0 | Z29: {=INDEX(Raw!R:FR, MATCH(Z$4, Raw!$A:$A, 0), MATCH(1, (Raw!$B$1:$FB$1=$I29)*(Raw!$B$2:$FB$2=$H29), 0))} -> 0 | AA29: {=INDEX(Raw!S:FS, MATCH(AA$4, Raw!$A:$A, 0), MATCH(1, (Raw!$B$1:$FB$1=$I29)*(Raw!$B$2:$FB$2=$H29), 0))} -> 0 | AB29: {=INDEX(Raw!T:FT, MATCH(AB$4, Raw!$A:$A, 0), MATCH(1, (Raw!$B$1:$FB$1=$I29)*(Raw!$B$2:$FB$2=$H29), 0))} -> 0 | AC29: {=INDEX(Raw!U:FU, MATCH(AC$4, Raw!$A:$A, 0), MATCH(1, (Raw!$B$1:$FB$1=$I29)*(Raw!$B$2:$FB$2=$H29), 0))} -> 0.36 | AD29: {=INDEX(Raw!V:FV, MATCH(AD$4, Raw!$A:$A, 0), MATCH(1, (Raw!$B$1:$FB$1=$I29)*(Raw!$B$2:$FB$2=$H29), 0))} -> 0.18
F30: KO | G30: =TODAY() -> 46088 | H30: =H29 -> 2019 | I30: Q3 | J30: {=INDEX(Raw!B:FB, MATCH(J$4, Raw!$A:$A, 0), MATCH(1, (Raw!$B$1:$FB$1=$I30)*(Raw!$B$2:$FB$2=$H30), 0))} -> 9507000000 | K30: {=INDEX(Raw!C:FC, MATCH(K$4, Raw!$A:$A, 0), MATCH(1, (Raw!$B$1:$FB$1=$I30)*(Raw!$B$2:$FB$2=$H30), 0))} -> 3921000000 | L30: {=INDEX(Raw!D:FD, MATCH(L$4, Raw!$A:$A, 0), MATCH(1, (Raw!$B$1:$FB$1=$I30)*(Raw!$B$2:$FB$2=$H30), 0))} -> 5329000000 | M30: {=INDEX(Raw!E:FE, MATCH(M$4, Raw!$A:$A, 0), MATCH(1, (Raw!$B$1:$FB$1=$I30)*(Raw!$B$2:$FB$2=$H30), 0))} -> 2914000000 | N30: {=INDEX(Raw!F:FF, MATCH(N$4, Raw!$A:$A, 0), MATCH(1, (Raw!$B$1:$FB$1=$I30)*(Raw!$B$2:$FB$2=$H30), 0))} -> -155000000 | O30: {=INDEX(Raw!G:FG, MATCH(O$4, Raw!$A:$A, 0), MATCH(1, (Raw!$B$1:$FB$1=$I30)*(Raw!$B$2:$FB$2=$H30), 0))} -> 3112000000 | P30: {=INDEX(Raw!H:FH, MATCH(P$4, Raw!$A:$A, 0), MATCH(1, (Raw!$B$1:$FB$1=$I30)*(Raw!$B$2:$FB$2=$H30), 0))} -> 1811000000 | Q30: {=INDEX(Raw!I:FI, MATCH(Q$4, Raw!$A:$A, 0), MATCH(1, (Raw!$B$1:$FB$1=$I30)*(Raw!$B$2:$FB$2=$H30), 0))} -> -425000000 | R30: {=INDEX(Raw!J:FJ, MATCH(R$4, Raw!$A:$A, 0), MATCH(1, (Raw!$B$1:$FB$1=$I30)*(Raw!$B$2:$FB$2=$H30), 0))} -> 1674000000 | S30: {=INDEX(Raw!K:FK, MATCH(S$4, Raw!$A:$A, 0), MATCH(1, (Raw!$B$1:$FB$1=$I30)*(Raw!$B$2:$FB$2=$H30), 0))} -> 1252000000 | T30: {=INDEX(Raw!L:FL, MATCH(T$4, Raw!$A:$A, 0), MATCH(1, (Raw!$B$1:$FB$1=$I30)*(Raw!$B$2:$FB$2=$H30), 0))} -> 1184000000 | U30: {=INDEX(Raw!M:FM, MATCH(U$4, Raw!$A:$A, 0), MATCH(1, (Raw!$B$1:$FB$1=$I30)*(Raw!$B$2:$FB$2=$H30), 0))} -> 0 | V30: {=INDEX(Raw!N:FN, MATCH(V$4, Raw!$A:$A, 0), MATCH(1, (Raw!$B$1:$FB$1=$I30)*(Raw!$B$2:$FB$2=$H30), 0))} -> 1050000000 | W30: {=INDEX(Raw!O:FO, MATCH(W$4, Raw!$A:$A, 0), MATCH(1, (Raw!$B$1:$FB$1=$I30)*(Raw!$B$2:$FB$2=$H30), 0))} -> 0 | X30: {=INDEX(Raw!P:FP, MATCH(X$4, Raw!$A:$A, 0), MATCH(1, (Raw!$B$1:$FB$1=$I30)*(Raw!$B$2:$FB$2=$H30), 0))} -> 1483000000 | Y30: {=INDEX(Raw!Q:FQ, MATCH(Y$4, Raw!$A:$A, 0), MATCH(1, (Raw!$B$1:$FB$1=$I30)*(Raw!$B$2:$FB$2=$H30), 0))} -> 0 | Z30: {=INDEX(Raw!R:FR, MATCH(Z$4, Raw!$A:$A, 0), MATCH(1, (Raw!$B$1:$FB$1=$I30)*(Raw!$B$2:$FB$2=$H30), 0))} -> 0 | AA30: {=INDEX(Raw!S:FS, MATCH(AA$4, Raw!$A:$A, 0), MATCH(1, (Raw!$B$1:$FB$1=$I30)*(Raw!$B$2:$FB$2=$H30), 0))} -> 0 | AB30: {=INDEX(Raw!T:FT, MATCH(AB$4, Raw!$A:$A, 0), MATCH(1, (Raw!$B$1:$FB$1=$I30)*(Raw!$B$2:$FB$2=$H30), 0))} -> 0 | AC30: {=INDEX(Raw!U:FU, MATCH(AC$4, Raw!$A:$A, 0), MATCH(1, (Raw!$B$1:$FB$1=$I30)*(Raw!$B$2:$FB$2=$H30), 0))} -> 0.18 | AD30: {=INDEX(Raw!V:FV, MATCH(AD$4, Raw!$A:$A, 0), MATCH(1, (Raw!$B$1:$FB$1=$I30)*(Raw!$B$2:$FB$2=$H30), 0))} -> 0.48
F31: KO | G31: =TODAY() -> 46088 | H31: =H30 -> 2019 | I31: Q2 | J31: {=INDEX(Raw!B:FB, MATCH(J$4, Raw!$A:$A, 0), MATCH(1, (Raw!$B$1:$FB$1=$I31)*(Raw!$B$2:$FB$2=$H31), 0))} -> 9997000000 | K31: {=INDEX(Raw!C:FC, MATCH(K$4, Raw!$A:$A, 0), MATCH(1, (Raw!$B$1:$FB$1=$I31)*(Raw!$B$2:$FB$2=$H31), 0))} -> 3365000000 | L31: {=INDEX(Raw!D:FD, MATCH(L$4, Raw!$A:$A, 0), MATCH(1, (Raw!$B$1:$FB$1=$I31)*(Raw!$B$2:$FB$2=$H31), 0))} -> 5038000000 | M31: {=INDEX(Raw!E:FE, MATCH(M$4, Raw!$A:$A, 0), MATCH(1, (Raw!$B$1:$FB$1=$I31)*(Raw!$B$2:$FB$2=$H31), 0))} -> 2660000000 | N31: {=INDEX(Raw!F:FF, MATCH(N$4, Raw!$A:$A, 0), MATCH(1, (Raw!$B$1:$FB$1=$I31)*(Raw!$B$2:$FB$2=$H31), 0))} -> -225000000 | O31: {=INDEX(Raw!G:FG, MATCH(O$4, Raw!$A:$A, 0), MATCH(1, (Raw!$B$1:$FB$1=$I31)*(Raw!$B$2:$FB$2=$H31), 0))} -> 3077000000 | P31: {=INDEX(Raw!H:FH, MATCH(P$4, Raw!$A:$A, 0), MATCH(1, (Raw!$B$1:$FB$1=$I31)*(Raw!$B$2:$FB$2=$H31), 0))} -> 1510000000 | Q31: {=INDEX(Raw!I:FI, MATCH(Q$4, Raw!$A:$A, 0), MATCH(1, (Raw!$B$1:$FB$1=$I31)*(Raw!$B$2:$FB$2=$H31), 0))} -> -571000000 | R31: {=INDEX(Raw!J:FJ, MATCH(R$4, Raw!$A:$A, 0), MATCH(1, (Raw!$B$1:$FB$1=$I31)*(Raw!$B$2:$FB$2=$H31), 0))} -> 2624000000 | S31: {=INDEX(Raw!K:FK, MATCH(S$4, Raw!$A:$A, 0), MATCH(1, (Raw!$B$1:$FB$1=$I31)*(Raw!$B$2:$FB$2=$H31), 0))} -> 323000000 | T31: {=INDEX(Raw!L:FL, MATCH(T$4, Raw!$A:$A, 0), MATCH(1, (Raw!$B$1:$FB$1=$I31)*(Raw!$B$2:$FB$2=$H31), 0))} -> 547000000 | U31: {=INDEX(Raw!M:FM, MATCH(U$4, Raw!$A:$A, 0), MATCH(1, (Raw!$B$1:$FB$1=$I31)*(Raw!$B$2:$FB$2=$H31), 0))} -> 0 | V31: {=INDEX(Raw!N:FN, MATCH(V$4, Raw!$A:$A, 0), MATCH(1, (Raw!$B$1:$FB$1=$I31)*(Raw!$B$2:$FB$2=$H31), 0))} -> 3460000000 | W31: {=INDEX(Raw!O:FO, MATCH(W$4, Raw!$A:$A, 0), MATCH(1, (Raw!$B$1:$FB$1=$I31)*(Raw!$B$2:$FB$2=$H31), 0))} -> 0 | X31: {=INDEX(Raw!P:FP, MATCH(X$4, Raw!$A:$A, 0), MATCH(1, (Raw!$B$1:$FB$1=$I31)*(Raw!$B$2:$FB$2=$H31), 0))} -> 1237000000 | Y31: {=INDEX(Raw!Q:FQ, MATCH(Y$4, Raw!$A:$A, 0), MATCH(1, (Raw!$B$1:$FB$1=$I31)*(Raw!$B$2:$FB$2=$H31), 0))} -> 0 | Z31: {=INDEX(Raw!R:FR, MATCH(Z$4, Raw!$A:$A, 0), MATCH(1, (Raw!$B$1:$FB$1=$I31)*(Raw!$B$2:$FB$2=$H31), 0))} -> 0 | AA31: {=INDEX(Raw!S:FS, MATCH(AA$4, Raw!$A:$A, 0), MATCH(1, (Raw!$B$1:$FB$1=$I31)*(Raw!$B$2:$FB$2=$H31), 0))} -> 0 | AB31: {=INDEX(Raw!T:FT, MATCH(AB$4, Raw!$A:$A, 0), MATCH(1, (Raw!$B$1:$FB$1=$I31)*(Raw!$B$2:$FB$2=$H31), 0))} -> 0 | AC31: {=INDEX(Raw!U:FU, MATCH(AC$4, Raw!$A:$A, 0), MATCH(1, (Raw!$B$1:$FB$1=$I31)*(Raw!$B$2:$FB$2=$H31), 0))} -> 0.48 | AD31: {=INDEX(Raw!V:FV, MATCH(AD$4, Raw!$A:$A, 0), MATCH(1, (Raw!$B$1:$FB$1=$I31)*(Raw!$B$2:$FB$2=$H31), 0))} -> 0.58
F32: KO | G32: =TODAY() -> 46088 | H32: =H31 -> 2019 | I32: Q1 | J32: {=INDEX(Raw!B:FB, MATCH(J$4, Raw!$A:$A, 0), MATCH(1, (Raw!$B$1:$FB$1=$I32)*(Raw!$B$2:$FB$2=$H32), 0))} -> 8694000000 | K32: {=INDEX(Raw!C:FC, MATCH(K$4, Raw!$A:$A, 0), MATCH(1, (Raw!$B$1:$FB$1=$I32)*(Raw!$B$2:$FB$2=$H32), 0))} -> 3440000000 | L32: {=INDEX(Raw!D:FD, MATCH(L$4, Raw!$A:$A, 0), MATCH(1, (Raw!$B$1:$FB$1=$I32)*(Raw!$B$2:$FB$2=$H32), 0))} -> 5429000000 | M32: {=INDEX(Raw!E:FE, MATCH(M$4, Raw!$A:$A, 0), MATCH(1, (Raw!$B$1:$FB$1=$I32)*(Raw!$B$2:$FB$2=$H32), 0))} -> 2887000000 | N32: {=INDEX(Raw!F:FF, MATCH(N$4, Raw!$A:$A, 0), MATCH(1, (Raw!$B$1:$FB$1=$I32)*(Raw!$B$2:$FB$2=$H32), 0))} -> -536000000 | O32: {=INDEX(Raw!G:FG, MATCH(O$4, Raw!$A:$A, 0), MATCH(1, (Raw!$B$1:$FB$1=$I32)*(Raw!$B$2:$FB$2=$H32), 0))} -> 3649000000 | P32: {=INDEX(Raw!H:FH, MATCH(P$4, Raw!$A:$A, 0), MATCH(1, (Raw!$B$1:$FB$1=$I32)*(Raw!$B$2:$FB$2=$H32), 0))} -> 2245000000 | Q32: {=INDEX(Raw!I:FI, MATCH(Q$4, Raw!$A:$A, 0), MATCH(1, (Raw!$B$1:$FB$1=$I32)*(Raw!$B$2:$FB$2=$H32), 0))} -> 587000000 | R32: {=INDEX(Raw!J:FJ, MATCH(R$4, Raw!$A:$A, 0), MATCH(1, (Raw!$B$1:$FB$1=$I32)*(Raw!$B$2:$FB$2=$H32), 0))} -> 1507000000 | S32: {=INDEX(Raw!K:FK, MATCH(S$4, Raw!$A:$A, 0), MATCH(1, (Raw!$B$1:$FB$1=$I32)*(Raw!$B$2:$FB$2=$H32), 0))} -> -32000000 | T32: {=INDEX(Raw!L:FL, MATCH(T$4, Raw!$A:$A, 0), MATCH(1, (Raw!$B$1:$FB$1=$I32)*(Raw!$B$2:$FB$2=$H32), 0))} -> 1050000000 | U32: {=INDEX(Raw!M:FM, MATCH(U$4, Raw!$A:$A, 0), MATCH(1, (Raw!$B$1:$FB$1=$I32)*(Raw!$B$2:$FB$2=$H32), 0))} -> 0 | V32: {=INDEX(Raw!N:FN, MATCH(V$4, Raw!$A:$A, 0), MATCH(1, (Raw!$B$1:$FB$1=$I32)*(Raw!$B$2:$FB$2=$H32), 0))} -> 1493000000 | W32: {=INDEX(Raw!O:FO, MATCH(W$4, Raw!$A:$A, 0), MATCH(1, (Raw!$B$1:$FB$1=$I32)*(Raw!$B$2:$FB$2=$H32), 0))} -> 0 | X32: {=INDEX(Raw!P:FP, MATCH(X$4, Raw!$A:$A, 0), MATCH(1, (Raw!$B$1:$FB$1=$I32)*(Raw!$B$2:$FB$2=$H32), 0))} -> 1449000000 | Y32: {=INDEX(Raw!Q:FQ, MATCH(Y$4, Raw!$A:$A, 0), MATCH(1, (Raw!$B$1:$FB$1=$I32)*(Raw!$B$2:$FB$2=$H32), 0))} -> 0 | Z32: {=INDEX(Raw!R:FR, MATCH(Z$4, Raw!$A:$A, 0), MATCH(1, (Raw!$B$1:$FB$1=$I32)*(Raw!$B$2:$FB$2=$H32), 0))} -> 0 | AA32: {=INDEX(Raw!S:FS, MATCH(AA$4, Raw!$A:$A, 0), MATCH(1, (Raw!$B$1:$FB$1=$I32)*(Raw!$B$2:$FB$2=$H32), 0))} -> 0 | AB32: {=INDEX(Raw!T:FT, MATCH(AB$4, Raw!$A:$A, 0), MATCH(1, (Raw!$B$1:$FB$1=$I32)*(Raw!$B$2:$FB$2=$H32), 0))} -> 0 | AC32: {=INDEX(Raw!U:FU, MATCH(AC$4, Raw!$A:$A, 0), MATCH(1, (Raw!$B$1:$FB$1=$I32)*(Raw!$B$2:$FB$2=$H32), 0))} -> 0.59 | AD32: {=INDEX(Raw!V:FV, MATCH(AD$4, Raw!$A:$A, 0), MATCH(1, (Raw!$B$1:$FB$1=$I32)*(Raw!$B$2:$FB$2=$H32), 0))} -> 0.36
F33: KO | G33: =TODAY() -> 46088 | H33: =H29-1 -> 2018 | I33: Q4 | J33: {=INDEX(Raw!B:FB, MATCH(J$4, Raw!$A:$A, 0), MATCH(1, (Raw!$B$1:$FB$1=$I33)*(Raw!$B$2:$FB$2=$H33), 0))} -> 8478000000 | K33: {=INDEX(Raw!C:FC, MATCH(K$4, Raw!$A:$A, 0), MATCH(1, (Raw!$B$1:$FB$1=$I33)*(Raw!$B$2:$FB$2=$H33), 0))} -> 3346000000 | L33: {=INDEX(Raw!D:FD, MATCH(L$4, Raw!$A:$A, 0), MATCH(1, (Raw!$B$1:$FB$1=$I33)*(Raw!$B$2:$FB$2=$H33), 0))} -> 5878000000 | M33: {=INDEX(Raw!E:FE, MATCH(M$4, Raw!$A:$A, 0), MATCH(1, (Raw!$B$1:$FB$1=$I33)*(Raw!$B$2:$FB$2=$H33), 0))} -> 2541000000 | N33: {=INDEX(Raw!F:FF, MATCH(N$4, Raw!$A:$A, 0), MATCH(1, (Raw!$B$1:$FB$1=$I33)*(Raw!$B$2:$FB$2=$H33), 0))} -> -592000000 | O33: {=INDEX(Raw!G:FG, MATCH(O$4, Raw!$A:$A, 0), MATCH(1, (Raw!$B$1:$FB$1=$I33)*(Raw!$B$2:$FB$2=$H33), 0))} -> 3439000000 | P33: {=INDEX(Raw!H:FH, MATCH(P$4, Raw!$A:$A, 0), MATCH(1, (Raw!$B$1:$FB$1=$I33)*(Raw!$B$2:$FB$2=$H33), 0))} -> 2037000000 | Q33: {=INDEX(Raw!I:FI, MATCH(Q$4, Raw!$A:$A, 0), MATCH(1, (Raw!$B$1:$FB$1=$I33)*(Raw!$B$2:$FB$2=$H33), 0))} -> -456000000 | R33: {=INDEX(Raw!J:FJ, MATCH(R$4, Raw!$A:$A, 0), MATCH(1, (Raw!$B$1:$FB$1=$I33)*(Raw!$B$2:$FB$2=$H33), 0))} -> 515000000 | S33: {=INDEX(Raw!K:FK, MATCH(S$4, Raw!$A:$A, 0), MATCH(1, (Raw!$B$1:$FB$1=$I33)*(Raw!$B$2:$FB$2=$H33), 0))} -> 378000000 | T33: {=INDEX(Raw!L:FL, MATCH(T$4, Raw!$A:$A, 0), MATCH(1, (Raw!$B$1:$FB$1=$I33)*(Raw!$B$2:$FB$2=$H33), 0))} -> 3460000000 | U33: {=INDEX(Raw!M:FM, MATCH(U$4, Raw!$A:$A, 0), MATCH(1, (Raw!$B$1:$FB$1=$I33)*(Raw!$B$2:$FB$2=$H33), 0))} -> 0 | V33: {=INDEX(Raw!N:FN, MATCH(V$4, Raw!$A:$A, 0), MATCH(1, (Raw!$B$1:$FB$1=$I33)*(Raw!$B$2:$FB$2=$H33), 0))} -> 1236000000 | W33: {=INDEX(Raw!O:FO, MATCH(W$4, Raw!$A:$A, 0), MATCH(1, (Raw!$B$1:$FB$1=$I33)*(Raw!$B$2:$FB$2=$H33), 0))} -> 0 | X33: {=INDEX(Raw!P:FP, MATCH(X$4, Raw!$A:$A, 0), MATCH(1, (Raw!$B$1:$FB$1=$I33)*(Raw!$B$2:$FB$2=$H33), 0))} -> 3108000000 | Y33: {=INDEX(Raw!Q:FQ, MATCH(Y$4, Raw!$A:$A, 0), MATCH(1, (Raw!$B$1:$FB$1=$I33)*(Raw!$B$2:$FB$2=$H33), 0))} -> 0 | Z33: {=INDEX(Raw!R:FR, MATCH(Z$4, Raw!$A:$A, 0), MATCH(1, (Raw!$B$1:$FB$1=$I33)*(Raw!$B$2:$FB$2=$H33), 0))} -> 0 | AA33: {=INDEX(Raw!S:FS, MATCH(AA$4, Raw!$A:$A, 0), MATCH(1, (Raw!$B$1:$FB$1=$I33)*(Raw!$B$2:$FB$2=$H33), 0))} -> 0 | AB33: {=INDEX(Raw!T:FT, MATCH(AB$4, Raw!$A:$A, 0), MATCH(1, (Raw!$B$1:$FB$1=$I33)*(Raw!$B$2:$FB$2=$H33), 0))} -> 0 | AC33: {=INDEX(Raw!U:FU, MATCH(AC$4, Raw!$A:$A, 0), MATCH(1, (Raw!$B$1:$FB$1=$I33)*(Raw!$B$2:$FB$2=$H33), 0))} -> 0.37 | AD33: {=INDEX(Raw!V:FV, MATCH(AD$4, Raw!$A:$A, 0), MATCH(1, (Raw!$B$1:$FB$1=$I33)*(Raw!$B$2:$FB$2=$H33), 0))} -> 0.38
F34: KO | G34: =TODAY() -> 46088 | H34: =H33 -> 2018 | I34: Q3 | J34: {=INDEX(Raw!B:FB, MATCH(J$4, Raw!$A:$A, 0), MATCH(1, (Raw!$B$1:$FB$1=$I34)*(Raw!$B$2:$FB$2=$H34), 0))} -> 8775000000 | K34: {=INDEX(Raw!C:FC, MATCH(K$4, Raw!$A:$A, 0), MATCH(1, (Raw!$B$1:$FB$1=$I34)*(Raw!$B$2:$FB$2=$H34), 0))} -> 3543000000 | L34: {=INDEX(Raw!D:FD, MATCH(L$4, Raw!$A:$A, 0), MATCH(1, (Raw!$B$1:$FB$1=$I34)*(Raw!$B$2:$FB$2=$H34), 0))} -> 4888000000 | M34: {=INDEX(Raw!E:FE, MATCH(M$4, Raw!$A:$A, 0), MATCH(1, (Raw!$B$1:$FB$1=$I34)*(Raw!$B$2:$FB$2=$H34), 0))} -> 3057000000 | N34: {=INDEX(Raw!F:FF, MATCH(N$4, Raw!$A:$A, 0), MATCH(1, (Raw!$B$1:$FB$1=$I34)*(Raw!$B$2:$FB$2=$H34), 0))} -> -194000000 | O34: {=INDEX(Raw!G:FG, MATCH(O$4, Raw!$A:$A, 0), MATCH(1, (Raw!$B$1:$FB$1=$I34)*(Raw!$B$2:$FB$2=$H34), 0))} -> 4006000000 | P34: {=INDEX(Raw!H:FH, MATCH(P$4, Raw!$A:$A, 0), MATCH(1, (Raw!$B$1:$FB$1=$I34)*(Raw!$B$2:$FB$2=$H34), 0))} -> 1963000000 | Q34: {=INDEX(Raw!I:FI, MATCH(Q$4, Raw!$A:$A, 0), MATCH(1, (Raw!$B$1:$FB$1=$I34)*(Raw!$B$2:$FB$2=$H34), 0))} -> -871000000 | R34: {=INDEX(Raw!J:FJ, MATCH(R$4, Raw!$A:$A, 0), MATCH(1, (Raw!$B$1:$FB$1=$I34)*(Raw!$B$2:$FB$2=$H34), 0))} -> 1428000000 | S34: {=INDEX(Raw!K:FK, MATCH(S$4, Raw!$A:$A, 0), MATCH(1, (Raw!$B$1:$FB$1=$I34)*(Raw!$B$2:$FB$2=$H34), 0))} -> 839000000 | T34: {=INDEX(Raw!L:FL, MATCH(T$4, Raw!$A:$A, 0), MATCH(1, (Raw!$B$1:$FB$1=$I34)*(Raw!$B$2:$FB$2=$H34), 0))} -> 1493000000 | U34: {=INDEX(Raw!M:FM, MATCH(U$4, Raw!$A:$A, 0), MATCH(1, (Raw!$B$1:$FB$1=$I34)*(Raw!$B$2:$FB$2=$H34), 0))} -> 0 | V34: {=INDEX(Raw!N:FN, MATCH(V$4, Raw!$A:$A, 0), MATCH(1, (Raw!$B$1:$FB$1=$I34)*(Raw!$B$2:$FB$2=$H34), 0))} -> 1453000000 | W34: {=INDEX(Raw!O:FO, MATCH(W$4, Raw!$A:$A, 0), MATCH(1, (Raw!$B$1:$FB$1=$I34)*(Raw!$B$2:$FB$2=$H34), 0))} -> 0 | X34: {=INDEX(Raw!P:FP, MATCH(X$4, Raw!$A:$A, 0), MATCH(1, (Raw!$B$1:$FB$1=$I34)*(Raw!$B$2:$FB$2=$H34), 0))} -> 1557000000 | Y34: {=INDEX(Raw!Q:FQ, MATCH(Y$4, Raw!$A:$A, 0), MATCH(1, (Raw!$B$1:$FB$1=$I34)*(Raw!$B$2:$FB$2=$H34), 0))} -> 0 | Z34: {=INDEX(Raw!R:FR, MATCH(Z$4, Raw!$A:$A, 0), MATCH(1, (Raw!$B$1:$FB$1=$I34)*(Raw!$B$2:$FB$2=$H34), 0))} -> 0 | AA34: {=INDEX(Raw!S:FS, MATCH(AA$4, Raw!$A:$A, 0), MATCH(1, (Raw!$B$1:$FB$1=$I34)*(Raw!$B$2:$FB$2=$H34), 0))} -> 0 | AB34: {=INDEX(Raw!T:FT, MATCH(AB$4, Raw!$A:$A, 0), MATCH(1, (Raw!$B$1:$FB$1=$I34)*(Raw!$B$2:$FB$2=$H34), 0))} -> 0 | AC34: {=INDEX(Raw!U:FU, MATCH(AC$4, Raw!$A:$A, 0), MATCH(1, (Raw!$B$1:$FB$1=$I34)*(Raw!$B$2:$FB$2=$H34), 0))} -> 0.4 | AD34: {=INDEX(Raw!V:FV, MATCH(AD$4, Raw!$A:$A, 0), MATCH(1, (Raw!$B$1:$FB$1=$I34)*(Raw!$B$2:$FB$2=$H34), 0))} -> 0.54
F35: KO | G35: =TODAY() -> 46088 | H35: =H34 -> 2018 | I35: Q2 | J35: {=INDEX(Raw!B:FB, MATCH(J$4, Raw!$A:$A, 0), MATCH(1, (Raw!$B$1:$FB$1=$I35)*(Raw!$B$2:$FB$2=$H35), 0))} -> 9421000000 | K35: {=INDEX(Raw!C:FC, MATCH(K$4, Raw!$A:$A, 0), MATCH(1, (Raw!$B$1:$FB$1=$I35)*(Raw!$B$2:$FB$2=$H35), 0))} -> 2738000000 | L35: {=INDEX(Raw!D:FD, MATCH(L$4, Raw!$A:$A, 0), MATCH(1, (Raw!$B$1:$FB$1=$I35)*(Raw!$B$2:$FB$2=$H35), 0))} -> 5159000000 | M35: {=INDEX(Raw!E:FE, MATCH(M$4, Raw!$A:$A, 0), MATCH(1, (Raw!$B$1:$FB$1=$I35)*(Raw!$B$2:$FB$2=$H35), 0))} -> 3245000000 | N35: {=INDEX(Raw!F:FF, MATCH(N$4, Raw!$A:$A, 0), MATCH(1, (Raw!$B$1:$FB$1=$I35)*(Raw!$B$2:$FB$2=$H35), 0))} -> -826000000 | O35: {=INDEX(Raw!G:FG, MATCH(O$4, Raw!$A:$A, 0), MATCH(1, (Raw!$B$1:$FB$1=$I35)*(Raw!$B$2:$FB$2=$H35), 0))} -> 3642000000 | P35: {=INDEX(Raw!H:FH, MATCH(P$4, Raw!$A:$A, 0), MATCH(1, (Raw!$B$1:$FB$1=$I35)*(Raw!$B$2:$FB$2=$H35), 0))} -> 1386000000 | Q35: {=INDEX(Raw!I:FI, MATCH(Q$4, Raw!$A:$A, 0), MATCH(1, (Raw!$B$1:$FB$1=$I35)*(Raw!$B$2:$FB$2=$H35), 0))} -> -843000000 | R35: {=INDEX(Raw!J:FJ, MATCH(R$4, Raw!$A:$A, 0), MATCH(1, (Raw!$B$1:$FB$1=$I35)*(Raw!$B$2:$FB$2=$H35), 0))} -> 4299000000 | S35: {=INDEX(Raw!K:FK, MATCH(S$4, Raw!$A:$A, 0), MATCH(1, (Raw!$B$1:$FB$1=$I35)*(Raw!$B$2:$FB$2=$H35), 0))} -> 401000000 | T35: {=INDEX(Raw!L:FL, MATCH(T$4, Raw!$A:$A, 0), MATCH(1, (Raw!$B$1:$FB$1=$I35)*(Raw!$B$2:$FB$2=$H35), 0))} -> 1236000000 | U35: {=INDEX(Raw!M:FM, MATCH(U$4, Raw!$A:$A, 0), MATCH(1, (Raw!$B$1:$FB$1=$I35)*(Raw!$B$2:$FB$2=$H35), 0))} -> 0 | V35: {=INDEX(Raw!N:FN, MATCH(V$4, Raw!$A:$A, 0), MATCH(1, (Raw!$B$1:$FB$1=$I35)*(Raw!$B$2:$FB$2=$H35), 0))} -> 3111000000 | W35: {=INDEX(Raw!O:FO, MATCH(W$4, Raw!$A:$A, 0), MATCH(1, (Raw!$B$1:$FB$1=$I35)*(Raw!$B$2:$FB$2=$H35), 0))} -> 0 | X35: {=INDEX(Raw!P:FP, MATCH(X$4, Raw!$A:$A, 0), MATCH(1, (Raw!$B$1:$FB$1=$I35)*(Raw!$B$2:$FB$2=$H35), 0))} -> 770000000 | Y35: {=INDEX(Raw!Q:FQ, MATCH(Y$4, Raw!$A:$A, 0), MATCH(1, (Raw!$B$1:$FB$1=$I35)*(Raw!$B$2:$FB$2=$H35), 0))} -> 0 | Z35: {=INDEX(Raw!R:FR, MATCH(Z$4, Raw!$A:$A, 0), MATCH(1, (Raw!$B$1:$FB$1=$I35)*(Raw!$B$2:$FB$2=$H35), 0))} -> 0 | AA35: {=INDEX(Raw!S:FS, MATCH(AA$4, Raw!$A:$A, 0), MATCH(1, (Raw!$B$1:$FB$1=$I35)*(Raw!$B$2:$FB$2=$H35), 0))} -> 0 | AB35: {=INDEX(Raw!T:FT, MATCH(AB$4, Raw!$A:$A, 0), MATCH(1, (Raw!$B$1:$FB$1=$I35)*(Raw!$B$2:$FB$2=$H35), 0))} -> 0 | AC35: {=INDEX(Raw!U:FU, MATCH(AC$4, Raw!$A:$A, 0), MATCH(1, (Raw!$B$1:$FB$1=$I35)*(Raw!$B$2:$FB$2=$H35), 0))} -> 0.55 | AD35: {=INDEX(Raw!V:FV, MATCH(AD$4, Raw!$A:$A, 0), MATCH(1, (Raw!$B$1:$FB$1=$I35)*(Raw!$B$2:$FB$2=$H35), 0))} -> 0.59
F36: KO | G36: =TODAY() -> 46088 | H36: =H35 -> 2018 | I36: Q1 | J36: {=INDEX(Raw!B:FB, MATCH(J$4, Raw!$A:$A, 0), MATCH(1, (Raw!$B$1:$FB$1=$I36)*(Raw!$B$2:$FB$2=$H36), 0))} -> 7626000000 | K36: {=INDEX(Raw!C:FC, MATCH(K$4, Raw!$A:$A, 0), MATCH(1, (Raw!$B$1:$FB$1=$I36)*(Raw!$B$2:$FB$2=$H36), 0))} -> 3155000000 | L36: {=INDEX(Raw!D:FD, MATCH(L$4, Raw!$A:$A, 0), MATCH(1, (Raw!$B$1:$FB$1=$I36)*(Raw!$B$2:$FB$2=$H36), 0))} -> 5684000000 | M36: {=INDEX(Raw!E:FE, MATCH(M$4, Raw!$A:$A, 0), MATCH(1, (Raw!$B$1:$FB$1=$I36)*(Raw!$B$2:$FB$2=$H36), 0))} -> 3180000000 | N36: {=INDEX(Raw!F:FF, MATCH(N$4, Raw!$A:$A, 0), MATCH(1, (Raw!$B$1:$FB$1=$I36)*(Raw!$B$2:$FB$2=$H36), 0))} -> -290000000 | O36: {=INDEX(Raw!G:FG, MATCH(O$4, Raw!$A:$A, 0), MATCH(1, (Raw!$B$1:$FB$1=$I36)*(Raw!$B$2:$FB$2=$H36), 0))} -> 4229000000 | P36: {=INDEX(Raw!H:FH, MATCH(P$4, Raw!$A:$A, 0), MATCH(1, (Raw!$B$1:$FB$1=$I36)*(Raw!$B$2:$FB$2=$H36), 0))} -> 2271000000 | Q36: {=INDEX(Raw!I:FI, MATCH(Q$4, Raw!$A:$A, 0), MATCH(1, (Raw!$B$1:$FB$1=$I36)*(Raw!$B$2:$FB$2=$H36), 0))} -> 1440000000 | R36: {=INDEX(Raw!J:FJ, MATCH(R$4, Raw!$A:$A, 0), MATCH(1, (Raw!$B$1:$FB$1=$I36)*(Raw!$B$2:$FB$2=$H36), 0))} -> 1894000000 | S36: {=INDEX(Raw!K:FK, MATCH(S$4, Raw!$A:$A, 0), MATCH(1, (Raw!$B$1:$FB$1=$I36)*(Raw!$B$2:$FB$2=$H36), 0))} -> 302000000 | T36: {=INDEX(Raw!L:FL, MATCH(T$4, Raw!$A:$A, 0), MATCH(1, (Raw!$B$1:$FB$1=$I36)*(Raw!$B$2:$FB$2=$H36), 0))} -> 1453000000 | U36: {=INDEX(Raw!M:FM, MATCH(U$4, Raw!$A:$A, 0), MATCH(1, (Raw!$B$1:$FB$1=$I36)*(Raw!$B$2:$FB$2=$H36), 0))} -> 0 | V36: {=INDEX(Raw!N:FN, MATCH(V$4, Raw!$A:$A, 0), MATCH(1, (Raw!$B$1:$FB$1=$I36)*(Raw!$B$2:$FB$2=$H36), 0))} -> 1566000000 | W36: {=INDEX(Raw!O:FO, MATCH(W$4, Raw!$A:$A, 0), MATCH(1, (Raw!$B$1:$FB$1=$I36)*(Raw!$B$2:$FB$2=$H36), 0))} -> 0 | X36: {=INDEX(Raw!P:FP, MATCH(X$4, Raw!$A:$A, 0), MATCH(1, (Raw!$B$1:$FB$1=$I36)*(Raw!$B$2:$FB$2=$H36), 0))} -> 2114000000 | Y36: {=INDEX(Raw!Q:FQ, MATCH(Y$4, Raw!$A:$A, 0), MATCH(1, (Raw!$B$1:$FB$1=$I36)*(Raw!$B$2:$FB$2=$H36), 0))} -> 0 | Z36: {=INDEX(Raw!R:FR, MATCH(Z$4, Raw!$A:$A, 0), MATCH(1, (Raw!$B$1:$FB$1=$I36)*(Raw!$B$2:$FB$2=$H36), 0))} -> 0 | AA36: {=INDEX(Raw!S:FS, MATCH(AA$4, Raw!$A:$A, 0), MATCH(1, (Raw!$B$1:$FB$1=$I36)*(Raw!$B$2:$FB$2=$H36), 0))} -> 0 | AB36: {=INDEX(Raw!T:FT, MATCH(AB$4, Raw!$A:$A, 0), MATCH(1, (Raw!$B$1:$FB$1=$I36)*(Raw!$B$2:$FB$2=$H36), 0))} -> 0 | AC36: {=INDEX(Raw!U:FU, MATCH(AC$4, Raw!$A:$A, 0), MATCH(1, (Raw!$B$1:$FB$1=$I36)*(Raw!$B$2:$FB$2=$H36), 0))} -> 0.6 | AD36: {=INDEX(Raw!V:FV, MATCH(AD$4, Raw!$A:$A, 0), MATCH(1, (Raw!$B$1:$FB$1=$I36)*(Raw!$B$2:$FB$2=$H36), 0))} -> 0.39
F37: KO | G37: =TODAY() -> 46088 | H37: =H33-1 -> 2017 | I37: Q4 | J37: {=INDEX(Raw!B:FB, MATCH(J$4, Raw!$A:$A, 0), MATCH(1, (Raw!$B$1:$FB$1=$I37)*(Raw!$B$2:$FB$2=$H37), 0))} -> 8314000000 | K37: {=INDEX(Raw!C:FC, MATCH(K$4, Raw!$A:$A, 0), MATCH(1, (Raw!$B$1:$FB$1=$I37)*(Raw!$B$2:$FB$2=$H37), 0))} -> 3394000000 | L37: {=INDEX(Raw!D:FD, MATCH(L$4, Raw!$A:$A, 0), MATCH(1, (Raw!$B$1:$FB$1=$I37)*(Raw!$B$2:$FB$2=$H37), 0))} -> 6043000000 | M37: {=INDEX(Raw!E:FE, MATCH(M$4, Raw!$A:$A, 0), MATCH(1, (Raw!$B$1:$FB$1=$I37)*(Raw!$B$2:$FB$2=$H37), 0))} -> 3352000000 | N37: {=INDEX(Raw!F:FF, MATCH(N$4, Raw!$A:$A, 0), MATCH(1, (Raw!$B$1:$FB$1=$I37)*(Raw!$B$2:$FB$2=$H37), 0))} -> -541000000 | O37: {=INDEX(Raw!G:FG, MATCH(O$4, Raw!$A:$A, 0), MATCH(1, (Raw!$B$1:$FB$1=$I37)*(Raw!$B$2:$FB$2=$H37), 0))} -> 4231000000 | P37: {=INDEX(Raw!H:FH, MATCH(P$4, Raw!$A:$A, 0), MATCH(1, (Raw!$B$1:$FB$1=$I37)*(Raw!$B$2:$FB$2=$H37), 0))} -> 2859000000 | Q37: {=INDEX(Raw!I:FI, MATCH(Q$4, Raw!$A:$A, 0), MATCH(1, (Raw!$B$1:$FB$1=$I37)*(Raw!$B$2:$FB$2=$H37), 0))} -> -247000000 | R37: {=INDEX(Raw!J:FJ, MATCH(R$4, Raw!$A:$A, 0), MATCH(1, (Raw!$B$1:$FB$1=$I37)*(Raw!$B$2:$FB$2=$H37), 0))} -> 1538000000 | S37: {=INDEX(Raw!K:FK, MATCH(S$4, Raw!$A:$A, 0), MATCH(1, (Raw!$B$1:$FB$1=$I37)*(Raw!$B$2:$FB$2=$H37), 0))} -> 272000000 | T37: {=INDEX(Raw!L:FL, MATCH(T$4, Raw!$A:$A, 0), MATCH(1, (Raw!$B$1:$FB$1=$I37)*(Raw!$B$2:$FB$2=$H37), 0))} -> 3111000000 | U37: {=INDEX(Raw!M:FM, MATCH(U$4, Raw!$A:$A, 0), MATCH(1, (Raw!$B$1:$FB$1=$I37)*(Raw!$B$2:$FB$2=$H37), 0))} -> 0 | V37: {=INDEX(Raw!N:FN, MATCH(V$4, Raw!$A:$A, 0), MATCH(1, (Raw!$B$1:$FB$1=$I37)*(Raw!$B$2:$FB$2=$H37), 0))} -> 771000000 | W37: {=INDEX(Raw!O:FO, MATCH(W$4, Raw!$A:$A, 0), MATCH(1, (Raw!$B$1:$FB$1=$I37)*(Raw!$B$2:$FB$2=$H37), 0))} -> 0 | X37: {=INDEX(Raw!P:FP, MATCH(X$4, Raw!$A:$A, 0), MATCH(1, (Raw!$B$1:$FB$1=$I37)*(Raw!$B$2:$FB$2=$H37), 0))} -> 2595000000 | Y37: {=INDEX(Raw!Q:FQ, MATCH(Y$4, Raw!$A:$A, 0), MATCH(1, (Raw!$B$1:$FB$1=$I37)*(Raw!$B$2:$FB$2=$H37), 0))} -> 0 | Z37: {=INDEX(Raw!R:FR, MATCH(Z$4, Raw!$A:$A, 0), MATCH(1, (Raw!$B$1:$FB$1=$I37)*(Raw!$B$2:$FB$2=$H37), 0))} -> 0 | AA37: {=INDEX(Raw!S:FS, MATCH(AA$4, Raw!$A:$A, 0), MATCH(1, (Raw!$B$1:$FB$1=$I37)*(Raw!$B$2:$FB$2=$H37), 0))} -> 0 | AB37: {=INDEX(Raw!T:FT, MATCH(AB$4, Raw!$A:$A, 0), MATCH(1, (Raw!$B$1:$FB$1=$I37)*(Raw!$B$2:$FB$2=$H37), 0))} -> 0 | AC37: {=INDEX(Raw!U:FU, MATCH(AC$4, Raw!$A:$A, 0), MATCH(1, (Raw!$B$1:$FB$1=$I37)*(Raw!$B$2:$FB$2=$H37), 0))} -> 0.39 | AD37: {=INDEX(Raw!V:FV, MATCH(AD$4, Raw!$A:$A, 0), MATCH(1, (Raw!$B$1:$FB$1=$I37)*(Raw!$B$2:$FB$2=$H37), 0))} -> 0.41
F38: KO | G38: =TODAY() -> 46088 | H38: =H37 -> 2017 | I38: Q3 | J38: {=INDEX(Raw!B:FB, MATCH(J$4, Raw!$A:$A, 0), MATCH(1, (Raw!$B$1:$FB$1=$I38)*(Raw!$B$2:$FB$2=$H38), 0))} -> 9078000000 | K38: {=INDEX(Raw!C:FC, MATCH(K$4, Raw!$A:$A, 0), MATCH(1, (Raw!$B$1:$FB$1=$I38)*(Raw!$B$2:$FB$2=$H38), 0))} -> 3659000000 | L38: {=INDEX(Raw!D:FD, MATCH(L$4, Raw!$A:$A, 0), MATCH(1, (Raw!$B$1:$FB$1=$I38)*(Raw!$B$2:$FB$2=$H38), 0))} -> 5605000000 | M38: {=INDEX(Raw!E:FE, MATCH(M$4, Raw!$A:$A, 0), MATCH(1, (Raw!$B$1:$FB$1=$I38)*(Raw!$B$2:$FB$2=$H38), 0))} -> 3688000000 | N38: {=INDEX(Raw!F:FF, MATCH(N$4, Raw!$A:$A, 0), MATCH(1, (Raw!$B$1:$FB$1=$I38)*(Raw!$B$2:$FB$2=$H38), 0))} -> -222000000 | O38: {=INDEX(Raw!G:FG, MATCH(O$4, Raw!$A:$A, 0), MATCH(1, (Raw!$B$1:$FB$1=$I38)*(Raw!$B$2:$FB$2=$H38), 0))} -> 4209000000 | P38: {=INDEX(Raw!H:FH, MATCH(P$4, Raw!$A:$A, 0), MATCH(1, (Raw!$B$1:$FB$1=$I38)*(Raw!$B$2:$FB$2=$H38), 0))} -> 2141000000 | Q38: {=INDEX(Raw!I:FI, MATCH(Q$4, Raw!$A:$A, 0), MATCH(1, (Raw!$B$1:$FB$1=$I38)*(Raw!$B$2:$FB$2=$H38), 0))} -> 20000000 | R38: {=INDEX(Raw!J:FJ, MATCH(R$4, Raw!$A:$A, 0), MATCH(1, (Raw!$B$1:$FB$1=$I38)*(Raw!$B$2:$FB$2=$H38), 0))} -> 1725000000 | S38: {=INDEX(Raw!K:FK, MATCH(S$4, Raw!$A:$A, 0), MATCH(1, (Raw!$B$1:$FB$1=$I38)*(Raw!$B$2:$FB$2=$H38), 0))} -> 1250000000 | T38: {=INDEX(Raw!L:FL, MATCH(T$4, Raw!$A:$A, 0), MATCH(1, (Raw!$B$1:$FB$1=$I38)*(Raw!$B$2:$FB$2=$H38), 0))} -> 1566000000 | U38: {=INDEX(Raw!M:FM, MATCH(U$4, Raw!$A:$A, 0), MATCH(1, (Raw!$B$1:$FB$1=$I38)*(Raw!$B$2:$FB$2=$H38), 0))} -> 0 | V38: {=INDEX(Raw!N:FN, MATCH(V$4, Raw!$A:$A, 0), MATCH(1, (Raw!$B$1:$FB$1=$I38)*(Raw!$B$2:$FB$2=$H38), 0))} -> 2122000000 | W38: {=INDEX(Raw!O:FO, MATCH(W$4, Raw!$A:$A, 0), MATCH(1, (Raw!$B$1:$FB$1=$I38)*(Raw!$B$2:$FB$2=$H38), 0))} -> 0 | X38: {=INDEX(Raw!P:FP, MATCH(X$4, Raw!$A:$A, 0), MATCH(1, (Raw!$B$1:$FB$1=$I38)*(Raw!$B$2:$FB$2=$H38), 0))} -> 1619000000 | Y38: {=INDEX(Raw!Q:FQ, MATCH(Y$4, Raw!$A:$A, 0), MATCH(1, (Raw!$B$1:$FB$1=$I38)*(Raw!$B$2:$FB$2=$H38), 0))} -> 0 | Z38: {=INDEX(Raw!R:FR, MATCH(Z$4, Raw!$A:$A, 0), MATCH(1, (Raw!$B$1:$FB$1=$I38)*(Raw!$B$2:$FB$2=$H38), 0))} -> 0 | AA38: {=INDEX(Raw!S:FS, MATCH(AA$4, Raw!$A:$A, 0), MATCH(1, (Raw!$B$1:$FB$1=$I38)*(Raw!$B$2:$FB$2=$H38), 0))} -> 0 | AB38: {=INDEX(Raw!T:FT, MATCH(AB$4, Raw!$A:$A, 0), MATCH(1, (Raw!$B$1:$FB$1=$I38)*(Raw!$B$2:$FB$2=$H38), 0))} -> 0 | AC38: {=INDEX(Raw!U:FU, MATCH(AC$4, Raw!$A:$A, 0), MATCH(1, (Raw!$B$1:$FB$1=$I38)*(Raw!$B$2:$FB$2=$H38), 0))} -> 0.42 | AD38: {=INDEX(Raw!V:FV, MATCH(AD$4, Raw!$A:$A, 0), MATCH(1, (Raw!$B$1:$FB$1=$I38)*(Raw!$B$2:$FB$2=$H38), 0))} -> 0.5
F39: KO | G39: =TODAY() -> 46088 | H39: =H38 -> 2017 | I39: Q2 | J39: {=INDEX(Raw!B:FB, MATCH(J$4, Raw!$A:$A, 0), MATCH(1, (Raw!$B$1:$FB$1=$I39)*(Raw!$B$2:$FB$2=$H39), 0))} -> 9702000000 | K39: {=INDEX(Raw!C:FC, MATCH(K$4, Raw!$A:$A, 0), MATCH(1, (Raw!$B$1:$FB$1=$I39)*(Raw!$B$2:$FB$2=$H39), 0))} -> 3513000000 | L39: {=INDEX(Raw!D:FD, MATCH(L$4, Raw!$A:$A, 0), MATCH(1, (Raw!$B$1:$FB$1=$I39)*(Raw!$B$2:$FB$2=$H39), 0))} -> 5615000000 | M39: {=INDEX(Raw!E:FE, MATCH(M$4, Raw!$A:$A, 0), MATCH(1, (Raw!$B$1:$FB$1=$I39)*(Raw!$B$2:$FB$2=$H39), 0))} -> 4009000000 | N39: {=INDEX(Raw!F:FF, MATCH(N$4, Raw!$A:$A, 0), MATCH(1, (Raw!$B$1:$FB$1=$I39)*(Raw!$B$2:$FB$2=$H39), 0))} -> -297000000 | O39: {=INDEX(Raw!G:FG, MATCH(O$4, Raw!$A:$A, 0), MATCH(1, (Raw!$B$1:$FB$1=$I39)*(Raw!$B$2:$FB$2=$H39), 0))} -> 4072000000 | P39: {=INDEX(Raw!H:FH, MATCH(P$4, Raw!$A:$A, 0), MATCH(1, (Raw!$B$1:$FB$1=$I39)*(Raw!$B$2:$FB$2=$H39), 0))} -> 1518000000 | Q39: {=INDEX(Raw!I:FI, MATCH(Q$4, Raw!$A:$A, 0), MATCH(1, (Raw!$B$1:$FB$1=$I39)*(Raw!$B$2:$FB$2=$H39), 0))} -> -654000000 | R39: {=INDEX(Raw!J:FJ, MATCH(R$4, Raw!$A:$A, 0), MATCH(1, (Raw!$B$1:$FB$1=$I39)*(Raw!$B$2:$FB$2=$H39), 0))} -> 4361000000 | S39: {=INDEX(Raw!K:FK, MATCH(S$4, Raw!$A:$A, 0), MATCH(1, (Raw!$B$1:$FB$1=$I39)*(Raw!$B$2:$FB$2=$H39), 0))} -> 415000000 | T39: {=INDEX(Raw!L:FL, MATCH(T$4, Raw!$A:$A, 0), MATCH(1, (Raw!$B$1:$FB$1=$I39)*(Raw!$B$2:$FB$2=$H39), 0))} -> 771000000 | U39: {=INDEX(Raw!M:FM, MATCH(U$4, Raw!$A:$A, 0), MATCH(1, (Raw!$B$1:$FB$1=$I39)*(Raw!$B$2:$FB$2=$H39), 0))} -> 0 | V39: {=INDEX(Raw!N:FN, MATCH(V$4, Raw!$A:$A, 0), MATCH(1, (Raw!$B$1:$FB$1=$I39)*(Raw!$B$2:$FB$2=$H39), 0))} -> 2605000000 | W39: {=INDEX(Raw!O:FO, MATCH(W$4, Raw!$A:$A, 0), MATCH(1, (Raw!$B$1:$FB$1=$I39)*(Raw!$B$2:$FB$2=$H39), 0))} -> 0 | X39: {=INDEX(Raw!P:FP, MATCH(X$4, Raw!$A:$A, 0), MATCH(1, (Raw!$B$1:$FB$1=$I39)*(Raw!$B$2:$FB$2=$H39), 0))} -> 1710000000 | Y39: {=INDEX(Raw!Q:FQ, MATCH(Y$4, Raw!$A:$A, 0), MATCH(1, (Raw!$B$1:$FB$1=$I39)*(Raw!$B$2:$FB$2=$H39), 0))} -> 0 | Z39: {=INDEX(Raw!R:FR, MATCH(Z$4, Raw!$A:$A, 0), MATCH(1, (Raw!$B$1:$FB$1=$I39)*(Raw!$B$2:$FB$2=$H39), 0))} -> 0 | AA39: {=INDEX(Raw!S:FS, MATCH(AA$4, Raw!$A:$A, 0), MATCH(1, (Raw!$B$1:$FB$1=$I39)*(Raw!$B$2:$FB$2=$H39), 0))} -> 0 | AB39: {=INDEX(Raw!T:FT, MATCH(AB$4, Raw!$A:$A, 0), MATCH(1, (Raw!$B$1:$FB$1=$I39)*(Raw!$B$2:$FB$2=$H39), 0))} -> 0 | AC39: {=INDEX(Raw!U:FU, MATCH(AC$4, Raw!$A:$A, 0), MATCH(1, (Raw!$B$1:$FB$1=$I39)*(Raw!$B$2:$FB$2=$H39), 0))} -> 0.51 | AD39: {=INDEX(Raw!V:FV, MATCH(AD$4, Raw!$A:$A, 0), MATCH(1, (Raw!$B$1:$FB$1=$I39)*(Raw!$B$2:$FB$2=$H39), 0))} -> 0.61
F40: KO | G40: =TODAY() -> 46088 | H40: =H39 -> 2017 | I40: Q1 | J40: {=INDEX(Raw!B:FB, MATCH(J$4, Raw!$A:$A, 0), MATCH(1, (Raw!$B$1:$FB$1=$I40)*(Raw!$B$2:$FB$2=$H40), 0))} -> 9118000000 | K40: {=INDEX(Raw!C:FC, MATCH(K$4, Raw!$A:$A, 0), MATCH(1, (Raw!$B$1:$FB$1=$I40)*(Raw!$B$2:$FB$2=$H40), 0))} -> 3794000000 | L40: {=INDEX(Raw!D:FD, MATCH(L$4, Raw!$A:$A, 0), MATCH(1, (Raw!$B$1:$FB$1=$I40)*(Raw!$B$2:$FB$2=$H40), 0))} -> 6502000000 | M40: {=INDEX(Raw!E:FE, MATCH(M$4, Raw!$A:$A, 0), MATCH(1, (Raw!$B$1:$FB$1=$I40)*(Raw!$B$2:$FB$2=$H40), 0))} -> 3912000000 | N40: {=INDEX(Raw!F:FF, MATCH(N$4, Raw!$A:$A, 0), MATCH(1, (Raw!$B$1:$FB$1=$I40)*(Raw!$B$2:$FB$2=$H40), 0))} -> -311000000 | O40: {=INDEX(Raw!G:FG, MATCH(O$4, Raw!$A:$A, 0), MATCH(1, (Raw!$B$1:$FB$1=$I40)*(Raw!$B$2:$FB$2=$H40), 0))} -> 4428000000 | P40: {=INDEX(Raw!H:FH, MATCH(P$4, Raw!$A:$A, 0), MATCH(1, (Raw!$B$1:$FB$1=$I40)*(Raw!$B$2:$FB$2=$H40), 0))} -> 2379000000 | Q40: {=INDEX(Raw!I:FI, MATCH(Q$4, Raw!$A:$A, 0), MATCH(1, (Raw!$B$1:$FB$1=$I40)*(Raw!$B$2:$FB$2=$H40), 0))} -> 1826000000 | R40: {=INDEX(Raw!J:FJ, MATCH(R$4, Raw!$A:$A, 0), MATCH(1, (Raw!$B$1:$FB$1=$I40)*(Raw!$B$2:$FB$2=$H40), 0))} -> 1981000000 | S40: {=INDEX(Raw!K:FK, MATCH(S$4, Raw!$A:$A, 0), MATCH(1, (Raw!$B$1:$FB$1=$I40)*(Raw!$B$2:$FB$2=$H40), 0))} -> 305000000 | T40: {=INDEX(Raw!L:FL, MATCH(T$4, Raw!$A:$A, 0), MATCH(1, (Raw!$B$1:$FB$1=$I40)*(Raw!$B$2:$FB$2=$H40), 0))} -> 2122000000 | U40: {=INDEX(Raw!M:FM, MATCH(U$4, Raw!$A:$A, 0), MATCH(1, (Raw!$B$1:$FB$1=$I40)*(Raw!$B$2:$FB$2=$H40), 0))} -> 0 | V40: {=INDEX(Raw!N:FN, MATCH(V$4, Raw!$A:$A, 0), MATCH(1, (Raw!$B$1:$FB$1=$I40)*(Raw!$B$2:$FB$2=$H40), 0))} -> 1626000000 | W40: {=INDEX(Raw!O:FO, MATCH(W$4, Raw!$A:$A, 0), MATCH(1, (Raw!$B$1:$FB$1=$I40)*(Raw!$B$2:$FB$2=$H40), 0))} -> 0 | X40: {=INDEX(Raw!P:FP, MATCH(X$4, Raw!$A:$A, 0), MATCH(1, (Raw!$B$1:$FB$1=$I40)*(Raw!$B$2:$FB$2=$H40), 0))} -> 2447000000 | Y40: {=INDEX(Raw!Q:FQ, MATCH(Y$4, Raw!$A:$A, 0), MATCH(1, (Raw!$B$1:$FB$1=$I40)*(Raw!$B$2:$FB$2=$H40), 0))} -> 0 | Z40: {=INDEX(Raw!R:FR, MATCH(Z$4, Raw!$A:$A, 0), MATCH(1, (Raw!$B$1:$FB$1=$I40)*(Raw!$B$2:$FB$2=$H40), 0))} -> 0 | AA40: {=INDEX(Raw!S:FS, MATCH(AA$4, Raw!$A:$A, 0), MATCH(1, (Raw!$B$1:$FB$1=$I40)*(Raw!$B$2:$FB$2=$H40), 0))} -> 0 | AB40: {=INDEX(Raw!T:FT, MATCH(AB$4, Raw!$A:$A, 0), MATCH(1, (Raw!$B$1:$FB$1=$I40)*(Raw!$B$2:$FB$2=$H40), 0))} -> 0 | AC40: {=INDEX(Raw!U:FU, MATCH(AC$4, Raw!$A:$A, 0), MATCH(1, (Raw!$B$1:$FB$1=$I40)*(Raw!$B$2:$FB$2=$H40), 0))} -> 0.62 | AD40: {=INDEX(Raw!V:FV, MATCH(AD$4, Raw!$A:$A, 0), MATCH(1, (Raw!$B$1:$FB$1=$I40)*(Raw!$B$2:$FB$2=$H40), 0))} -> 0.45
F41: KO | G41: =TODAY() -> 46088 | H41: =H37-1 -> 2016 | I41: Q4 | J41: {=INDEX(Raw!B:FB, MATCH(J$4, Raw!$A:$A, 0), MATCH(1, (Raw!$B$1:$FB$1=$I41)*(Raw!$B$2:$FB$2=$H41), 0))} -> 9409000000 | K41: {=INDEX(Raw!C:FC, MATCH(K$4, Raw!$A:$A, 0), MATCH(1, (Raw!$B$1:$FB$1=$I41)*(Raw!$B$2:$FB$2=$H41), 0))} -> 4131000000 | L41: {=INDEX(Raw!D:FD, MATCH(L$4, Raw!$A:$A, 0), MATCH(1, (Raw!$B$1:$FB$1=$I41)*(Raw!$B$2:$FB$2=$H41), 0))} -> 7068000000 | M41: {=INDEX(Raw!E:FE, MATCH(M$4, Raw!$A:$A, 0), MATCH(1, (Raw!$B$1:$FB$1=$I41)*(Raw!$B$2:$FB$2=$H41), 0))} -> 3761000000 | N41: {=INDEX(Raw!F:FF, MATCH(N$4, Raw!$A:$A, 0), MATCH(1, (Raw!$B$1:$FB$1=$I41)*(Raw!$B$2:$FB$2=$H41), 0))} -> -491000000 | O41: {=INDEX(Raw!G:FG, MATCH(O$4, Raw!$A:$A, 0), MATCH(1, (Raw!$B$1:$FB$1=$I41)*(Raw!$B$2:$FB$2=$H41), 0))} -> 4471000000 | P41: {=INDEX(Raw!H:FH, MATCH(P$4, Raw!$A:$A, 0), MATCH(1, (Raw!$B$1:$FB$1=$I41)*(Raw!$B$2:$FB$2=$H41), 0))} -> 2535000000 | Q41: {=INDEX(Raw!I:FI, MATCH(Q$4, Raw!$A:$A, 0), MATCH(1, (Raw!$B$1:$FB$1=$I41)*(Raw!$B$2:$FB$2=$H41), 0))} -> -315000000 | R41: {=INDEX(Raw!J:FJ, MATCH(R$4, Raw!$A:$A, 0), MATCH(1, (Raw!$B$1:$FB$1=$I41)*(Raw!$B$2:$FB$2=$H41), 0))} -> 1076000000 | S41: {=INDEX(Raw!K:FK, MATCH(S$4, Raw!$A:$A, 0), MATCH(1, (Raw!$B$1:$FB$1=$I41)*(Raw!$B$2:$FB$2=$H41), 0))} -> 538000000 | T41: {=INDEX(Raw!L:FL, MATCH(T$4, Raw!$A:$A, 0), MATCH(1, (Raw!$B$1:$FB$1=$I41)*(Raw!$B$2:$FB$2=$H41), 0))} -> 2605000000 | U41: {=INDEX(Raw!M:FM, MATCH(U$4, Raw!$A:$A, 0), MATCH(1, (Raw!$B$1:$FB$1=$I41)*(Raw!$B$2:$FB$2=$H41), 0))} -> 0 | V41: {=INDEX(Raw!N:FN, MATCH(V$4, Raw!$A:$A, 0), MATCH(1, (Raw!$B$1:$FB$1=$I41)*(Raw!$B$2:$FB$2=$H41), 0))} -> 1708000000 | W41: {=INDEX(Raw!O:FO, MATCH(W$4, Raw!$A:$A, 0), MATCH(1, (Raw!$B$1:$FB$1=$I41)*(Raw!$B$2:$FB$2=$H41), 0))} -> 0 | X41: {=INDEX(Raw!P:FP, MATCH(X$4, Raw!$A:$A, 0), MATCH(1, (Raw!$B$1:$FB$1=$I41)*(Raw!$B$2:$FB$2=$H41), 0))} -> 2676000000 | Y41: {=INDEX(Raw!Q:FQ, MATCH(Y$4, Raw!$A:$A, 0), MATCH(1, (Raw!$B$1:$FB$1=$I41)*(Raw!$B$2:$FB$2=$H41), 0))} -> 0 | Z41: {=INDEX(Raw!R:FR, MATCH(Z$4, Raw!$A:$A, 0), MATCH(1, (Raw!$B$1:$FB$1=$I41)*(Raw!$B$2:$FB$2=$H41), 0))} -> 0 | AA41: {=INDEX(Raw!S:FS, MATCH(AA$4, Raw!$A:$A, 0), MATCH(1, (Raw!$B$1:$FB$1=$I41)*(Raw!$B$2:$FB$2=$H41), 0))} -> 0 | AB41: {=INDEX(Raw!T:FT, MATCH(AB$4, Raw!$A:$A, 0), MATCH(1, (Raw!$B$1:$FB$1=$I41)*(Raw!$B$2:$FB$2=$H41), 0))} -> 0 | AC41: {=INDEX(Raw!U:FU, MATCH(AC$4, Raw!$A:$A, 0), MATCH(1, (Raw!$B$1:$FB$1=$I41)*(Raw!$B$2:$FB$2=$H41), 0))} -> 0.45 | AD41: {=INDEX(Raw!V:FV, MATCH(AD$4, Raw!$A:$A, 0), MATCH(1, (Raw!$B$1:$FB$1=$I41)*(Raw!$B$2:$FB$2=$H41), 0))} -> 0.36
F42: KO | G42: =TODAY() -> 46088 | H42: =H41 -> 2016 | I42: Q3 | J42: {=INDEX(Raw!B:FB, MATCH(J$4, Raw!$A:$A, 0), MATCH(1, (Raw!$B$1:$FB$1=$I42)*(Raw!$B$2:$FB$2=$H42), 0))} -> 10633000000 | K42: {=INDEX(Raw!C:FC, MATCH(K$4, Raw!$A:$A, 0), MATCH(1, (Raw!$B$1:$FB$1=$I42)*(Raw!$B$2:$FB$2=$H42), 0))} -> 4471000000 | L42: {=INDEX(Raw!D:FD, MATCH(L$4, Raw!$A:$A, 0), MATCH(1, (Raw!$B$1:$FB$1=$I42)*(Raw!$B$2:$FB$2=$H42), 0))} -> 6213000000 | M42: {=INDEX(Raw!E:FE, MATCH(M$4, Raw!$A:$A, 0), MATCH(1, (Raw!$B$1:$FB$1=$I42)*(Raw!$B$2:$FB$2=$H42), 0))} -> 3937000000 | N42: {=INDEX(Raw!F:FF, MATCH(N$4, Raw!$A:$A, 0), MATCH(1, (Raw!$B$1:$FB$1=$I42)*(Raw!$B$2:$FB$2=$H42), 0))} -> -264000000 | O42: {=INDEX(Raw!G:FG, MATCH(O$4, Raw!$A:$A, 0), MATCH(1, (Raw!$B$1:$FB$1=$I42)*(Raw!$B$2:$FB$2=$H42), 0))} -> 4873000000 | P42: {=INDEX(Raw!H:FH, MATCH(P$4, Raw!$A:$A, 0), MATCH(1, (Raw!$B$1:$FB$1=$I42)*(Raw!$B$2:$FB$2=$H42), 0))} -> 2296000000 | Q42: {=INDEX(Raw!I:FI, MATCH(Q$4, Raw!$A:$A, 0), MATCH(1, (Raw!$B$1:$FB$1=$I42)*(Raw!$B$2:$FB$2=$H42), 0))} -> -375000000 | R42: {=INDEX(Raw!J:FJ, MATCH(R$4, Raw!$A:$A, 0), MATCH(1, (Raw!$B$1:$FB$1=$I42)*(Raw!$B$2:$FB$2=$H42), 0))} -> 2660000000 | S42: {=INDEX(Raw!K:FK, MATCH(S$4, Raw!$A:$A, 0), MATCH(1, (Raw!$B$1:$FB$1=$I42)*(Raw!$B$2:$FB$2=$H42), 0))} -> 779000000 | T42: {=INDEX(Raw!L:FL, MATCH(T$4, Raw!$A:$A, 0), MATCH(1, (Raw!$B$1:$FB$1=$I42)*(Raw!$B$2:$FB$2=$H42), 0))} -> 1626000000 | U42: {=INDEX(Raw!M:FM, MATCH(U$4, Raw!$A:$A, 0), MATCH(1, (Raw!$B$1:$FB$1=$I42)*(Raw!$B$2:$FB$2=$H42), 0))} -> 0 | V42: {=INDEX(Raw!N:FN, MATCH(V$4, Raw!$A:$A, 0), MATCH(1, (Raw!$B$1:$FB$1=$I42)*(Raw!$B$2:$FB$2=$H42), 0))} -> 2455000000 | W42: {=INDEX(Raw!O:FO, MATCH(W$4, Raw!$A:$A, 0), MATCH(1, (Raw!$B$1:$FB$1=$I42)*(Raw!$B$2:$FB$2=$H42), 0))} -> 0 | X42: {=INDEX(Raw!P:FP, MATCH(X$4, Raw!$A:$A, 0), MATCH(1, (Raw!$B$1:$FB$1=$I42)*(Raw!$B$2:$FB$2=$H42), 0))} -> 1751000000 | Y42: {=INDEX(Raw!Q:FQ, MATCH(Y$4, Raw!$A:$A, 0), MATCH(1, (Raw!$B$1:$FB$1=$I42)*(Raw!$B$2:$FB$2=$H42), 0))} -> 0 | Z42: {=INDEX(Raw!R:FR, MATCH(Z$4, Raw!$A:$A, 0), MATCH(1, (Raw!$B$1:$FB$1=$I42)*(Raw!$B$2:$FB$2=$H42), 0))} -> 0 | AA42: {=INDEX(Raw!S:FS, MATCH(AA$4, Raw!$A:$A, 0), MATCH(1, (Raw!$B$1:$FB$1=$I42)*(Raw!$B$2:$FB$2=$H42), 0))} -> 0 | AB42: {=INDEX(Raw!T:FT, MATCH(AB$4, Raw!$A:$A, 0), MATCH(1, (Raw!$B$1:$FB$1=$I42)*(Raw!$B$2:$FB$2=$H42), 0))} -> 0 | AC42: {=INDEX(Raw!U:FU, MATCH(AC$4, Raw!$A:$A, 0), MATCH(1, (Raw!$B$1:$FB$1=$I42)*(Raw!$B$2:$FB$2=$H42), 0))} -> 0.365 | AD42: {=INDEX(Raw!V:FV, MATCH(AD$4, Raw!$A:$A, 0), MATCH(1, (Raw!$B$1:$FB$1=$I42)*(Raw!$B$2:$FB$2=$H42), 0))} -> 0.48
F43: KO | G43: =TODAY() -> 46088 | H43: =H42 -> 2016 | I43: Q2 | J43: {=INDEX(Raw!B:FB, MATCH(J$4, Raw!$A:$A, 0), MATCH(1, (Raw!$B$1:$FB$1=$I43)*(Raw!$B$2:$FB$2=$H43), 0))} -> 11539000000 | K43: {=INDEX(Raw!C:FC, MATCH(K$4, Raw!$A:$A, 0), MATCH(1, (Raw!$B$1:$FB$1=$I43)*(Raw!$B$2:$FB$2=$H43), 0))} -> 4069000000 | L43: {=INDEX(Raw!D:FD, MATCH(L$4, Raw!$A:$A, 0), MATCH(1, (Raw!$B$1:$FB$1=$I43)*(Raw!$B$2:$FB$2=$H43), 0))} -> 5946000000 | M43: {=INDEX(Raw!E:FE, MATCH(M$4, Raw!$A:$A, 0), MATCH(1, (Raw!$B$1:$FB$1=$I43)*(Raw!$B$2:$FB$2=$H43), 0))} -> 4207000000 | N43: {=INDEX(Raw!F:FF, MATCH(N$4, Raw!$A:$A, 0), MATCH(1, (Raw!$B$1:$FB$1=$I43)*(Raw!$B$2:$FB$2=$H43), 0))} -> -669000000 | O43: {=INDEX(Raw!G:FG, MATCH(O$4, Raw!$A:$A, 0), MATCH(1, (Raw!$B$1:$FB$1=$I43)*(Raw!$B$2:$FB$2=$H43), 0))} -> 4312000000 | P43: {=INDEX(Raw!H:FH, MATCH(P$4, Raw!$A:$A, 0), MATCH(1, (Raw!$B$1:$FB$1=$I43)*(Raw!$B$2:$FB$2=$H43), 0))} -> 1451000000 | Q43: {=INDEX(Raw!I:FI, MATCH(Q$4, Raw!$A:$A, 0), MATCH(1, (Raw!$B$1:$FB$1=$I43)*(Raw!$B$2:$FB$2=$H43), 0))} -> -51000000 | R43: {=INDEX(Raw!J:FJ, MATCH(R$4, Raw!$A:$A, 0), MATCH(1, (Raw!$B$1:$FB$1=$I43)*(Raw!$B$2:$FB$2=$H43), 0))} -> 3384000000 | S43: {=INDEX(Raw!K:FK, MATCH(S$4, Raw!$A:$A, 0), MATCH(1, (Raw!$B$1:$FB$1=$I43)*(Raw!$B$2:$FB$2=$H43), 0))} -> 579000000 | T43: {=INDEX(Raw!L:FL, MATCH(T$4, Raw!$A:$A, 0), MATCH(1, (Raw!$B$1:$FB$1=$I43)*(Raw!$B$2:$FB$2=$H43), 0))} -> 1708000000 | U43: {=INDEX(Raw!M:FM, MATCH(U$4, Raw!$A:$A, 0), MATCH(1, (Raw!$B$1:$FB$1=$I43)*(Raw!$B$2:$FB$2=$H43), 0))} -> 0 | V43: {=INDEX(Raw!N:FN, MATCH(V$4, Raw!$A:$A, 0), MATCH(1, (Raw!$B$1:$FB$1=$I43)*(Raw!$B$2:$FB$2=$H43), 0))} -> 2694000000 | W43: {=INDEX(Raw!O:FO, MATCH(W$4, Raw!$A:$A, 0), MATCH(1, (Raw!$B$1:$FB$1=$I43)*(Raw!$B$2:$FB$2=$H43), 0))} -> 0 | X43: {=INDEX(Raw!P:FP, MATCH(X$4, Raw!$A:$A, 0), MATCH(1, (Raw!$B$1:$FB$1=$I43)*(Raw!$B$2:$FB$2=$H43), 0))} -> 1866000000 | Y43: {=INDEX(Raw!Q:FQ, MATCH(Y$4, Raw!$A:$A, 0), MATCH(1, (Raw!$B$1:$FB$1=$I43)*(Raw!$B$2:$FB$2=$H43), 0))} -> 0 | Z43: {=INDEX(Raw!R:FR, MATCH(Z$4, Raw!$A:$A, 0), MATCH(1, (Raw!$B$1:$FB$1=$I43)*(Raw!$B$2:$FB$2=$H43), 0))} -> 0 | AA43: {=INDEX(Raw!S:FS, MATCH(AA$4, Raw!$A:$A, 0), MATCH(1, (Raw!$B$1:$FB$1=$I43)*(Raw!$B$2:$FB$2=$H43), 0))} -> 0 | AB43: {=INDEX(Raw!T:FT, MATCH(AB$4, Raw!$A:$A, 0), MATCH(1, (Raw!$B$1:$FB$1=$I43)*(Raw!$B$2:$FB$2=$H43), 0))} -> 0 | AC43: {=INDEX(Raw!U:FU, MATCH(AC$4, Raw!$A:$A, 0), MATCH(1, (Raw!$B$1:$FB$1=$I43)*(Raw!$B$2:$FB$2=$H43), 0))} -> 0.49 | AD43: {=INDEX(Raw!V:FV, MATCH(AD$4, Raw!$A:$A, 0), MATCH(1, (Raw!$B$1:$FB$1=$I43)*(Raw!$B$2:$FB$2=$H43), 0))} -> 0.6
F44: KO | G44: =TODAY() -> 46088 | H44: =H43 -> 2016 | I44: Q1 | J44: {=INDEX(Raw!B:FB, MATCH(J$4, Raw!$A:$A, 0), MATCH(1, (Raw!$B$1:$FB$1=$I44)*(Raw!$B$2:$FB$2=$H44), 0))} -> 10282000000 | K44: {=INDEX(Raw!C:FC, MATCH(K$4, Raw!$A:$A, 0), MATCH(1, (Raw!$B$1:$FB$1=$I44)*(Raw!$B$2:$FB$2=$H44), 0))} -> 4054000000 | L44: {=INDEX(Raw!D:FD, MATCH(L$4, Raw!$A:$A, 0), MATCH(1, (Raw!$B$1:$FB$1=$I44)*(Raw!$B$2:$FB$2=$H44), 0))} -> 6850000000 | M44: {=INDEX(Raw!E:FE, MATCH(M$4, Raw!$A:$A, 0), MATCH(1, (Raw!$B$1:$FB$1=$I44)*(Raw!$B$2:$FB$2=$H44), 0))} -> 4204000000 | N44: {=INDEX(Raw!F:FF, MATCH(N$4, Raw!$A:$A, 0), MATCH(1, (Raw!$B$1:$FB$1=$I44)*(Raw!$B$2:$FB$2=$H44), 0))} -> -233000000 | O44: {=INDEX(Raw!G:FG, MATCH(O$4, Raw!$A:$A, 0), MATCH(1, (Raw!$B$1:$FB$1=$I44)*(Raw!$B$2:$FB$2=$H44), 0))} -> 5064000000 | P44: {=INDEX(Raw!H:FH, MATCH(P$4, Raw!$A:$A, 0), MATCH(1, (Raw!$B$1:$FB$1=$I44)*(Raw!$B$2:$FB$2=$H44), 0))} -> 2711000000 | Q44: {=INDEX(Raw!I:FI, MATCH(Q$4, Raw!$A:$A, 0), MATCH(1, (Raw!$B$1:$FB$1=$I44)*(Raw!$B$2:$FB$2=$H44), 0))} -> 214000000 | R44: {=INDEX(Raw!J:FJ, MATCH(R$4, Raw!$A:$A, 0), MATCH(1, (Raw!$B$1:$FB$1=$I44)*(Raw!$B$2:$FB$2=$H44), 0))} -> 2205000000 | S44: {=INDEX(Raw!K:FK, MATCH(S$4, Raw!$A:$A, 0), MATCH(1, (Raw!$B$1:$FB$1=$I44)*(Raw!$B$2:$FB$2=$H44), 0))} -> 520000000 | T44: {=INDEX(Raw!L:FL, MATCH(T$4, Raw!$A:$A, 0), MATCH(1, (Raw!$B$1:$FB$1=$I44)*(Raw!$B$2:$FB$2=$H44), 0))} -> 2455000000 | U44: {=INDEX(Raw!M:FM, MATCH(U$4, Raw!$A:$A, 0), MATCH(1, (Raw!$B$1:$FB$1=$I44)*(Raw!$B$2:$FB$2=$H44), 0))} -> 0 | V44: {=INDEX(Raw!N:FN, MATCH(V$4, Raw!$A:$A, 0), MATCH(1, (Raw!$B$1:$FB$1=$I44)*(Raw!$B$2:$FB$2=$H44), 0))} -> 1769000000 | W44: {=INDEX(Raw!O:FO, MATCH(W$4, Raw!$A:$A, 0), MATCH(1, (Raw!$B$1:$FB$1=$I44)*(Raw!$B$2:$FB$2=$H44), 0))} -> 0 | X44: {=INDEX(Raw!P:FP, MATCH(X$4, Raw!$A:$A, 0), MATCH(1, (Raw!$B$1:$FB$1=$I44)*(Raw!$B$2:$FB$2=$H44), 0))} -> 2311000000 | Y44: {=INDEX(Raw!Q:FQ, MATCH(Y$4, Raw!$A:$A, 0), MATCH(1, (Raw!$B$1:$FB$1=$I44)*(Raw!$B$2:$FB$2=$H44), 0))} -> 0 | Z44: {=INDEX(Raw!R:FR, MATCH(Z$4, Raw!$A:$A, 0), MATCH(1, (Raw!$B$1:$FB$1=$I44)*(Raw!$B$2:$FB$2=$H44), 0))} -> 0 | AA44: {=INDEX(Raw!S:FS, MATCH(AA$4, Raw!$A:$A, 0), MATCH(1, (Raw!$B$1:$FB$1=$I44)*(Raw!$B$2:$FB$2=$H44), 0))} -> 0 | AB44: {=INDEX(Raw!T:FT, MATCH(AB$4, Raw!$A:$A, 0), MATCH(1, (Raw!$B$1:$FB$1=$I44)*(Raw!$B$2:$FB$2=$H44), 0))} -> 0 | AC44: {=INDEX(Raw!U:FU, MATCH(AC$4, Raw!$A:$A, 0), MATCH(1, (Raw!$B$1:$FB$1=$I44)*(Raw!$B$2:$FB$2=$H44), 0))} -> 0.61 | AD44: {=INDEX(Raw!V:FV, MATCH(AD$4, Raw!$A:$A, 0), MATCH(1, (Raw!$B$1:$FB$1=$I44)*(Raw!$B$2:$FB$2=$H44), 0))} -> 0.41
F45: KO | G45: =TODAY() -> 46088 | H45: =H41-1 -> 2015 | I45: Q4 | J45: {=INDEX(Raw!B:FB, MATCH(J$4, Raw!$A:$A, 0), MATCH(1, (Raw!$B$1:$FB$1=$I45)*(Raw!$B$2:$FB$2=$H45), 0))} -> 10000000000 | K45: {=INDEX(Raw!C:FC, MATCH(K$4, Raw!$A:$A, 0), MATCH(1, (Raw!$B$1:$FB$1=$I45)*(Raw!$B$2:$FB$2=$H45), 0))} -> 4577000000 | L45: {=INDEX(Raw!D:FD, MATCH(L$4, Raw!$A:$A, 0), MATCH(1, (Raw!$B$1:$FB$1=$I45)*(Raw!$B$2:$FB$2=$H45), 0))} -> 7408000000 | M45: {=INDEX(Raw!E:FE, MATCH(M$4, Raw!$A:$A, 0), MATCH(1, (Raw!$B$1:$FB$1=$I45)*(Raw!$B$2:$FB$2=$H45), 0))} -> 4079000000 | N45: {=INDEX(Raw!F:FF, MATCH(N$4, Raw!$A:$A, 0), MATCH(1, (Raw!$B$1:$FB$1=$I45)*(Raw!$B$2:$FB$2=$H45), 0))} -> -726000000 | O45: {=INDEX(Raw!G:FG, MATCH(O$4, Raw!$A:$A, 0), MATCH(1, (Raw!$B$1:$FB$1=$I45)*(Raw!$B$2:$FB$2=$H45), 0))} -> 4635000000 | P45: {=INDEX(Raw!H:FH, MATCH(P$4, Raw!$A:$A, 0), MATCH(1, (Raw!$B$1:$FB$1=$I45)*(Raw!$B$2:$FB$2=$H45), 0))} -> 3170000000 | Q45: {=INDEX(Raw!I:FI, MATCH(Q$4, Raw!$A:$A, 0), MATCH(1, (Raw!$B$1:$FB$1=$I45)*(Raw!$B$2:$FB$2=$H45), 0))} -> -171000000 | R45: {=INDEX(Raw!J:FJ, MATCH(R$4, Raw!$A:$A, 0), MATCH(1, (Raw!$B$1:$FB$1=$I45)*(Raw!$B$2:$FB$2=$H45), 0))} -> 2228000000 | S45: {=INDEX(Raw!K:FK, MATCH(S$4, Raw!$A:$A, 0), MATCH(1, (Raw!$B$1:$FB$1=$I45)*(Raw!$B$2:$FB$2=$H45), 0))} -> 925000000 | T45: {=INDEX(Raw!L:FL, MATCH(T$4, Raw!$A:$A, 0), MATCH(1, (Raw!$B$1:$FB$1=$I45)*(Raw!$B$2:$FB$2=$H45), 0))} -> 2694000000 | U45: {=INDEX(Raw!M:FM, MATCH(U$4, Raw!$A:$A, 0), MATCH(1, (Raw!$B$1:$FB$1=$I45)*(Raw!$B$2:$FB$2=$H45), 0))} -> 0 | V45: {=INDEX(Raw!N:FN, MATCH(V$4, Raw!$A:$A, 0), MATCH(1, (Raw!$B$1:$FB$1=$I45)*(Raw!$B$2:$FB$2=$H45), 0))} -> 1890000000 | W45: {=INDEX(Raw!O:FO, MATCH(W$4, Raw!$A:$A, 0), MATCH(1, (Raw!$B$1:$FB$1=$I45)*(Raw!$B$2:$FB$2=$H45), 0))} -> 0 | X45: {=INDEX(Raw!P:FP, MATCH(X$4, Raw!$A:$A, 0), MATCH(1, (Raw!$B$1:$FB$1=$I45)*(Raw!$B$2:$FB$2=$H45), 0))} -> 2788000000 | Y45: {=INDEX(Raw!Q:FQ, MATCH(Y$4, Raw!$A:$A, 0), MATCH(1, (Raw!$B$1:$FB$1=$I45)*(Raw!$B$2:$FB$2=$H45), 0))} -> 0 | Z45: {=INDEX(Raw!R:FR, MATCH(Z$4, Raw!$A:$A, 0), MATCH(1, (Raw!$B$1:$FB$1=$I45)*(Raw!$B$2:$FB$2=$H45), 0))} -> 0 | AA45: {=INDEX(Raw!S:FS, MATCH(AA$4, Raw!$A:$A, 0), MATCH(1, (Raw!$B$1:$FB$1=$I45)*(Raw!$B$2:$FB$2=$H45), 0))} -> 0 | AB45: {=INDEX(Raw!T:FT, MATCH(AB$4, Raw!$A:$A, 0), MATCH(1, (Raw!$B$1:$FB$1=$I45)*(Raw!$B$2:$FB$2=$H45), 0))} -> 0 | AC45: {=INDEX(Raw!U:FU, MATCH(AC$4, Raw!$A:$A, 0), MATCH(1, (Raw!$B$1:$FB$1=$I45)*(Raw!$B$2:$FB$2=$H45), 0))} -> 0.415 | AD45: {=INDEX(Raw!V:FV, MATCH(AD$4, Raw!$A:$A, 0), MATCH(1, (Raw!$B$1:$FB$1=$I45)*(Raw!$B$2:$FB$2=$H45), 0))} -> 1.235
F46: KO | G46: =TODAY() -> 46088 | H46: =H45 -> 2015 | I46: Q3 | J46: {=INDEX(Raw!B:FB, MATCH(J$4, Raw!$A:$A, 0), MATCH(1, (Raw!$B$1:$FB$1=$I46)*(Raw!$B$2:$FB$2=$H46), 0))} -> 11427000000 | K46: {=INDEX(Raw!C:FC, MATCH(K$4, Raw!$A:$A, 0), MATCH(1, (Raw!$B$1:$FB$1=$I46)*(Raw!$B$2:$FB$2=$H46), 0))} -> 4748000000 | L46: {=INDEX(Raw!D:FD, MATCH(L$4, Raw!$A:$A, 0), MATCH(1, (Raw!$B$1:$FB$1=$I46)*(Raw!$B$2:$FB$2=$H46), 0))} -> 6608000000 | M46: {=INDEX(Raw!E:FE, MATCH(M$4, Raw!$A:$A, 0), MATCH(1, (Raw!$B$1:$FB$1=$I46)*(Raw!$B$2:$FB$2=$H46), 0))} -> 4338000000 | N46: {=INDEX(Raw!F:FF, MATCH(N$4, Raw!$A:$A, 0), MATCH(1, (Raw!$B$1:$FB$1=$I46)*(Raw!$B$2:$FB$2=$H46), 0))} -> -128000000 | O46: {=INDEX(Raw!G:FG, MATCH(O$4, Raw!$A:$A, 0), MATCH(1, (Raw!$B$1:$FB$1=$I46)*(Raw!$B$2:$FB$2=$H46), 0))} -> 4585000000 | P46: {=INDEX(Raw!H:FH, MATCH(P$4, Raw!$A:$A, 0), MATCH(1, (Raw!$B$1:$FB$1=$I46)*(Raw!$B$2:$FB$2=$H46), 0))} -> 2376000000 | Q46: {=INDEX(Raw!I:FI, MATCH(Q$4, Raw!$A:$A, 0), MATCH(1, (Raw!$B$1:$FB$1=$I46)*(Raw!$B$2:$FB$2=$H46), 0))} -> 123000000 | R46: {=INDEX(Raw!J:FJ, MATCH(R$4, Raw!$A:$A, 0), MATCH(1, (Raw!$B$1:$FB$1=$I46)*(Raw!$B$2:$FB$2=$H46), 0))} -> 3380000000 | S46: {=INDEX(Raw!K:FK, MATCH(S$4, Raw!$A:$A, 0), MATCH(1, (Raw!$B$1:$FB$1=$I46)*(Raw!$B$2:$FB$2=$H46), 0))} -> 831000000 | T46: {=INDEX(Raw!L:FL, MATCH(T$4, Raw!$A:$A, 0), MATCH(1, (Raw!$B$1:$FB$1=$I46)*(Raw!$B$2:$FB$2=$H46), 0))} -> 1769000000 | U46: {=INDEX(Raw!M:FM, MATCH(U$4, Raw!$A:$A, 0), MATCH(1, (Raw!$B$1:$FB$1=$I46)*(Raw!$B$2:$FB$2=$H46), 0))} -> 0 | V46: {=INDEX(Raw!N:FN, MATCH(V$4, Raw!$A:$A, 0), MATCH(1, (Raw!$B$1:$FB$1=$I46)*(Raw!$B$2:$FB$2=$H46), 0))} -> 2329000000 | W46: {=INDEX(Raw!O:FO, MATCH(W$4, Raw!$A:$A, 0), MATCH(1, (Raw!$B$1:$FB$1=$I46)*(Raw!$B$2:$FB$2=$H46), 0))} -> 0 | X46: {=INDEX(Raw!P:FP, MATCH(X$4, Raw!$A:$A, 0), MATCH(1, (Raw!$B$1:$FB$1=$I46)*(Raw!$B$2:$FB$2=$H46), 0))} -> 2054000000 | Y46: {=INDEX(Raw!Q:FQ, MATCH(Y$4, Raw!$A:$A, 0), MATCH(1, (Raw!$B$1:$FB$1=$I46)*(Raw!$B$2:$FB$2=$H46), 0))} -> 0 | Z46: {=INDEX(Raw!R:FR, MATCH(Z$4, Raw!$A:$A, 0), MATCH(1, (Raw!$B$1:$FB$1=$I46)*(Raw!$B$2:$FB$2=$H46), 0))} -> 0 | AA46: {=INDEX(Raw!S:FS, MATCH(AA$4, Raw!$A:$A, 0), MATCH(1, (Raw!$B$1:$FB$1=$I46)*(Raw!$B$2:$FB$2=$H46), 0))} -> 0 | AB46: {=INDEX(Raw!T:FT, MATCH(AB$4, Raw!$A:$A, 0), MATCH(1, (Raw!$B$1:$FB$1=$I46)*(Raw!$B$2:$FB$2=$H46), 0))} -> 0 | AC46: {=INDEX(Raw!U:FU, MATCH(AC$4, Raw!$A:$A, 0), MATCH(1, (Raw!$B$1:$FB$1=$I46)*(Raw!$B$2:$FB$2=$H46), 0))} -> 1.24 | AD46: {=INDEX(Raw!V:FV, MATCH(AD$4, Raw!$A:$A, 0), MATCH(1, (Raw!$B$1:$FB$1=$I46)*(Raw!$B$2:$FB$2=$H46), 0))} -> 0.44
F47: KO | G47: =TODAY() -> 46088 | H47: =H46 -> 2015 | I47: Q2 | J47: {=INDEX(Raw!B:FB, MATCH(J$4, Raw!$A:$A, 0), MATCH(1, (Raw!$B$1:$FB$1=$I47)*(Raw!$B$2:$FB$2=$H47), 0))} -> 12156000000 | K47: {=INDEX(Raw!C:FC, MATCH(K$4, Raw!$A:$A, 0), MATCH(1, (Raw!$B$1:$FB$1=$I47)*(Raw!$B$2:$FB$2=$H47), 0))} -> 4103000000 | L47: {=INDEX(Raw!D:FD, MATCH(L$4, Raw!$A:$A, 0), MATCH(1, (Raw!$B$1:$FB$1=$I47)*(Raw!$B$2:$FB$2=$H47), 0))} -> 6515000000 | M47: {=INDEX(Raw!E:FE, MATCH(M$4, Raw!$A:$A, 0), MATCH(1, (Raw!$B$1:$FB$1=$I47)*(Raw!$B$2:$FB$2=$H47), 0))} -> 4507000000 | N47: {=INDEX(Raw!F:FF, MATCH(N$4, Raw!$A:$A, 0), MATCH(1, (Raw!$B$1:$FB$1=$I47)*(Raw!$B$2:$FB$2=$H47), 0))} -> -201000000 | O47: {=INDEX(Raw!G:FG, MATCH(O$4, Raw!$A:$A, 0), MATCH(1, (Raw!$B$1:$FB$1=$I47)*(Raw!$B$2:$FB$2=$H47), 0))} -> 4117000000 | P47: {=INDEX(Raw!H:FH, MATCH(P$4, Raw!$A:$A, 0), MATCH(1, (Raw!$B$1:$FB$1=$I47)*(Raw!$B$2:$FB$2=$H47), 0))} -> 2105000000 | Q47: {=INDEX(Raw!I:FI, MATCH(Q$4, Raw!$A:$A, 0), MATCH(1, (Raw!$B$1:$FB$1=$I47)*(Raw!$B$2:$FB$2=$H47), 0))} -> 908000000 | R47: {=INDEX(Raw!J:FJ, MATCH(R$4, Raw!$A:$A, 0), MATCH(1, (Raw!$B$1:$FB$1=$I47)*(Raw!$B$2:$FB$2=$H47), 0))} -> 3525000000 | S47: {=INDEX(Raw!K:FK, MATCH(S$4, Raw!$A:$A, 0), MATCH(1, (Raw!$B$1:$FB$1=$I47)*(Raw!$B$2:$FB$2=$H47), 0))} -> 575000000 | T47: {=INDEX(Raw!L:FL, MATCH(T$4, Raw!$A:$A, 0), MATCH(1, (Raw!$B$1:$FB$1=$I47)*(Raw!$B$2:$FB$2=$H47), 0))} -> 1890000000 | U47: {=INDEX(Raw!M:FM, MATCH(U$4, Raw!$A:$A, 0), MATCH(1, (Raw!$B$1:$FB$1=$I47)*(Raw!$B$2:$FB$2=$H47), 0))} -> 0 | V47: {=INDEX(Raw!N:FN, MATCH(V$4, Raw!$A:$A, 0), MATCH(1, (Raw!$B$1:$FB$1=$I47)*(Raw!$B$2:$FB$2=$H47), 0))} -> 2800000000 | W47: {=INDEX(Raw!O:FO, MATCH(W$4, Raw!$A:$A, 0), MATCH(1, (Raw!$B$1:$FB$1=$I47)*(Raw!$B$2:$FB$2=$H47), 0))} -> 0 | X47: {=INDEX(Raw!P:FP, MATCH(X$4, Raw!$A:$A, 0), MATCH(1, (Raw!$B$1:$FB$1=$I47)*(Raw!$B$2:$FB$2=$H47), 0))} -> 1657000000 | Y47: {=INDEX(Raw!Q:FQ, MATCH(Y$4, Raw!$A:$A, 0), MATCH(1, (Raw!$B$1:$FB$1=$I47)*(Raw!$B$2:$FB$2=$H47), 0))} -> 0 | Z47: {=INDEX(Raw!R:FR, MATCH(Z$4, Raw!$A:$A, 0), MATCH(1, (Raw!$B$1:$FB$1=$I47)*(Raw!$B$2:$FB$2=$H47), 0))} -> 0 | AA47: {=INDEX(Raw!S:FS, MATCH(AA$4, Raw!$A:$A, 0), MATCH(1, (Raw!$B$1:$FB$1=$I47)*(Raw!$B$2:$FB$2=$H47), 0))} -> 0 | AB47: {=INDEX(Raw!T:FT, MATCH(AB$4, Raw!$A:$A, 0), MATCH(1, (Raw!$B$1:$FB$1=$I47)*(Raw!$B$2:$FB$2=$H47), 0))} -> 0 | AC47: {=INDEX(Raw!U:FU, MATCH(AC$4, Raw!$A:$A, 0), MATCH(1, (Raw!$B$1:$FB$1=$I47)*(Raw!$B$2:$FB$2=$H47), 0))} -> 0.445 | AD47: {=INDEX(Raw!V:FV, MATCH(AD$4, Raw!$A:$A, 0), MATCH(1, (Raw!$B$1:$FB$1=$I47)*(Raw!$B$2:$FB$2=$H47), 0))} -> 0.51
F48: KO | G48: =TODAY() -> 46088 | H48: =H47 -> 2015 | I48: Q1 | J48: {=INDEX(Raw!B:FB, MATCH(J$4, Raw!$A:$A, 0), MATCH(1, (Raw!$B$1:$FB$1=$I48)*(Raw!$B$2:$FB$2=$H48), 0))} -> 10711000000 | K48: {=INDEX(Raw!C:FC, MATCH(K$4, Raw!$A:$A, 0), MATCH(1, (Raw!$B$1:$FB$1=$I48)*(Raw!$B$2:$FB$2=$H48), 0))} -> 4357000000 | L48: {=INDEX(Raw!D:FD, MATCH(L$4, Raw!$A:$A, 0), MATCH(1, (Raw!$B$1:$FB$1=$I48)*(Raw!$B$2:$FB$2=$H48), 0))} -> 7346000000 | M48: {=INDEX(Raw!E:FE, MATCH(M$4, Raw!$A:$A, 0), MATCH(1, (Raw!$B$1:$FB$1=$I48)*(Raw!$B$2:$FB$2=$H48), 0))} -> 4384000000 | N48: {=INDEX(Raw!F:FF, MATCH(N$4, Raw!$A:$A, 0), MATCH(1, (Raw!$B$1:$FB$1=$I48)*(Raw!$B$2:$FB$2=$H48), 0))} -> -128000000 | O48: {=INDEX(Raw!G:FG, MATCH(O$4, Raw!$A:$A, 0), MATCH(1, (Raw!$B$1:$FB$1=$I48)*(Raw!$B$2:$FB$2=$H48), 0))} -> 4620000000 | P48: {=INDEX(Raw!H:FH, MATCH(P$4, Raw!$A:$A, 0), MATCH(1, (Raw!$B$1:$FB$1=$I48)*(Raw!$B$2:$FB$2=$H48), 0))} -> 2472000000 | Q48: {=INDEX(Raw!I:FI, MATCH(Q$4, Raw!$A:$A, 0), MATCH(1, (Raw!$B$1:$FB$1=$I48)*(Raw!$B$2:$FB$2=$H48), 0))} -> 282000000 | R48: {=INDEX(Raw!J:FJ, MATCH(R$4, Raw!$A:$A, 0), MATCH(1, (Raw!$B$1:$FB$1=$I48)*(Raw!$B$2:$FB$2=$H48), 0))} -> 2344000000 | S48: {=INDEX(Raw!K:FK, MATCH(S$4, Raw!$A:$A, 0), MATCH(1, (Raw!$B$1:$FB$1=$I48)*(Raw!$B$2:$FB$2=$H48), 0))} -> 487000000 | T48: {=INDEX(Raw!L:FL, MATCH(T$4, Raw!$A:$A, 0), MATCH(1, (Raw!$B$1:$FB$1=$I48)*(Raw!$B$2:$FB$2=$H48), 0))} -> 2329000000 | U48: {=INDEX(Raw!M:FM, MATCH(U$4, Raw!$A:$A, 0), MATCH(1, (Raw!$B$1:$FB$1=$I48)*(Raw!$B$2:$FB$2=$H48), 0))} -> 0 | V48: {=INDEX(Raw!N:FN, MATCH(V$4, Raw!$A:$A, 0), MATCH(1, (Raw!$B$1:$FB$1=$I48)*(Raw!$B$2:$FB$2=$H48), 0))} -> 2067000000 | W48: {=INDEX(Raw!O:FO, MATCH(W$4, Raw!$A:$A, 0), MATCH(1, (Raw!$B$1:$FB$1=$I48)*(Raw!$B$2:$FB$2=$H48), 0))} -> 0 | X48: {=INDEX(Raw!P:FP, MATCH(X$4, Raw!$A:$A, 0), MATCH(1, (Raw!$B$1:$FB$1=$I48)*(Raw!$B$2:$FB$2=$H48), 0))} -> 2224000000 | Y48: {=INDEX(Raw!Q:FQ, MATCH(Y$4, Raw!$A:$A, 0), MATCH(1, (Raw!$B$1:$FB$1=$I48)*(Raw!$B$2:$FB$2=$H48), 0))} -> 0 | Z48: {=INDEX(Raw!R:FR, MATCH(Z$4, Raw!$A:$A, 0), MATCH(1, (Raw!$B$1:$FB$1=$I48)*(Raw!$B$2:$FB$2=$H48), 0))} -> 0 | AA48: {=INDEX(Raw!S:FS, MATCH(AA$4, Raw!$A:$A, 0), MATCH(1, (Raw!$B$1:$FB$1=$I48)*(Raw!$B$2:$FB$2=$H48), 0))} -> 0 | AB48: {=INDEX(Raw!T:FT, MATCH(AB$4, Raw!$A:$A, 0), MATCH(1, (Raw!$B$1:$FB$1=$I48)*(Raw!$B$2:$FB$2=$H48), 0))} -> 0 | AC48: {=INDEX(Raw!U:FU, MATCH(AC$4, Raw!$A:$A, 0), MATCH(1, (Raw!$B$1:$FB$1=$I48)*(Raw!$B$2:$FB$2=$H48), 0))} -> 0.515 | AD48: {=INDEX(Raw!V:FV, MATCH(AD$4, Raw!$A:$A, 0), MATCH(1, (Raw!$B$1:$FB$1=$I48)*(Raw!$B$2:$FB$2=$H48), 0))} -> 0.345
F49: KO | G49: =TODAY() -> 46088 | H49: =H45-1 -> 2014 | I49: Q4 | J49: {=INDEX(Raw!B:FB, MATCH(J$4, Raw!$A:$A, 0), MATCH(1, (Raw!$B$1:$FB$1=$I49)*(Raw!$B$2:$FB$2=$H49), 0))} -> 10872000000 | K49: {=INDEX(Raw!C:FC, MATCH(K$4, Raw!$A:$A, 0), MATCH(1, (Raw!$B$1:$FB$1=$I49)*(Raw!$B$2:$FB$2=$H49), 0))} -> 4630000000 | L49: {=INDEX(Raw!D:FD, MATCH(L$4, Raw!$A:$A, 0), MATCH(1, (Raw!$B$1:$FB$1=$I49)*(Raw!$B$2:$FB$2=$H49), 0))} -> 7755000000 | M49: {=INDEX(Raw!E:FE, MATCH(M$4, Raw!$A:$A, 0), MATCH(1, (Raw!$B$1:$FB$1=$I49)*(Raw!$B$2:$FB$2=$H49), 0))} -> 3989000000 | N49: {=INDEX(Raw!F:FF, MATCH(N$4, Raw!$A:$A, 0), MATCH(1, (Raw!$B$1:$FB$1=$I49)*(Raw!$B$2:$FB$2=$H49), 0))} -> -301000000 | O49: {=INDEX(Raw!G:FG, MATCH(O$4, Raw!$A:$A, 0), MATCH(1, (Raw!$B$1:$FB$1=$I49)*(Raw!$B$2:$FB$2=$H49), 0))} -> 4765000000 | P49: {=INDEX(Raw!H:FH, MATCH(P$4, Raw!$A:$A, 0), MATCH(1, (Raw!$B$1:$FB$1=$I49)*(Raw!$B$2:$FB$2=$H49), 0))} -> 3243000000 | Q49: {=INDEX(Raw!I:FI, MATCH(Q$4, Raw!$A:$A, 0), MATCH(1, (Raw!$B$1:$FB$1=$I49)*(Raw!$B$2:$FB$2=$H49), 0))} -> -64000000 | R49: {=INDEX(Raw!J:FJ, MATCH(R$4, Raw!$A:$A, 0), MATCH(1, (Raw!$B$1:$FB$1=$I49)*(Raw!$B$2:$FB$2=$H49), 0))} -> 2377000000 | S49: {=INDEX(Raw!K:FK, MATCH(S$4, Raw!$A:$A, 0), MATCH(1, (Raw!$B$1:$FB$1=$I49)*(Raw!$B$2:$FB$2=$H49), 0))} -> 755000000 | T49: {=INDEX(Raw!L:FL, MATCH(T$4, Raw!$A:$A, 0), MATCH(1, (Raw!$B$1:$FB$1=$I49)*(Raw!$B$2:$FB$2=$H49), 0))} -> 2800000000 | U49: {=INDEX(Raw!M:FM, MATCH(U$4, Raw!$A:$A, 0), MATCH(1, (Raw!$B$1:$FB$1=$I49)*(Raw!$B$2:$FB$2=$H49), 0))} -> 0 | V49: {=INDEX(Raw!N:FN, MATCH(V$4, Raw!$A:$A, 0), MATCH(1, (Raw!$B$1:$FB$1=$I49)*(Raw!$B$2:$FB$2=$H49), 0))} -> 1677000000 | W49: {=INDEX(Raw!O:FO, MATCH(W$4, Raw!$A:$A, 0), MATCH(1, (Raw!$B$1:$FB$1=$I49)*(Raw!$B$2:$FB$2=$H49), 0))} -> 0 | X49: {=INDEX(Raw!P:FP, MATCH(X$4, Raw!$A:$A, 0), MATCH(1, (Raw!$B$1:$FB$1=$I49)*(Raw!$B$2:$FB$2=$H49), 0))} -> 2800000000 | Y49: {=INDEX(Raw!Q:FQ, MATCH(Y$4, Raw!$A:$A, 0), MATCH(1, (Raw!$B$1:$FB$1=$I49)*(Raw!$B$2:$FB$2=$H49), 0))} -> 0 | Z49: {=INDEX(Raw!R:FR, MATCH(Z$4, Raw!$A:$A, 0), MATCH(1, (Raw!$B$1:$FB$1=$I49)*(Raw!$B$2:$FB$2=$H49), 0))} -> 0 | AA49: {=INDEX(Raw!S:FS, MATCH(AA$4, Raw!$A:$A, 0), MATCH(1, (Raw!$B$1:$FB$1=$I49)*(Raw!$B$2:$FB$2=$H49), 0))} -> 0 | AB49: {=INDEX(Raw!T:FT, MATCH(AB$4, Raw!$A:$A, 0), MATCH(1, (Raw!$B$1:$FB$1=$I49)*(Raw!$B$2:$FB$2=$H49), 0))} -> 0 | AC49: {=INDEX(Raw!U:FU, MATCH(AC$4, Raw!$A:$A, 0), MATCH(1, (Raw!$B$1:$FB$1=$I49)*(Raw!$B$2:$FB$2=$H49), 0))} -> 0.35 | AD49: {=INDEX(Raw!V:FV, MATCH(AD$4, Raw!$A:$A, 0), MATCH(1, (Raw!$B$1:$FB$1=$I49)*(Raw!$B$2:$FB$2=$H49), 0))} -> 0.33
F50: KO | G50: =TODAY() -> 46088 | H50: =H49 -> 2014 | I50: Q3 | J50: {=INDEX(Raw!B:FB, MATCH(J$4, Raw!$A:$A, 0), MATCH(1, (Raw!$B$1:$FB$1=$I50)*(Raw!$B$2:$FB$2=$H50), 0))} -> 11976000000 | K50: {=INDEX(Raw!C:FC, MATCH(K$4, Raw!$A:$A, 0), MATCH(1, (Raw!$B$1:$FB$1=$I50)*(Raw!$B$2:$FB$2=$H50), 0))} -> 4819000000 | L50: {=INDEX(Raw!D:FD, MATCH(L$4, Raw!$A:$A, 0), MATCH(1, (Raw!$B$1:$FB$1=$I50)*(Raw!$B$2:$FB$2=$H50), 0))} -> 6493000000 | M50: {=INDEX(Raw!E:FE, MATCH(M$4, Raw!$A:$A, 0), MATCH(1, (Raw!$B$1:$FB$1=$I50)*(Raw!$B$2:$FB$2=$H50), 0))} -> 4319000000 | N50: {=INDEX(Raw!F:FF, MATCH(N$4, Raw!$A:$A, 0), MATCH(1, (Raw!$B$1:$FB$1=$I50)*(Raw!$B$2:$FB$2=$H50), 0))} -> -341000000 | O50: {=INDEX(Raw!G:FG, MATCH(O$4, Raw!$A:$A, 0), MATCH(1, (Raw!$B$1:$FB$1=$I50)*(Raw!$B$2:$FB$2=$H50), 0))} -> 4517000000 | P50: {=INDEX(Raw!H:FH, MATCH(P$4, Raw!$A:$A, 0), MATCH(1, (Raw!$B$1:$FB$1=$I50)*(Raw!$B$2:$FB$2=$H50), 0))} -> 2408000000 | Q50: {=INDEX(Raw!I:FI, MATCH(Q$4, Raw!$A:$A, 0), MATCH(1, (Raw!$B$1:$FB$1=$I50)*(Raw!$B$2:$FB$2=$H50), 0))} -> 194000000 | R50: {=INDEX(Raw!J:FJ, MATCH(R$4, Raw!$A:$A, 0), MATCH(1, (Raw!$B$1:$FB$1=$I50)*(Raw!$B$2:$FB$2=$H50), 0))} -> 3084000000 | S50: {=INDEX(Raw!K:FK, MATCH(S$4, Raw!$A:$A, 0), MATCH(1, (Raw!$B$1:$FB$1=$I50)*(Raw!$B$2:$FB$2=$H50), 0))} -> 823000000 | T50: {=INDEX(Raw!L:FL, MATCH(T$4, Raw!$A:$A, 0), MATCH(1, (Raw!$B$1:$FB$1=$I50)*(Raw!$B$2:$FB$2=$H50), 0))} -> 2067000000 | U50: {=INDEX(Raw!M:FM, MATCH(U$4, Raw!$A:$A, 0), MATCH(1, (Raw!$B$1:$FB$1=$I50)*(Raw!$B$2:$FB$2=$H50), 0))} -> 0 | V50: {=INDEX(Raw!N:FN, MATCH(V$4, Raw!$A:$A, 0), MATCH(1, (Raw!$B$1:$FB$1=$I50)*(Raw!$B$2:$FB$2=$H50), 0))} -> 2246000000 | W50: {=INDEX(Raw!O:FO, MATCH(W$4, Raw!$A:$A, 0), MATCH(1, (Raw!$B$1:$FB$1=$I50)*(Raw!$B$2:$FB$2=$H50), 0))} -> 0 | X50: {=INDEX(Raw!P:FP, MATCH(X$4, Raw!$A:$A, 0), MATCH(1, (Raw!$B$1:$FB$1=$I50)*(Raw!$B$2:$FB$2=$H50), 0))} -> 1903000000 | Y50: {=INDEX(Raw!Q:FQ, MATCH(Y$4, Raw!$A:$A, 0), MATCH(1, (Raw!$B$1:$FB$1=$I50)*(Raw!$B$2:$FB$2=$H50), 0))} -> 0 | Z50: {=INDEX(Raw!R:FR, MATCH(Z$4, Raw!$A:$A, 0), MATCH(1, (Raw!$B$1:$FB$1=$I50)*(Raw!$B$2:$FB$2=$H50), 0))} -> 0 | AA50: {=INDEX(Raw!S:FS, MATCH(AA$4, Raw!$A:$A, 0), MATCH(1, (Raw!$B$1:$FB$1=$I50)*(Raw!$B$2:$FB$2=$H50), 0))} -> 0 | AB50: {=INDEX(Raw!T:FT, MATCH(AB$4, Raw!$A:$A, 0), MATCH(1, (Raw!$B$1:$FB$1=$I50)*(Raw!$B$2:$FB$2=$H50), 0))} -> 0 | AC50: {=INDEX(Raw!U:FU, MATCH(AC$4, Raw!$A:$A, 0), MATCH(1, (Raw!$B$1:$FB$1=$I50)*(Raw!$B$2:$FB$2=$H50), 0))} -> 0.335 | AD50: {=INDEX(Raw!V:FV, MATCH(AD$4, Raw!$A:$A, 0), MATCH(1, (Raw!$B$1:$FB$1=$I50)*(Raw!$B$2:$FB$2=$H50), 0))} -> 0.405
F51: KO | G51: =TODAY() -> 46088 | H51: =H50 -> 2014 | I51: Q2 | J51: {=INDEX(Raw!B:FB, MATCH(J$4, Raw!$A:$A, 0), MATCH(1, (Raw!$B$1:$FB$1=$I51)*(Raw!$B$2:$FB$2=$H51), 0))} -> 12574000000 | K51: {=INDEX(Raw!C:FC, MATCH(K$4, Raw!$A:$A, 0), MATCH(1, (Raw!$B$1:$FB$1=$I51)*(Raw!$B$2:$FB$2=$H51), 0))} -> 4083000000 | L51: {=INDEX(Raw!D:FD, MATCH(L$4, Raw!$A:$A, 0), MATCH(1, (Raw!$B$1:$FB$1=$I51)*(Raw!$B$2:$FB$2=$H51), 0))} -> 6725000000 | M51: {=INDEX(Raw!E:FE, MATCH(M$4, Raw!$A:$A, 0), MATCH(1, (Raw!$B$1:$FB$1=$I51)*(Raw!$B$2:$FB$2=$H51), 0))} -> 4424000000 | N51: {=INDEX(Raw!F:FF, MATCH(N$4, Raw!$A:$A, 0), MATCH(1, (Raw!$B$1:$FB$1=$I51)*(Raw!$B$2:$FB$2=$H51), 0))} -> -132000000 | O51: {=INDEX(Raw!G:FG, MATCH(O$4, Raw!$A:$A, 0), MATCH(1, (Raw!$B$1:$FB$1=$I51)*(Raw!$B$2:$FB$2=$H51), 0))} -> 4303000000 | P51: {=INDEX(Raw!H:FH, MATCH(P$4, Raw!$A:$A, 0), MATCH(1, (Raw!$B$1:$FB$1=$I51)*(Raw!$B$2:$FB$2=$H51), 0))} -> 2183000000 | Q51: {=INDEX(Raw!I:FI, MATCH(Q$4, Raw!$A:$A, 0), MATCH(1, (Raw!$B$1:$FB$1=$I51)*(Raw!$B$2:$FB$2=$H51), 0))} -> 291000000 | R51: {=INDEX(Raw!J:FJ, MATCH(R$4, Raw!$A:$A, 0), MATCH(1, (Raw!$B$1:$FB$1=$I51)*(Raw!$B$2:$FB$2=$H51), 0))} -> 3623000000 | S51: {=INDEX(Raw!K:FK, MATCH(S$4, Raw!$A:$A, 0), MATCH(1, (Raw!$B$1:$FB$1=$I51)*(Raw!$B$2:$FB$2=$H51), 0))} -> 658000000 | T51: {=INDEX(Raw!L:FL, MATCH(T$4, Raw!$A:$A, 0), MATCH(1, (Raw!$B$1:$FB$1=$I51)*(Raw!$B$2:$FB$2=$H51), 0))} -> 1677000000 | U51: {=INDEX(Raw!M:FM, MATCH(U$4, Raw!$A:$A, 0), MATCH(1, (Raw!$B$1:$FB$1=$I51)*(Raw!$B$2:$FB$2=$H51), 0))} -> 0 | V51: {=INDEX(Raw!N:FN, MATCH(V$4, Raw!$A:$A, 0), MATCH(1, (Raw!$B$1:$FB$1=$I51)*(Raw!$B$2:$FB$2=$H51), 0))} -> 2807000000 | W51: {=INDEX(Raw!O:FO, MATCH(W$4, Raw!$A:$A, 0), MATCH(1, (Raw!$B$1:$FB$1=$I51)*(Raw!$B$2:$FB$2=$H51), 0))} -> 0 | X51: {=INDEX(Raw!P:FP, MATCH(X$4, Raw!$A:$A, 0), MATCH(1, (Raw!$B$1:$FB$1=$I51)*(Raw!$B$2:$FB$2=$H51), 0))} -> 5749000000 | Y51: {=INDEX(Raw!Q:FQ, MATCH(Y$4, Raw!$A:$A, 0), MATCH(1, (Raw!$B$1:$FB$1=$I51)*(Raw!$B$2:$FB$2=$H51), 0))} -> 0 | Z51: {=INDEX(Raw!R:FR, MATCH(Z$4, Raw!$A:$A, 0), MATCH(1, (Raw!$B$1:$FB$1=$I51)*(Raw!$B$2:$FB$2=$H51), 0))} -> 0 | AA51: {=INDEX(Raw!S:FS, MATCH(AA$4, Raw!$A:$A, 0), MATCH(1, (Raw!$B$1:$FB$1=$I51)*(Raw!$B$2:$FB$2=$H51), 0))} -> 0 | AB51: {=INDEX(Raw!T:FT, MATCH(AB$4, Raw!$A:$A, 0), MATCH(1, (Raw!$B$1:$FB$1=$I51)*(Raw!$B$2:$FB$2=$H51), 0))} -> 0 | AC51: {=INDEX(Raw!U:FU, MATCH(AC$4, Raw!$A:$A, 0), MATCH(1, (Raw!$B$1:$FB$1=$I51)*(Raw!$B$2:$FB$2=$H51), 0))} -> 0.41 | AD51: {=INDEX(Raw!V:FV, MATCH(AD$4, Raw!$A:$A, 0), MATCH(1, (Raw!$B$1:$FB$1=$I51)*(Raw!$B$2:$FB$2=$H51), 0))} -> 0.44
F52: KO | G52: =TODAY() -> 46088 | H52: =H51 -> 2014 | I52: Q1 | J52: {=INDEX(Raw!B:FB, MATCH(J$4, Raw!$A:$A, 0), MATCH(1, (Raw!$B$1:$FB$1=$I52)*(Raw!$B$2:$FB$2=$H52), 0))} -> 10576000000 | K52: {=INDEX(Raw!C:FC, MATCH(K$4, Raw!$A:$A, 0), MATCH(1, (Raw!$B$1:$FB$1=$I52)*(Raw!$B$2:$FB$2=$H52), 0))} -> 4315000000 | L52: {=INDEX(Raw!D:FD, MATCH(L$4, Raw!$A:$A, 0), MATCH(1, (Raw!$B$1:$FB$1=$I52)*(Raw!$B$2:$FB$2=$H52), 0))} -> 7237000000 | M52: {=INDEX(Raw!E:FE, MATCH(M$4, Raw!$A:$A, 0), MATCH(1, (Raw!$B$1:$FB$1=$I52)*(Raw!$B$2:$FB$2=$H52), 0))} -> 4385000000 | N52: {=INDEX(Raw!F:FF, MATCH(N$4, Raw!$A:$A, 0), MATCH(1, (Raw!$B$1:$FB$1=$I52)*(Raw!$B$2:$FB$2=$H52), 0))} -> -121000000 | O52: {=INDEX(Raw!G:FG, MATCH(O$4, Raw!$A:$A, 0), MATCH(1, (Raw!$B$1:$FB$1=$I52)*(Raw!$B$2:$FB$2=$H52), 0))} -> 4644000000 | P52: {=INDEX(Raw!H:FH, MATCH(P$4, Raw!$A:$A, 0), MATCH(1, (Raw!$B$1:$FB$1=$I52)*(Raw!$B$2:$FB$2=$H52), 0))} -> 2793000000 | Q52: {=INDEX(Raw!I:FI, MATCH(Q$4, Raw!$A:$A, 0), MATCH(1, (Raw!$B$1:$FB$1=$I52)*(Raw!$B$2:$FB$2=$H52), 0))} -> 329000000 | R52: {=INDEX(Raw!J:FJ, MATCH(R$4, Raw!$A:$A, 0), MATCH(1, (Raw!$B$1:$FB$1=$I52)*(Raw!$B$2:$FB$2=$H52), 0))} -> 2725000000 | S52: {=INDEX(Raw!K:FK, MATCH(S$4, Raw!$A:$A, 0), MATCH(1, (Raw!$B$1:$FB$1=$I52)*(Raw!$B$2:$FB$2=$H52), 0))} -> 539000000 | T52: {=INDEX(Raw!L:FL, MATCH(T$4, Raw!$A:$A, 0), MATCH(1, (Raw!$B$1:$FB$1=$I52)*(Raw!$B$2:$FB$2=$H52), 0))} -> 2246000000 | U52: {=INDEX(Raw!M:FM, MATCH(U$4, Raw!$A:$A, 0), MATCH(1, (Raw!$B$1:$FB$1=$I52)*(Raw!$B$2:$FB$2=$H52), 0))} -> 0 | V52: {=INDEX(Raw!N:FN, MATCH(V$4, Raw!$A:$A, 0), MATCH(1, (Raw!$B$1:$FB$1=$I52)*(Raw!$B$2:$FB$2=$H52), 0))} -> 1916000000 | W52: {=INDEX(Raw!O:FO, MATCH(W$4, Raw!$A:$A, 0), MATCH(1, (Raw!$B$1:$FB$1=$I52)*(Raw!$B$2:$FB$2=$H52), 0))} -> 0 | X52: {=INDEX(Raw!P:FP, MATCH(X$4, Raw!$A:$A, 0), MATCH(1, (Raw!$B$1:$FB$1=$I52)*(Raw!$B$2:$FB$2=$H52), 0))} -> 2055000000 | Y52: {=INDEX(Raw!Q:FQ, MATCH(Y$4, Raw!$A:$A, 0), MATCH(1, (Raw!$B$1:$FB$1=$I52)*(Raw!$B$2:$FB$2=$H52), 0))} -> 0 | Z52: {=INDEX(Raw!R:FR, MATCH(Z$4, Raw!$A:$A, 0), MATCH(1, (Raw!$B$1:$FB$1=$I52)*(Raw!$B$2:$FB$2=$H52), 0))} -> 0 | AA52: {=INDEX(Raw!S:FS, MATCH(AA$4, Raw!$A:$A, 0), MATCH(1, (Raw!$B$1:$FB$1=$I52)*(Raw!$B$2:$FB$2=$H52), 0))} -> 0 | AB52: {=INDEX(Raw!T:FT, MATCH(AB$4, Raw!$A:$A, 0), MATCH(1, (Raw!$B$1:$FB$1=$I52)*(Raw!$B$2:$FB$2=$H52), 0))} -> 0 | AC52: {=INDEX(Raw!U:FU, MATCH(AC$4, Raw!$A:$A, 0), MATCH(1, (Raw!$B$1:$FB$1=$I52)*(Raw!$B$2:$FB$2=$H52), 0))} -> 0.44 | AD52: {=INDEX(Raw!V:FV, MATCH(AD$4, Raw!$A:$A, 0), MATCH(1, (Raw!$B$1:$FB$1=$I52)*(Raw!$B$2:$FB$2=$H52), 0))} -> 0.29
F53: KO | G53: =TODAY() -> 46088 | H53: =H49-1 -> 2013 | I53: Q4 | J53: {=INDEX(Raw!B:FB, MATCH(J$4, Raw!$A:$A, 0), MATCH(1, (Raw!$B$1:$FB$1=$I53)*(Raw!$B$2:$FB$2=$H53), 0))} -> 11040000000 | K53: {=INDEX(Raw!C:FC, MATCH(K$4, Raw!$A:$A, 0), MATCH(1, (Raw!$B$1:$FB$1=$I53)*(Raw!$B$2:$FB$2=$H53), 0))} -> 4793000000 | L53: {=INDEX(Raw!D:FD, MATCH(L$4, Raw!$A:$A, 0), MATCH(1, (Raw!$B$1:$FB$1=$I53)*(Raw!$B$2:$FB$2=$H53), 0))} -> 7760000000 | M53: {=INDEX(Raw!E:FE, MATCH(M$4, Raw!$A:$A, 0), MATCH(1, (Raw!$B$1:$FB$1=$I53)*(Raw!$B$2:$FB$2=$H53), 0))} -> 4182000000 | N53: {=INDEX(Raw!F:FF, MATCH(N$4, Raw!$A:$A, 0), MATCH(1, (Raw!$B$1:$FB$1=$I53)*(Raw!$B$2:$FB$2=$H53), 0))} -> -214000000 | O53: {=INDEX(Raw!G:FG, MATCH(O$4, Raw!$A:$A, 0), MATCH(1, (Raw!$B$1:$FB$1=$I53)*(Raw!$B$2:$FB$2=$H53), 0))} -> 4694000000 | P53: {=INDEX(Raw!H:FH, MATCH(P$4, Raw!$A:$A, 0), MATCH(1, (Raw!$B$1:$FB$1=$I53)*(Raw!$B$2:$FB$2=$H53), 0))} -> 3294000000 | Q53: {=INDEX(Raw!I:FI, MATCH(Q$4, Raw!$A:$A, 0), MATCH(1, (Raw!$B$1:$FB$1=$I53)*(Raw!$B$2:$FB$2=$H53), 0))} -> 216000000 | R53: {=INDEX(Raw!J:FJ, MATCH(R$4, Raw!$A:$A, 0), MATCH(1, (Raw!$B$1:$FB$1=$I53)*(Raw!$B$2:$FB$2=$H53), 0))} -> 2216000000 | S53: {=INDEX(Raw!K:FK, MATCH(S$4, Raw!$A:$A, 0), MATCH(1, (Raw!$B$1:$FB$1=$I53)*(Raw!$B$2:$FB$2=$H53), 0))} -> 681000000 | T53: {=INDEX(Raw!L:FL, MATCH(T$4, Raw!$A:$A, 0), MATCH(1, (Raw!$B$1:$FB$1=$I53)*(Raw!$B$2:$FB$2=$H53), 0))} -> 2807000000 | U53: {=INDEX(Raw!M:FM, MATCH(U$4, Raw!$A:$A, 0), MATCH(1, (Raw!$B$1:$FB$1=$I53)*(Raw!$B$2:$FB$2=$H53), 0))} -> 0 | V53: {=INDEX(Raw!N:FN, MATCH(V$4, Raw!$A:$A, 0), MATCH(1, (Raw!$B$1:$FB$1=$I53)*(Raw!$B$2:$FB$2=$H53), 0))} -> 5762000000 | W53: {=INDEX(Raw!O:FO, MATCH(W$4, Raw!$A:$A, 0), MATCH(1, (Raw!$B$1:$FB$1=$I53)*(Raw!$B$2:$FB$2=$H53), 0))} -> 0 | X53: {=INDEX(Raw!P:FP, MATCH(X$4, Raw!$A:$A, 0), MATCH(1, (Raw!$B$1:$FB$1=$I53)*(Raw!$B$2:$FB$2=$H53), 0))} -> 2369000000 | Y53: {=INDEX(Raw!Q:FQ, MATCH(Y$4, Raw!$A:$A, 0), MATCH(1, (Raw!$B$1:$FB$1=$I53)*(Raw!$B$2:$FB$2=$H53), 0))} -> 0 | Z53: {=INDEX(Raw!R:FR, MATCH(Z$4, Raw!$A:$A, 0), MATCH(1, (Raw!$B$1:$FB$1=$I53)*(Raw!$B$2:$FB$2=$H53), 0))} -> 0 | AA53: {=INDEX(Raw!S:FS, MATCH(AA$4, Raw!$A:$A, 0), MATCH(1, (Raw!$B$1:$FB$1=$I53)*(Raw!$B$2:$FB$2=$H53), 0))} -> 0 | AB53: {=INDEX(Raw!T:FT, MATCH(AB$4, Raw!$A:$A, 0), MATCH(1, (Raw!$B$1:$FB$1=$I53)*(Raw!$B$2:$FB$2=$H53), 0))} -> 0 | AC53: {=INDEX(Raw!U:FU, MATCH(AC$4, Raw!$A:$A, 0), MATCH(1, (Raw!$B$1:$FB$1=$I53)*(Raw!$B$2:$FB$2=$H53), 0))} -> 0.29 | AD53: {=INDEX(Raw!V:FV, MATCH(AD$4, Raw!$A:$A, 0), MATCH(1, (Raw!$B$1:$FB$1=$I53)*(Raw!$B$2:$FB$2=$H53), 0))} -> 0.215
F54: KO | G54: =TODAY() -> 46088 | H54: =H53 -> 2013 | I54: Q3 | J54: {=INDEX(Raw!B:FB, MATCH(J$4, Raw!$A:$A, 0), MATCH(1, (Raw!$B$1:$FB$1=$I54)*(Raw!$B$2:$FB$2=$H54), 0))} -> 12030000000 | K54: {=INDEX(Raw!C:FC, MATCH(K$4, Raw!$A:$A, 0), MATCH(1, (Raw!$B$1:$FB$1=$I54)*(Raw!$B$2:$FB$2=$H54), 0))} -> 4989000000 | L54: {=INDEX(Raw!D:FD, MATCH(L$4, Raw!$A:$A, 0), MATCH(1, (Raw!$B$1:$FB$1=$I54)*(Raw!$B$2:$FB$2=$H54), 0))} -> 6711000000 | M54: {=INDEX(Raw!E:FE, MATCH(M$4, Raw!$A:$A, 0), MATCH(1, (Raw!$B$1:$FB$1=$I54)*(Raw!$B$2:$FB$2=$H54), 0))} -> 4430000000 | N54: {=INDEX(Raw!F:FF, MATCH(N$4, Raw!$A:$A, 0), MATCH(1, (Raw!$B$1:$FB$1=$I54)*(Raw!$B$2:$FB$2=$H54), 0))} -> -64000000 | O54: {=INDEX(Raw!G:FG, MATCH(O$4, Raw!$A:$A, 0), MATCH(1, (Raw!$B$1:$FB$1=$I54)*(Raw!$B$2:$FB$2=$H54), 0))} -> 4567000000 | P54: {=INDEX(Raw!H:FH, MATCH(P$4, Raw!$A:$A, 0), MATCH(1, (Raw!$B$1:$FB$1=$I54)*(Raw!$B$2:$FB$2=$H54), 0))} -> 2509000000 | Q54: {=INDEX(Raw!I:FI, MATCH(Q$4, Raw!$A:$A, 0), MATCH(1, (Raw!$B$1:$FB$1=$I54)*(Raw!$B$2:$FB$2=$H54), 0))} -> 260000000 | R54: {=INDEX(Raw!J:FJ, MATCH(R$4, Raw!$A:$A, 0), MATCH(1, (Raw!$B$1:$FB$1=$I54)*(Raw!$B$2:$FB$2=$H54), 0))} -> 2927000000 | S54: {=INDEX(Raw!K:FK, MATCH(S$4, Raw!$A:$A, 0), MATCH(1, (Raw!$B$1:$FB$1=$I54)*(Raw!$B$2:$FB$2=$H54), 0))} -> 992000000 | T54: {=INDEX(Raw!L:FL, MATCH(T$4, Raw!$A:$A, 0), MATCH(1, (Raw!$B$1:$FB$1=$I54)*(Raw!$B$2:$FB$2=$H54), 0))} -> 1916000000 | U54: {=INDEX(Raw!M:FM, MATCH(U$4, Raw!$A:$A, 0), MATCH(1, (Raw!$B$1:$FB$1=$I54)*(Raw!$B$2:$FB$2=$H54), 0))} -> 0 | V54: {=INDEX(Raw!N:FN, MATCH(V$4, Raw!$A:$A, 0), MATCH(1, (Raw!$B$1:$FB$1=$I54)*(Raw!$B$2:$FB$2=$H54), 0))} -> 2067000000 | W54: {=INDEX(Raw!O:FO, MATCH(W$4, Raw!$A:$A, 0), MATCH(1, (Raw!$B$1:$FB$1=$I54)*(Raw!$B$2:$FB$2=$H54), 0))} -> 0 | X54: {=INDEX(Raw!P:FP, MATCH(X$4, Raw!$A:$A, 0), MATCH(1, (Raw!$B$1:$FB$1=$I54)*(Raw!$B$2:$FB$2=$H54), 0))} -> 1614000000 | Y54: {=INDEX(Raw!Q:FQ, MATCH(Y$4, Raw!$A:$A, 0), MATCH(1, (Raw!$B$1:$FB$1=$I54)*(Raw!$B$2:$FB$2=$H54), 0))} -> 0 | Z54: {=INDEX(Raw!R:FR, MATCH(Z$4, Raw!$A:$A, 0), MATCH(1, (Raw!$B$1:$FB$1=$I54)*(Raw!$B$2:$FB$2=$H54), 0))} -> 0 | AA54: {=INDEX(Raw!S:FS, MATCH(AA$4, Raw!$A:$A, 0), MATCH(1, (Raw!$B$1:$FB$1=$I54)*(Raw!$B$2:$FB$2=$H54), 0))} -> 0 | AB54: {=INDEX(Raw!T:FT, MATCH(AB$4, Raw!$A:$A, 0), MATCH(1, (Raw!$B$1:$FB$1=$I54)*(Raw!$B$2:$FB$2=$H54), 0))} -> 0 | AC54: {=INDEX(Raw!U:FU, MATCH(AC$4, Raw!$A:$A, 0), MATCH(1, (Raw!$B$1:$FB$1=$I54)*(Raw!$B$2:$FB$2=$H54), 0))} -> 0.215 | AD54: {=INDEX(Raw!V:FV, MATCH(AD$4, Raw!$A:$A, 0), MATCH(1, (Raw!$B$1:$FB$1=$I54)*(Raw!$B$2:$FB$2=$H54), 0))} -> 0.405
F55: KO | G55: =TODAY() -> 46088 | H55: =H54 -> 2013 | I55: Q2 | J55: {=INDEX(Raw!B:FB, MATCH(J$4, Raw!$A:$A, 0), MATCH(1, (Raw!$B$1:$FB$1=$I55)*(Raw!$B$2:$FB$2=$H55), 0))} -> 12749000000 | K55: {=INDEX(Raw!C:FC, MATCH(K$4, Raw!$A:$A, 0), MATCH(1, (Raw!$B$1:$FB$1=$I55)*(Raw!$B$2:$FB$2=$H55), 0))} -> 4324000000 | L55: {=INDEX(Raw!D:FD, MATCH(L$4, Raw!$A:$A, 0), MATCH(1, (Raw!$B$1:$FB$1=$I55)*(Raw!$B$2:$FB$2=$H55), 0))} -> 6827000000 | M55: {=INDEX(Raw!E:FE, MATCH(M$4, Raw!$A:$A, 0), MATCH(1, (Raw!$B$1:$FB$1=$I55)*(Raw!$B$2:$FB$2=$H55), 0))} -> 4630000000 | N55: {=INDEX(Raw!F:FF, MATCH(N$4, Raw!$A:$A, 0), MATCH(1, (Raw!$B$1:$FB$1=$I55)*(Raw!$B$2:$FB$2=$H55), 0))} -> -70000000 | O55: {=INDEX(Raw!G:FG, MATCH(O$4, Raw!$A:$A, 0), MATCH(1, (Raw!$B$1:$FB$1=$I55)*(Raw!$B$2:$FB$2=$H55), 0))} -> 4280000000 | P55: {=INDEX(Raw!H:FH, MATCH(P$4, Raw!$A:$A, 0), MATCH(1, (Raw!$B$1:$FB$1=$I55)*(Raw!$B$2:$FB$2=$H55), 0))} -> 1956000000 | Q55: {=INDEX(Raw!I:FI, MATCH(Q$4, Raw!$A:$A, 0), MATCH(1, (Raw!$B$1:$FB$1=$I55)*(Raw!$B$2:$FB$2=$H55), 0))} -> 173000000 | R55: {=INDEX(Raw!J:FJ, MATCH(R$4, Raw!$A:$A, 0), MATCH(1, (Raw!$B$1:$FB$1=$I55)*(Raw!$B$2:$FB$2=$H55), 0))} -> 3799000000 | S55: {=INDEX(Raw!K:FK, MATCH(S$4, Raw!$A:$A, 0), MATCH(1, (Raw!$B$1:$FB$1=$I55)*(Raw!$B$2:$FB$2=$H55), 0))} -> 600000000 | T55: {=INDEX(Raw!L:FL, MATCH(T$4, Raw!$A:$A, 0), MATCH(1, (Raw!$B$1:$FB$1=$I55)*(Raw!$B$2:$FB$2=$H55), 0))} -> 5762000000 | U55: {=INDEX(Raw!M:FM, MATCH(U$4, Raw!$A:$A, 0), MATCH(1, (Raw!$B$1:$FB$1=$I55)*(Raw!$B$2:$FB$2=$H55), 0))} -> 0 | V55: {=INDEX(Raw!N:FN, MATCH(V$4, Raw!$A:$A, 0), MATCH(1, (Raw!$B$1:$FB$1=$I55)*(Raw!$B$2:$FB$2=$H55), 0))} -> 2382000000 | W55: {=INDEX(Raw!O:FO, MATCH(W$4, Raw!$A:$A, 0), MATCH(1, (Raw!$B$1:$FB$1=$I55)*(Raw!$B$2:$FB$2=$H55), 0))} -> 0 | X55: {=INDEX(Raw!P:FP, MATCH(X$4, Raw!$A:$A, 0), MATCH(1, (Raw!$B$1:$FB$1=$I55)*(Raw!$B$2:$FB$2=$H55), 0))} -> 1543000000 | Y55: {=INDEX(Raw!Q:FQ, MATCH(Y$4, Raw!$A:$A, 0), MATCH(1, (Raw!$B$1:$FB$1=$I55)*(Raw!$B$2:$FB$2=$H55), 0))} -> 0 | Z55: {=INDEX(Raw!R:FR, MATCH(Z$4, Raw!$A:$A, 0), MATCH(1, (Raw!$B$1:$FB$1=$I55)*(Raw!$B$2:$FB$2=$H55), 0))} -> 0 | AA55: {=INDEX(Raw!S:FS, MATCH(AA$4, Raw!$A:$A, 0), MATCH(1, (Raw!$B$1:$FB$1=$I55)*(Raw!$B$2:$FB$2=$H55), 0))} -> 0 | AB55: {=INDEX(Raw!T:FT, MATCH(AB$4, Raw!$A:$A, 0), MATCH(1, (Raw!$B$1:$FB$1=$I55)*(Raw!$B$2:$FB$2=$H55), 0))} -> 0 | AC55: {=INDEX(Raw!U:FU, MATCH(AC$4, Raw!$A:$A, 0), MATCH(1, (Raw!$B$1:$FB$1=$I55)*(Raw!$B$2:$FB$2=$H55), 0))} -> 0.41 | AD55: {=INDEX(Raw!V:FV, MATCH(AD$4, Raw!$A:$A, 0), MATCH(1, (Raw!$B$1:$FB$1=$I55)*(Raw!$B$2:$FB$2=$H55), 0))} -> 0.305
F56: KO | G56: =TODAY() -> 46088 | H56: =H55 -> 2013 | I56: Q1 | J56: {=INDEX(Raw!B:FB, MATCH(J$4, Raw!$A:$A, 0), MATCH(1, (Raw!$B$1:$FB$1=$I56)*(Raw!$B$2:$FB$2=$H56), 0))} -> 11035000000 | K56: {=INDEX(Raw!C:FC, MATCH(K$4, Raw!$A:$A, 0), MATCH(1, (Raw!$B$1:$FB$1=$I56)*(Raw!$B$2:$FB$2=$H56), 0))} -> 4628000000 | L56: {=INDEX(Raw!D:FD, MATCH(L$4, Raw!$A:$A, 0), MATCH(1, (Raw!$B$1:$FB$1=$I56)*(Raw!$B$2:$FB$2=$H56), 0))} -> 7487000000 | M56: {=INDEX(Raw!E:FE, MATCH(M$4, Raw!$A:$A, 0), MATCH(1, (Raw!$B$1:$FB$1=$I56)*(Raw!$B$2:$FB$2=$H56), 0))} -> 4497000000 | N56: {=INDEX(Raw!F:FF, MATCH(N$4, Raw!$A:$A, 0), MATCH(1, (Raw!$B$1:$FB$1=$I56)*(Raw!$B$2:$FB$2=$H56), 0))} -> -99000000 | O56: {=INDEX(Raw!G:FG, MATCH(O$4, Raw!$A:$A, 0), MATCH(1, (Raw!$B$1:$FB$1=$I56)*(Raw!$B$2:$FB$2=$H56), 0))} -> 4681000000 | P56: {=INDEX(Raw!H:FH, MATCH(P$4, Raw!$A:$A, 0), MATCH(1, (Raw!$B$1:$FB$1=$I56)*(Raw!$B$2:$FB$2=$H56), 0))} -> 2754000000 | Q56: {=INDEX(Raw!I:FI, MATCH(Q$4, Raw!$A:$A, 0), MATCH(1, (Raw!$B$1:$FB$1=$I56)*(Raw!$B$2:$FB$2=$H56), 0))} -> 620000000 | R56: {=INDEX(Raw!J:FJ, MATCH(R$4, Raw!$A:$A, 0), MATCH(1, (Raw!$B$1:$FB$1=$I56)*(Raw!$B$2:$FB$2=$H56), 0))} -> 2516000000 | S56: {=INDEX(Raw!K:FK, MATCH(S$4, Raw!$A:$A, 0), MATCH(1, (Raw!$B$1:$FB$1=$I56)*(Raw!$B$2:$FB$2=$H56), 0))} -> 443000000 | T56: {=INDEX(Raw!L:FL, MATCH(T$4, Raw!$A:$A, 0), MATCH(1, (Raw!$B$1:$FB$1=$I56)*(Raw!$B$2:$FB$2=$H56), 0))} -> 2067000000 | U56: {=INDEX(Raw!M:FM, MATCH(U$4, Raw!$A:$A, 0), MATCH(1, (Raw!$B$1:$FB$1=$I56)*(Raw!$B$2:$FB$2=$H56), 0))} -> 0 | V56: {=INDEX(Raw!N:FN, MATCH(V$4, Raw!$A:$A, 0), MATCH(1, (Raw!$B$1:$FB$1=$I56)*(Raw!$B$2:$FB$2=$H56), 0))} -> 1626000000 | W56: {=INDEX(Raw!O:FO, MATCH(W$4, Raw!$A:$A, 0), MATCH(1, (Raw!$B$1:$FB$1=$I56)*(Raw!$B$2:$FB$2=$H56), 0))} -> 0 | X56: {=INDEX(Raw!P:FP, MATCH(X$4, Raw!$A:$A, 0), MATCH(1, (Raw!$B$1:$FB$1=$I56)*(Raw!$B$2:$FB$2=$H56), 0))} -> 1896000000 | Y56: {=INDEX(Raw!Q:FQ, MATCH(Y$4, Raw!$A:$A, 0), MATCH(1, (Raw!$B$1:$FB$1=$I56)*(Raw!$B$2:$FB$2=$H56), 0))} -> 0 | Z56: {=INDEX(Raw!R:FR, MATCH(Z$4, Raw!$A:$A, 0), MATCH(1, (Raw!$B$1:$FB$1=$I56)*(Raw!$B$2:$FB$2=$H56), 0))} -> 0 | AA56: {=INDEX(Raw!S:FS, MATCH(AA$4, Raw!$A:$A, 0), MATCH(1, (Raw!$B$1:$FB$1=$I56)*(Raw!$B$2:$FB$2=$H56), 0))} -> 0 | AB56: {=INDEX(Raw!T:FT, MATCH(AB$4, Raw!$A:$A, 0), MATCH(1, (Raw!$B$1:$FB$1=$I56)*(Raw!$B$2:$FB$2=$H56), 0))} -> 0 | AC56: {=INDEX(Raw!U:FU, MATCH(AC$4, Raw!$A:$A, 0), MATCH(1, (Raw!$B$1:$FB$1=$I56)*(Raw!$B$2:$FB$2=$H56), 0))} -> 0.305 | AD56: {=INDEX(Raw!V:FV, MATCH(AD$4, Raw!$A:$A, 0), MATCH(1, (Raw!$B$1:$FB$1=$I56)*(Raw!$B$2:$FB$2=$H56), 0))} -> 0.32
F57: KO | G57: =TODAY() -> 46088 | H57: =H53-1 -> 2012 | I57: Q4 | J57: {=INDEX(Raw!B:FB, MATCH(J$4, Raw!$A:$A, 0), MATCH(1, (Raw!$B$1:$FB$1=$I57)*(Raw!$B$2:$FB$2=$H57), 0))} -> 11455000000 | K57: {=INDEX(Raw!C:FC, MATCH(K$4, Raw!$A:$A, 0), MATCH(1, (Raw!$B$1:$FB$1=$I57)*(Raw!$B$2:$FB$2=$H57), 0))} -> 4853000000 | L57: {=INDEX(Raw!D:FD, MATCH(L$4, Raw!$A:$A, 0), MATCH(1, (Raw!$B$1:$FB$1=$I57)*(Raw!$B$2:$FB$2=$H57), 0))} -> 7861000000 | M57: {=INDEX(Raw!E:FE, MATCH(M$4, Raw!$A:$A, 0), MATCH(1, (Raw!$B$1:$FB$1=$I57)*(Raw!$B$2:$FB$2=$H57), 0))} -> 4181000000 | N57: {=INDEX(Raw!F:FF, MATCH(N$4, Raw!$A:$A, 0), MATCH(1, (Raw!$B$1:$FB$1=$I57)*(Raw!$B$2:$FB$2=$H57), 0))} -> -275000000 | O57: {=INDEX(Raw!G:FG, MATCH(O$4, Raw!$A:$A, 0), MATCH(1, (Raw!$B$1:$FB$1=$I57)*(Raw!$B$2:$FB$2=$H57), 0))} -> 4619000000 | P57: {=INDEX(Raw!H:FH, MATCH(P$4, Raw!$A:$A, 0), MATCH(1, (Raw!$B$1:$FB$1=$I57)*(Raw!$B$2:$FB$2=$H57), 0))} -> 3179000000 | Q57: {=INDEX(Raw!I:FI, MATCH(Q$4, Raw!$A:$A, 0), MATCH(1, (Raw!$B$1:$FB$1=$I57)*(Raw!$B$2:$FB$2=$H57), 0))} -> 232000000 | R57: {=INDEX(Raw!J:FJ, MATCH(R$4, Raw!$A:$A, 0), MATCH(1, (Raw!$B$1:$FB$1=$I57)*(Raw!$B$2:$FB$2=$H57), 0))} -> 6205000000 | S57: {=INDEX(Raw!K:FK, MATCH(S$4, Raw!$A:$A, 0), MATCH(1, (Raw!$B$1:$FB$1=$I57)*(Raw!$B$2:$FB$2=$H57), 0))} -> 633000000 | T57: {=INDEX(Raw!L:FL, MATCH(T$4, Raw!$A:$A, 0), MATCH(1, (Raw!$B$1:$FB$1=$I57)*(Raw!$B$2:$FB$2=$H57), 0))} -> 2382000000 | U57: {=INDEX(Raw!M:FM, MATCH(U$4, Raw!$A:$A, 0), MATCH(1, (Raw!$B$1:$FB$1=$I57)*(Raw!$B$2:$FB$2=$H57), 0))} -> 0 | V57: {=INDEX(Raw!N:FN, MATCH(V$4, Raw!$A:$A, 0), MATCH(1, (Raw!$B$1:$FB$1=$I57)*(Raw!$B$2:$FB$2=$H57), 0))} -> 1578000000 | W57: {=INDEX(Raw!O:FO, MATCH(W$4, Raw!$A:$A, 0), MATCH(1, (Raw!$B$1:$FB$1=$I57)*(Raw!$B$2:$FB$2=$H57), 0))} -> 0 | X57: {=INDEX(Raw!P:FP, MATCH(X$4, Raw!$A:$A, 0), MATCH(1, (Raw!$B$1:$FB$1=$I57)*(Raw!$B$2:$FB$2=$H57), 0))} -> 2037000000 | Y57: {=INDEX(Raw!Q:FQ, MATCH(Y$4, Raw!$A:$A, 0), MATCH(1, (Raw!$B$1:$FB$1=$I57)*(Raw!$B$2:$FB$2=$H57), 0))} -> 0 | Z57: {=INDEX(Raw!R:FR, MATCH(Z$4, Raw!$A:$A, 0), MATCH(1, (Raw!$B$1:$FB$1=$I57)*(Raw!$B$2:$FB$2=$H57), 0))} -> 0 | AA57: {=INDEX(Raw!S:FS, MATCH(AA$4, Raw!$A:$A, 0), MATCH(1, (Raw!$B$1:$FB$1=$I57)*(Raw!$B$2:$FB$2=$H57), 0))} -> 0 | AB57: {=INDEX(Raw!T:FT, MATCH(AB$4, Raw!$A:$A, 0), MATCH(1, (Raw!$B$1:$FB$1=$I57)*(Raw!$B$2:$FB$2=$H57), 0))} -> 0 | AC57: {=INDEX(Raw!U:FU, MATCH(AC$4, Raw!$A:$A, 0), MATCH(1, (Raw!$B$1:$FB$1=$I57)*(Raw!$B$2:$FB$2=$H57), 0))} -> 0.325 | AD57: {=INDEX(Raw!V:FV, MATCH(AD$4, Raw!$A:$A, 0), MATCH(1, (Raw!$B$1:$FB$1=$I57)*(Raw!$B$2:$FB$2=$H57), 0))} -> 0.26
F58: KO | G58: =TODAY() -> 46088 | H58: =H57 -> 2012 | I58: Q3 | J58: {=INDEX(Raw!B:FB, MATCH(J$4, Raw!$A:$A, 0), MATCH(1, (Raw!$B$1:$FB$1=$I58)*(Raw!$B$2:$FB$2=$H58), 0))} -> 12340000000 | K58: {=INDEX(Raw!C:FC, MATCH(K$4, Raw!$A:$A, 0), MATCH(1, (Raw!$B$1:$FB$1=$I58)*(Raw!$B$2:$FB$2=$H58), 0))} -> 5224000000 | L58: {=INDEX(Raw!D:FD, MATCH(L$4, Raw!$A:$A, 0), MATCH(1, (Raw!$B$1:$FB$1=$I58)*(Raw!$B$2:$FB$2=$H58), 0))} -> 6789000000 | M58: {=INDEX(Raw!E:FE, MATCH(M$4, Raw!$A:$A, 0), MATCH(1, (Raw!$B$1:$FB$1=$I58)*(Raw!$B$2:$FB$2=$H58), 0))} -> 4406000000 | N58: {=INDEX(Raw!F:FF, MATCH(N$4, Raw!$A:$A, 0), MATCH(1, (Raw!$B$1:$FB$1=$I58)*(Raw!$B$2:$FB$2=$H58), 0))} -> -96000000 | O58: {=INDEX(Raw!G:FG, MATCH(O$4, Raw!$A:$A, 0), MATCH(1, (Raw!$B$1:$FB$1=$I58)*(Raw!$B$2:$FB$2=$H58), 0))} -> 4569000000 | P58: {=INDEX(Raw!H:FH, MATCH(P$4, Raw!$A:$A, 0), MATCH(1, (Raw!$B$1:$FB$1=$I58)*(Raw!$B$2:$FB$2=$H58), 0))} -> 2284000000 | Q58: {=INDEX(Raw!I:FI, MATCH(Q$4, Raw!$A:$A, 0), MATCH(1, (Raw!$B$1:$FB$1=$I58)*(Raw!$B$2:$FB$2=$H58), 0))} -> 5082000000 | R58: {=INDEX(Raw!J:FJ, MATCH(R$4, Raw!$A:$A, 0), MATCH(1, (Raw!$B$1:$FB$1=$I58)*(Raw!$B$2:$FB$2=$H58), 0))} -> 2700000000 | S58: {=INDEX(Raw!K:FK, MATCH(S$4, Raw!$A:$A, 0), MATCH(1, (Raw!$B$1:$FB$1=$I58)*(Raw!$B$2:$FB$2=$H58), 0))} -> 741000000 | T58: {=INDEX(Raw!L:FL, MATCH(T$4, Raw!$A:$A, 0), MATCH(1, (Raw!$B$1:$FB$1=$I58)*(Raw!$B$2:$FB$2=$H58), 0))} -> 1626000000 | U58: {=INDEX(Raw!M:FM, MATCH(U$4, Raw!$A:$A, 0), MATCH(1, (Raw!$B$1:$FB$1=$I58)*(Raw!$B$2:$FB$2=$H58), 0))} -> 0 | V58: {=INDEX(Raw!N:FN, MATCH(V$4, Raw!$A:$A, 0), MATCH(1, (Raw!$B$1:$FB$1=$I58)*(Raw!$B$2:$FB$2=$H58), 0))} -> 1920000000 | W58: {=INDEX(Raw!O:FO, MATCH(W$4, Raw!$A:$A, 0), MATCH(1, (Raw!$B$1:$FB$1=$I58)*(Raw!$B$2:$FB$2=$H58), 0))} -> 0 | X58: {=INDEX(Raw!P:FP, MATCH(X$4, Raw!$A:$A, 0), MATCH(1, (Raw!$B$1:$FB$1=$I58)*(Raw!$B$2:$FB$2=$H58), 0))} -> 1348000000 | Y58: {=INDEX(Raw!Q:FQ, MATCH(Y$4, Raw!$A:$A, 0), MATCH(1, (Raw!$B$1:$FB$1=$I58)*(Raw!$B$2:$FB$2=$H58), 0))} -> 0 | Z58: {=INDEX(Raw!R:FR, MATCH(Z$4, Raw!$A:$A, 0), MATCH(1, (Raw!$B$1:$FB$1=$I58)*(Raw!$B$2:$FB$2=$H58), 0))} -> 0 | AA58: {=INDEX(Raw!S:FS, MATCH(AA$4, Raw!$A:$A, 0), MATCH(1, (Raw!$B$1:$FB$1=$I58)*(Raw!$B$2:$FB$2=$H58), 0))} -> 0 | AB58: {=INDEX(Raw!T:FT, MATCH(AB$4, Raw!$A:$A, 0), MATCH(1, (Raw!$B$1:$FB$1=$I58)*(Raw!$B$2:$FB$2=$H58), 0))} -> 0 | AC58: {=INDEX(Raw!U:FU, MATCH(AC$4, Raw!$A:$A, 0), MATCH(1, (Raw!$B$1:$FB$1=$I58)*(Raw!$B$2:$FB$2=$H58), 0))} -> 0.26 | AD58: {=INDEX(Raw!V:FV, MATCH(AD$4, Raw!$A:$A, 0), MATCH(1, (Raw!$B$1:$FB$1=$I58)*(Raw!$B$2:$FB$2=$H58), 0))} -> 0.355
F59: KO | G59: =TODAY() -> 46088 | H59: =H58 -> 2012 | I59: Q2 | J59: {=INDEX(Raw!B:FB, MATCH(J$4, Raw!$A:$A, 0), MATCH(1, (Raw!$B$1:$FB$1=$I59)*(Raw!$B$2:$FB$2=$H59), 0))} -> 13085000000 | K59: {=INDEX(Raw!C:FC, MATCH(K$4, Raw!$A:$A, 0), MATCH(1, (Raw!$B$1:$FB$1=$I59)*(Raw!$B$2:$FB$2=$H59), 0))} -> 4348000000 | L59: {=INDEX(Raw!D:FD, MATCH(L$4, Raw!$A:$A, 0), MATCH(1, (Raw!$B$1:$FB$1=$I59)*(Raw!$B$2:$FB$2=$H59), 0))} -> 6637000000 | M59: {=INDEX(Raw!E:FE, MATCH(M$4, Raw!$A:$A, 0), MATCH(1, (Raw!$B$1:$FB$1=$I59)*(Raw!$B$2:$FB$2=$H59), 0))} -> 4523000000 | N59: {=INDEX(Raw!F:FF, MATCH(N$4, Raw!$A:$A, 0), MATCH(1, (Raw!$B$1:$FB$1=$I59)*(Raw!$B$2:$FB$2=$H59), 0))} -> -152000000 | O59: {=INDEX(Raw!G:FG, MATCH(O$4, Raw!$A:$A, 0), MATCH(1, (Raw!$B$1:$FB$1=$I59)*(Raw!$B$2:$FB$2=$H59), 0))} -> 4285000000 | P59: {=INDEX(Raw!H:FH, MATCH(P$4, Raw!$A:$A, 0), MATCH(1, (Raw!$B$1:$FB$1=$I59)*(Raw!$B$2:$FB$2=$H59), 0))} -> 1123000000 | Q59: {=INDEX(Raw!I:FI, MATCH(Q$4, Raw!$A:$A, 0), MATCH(1, (Raw!$B$1:$FB$1=$I59)*(Raw!$B$2:$FB$2=$H59), 0))} -> 356000000 | R59: {=INDEX(Raw!J:FJ, MATCH(R$4, Raw!$A:$A, 0), MATCH(1, (Raw!$B$1:$FB$1=$I59)*(Raw!$B$2:$FB$2=$H59), 0))} -> 3123000000 | S59: {=INDEX(Raw!K:FK, MATCH(S$4, Raw!$A:$A, 0), MATCH(1, (Raw!$B$1:$FB$1=$I59)*(Raw!$B$2:$FB$2=$H59), 0))} -> 553000000 | T59: {=INDEX(Raw!L:FL, MATCH(T$4, Raw!$A:$A, 0), MATCH(1, (Raw!$B$1:$FB$1=$I59)*(Raw!$B$2:$FB$2=$H59), 0))} -> 1578000000 | U59: {=INDEX(Raw!M:FM, MATCH(U$4, Raw!$A:$A, 0), MATCH(1, (Raw!$B$1:$FB$1=$I59)*(Raw!$B$2:$FB$2=$H59), 0))} -> 0 | V59: {=INDEX(Raw!N:FN, MATCH(V$4, Raw!$A:$A, 0), MATCH(1, (Raw!$B$1:$FB$1=$I59)*(Raw!$B$2:$FB$2=$H59), 0))} -> 2049000000 | W59: {=INDEX(Raw!O:FO, MATCH(W$4, Raw!$A:$A, 0), MATCH(1, (Raw!$B$1:$FB$1=$I59)*(Raw!$B$2:$FB$2=$H59), 0))} -> 0 | X59: {=INDEX(Raw!P:FP, MATCH(X$4, Raw!$A:$A, 0), MATCH(1, (Raw!$B$1:$FB$1=$I59)*(Raw!$B$2:$FB$2=$H59), 0))} -> 995000000 | Y59: {=INDEX(Raw!Q:FQ, MATCH(Y$4, Raw!$A:$A, 0), MATCH(1, (Raw!$B$1:$FB$1=$I59)*(Raw!$B$2:$FB$2=$H59), 0))} -> 0 | Z59: {=INDEX(Raw!R:FR, MATCH(Z$4, Raw!$A:$A, 0), MATCH(1, (Raw!$B$1:$FB$1=$I59)*(Raw!$B$2:$FB$2=$H59), 0))} -> 0 | AA59: {=INDEX(Raw!S:FS, MATCH(AA$4, Raw!$A:$A, 0), MATCH(1, (Raw!$B$1:$FB$1=$I59)*(Raw!$B$2:$FB$2=$H59), 0))} -> 0 | AB59: {=INDEX(Raw!T:FT, MATCH(AB$4, Raw!$A:$A, 0), MATCH(1, (Raw!$B$1:$FB$1=$I59)*(Raw!$B$2:$FB$2=$H59), 0))} -> 0 | AC59: {=INDEX(Raw!U:FU, MATCH(AC$4, Raw!$A:$A, 0), MATCH(1, (Raw!$B$1:$FB$1=$I59)*(Raw!$B$2:$FB$2=$H59), 0))} -> 0.36 | AD59: {=INDEX(Raw!V:FV, MATCH(AD$4, Raw!$A:$A, 0), MATCH(1, (Raw!$B$1:$FB$1=$I59)*(Raw!$B$2:$FB$2=$H59), 0))} -> 0.4
F60: KO | G60: =TODAY() -> 46088 | H60: =H59 -> 2012 | I60: Q1 | J60: {=INDEX(Raw!B:FB, MATCH(J$4, Raw!$A:$A, 0), MATCH(1, (Raw!$B$1:$FB$1=$I60)*(Raw!$B$2:$FB$2=$H60), 0))} -> 11137000000 | K60: {=INDEX(Raw!C:FC, MATCH(K$4, Raw!$A:$A, 0), MATCH(1, (Raw!$B$1:$FB$1=$I60)*(Raw!$B$2:$FB$2=$H60), 0))} -> 4403000000 | L60: {=INDEX(Raw!D:FD, MATCH(L$4, Raw!$A:$A, 0), MATCH(1, (Raw!$B$1:$FB$1=$I60)*(Raw!$B$2:$FB$2=$H60), 0))} -> 7373000000 | M60: {=INDEX(Raw!E:FE, MATCH(M$4, Raw!$A:$A, 0), MATCH(1, (Raw!$B$1:$FB$1=$I60)*(Raw!$B$2:$FB$2=$H60), 0))} -> 4417000000 | N60: {=INDEX(Raw!F:FF, MATCH(N$4, Raw!$A:$A, 0), MATCH(1, (Raw!$B$1:$FB$1=$I60)*(Raw!$B$2:$FB$2=$H60), 0))} -> -209000000 | O60: {=INDEX(Raw!G:FG, MATCH(O$4, Raw!$A:$A, 0), MATCH(1, (Raw!$B$1:$FB$1=$I60)*(Raw!$B$2:$FB$2=$H60), 0))} -> 5092000000 | P60: {=INDEX(Raw!H:FH, MATCH(P$4, Raw!$A:$A, 0), MATCH(1, (Raw!$B$1:$FB$1=$I60)*(Raw!$B$2:$FB$2=$H60), 0))} -> 2344000000 | Q60: {=INDEX(Raw!I:FI, MATCH(Q$4, Raw!$A:$A, 0), MATCH(1, (Raw!$B$1:$FB$1=$I60)*(Raw!$B$2:$FB$2=$H60), 0))} -> 360000000 | R60: {=INDEX(Raw!J:FJ, MATCH(R$4, Raw!$A:$A, 0), MATCH(1, (Raw!$B$1:$FB$1=$I60)*(Raw!$B$2:$FB$2=$H60), 0))} -> 2179000000 | S60: {=INDEX(Raw!K:FK, MATCH(S$4, Raw!$A:$A, 0), MATCH(1, (Raw!$B$1:$FB$1=$I60)*(Raw!$B$2:$FB$2=$H60), 0))} -> 382000000 | T60: {=INDEX(Raw!L:FL, MATCH(T$4, Raw!$A:$A, 0), MATCH(1, (Raw!$B$1:$FB$1=$I60)*(Raw!$B$2:$FB$2=$H60), 0))} -> 1920000000 | U60: {=INDEX(Raw!M:FM, MATCH(U$4, Raw!$A:$A, 0), MATCH(1, (Raw!$B$1:$FB$1=$I60)*(Raw!$B$2:$FB$2=$H60), 0))} -> 0 | V60: {=INDEX(Raw!N:FN, MATCH(V$4, Raw!$A:$A, 0), MATCH(1, (Raw!$B$1:$FB$1=$I60)*(Raw!$B$2:$FB$2=$H60), 0))} -> 1359000000 | W60: {=INDEX(Raw!O:FO, MATCH(W$4, Raw!$A:$A, 0), MATCH(1, (Raw!$B$1:$FB$1=$I60)*(Raw!$B$2:$FB$2=$H60), 0))} -> 0 | X60: {=INDEX(Raw!P:FP, MATCH(X$4, Raw!$A:$A, 0), MATCH(1, (Raw!$B$1:$FB$1=$I60)*(Raw!$B$2:$FB$2=$H60), 0))} -> 1890000000 | Y60: {=INDEX(Raw!Q:FQ, MATCH(Y$4, Raw!$A:$A, 0), MATCH(1, (Raw!$B$1:$FB$1=$I60)*(Raw!$B$2:$FB$2=$H60), 0))} -> 0 | Z60: {=INDEX(Raw!R:FR, MATCH(Z$4, Raw!$A:$A, 0), MATCH(1, (Raw!$B$1:$FB$1=$I60)*(Raw!$B$2:$FB$2=$H60), 0))} -> 0 | AA60: {=INDEX(Raw!S:FS, MATCH(AA$4, Raw!$A:$A, 0), MATCH(1, (Raw!$B$1:$FB$1=$I60)*(Raw!$B$2:$FB$2=$H60), 0))} -> 0 | AB60: {=INDEX(Raw!T:FT, MATCH(AB$4, Raw!$A:$A, 0), MATCH(1, (Raw!$B$1:$FB$1=$I60)*(Raw!$B$2:$FB$2=$H60), 0))} -> 0 | AC60: {=INDEX(Raw!U:FU, MATCH(AC$4, Raw!$A:$A, 0), MATCH(1, (Raw!$B$1:$FB$1=$I60)*(Raw!$B$2:$FB$2=$H60), 0))} -> 0.4 | AD60: {=INDEX(Raw!V:FV, MATCH(AD$4, Raw!$A:$A, 0), MATCH(1, (Raw!$B$1:$FB$1=$I60)*(Raw!$B$2:$FB$2=$H60), 0))} -> 0.27
