Workbook

Sheet Raw
B1: =YEAR(B2) -> 2025 | C1: =YEAR(C2) -> 2024 | D1: =YEAR(D2) -> 2023 | E1: =YEAR(E2) -> 2022 | F1: =YEAR(F2) -> 2021 | G1: =YEAR(G2) -> 2020 | H1: =YEAR(H2) -> 2019 | I1: =YEAR(I2) -> 2018 | ... AO1: =YEAR(AO2) -> 1986
A2: Metric Name | B2: 46022 | C2: 45657 | D2: 45291 | E2: 44926 | F2: 44561 | G2: 44196 | H2: 43830 | I2: 43465 | J2: 43100 | K2: 42735 | L2: 42369 | M2: 42004 | N2: 41639 | O2: 41274 | P2: 40908 | Q2: 40543 | R2: 40178 | S2: 39813 | T2: 39447 | U2: 39082 | V2: 38717 | W2: 38352 | X2: 37986 | Y2: 37621 | Z2: 37256 | AA2: 36891 | AB2: 36525 | AC2: 36160 | AD2: 35795 | AE2: 35430 | AF2: 35064 | AG2: 34699 | AH2: 34334 | AI2: 33969 | AJ2: 33603 | AK2: 33238 | AL2: 32873 | AM2: 32508 | AN2: 32142 | AO2: 31777
A4: Net Income/Loss | B4: 13137000000 | C4: 10649000000 | D4: 10703000000 | E4: 9571000000 | F4: 9804000000 | G4: 7768000000 | H4: 8985000000 | I4: 6476000000 | J4: 1283000000 | K4: 6550000000 | L4: 7366000000 | M4: 7124000000 | N4: 8626000000 | O4: 9086000000 | P4: 8646000000 | Q4: 11837000000 | R4: 6906000000 | S4: 5874000000 | T4: 6027000000 | U4: 5080000000 | V4: 4872000000 | W4: 4847000000 | X4: 4347000000 | Y4: 3050000000 | Z4: 3969000000 | AA4: 2177000000 | AB4: 2431000000 | AC4: 3533000000 | AD4: 4129000000 | AE4: 3492000000 | AF4: 2986000000 | AG4: 2554000000 | AH4: 2176000000 | AI4: 1664382000 | AJ4: 1618002000 | AK4: 1381904000 | AL4: 1723825000 | AM4: 1044703000 | AN4: 916136000 | AO4: 934347000
A5: Total Depreciation And Amortization - Cash Flow | B5: 1050000000 | C5: 1075000000 | D5: 1128000000 | E5: 1260000000 | F5: 1452000000 | G5: 1536000000 | H5: 1365000000 | I5: 1086000000 | J5: 1260000000 | K5: 1787000000 | L5: 1970000000 | M5: 1976000000 | N5: 1977000000 | O5: 1982000000 | P5: 1954000000 | Q5: 1443000000 | R5: 1236000000 | S5: 1228000000 | T5: 1163000000 | U5: 938000000 | V5: 932000000 | W5: 893000000 | X5: 850000000 | Y5: 806000000 | Z5: 803000000 | AA5: 773000000 | AB5: 792000000 | AC5: 645000000 | AD5: 626000000 | AE5: 479000000 | AF5: 454000000 | AG5: 411000000 | AH5: 360000000 | AI5: 321922000 | AJ5: 2.61427e+08 | AK5: 243888000 | AL5: 183765000 | AM5: 169768000 | AN5: 151904000 | AO5: 166829000
A6: Other Non-Cash Items | B6: 429000000 | C6: 1315000000 | D6: 614000000 | E6: 792000000 | F6: 44000000 | G6: -150000000 | H6: -245000000 | I6: 1305000000 | J6: 1056000000 | K6: 680000000 | L6: 1349000000 | M6: 1954000000 | N6: 871000000 | O6: 657000000 | P6: 767000000 | Q6: -4118000000 | R6: 608000000 | S6: 1224000000 | T6: 0 | U6: 554000000 | V6: 189000000 | W6: 845000000 | X6: 427000000 | Y6: 1293000000 | Z6: -200000000 | AA6: 1487000000 | AB6: 0 | AC6: 0 | AD6: 0 | AE6: 0 | AF6: 0 | AG6: 0 | AH6: 12000000 | AI6: 219433000 | AJ6: 0 | AK6: 0 | AL6: 0 | AM6: 0 | AN6: -79701000 | AO6: 0
A7: Total Non-Cash Items | B7: 1479000000 | C7: 2390000000 | D7: 1742000000 | E7: 2052000000 | F7: 1496000000 | G7: 1386000000 | H7: 1120000000 | I7: 2391000000 | J7: 2316000000 | K7: 2467000000 | L7: 3319000000 | M7: 3930000000 | N7: 2848000000 | O7: 2639000000 | P7: 2721000000 | Q7: -2675000000 | R7: 1844000000 | S7: 2452000000 | T7: 1163000000 | U7: 1492000000 | V7: 1121000000 | W7: 1738000000 | X7: 1277000000 | Y7: 2099000000 | Z7: 603000000 | AA7: 2260000000 | AB7: 792000000 | AC7: 645000000 | AD7: 626000000 | AE7: 479000000 | AF7: 454000000 | AG7: 411000000 | AH7: 372000000 | AI7: 541355000 | AJ7: 2.61427e+08 | AK7: 243888000 | AL7: 183765000 | AM7: 169768000 | AN7: 72203000 | AO7: 166829000
A9: Change In Accounts Receivable | B9: 0 | C9: 0 | D9: 0 | E9: 0 | F9: 0 | G9: 0 | H9: 0 | I9: 0 | J9: 0 | K9: 0 | L9: 0 | M9: 0 | N9: 0 | O9: 0 | P9: 0 | Q9: 0 | R9: 0 | S9: 0 | T9: 0 | U9: 0 | V9: 0 | W9: 0 | X9: 0 | Y9: 0 | Z9: 0 | AA9: 0 | AB9: 0 | AC9: 0 | AD9: 0 | AE9: 0 | AF9: 0 | AG9: 0 | AH9: 0 | AI9: 0 | AJ9: 0 | AK9: 0 | AL9: 0 | AM9: 0 | AN9: 0 | AO9: 0
A10: Change In Inventories | B10: 0 | C10: 0 | D10: 0 | E10: 0 | F10: 0 | G10: 0 | H10: 0 | I10: 0 | J10: 0 | K10: 0 | L10: 0 | M10: 0 | N10: 0 | O10: 0 | P10: 0 | Q10: 0 | R10: 0 | S10: 0 | T10: 0 | U10: 0 | V10: 0 | W10: 0 | X10: 0 | Y10: 0 | Z10: 0 | AA10: 0 | AB10: 0 | AC10: 0 | AD10: 0 | AE10: 0 | AF10: 0 | AG10: 0 | AH10: 0 | AI10: 0 | AJ10: 0 | AK10: 0 | AL10: 0 | AM10: 0 | AN10: 0 | AO10: 0
A11: Change In Accounts Payable | B11: 0 | C11: 0 | D11: 0 | E11: 0 | F11: 0 | G11: 0 | H11: 0 | I11: 0 | J11: 0 | K11: 0 | L11: 0 | M11: 0 | N11: 0 | O11: 0 | P11: 0 | Q11: 0 | R11: 0 | S11: 0 | T11: 0 | U11: 0 | V11: 0 | W11: 0 | X11: 0 | Y11: 0 | Z11: 0 | AA11: 0 | AB11: 0 | AC11: 0 | AD11: 0 | AE11: 0 | AF11: 0 | AG11: 0 | AH11: 0 | AI11: 0 | AJ11: 0 | AK11: 0 | AL11: 0 | AM11: 0 | AN11: 0 | AO11: 0
A12: Change In Assets/Liabilities | B12: -7208000000 | C12: -6234000000 | D12: -846000000 | E12: -605000000 | F12: 1325000000 | G12: 690000000 | H12: 366000000 | I12: -1240000000 | J12: 3442000000 | K12: -225000000 | L12: -157000000 | M12: -439000000 | N12: -932000000 | O12: -1080000000 | P12: -1893000000 | Q12: 370000000 | R12: -564000000 | S12: -755000000 | T12: -40000000 | U12: -615000000 | V12: 430000000 | W12: -617000000 | X12: -168000000 | Y12: -407000000 | Z12: -462000000 | AA12: -852000000 | AB12: 0 | AC12: 0 | AD12: 0 | AE12: 0 | AF12: 0 | AG12: 0 | AH12: 0 | AI12: 0 | AJ12: 0 | AK12: 0 | AL12: 0 | AM12: 0 | AN12: 0 | AO12: 0
A13: Total Change In Assets/Liabilities | B13: -7208000000 | C13: -6234000000 | D13: -846000000 | E13: -605000000 | F13: 1325000000 | G13: 690000000 | H13: 366000000 | I13: -1240000000 | J13: 3442000000 | K13: -225000000 | L13: -157000000 | M13: -439000000 | N13: -932000000 | O13: -1080000000 | P13: -1893000000 | Q13: 370000000 | R13: -564000000 | S13: -755000000 | T13: -40000000 | U13: -615000000 | V13: 430000000 | W13: -617000000 | X13: -168000000 | Y13: -407000000 | Z13: -462000000 | AA13: -852000000 | AB13: -557000000 | AC13: -550000000 | AD13: -47000000 | AE13: 36000000 | AF13: -405000000 | AG13: 129000000 | AH13: 54000000 | AI13: -43130000 | AJ13: 222837000 | AK13: -178202000 | AL13: 279382000 | AM13: -83736000 | AN13: -28706000 | AO13: 94524000
A15: Cash Flow From Operating Activities | B15: 7408000000 | C15: 6805000000 | D15: 11599000000 | E15: 11018000000 | F15: 12625000000 | G15: 9844000000 | H15: 10471000000 | I15: 7627000000 | J15: 7041000000 | K15: 8792000000 | L15: 10528000000 | M15: 10615000000 | N15: 10542000000 | O15: 10645000000 | P15: 9474000000 | Q15: 9532000000 | R15: 8186000000 | S15: 7571000000 | T15: 7150000000 | U15: 5957000000 | V15: 6423000000 | W15: 5968000000 | X15: 5456000000 | Y15: 4742000000 | Z15: 4110000000 | AA15: 3585000000 | AB15: 3883000000 | AC15: 3433000000 | AD15: 4033000000 | AE15: 3463000000 | AF15: 3115000000 | AG15: 3183000000 | AH15: 2508000000 | AI15: 2232370000 | AJ15: 2.084401e+09 | AK15: 1283927000 | AL15: 1110213000 | AM15: 1166837000 | AN15: 958768000 | AO15: 1016287000
A17: Net Change In Property, Plant, And Equipment | B17: -2099000000 | C17: -2024000000 | D17: -1778000000 | E17: -1409000000 | F17: -1259000000 | G17: -988000000 | H17: -1076000000 | I17: -1300000000 | J17: -1642000000 | K17: -2112000000 | L17: -2468000000 | M17: -2183000000 | N17: -2439000000 | O17: -2637000000 | P17: -2819000000 | Q17: -2081000000 | R17: -1889000000 | S17: -1839000000 | T17: -1409000000 | U17: -767000000 | V17: -811000000 | W17: -414000000 | X17: -725000000 | Y17: -782000000 | Z17: -678000000 | AA17: -688000000 | AB17: -1024000000 | AC17: -809000000 | AD17: -1022000000 | AE17: -909000000 | AF17: -893000000 | AG17: -769000000 | AH17: -488000000 | AI17: -1036192000 | AJ17: -747719000 | AK17: -573763000 | AL17: -401801000 | AM17: -343425000 | AN17: 0 | AO17: 0
... A39: Common Stock Dividends Paid | B39: -8779000000 | C39: -8359000000 | D39: -7952000000 | E39: -7616000000 | F39: -7252000000 | G39: -7047000000 | H39: -6845000000 | I39: -6644000000 | J39: -6320000000 | K39: -6043000000 | L39: -5741000000 | M39: -5350000000 | N39: -4969000000 | O39: -4595000000 | P39: -4300000000 | Q39: -4068000000 | R39: -3800000000 | S39: -3521000000 | T39: -3149000000 | U39: -2911000000 | V39: -2678000000 | W39: -2429000000 | X39: -2166000000 | Y39: -1987000000 | Z39: -1791000000 | AA39: -1685000000 | AB39: 0 | AC39: 0 | AD39: 0 | AE39: 0 | AF39: 0 | AG39: 0 | AH39: 0 | AI39: 0 | AJ39: 0 | AK39: 0 | AL39: 0 | AM39: 0 | AN39: 0 | AO39: 0

Sheet Lookup
A1: TICKER | B1: ASOF_DATE | C1: YR | D1: Net Income/Loss | E1: Total Depreciation And Amortization - Cash Flow | F1: Other Non-Cash Items | G1: Total Non-Cash Items | H1: Change In Accounts Receivable | I1: Change In Inventories | J1: Change In Accounts Payable | K1: Change In Assets/Liabilities | L1: Total Change In Assets/Liabilities | M1: Cash Flow From Operating Activities | N1: Net Change In Property, Plant, And Equipment | O1: Net Change In Intangible Assets | P1: Net Acquisitions/Divestitures | Q1: Net Change In Short-term Investments | R1: Net Change In Long-Term Investments | S1: Net Change In Investments - Total | T1: Investing Activities - Other | U1: Cash Flow From Investing Activities | V1: Net Long-Term Debt | W1: Net Current Debt | X1: Debt Issuance/Retirement Net - Total | Y1: Net Common Equity Issued/Repurchased | Z1: Net Total Equity Issued/Repurchased | AA1: Total Common And Preferred Stock Dividends Paid | AB1: Financial Activities - Other | AC1: Cash Flow From Financial Activities | AD1: Net Cash Flow | AE1: Stock-Based Compensation | AF1: Common Stock Dividends Paid
A2: KO | B2: =TODAY() -> 46089 | C2: 2025 | D2: =INDEX(Raw!$B$4:$AO$39, MATCH(D$1, Raw!$A$4:$A$39, 0), MATCH($C2, Raw!$B$1:$AO$1, 0)) -> 13137000000 | E2: =INDEX(Raw!$B$4:$AO$39, MATCH(E$1, Raw!$A$4:$A$39, 0), MATCH($C2, Raw!$B$1:$AO$1, 0)) -> 1050000000 | F2: =INDEX(Raw!$B$4:$AO$39, MATCH(F$1, Raw!$A$4:$A$39, 0), MATCH($C2, Raw!$B$1:$AO$1, 0)) -> 429000000 | G2: =INDEX(Raw!$B$4:$AO$39, MATCH(G$1, Raw!$A$4:$A$39, 0), MATCH($C2, Raw!$B$1:$AO$1, 0)) -> 1479000000 | H2: =INDEX(Raw!$B$4:$AO$39, MATCH(H$1, Raw!$A$4:$A$39, 0), MATCH($C2, Raw!$B$1:$AO$1, 0)) -> 0 | I2: =INDEX(Raw!$B$4:$AO$39, MATCH(I$1, Raw!$A$4:$A$39, 0), MATCH($C2, Raw!$B$1:$AO$1, 0)) -> 0 | J2: =INDEX(Raw!$B$4:$AO$39, MATCH(J$1, Raw!$A$4:$A$39, 0), MATCH($C2, Raw!$B$1:$AO$1, 0)) -> 0 | K2: =INDEX(Raw!$B$4:$AO$39, MATCH(K$1, Raw!$A$4:$A$39, 0), MATCH($C2, Raw!$B$1:$AO$1, 0)) -> -7208000000 | ... AF2: =INDEX(Raw!$B$4:$AO$39, MATCH(AF$1, Raw!$A$4:$A$39, 0), MATCH($C2, Raw!$B$1:$AO$1, 0)) -> -8779000000
A3: KO | B3: =TODAY() -> 46089 | C3: 2024 | D3: =INDEX(Raw!$B$4:$AO$39, MATCH(D$1, Raw!$A$4:$A$39, 0), MATCH($C3, Raw!$B$1:$AO$1, 0)) -> 10649000000 | E3: =INDEX(Raw!$B$4:$AO$39, MATCH(E$1, Raw!$A$4:$A$39, 0), MATCH($C3, Raw!$B$1:$AO$1, 0)) -> 1075000000 | F3: =INDEX(Raw!$B$4:$AO$39, MATCH(F$1, Raw!$A$4:$A$39, 0), MATCH($C3, Raw!$B$1:$AO$1, 0)) -> 1315000000 | G3: =INDEX(Raw!$B$4:$AO$39, MATCH(G$1, Raw!$A$4:$A$39, 0), MATCH($C3, Raw!$B$1:$AO$1, 0)) -> 2390000000 | H3: =INDEX(Raw!$B$4:$AO$39, MATCH(H$1, Raw!$A$4:$A$39, 0), MATCH($C3, Raw!$B$1:$AO$1, 0)) -> 0 | I3: =INDEX(Raw!$B$4:$AO$39, MATCH(I$1, Raw!$A$4:$A$39, 0), MATCH($C3, Raw!$B$1:$AO$1, 0)) -> 0 | J3: =INDEX(Raw!$B$4:$AO$39, MATCH(J$1, Raw!$A$4:$A$39, 0), MATCH($C3, Raw!$B$1:$AO$1, 0)) -> 0 | K3: =INDEX(Raw!$B$4:$AO$39, MATCH(K$1, Raw!$A$4:$A$39, 0), MATCH($C3, Raw!$B$1:$AO$1, 0)) -> -6234000000 | ... AF3: =INDEX(Raw!$B$4:$AO$39, MATCH(AF$1, Raw!$A$4:$A$39, 0), MATCH($C3, Raw!$B$1:$AO$1, 0)) -> -8359000000
A4: KO | B4: =TODAY() -> 46089 | C4: 2023 | D4: =INDEX(Raw!$B$4:$AO$39, MATCH(D$1, Raw!$A$4:$A$39, 0), MATCH($C4, Raw!$B$1:$AO$1, 0)) -> 10703000000 | E4: =INDEX(Raw!$B$4:$AO$39, MATCH(E$1, Raw!$A$4:$A$39, 0), MATCH($C4, Raw!$B$1:$AO$1, 0)) -> 1128000000 | F4: =INDEX(Raw!$B$4:$AO$39, MATCH(F$1, Raw!$A$4:$A$39, 0), MATCH($C4, Raw!$B$1:$AO$1, 0)) -> 614000000 | G4: =INDEX(Raw!$B$4:$AO$39, MATCH(G$1, Raw!$A$4:$A$39, 0), MATCH($C4, Raw!$B$1:$AO$1, 0)) -> 1742000000 | H4: =INDEX(Raw!$B$4:$AO$39, MATCH(H$1, Raw!$A$4:$A$39, 0), MATCH($C4, Raw!$B$1:$AO$1, 0)) -> 0 | I4: =INDEX(Raw!$B$4:$AO$39, MATCH(I$1, Raw!$A$4:$A$39, 0), MATCH($C4, Raw!$B$1:$AO$1, 0)) -> 0 | J4: =INDEX(Raw!$B$4:$AO$39, MATCH(J$1, Raw!$A$4:$A$39, 0), MATCH($C4, Raw!$B$1:$AO$1, 0)) -> 0 | K4: =INDEX(Raw!$B$4:$AO$39, MATCH(K$1, Raw!$A$4:$A$39, 0), MATCH($C4, Raw!$B$1:$AO$1, 0)) -> -846000000 | ... AF4: =INDEX(Raw!$B$4:$AO$39, MATCH(AF$1, Raw!$A$4:$A$39, 0), MATCH($C4, Raw!$B$1:$AO$1, 0)) -> -7952000000
A5: KO | B5: =TODAY() -> 46089 | C5: 2022 | D5: =INDEX(Raw!$B$4:$AO$39, MATCH(D$1, Raw!$A$4:$A$39, 0), MATCH($C5, Raw!$B$1:$AO$1, 0)) -> 9571000000 | E5: =INDEX(Raw!$B$4:$AO$39, MATCH(E$1, Raw!$A$4:$A$39, 0), MATCH($C5, Raw!$B$1:$AO$1, 0)) -> 1260000000 | F5: =INDEX(Raw!$B$4:$AO$39, MATCH(F$1, Raw!$A$4:$A$39, 0), MATCH($C5, Raw!$B$1:$AO$1, 0)) -> 792000000 | G5: =INDEX(Raw!$B$4:$AO$39, MATCH(G$1, Raw!$A$4:$A$39, 0), MATCH($C5, Raw!$B$1:$AO$1, 0)) -> 2052000000 | H5: =INDEX(Raw!$B$4:$AO$39, MATCH(H$1, Raw!$A$4:$A$39, 0), MATCH($C5, Raw!$B$1:$AO$1, 0)) -> 0 | I5: =INDEX(Raw!$B$4:$AO$39, MATCH(I$1, Raw!$A$4:$A$39, 0), MATCH($C5, Raw!$B$1:$AO$1, 0)) -> 0 | J5: =INDEX(Raw!$B$4:$AO$39, MATCH(J$1, Raw!$A$4:$A$39, 0), MATCH($C5, Raw!$B$1:$AO$1, 0)) -> 0 | K5: =INDEX(Raw!$B$4:$AO$39, MATCH(K$1, Raw!$A$4:$A$39, 0), MATCH($C5, Raw!$B$1:$AO$1, 0)) -> -605000000 | ... AF5: =INDEX(Raw!$B$4:$AO$39, MATCH(AF$1, Raw!$A$4:$A$39, 0), MATCH($C5, Raw!$B$1:$AO$1, 0)) -> -7616000000
A6: KO | B6: =TODAY() -> 46089 | C6: 2021 | D6: =INDEX(Raw!$B$4:$AO$39, MATCH(D$1, Raw!$A$4:$A$39, 0), MATCH($C6, Raw!$B$1:$AO$1, 0)) -> 9804000000 | E6: =INDEX(Raw!$B$4:$AO$39, MATCH(E$1, Raw!$A$4:$A$39, 0), MATCH($C6, Raw!$B$1:$AO$1, 0)) -> 1452000000 | F6: =INDEX(Raw!$B$4:$AO$39, MATCH(F$1, Raw!$A$4:$A$39, 0), MATCH($C6, Raw!$B$1:$AO$1, 0)) -> 44000000 | G6: =INDEX(Raw!$B$4:$AO$39, MATCH(G$1, Raw!$A$4:$A$39, 0), MATCH($C6, Raw!$B$1:$AO$1, 0)) -> 1496000000 | H6: =INDEX(Raw!$B$4:$AO$39, MATCH(H$1, Raw!$A$4:$A$39, 0), MATCH($C6, Raw!$B$1:$AO$1, 0)) -> 0 | I6: =INDEX(Raw!$B$4:$AO$39, MATCH(I$1, Raw!$A$4:$A$39, 0), MATCH($C6, Raw!$B$1:$AO$1, 0)) -> 0 | J6: =INDEX(Raw!$B$4:$AO$39, MATCH(J$1, Raw!$A$4:$A$39, 0), MATCH($C6, Raw!$B$1:$AO$1, 0)) -> 0 | K6: =INDEX(Raw!$B$4:$AO$39, MATCH(K$1, Raw!$A$4:$A$39, 0), MATCH($C6, Raw!$B$1:$AO$1, 0)) -> 1325000000 | ... AF6: =INDEX(Raw!$B$4:$AO$39, MATCH(AF$1, Raw!$A$4:$A$39, 0), MATCH($C6, Raw!$B$1:$AO$1, 0)) -> -7252000000
A7: KO | B7: =TODAY() -> 46089 | C7: 2020 | D7: =INDEX(Raw!$B$4:$AO$39, MATCH(D$1, Raw!$A$4:$A$39, 0), MATCH($C7, Raw!$B$1:$AO$1, 0)) -> 7768000000 | E7: =INDEX(Raw!$B$4:$AO$39, MATCH(E$1, Raw!$A$4:$A$39, 0), MATCH($C7, Raw!$B$1:$AO$1, 0)) -> 1536000000 | F7: =INDEX(Raw!$B$4:$AO$39, MATCH(F$1, Raw!$A$4:$A$39, 0), MATCH($C7, Raw!$B$1:$AO$1, 0)) -> -150000000 | G7: =INDEX(Raw!$B$4:$AO$39, MATCH(G$1, Raw!$A$4:$A$39, 0), MATCH($C7, Raw!$B$1:$AO$1, 0)) -> 1386000000 | H7: =INDEX(Raw!$B$4:$AO$39, MATCH(H$1, Raw!$A$4:$A$39, 0), MATCH($C7, Raw!$B$1:$AO$1, 0)) -> 0 | I7: =INDEX(Raw!$B$4:$AO$39, MATCH(I$1, Raw!$A$4:$A$39, 0), MATCH($C7, Raw!$B$1:$AO$1, 0)) -> 0 | J7: =INDEX(Raw!$B$4:$AO$39, MATCH(J$1, Raw!$A$4:$A$39, 0), MATCH($C7, Raw!$B$1:$AO$1, 0)) -> 0 | K7: =INDEX(Raw!$B$4:$AO$39, MATCH(K$1, Raw!$A$4:$A$39, 0), MATCH($C7, Raw!$B$1:$AO$1, 0)) -> 690000000 | ... AF7: =INDEX(Raw!$B$4:$AO$39, MATCH(AF$1, Raw!$A$4:$A$39, 0), MATCH($C7, Raw!$B$1:$AO$1, 0)) -> -7047000000
A8: KO | B8: =TODAY() -> 46089 | C8: 2019 | D8: =INDEX(Raw!$B$4:$AO$39, MATCH(D$1, Raw!$A$4:$A$39, 0), MATCH($C8, Raw!$B$1:$AO$1, 0)) -> 8985000000 | E8: =INDEX(Raw!$B$4:$AO$39, MATCH(E$1, Raw!$A$4:$A$39, 0), MATCH($C8, Raw!$B$1:$AO$1, 0)) -> 1365000000 | F8: =INDEX(Raw!$B$4:$AO$39, MATCH(F$1, Raw!$A$4:$A$39, 0), MATCH($C8, Raw!$B$1:$AO$1, 0)) -> -245000000 | G8: =INDEX(Raw!$B$4:$AO$39, MATCH(G$1, Raw!$A$4:$A$39, 0), MATCH($C8, Raw!$B$1:$AO$1, 0)) -> 1120000000 | H8: =INDEX(Raw!$B$4:$AO$39, MATCH(H$1, Raw!$A$4:$A$39, 0), MATCH($C8, Raw!$B$1:$AO$1, 0)) -> 0 | I8: =INDEX(Raw!$B$4:$AO$39, MATCH(I$1, Raw!$A$4:$A$39, 0), MATCH($C8, Raw!$B$1:$AO$1, 0)) -> 0 | J8: =INDEX(Raw!$B$4:$AO$39, MATCH(J$1, Raw!$A$4:$A$39, 0), MATCH($C8, Raw!$B$1:$AO$1, 0)) -> 0 | K8: =INDEX(Raw!$B$4:$AO$39, MATCH(K$1, Raw!$A$4:$A$39, 0), MATCH($C8, Raw!$B$1:$AO$1, 0)) -> 366000000 | ... AF8: =INDEX(Raw!$B$4:$AO$39, MATCH(AF$1, Raw!$A$4:$A$39, 0), MATCH($C8, Raw!$B$1:$AO$1, 0)) -> -6845000000
A9: KO | B9: =TODAY() -> 46089 | C9: 2018 | D9: =INDEX(Raw!$B$4:$AO$39, MATCH(D$1, Raw!$A$4:$A$39, 0), MATCH($C9, Raw!$B$1:$AO$1, 0)) -> 6476000000 | E9: =INDEX(Raw!$B$4:$AO$39, MATCH(E$1, Raw!$A$4:$A$39, 0), MATCH($C9, Raw!$B$1:$AO$1, 0)) -> 1086000000 | F9: =INDEX(Raw!$B$4:$AO$39, MATCH(F$1, Raw!$A$4:$A$39, 0), MATCH($C9, Raw!$B$1:$AO$1, 0)) -> 1305000000 | G9: =INDEX(Raw!$B$4:$AO$39, MATCH(G$1, Raw!$A$4:$A$39, 0), MATCH($C9, Raw!$B$1:$AO$1, 0)) -> 2391000000 | H9: =INDEX(Raw!$B$4:$AO$39, MATCH(H$1, Raw!$A$4:$A$39, 0), MATCH($C9, Raw!$B$1:$AO$1, 0)) -> 0 | I9: =INDEX(Raw!$B$4:$AO$39, MATCH(I$1, Raw!$A$4:$A$39, 0), MATCH($C9, Raw!$B$1:$AO$1, 0)) -> 0 | J9: =INDEX(Raw!$B$4:$AO$39, MATCH(J$1, Raw!$A$4:$A$39, 0), MATCH($C9, Raw!$B$1:$AO$1, 0)) -> 0 | K9: =INDEX(Raw!$B$4:$AO$39, MATCH(K$1, Raw!$A$4:$A$39, 0), MATCH($C9, Raw!$B$1:$AO$1, 0)) -> -1240000000 | ... AF9: =INDEX(Raw!$B$4:$AO$39, MATCH(AF$1, Raw!$A$4:$A$39, 0), MATCH($C9, Raw!$B$1:$AO$1, 0)) -> -6644000000
A10: KO | B10: =TODAY() -> 46089 | C10: 2017 | D10: =INDEX(Raw!$B$4:$AO$39, MATCH(D$1, Raw!$A$4:$A$39, 0), MATCH($C10, Raw!$B$1:$AO$1, 0)) -> 1283000000 | E10: =INDEX(Raw!$B$4:$AO$39, MATCH(E$1, Raw!$A$4:$A$39, 0), MATCH($C10, Raw!$B$1:$AO$1, 0)) -> 1260000000 | F10: =INDEX(Raw!$B$4:$AO$39, MATCH(F$1, Raw!$A$4:$A$39, 0), MATCH($C10, Raw!$B$1:$AO$1, 0)) -> 1056000000 | G10: =INDEX(Raw!$B$4:$AO$39, MATCH(G$1, Raw!$A$4:$A$39, 0), MATCH($C10, Raw!$B$1:$AO$1, 0)) -> 2316000000 | H10: =INDEX(Raw!$B$4:$AO$39, MATCH(H$1, Raw!$A$4:$A$39, 0), MATCH($C10, Raw!$B$1:$AO$1, 0)) -> 0 | I10: =INDEX(Raw!$B$4:$AO$39, MATCH(I$1, Raw!$A$4:$A$39, 0), MATCH($C10, Raw!$B$1:$AO$1, 0)) -> 0 | J10: =INDEX(Raw!$B$4:$AO$39, MATCH(J$1, Raw!$A$4:$A$39, 0), MATCH($C10, Raw!$B$1:$AO$1, 0)) -> 0 | K10: =INDEX(Raw!$B$4:$AO$39, MATCH(K$1, Raw!$A$4:$A$39, 0), MATCH($C10, Raw!$B$1:$AO$1, 0)) -> 3442000000 | ... AF10: =INDEX(Raw!$B$4:$AO$39, MATCH(AF$1, Raw!$A$4:$A$39, 0), MATCH($C10, Raw!$B$1:$AO$1, 0)) -> -6320000000
A11: KO | B11: =TODAY() -> 46089 | C11: 2016 | D11: =INDEX(Raw!$B$4:$AO$39, MATCH(D$1, Raw!$A$4:$A$39, 0), MATCH($C11, Raw!$B$1:$AO$1, 0)) -> 6550000000 | E11: =INDEX(Raw!$B$4:$AO$39, MATCH(E$1, Raw!$A$4:$A$39, 0), MATCH($C11, Raw!$B$1:$AO$1, 0)) -> 1787000000 | F11: =INDEX(Raw!$B$4:$AO$39, MATCH(F$1, Raw!$A$4:$A$39, 0), MATCH($C11, Raw!$B$1:$AO$1, 0)) -> 680000000 | G11: =INDEX(Raw!$B$4:$AO$39, MATCH(G$1, Raw!$A$4:$A$39, 0), MATCH($C11, Raw!$B$1:$AO$1, 0)) -> 2467000000 | H11: =INDEX(Raw!$B$4:$AO$39, MATCH(H$1, Raw!$A$4:$A$39, 0), MATCH($C11, Raw!$B$1:$AO$1, 0)) -> 0 | I11: =INDEX(Raw!$B$4:$AO$39, MATCH(I$1, Raw!$A$4:$A$39, 0), MATCH($C11, Raw!$B$1:$AO$1, 0)) -> 0 | J11: =INDEX(Raw!$B$4:$AO$39, MATCH(J$1, Raw!$A$4:$A$39, 0), MATCH($C11, Raw!$B$1:$AO$1, 0)) -> 0 | K11: =INDEX(Raw!$B$4:$AO$39, MATCH(K$1, Raw!$A$4:$A$39, 0), MATCH($C11, Raw!$B$1:$AO$1, 0)) -> -225000000 | ... AF11: =INDEX(Raw!$B$4:$AO$39, MATCH(AF$1, Raw!$A$4:$A$39, 0), MATCH($C11, Raw!$B$1:$AO$1, 0)) -> -6043000000
A12: KO | B12: =TODAY() -> 46089 | C12: 2015 | D12: =INDEX(Raw!$B$4:$AO$39, MATCH(D$1, Raw!$A$4:$A$39, 0), MATCH($C12, Raw!$B$1:$AO$1, 0)) -> 7366000000 | E12: =INDEX(Raw!$B$4:$AO$39, MATCH(E$1, Raw!$A$4:$A$39, 0), MATCH($C12, Raw!$B$1:$AO$1, 0)) -> 1970000000 | F12: =INDEX(Raw!$B$4:$AO$39, MATCH(F$1, Raw!$A$4:$A$39, 0), MATCH($C12, Raw!$B$1:$AO$1, 0)) -> 1349000000 | G12: =INDEX(Raw!$B$4:$AO$39, MATCH(G$1, Raw!$A$4:$A$39, 0), MATCH($C12, Raw!$B$1:$AO$1, 0)) -> 3319000000 | H12: =INDEX(Raw!$B$4:$AO$39, MATCH(H$1, Raw!$A$4:$A$39, 0), MATCH($C12, Raw!$B$1:$AO$1, 0)) -> 0 | I12: =INDEX(Raw!$B$4:$AO$39, MATCH(I$1, Raw!$A$4:$A$39, 0), MATCH($C12, Raw!$B$1:$AO$1, 0)) -> 0 | J12: =INDEX(Raw!$B$4:$AO$39, MATCH(J$1, Raw!$A$4:$A$39, 0), MATCH($C12, Raw!$B$1:$AO$1, 0)) -> 0 | K12: =INDEX(Raw!$B$4:$AO$39, MATCH(K$1, Raw!$A$4:$A$39, 0), MATCH($C12, Raw!$B$1:$AO$1, 0)) -> -157000000 | ... AF12: =INDEX(Raw!$B$4:$AO$39, MATCH(AF$1, Raw!$A$4:$A$39, 0), MATCH($C12, Raw!$B$1:$AO$1, 0)) -> -5741000000
A13: KO | B13: =TODAY() -> 46089 | C13: 2014 | D13: =INDEX(Raw!$B$4:$AO$39, MATCH(D$1, Raw!$A$4:$A$39, 0), MATCH($C13, Raw!$B$1:$AO$1, 0)) -> 7124000000 | E13: =INDEX(Raw!$B$4:$AO$39, MATCH(E$1, Raw!$A$4:$A$39, 0), MATCH($C13, Raw!$B$1:$AO$1, 0)) -> 1976000000 | F13: =INDEX(Raw!$B$4:$AO$39, MATCH(F$1, Raw!$A$4:$A$39, 0), MATCH($C13, Raw!$B$1:$AO$1, 0)) -> 1954000000 | G13: =INDEX(Raw!$B$4:$AO$39, MATCH(G$1, Raw!$A$4:$A$39, 0), MATCH($C13, Raw!$B$1:$AO$1, 0)) -> 3930000000 | H13: =INDEX(Raw!$B$4:$AO$39, MATCH(H$1, Raw!$A$4:$A$39, 0), MATCH($C13, Raw!$B$1:$AO$1, 0)) -> 0 | I13: =INDEX(Raw!$B$4:$AO$39, MATCH(I$1, Raw!$A$4:$A$39, 0), MATCH($C13, Raw!$B$1:$AO$1, 0)) -> 0 | J13: =INDEX(Raw!$B$4:$AO$39, MATCH(J$1, Raw!$A$4:$A$39, 0), MATCH($C13, Raw!$B$1:$AO$1, 0)) -> 0 | K13: =INDEX(Raw!$B$4:$AO$39, MATCH(K$1, Raw!$A$4:$A$39, 0), MATCH($C13, Raw!$B$1:$AO$1, 0)) -> -439000000 | ... AF13: =INDEX(Raw!$B$4:$AO$39, MATCH(AF$1, Raw!$A$4:$A$39, 0), MATCH($C13, Raw!$B$1:$AO$1, 0)) -> -5350000000
... A41: KO | B41: =TODAY() -> 46089 | C41: 1986 | D41: =INDEX(Raw!$B$4:$AO$39, MATCH(D$1, Raw!$A$4:$A$39, 0), MATCH($C41, Raw!$B$1:$AO$1, 0)) -> 934347000 | E41: =INDEX(Raw!$B$4:$AO$39, MATCH(E$1, Raw!$A$4:$A$39, 0), MATCH($C41, Raw!$B$1:$AO$1, 0)) -> 166829000 | F41: =INDEX(Raw!$B$4:$AO$39, MATCH(F$1, Raw!$A$4:$A$39, 0), MATCH($C41, Raw!$B$1:$AO$1, 0)) -> 0 | G41: =INDEX(Raw!$B$4:$AO$39, MATCH(G$1, Raw!$A$4:$A$39, 0), MATCH($C41, Raw!$B$1:$AO$1, 0)) -> 166829000 | H41: =INDEX(Raw!$B$4:$AO$39, MATCH(H$1, Raw!$A$4:$A$39, 0), MATCH($C41, Raw!$B$1:$AO$1, 0)) -> 0 | I41: =INDEX(Raw!$B$4:$AO$39, MATCH(I$1, Raw!$A$4:$A$39, 0), MATCH($C41, Raw!$B$1:$AO$1, 0)) -> 0 | J41: =INDEX(Raw!$B$4:$AO$39, MATCH(J$1, Raw!$A$4:$A$39, 0), MATCH($C41, Raw!$B$1:$AO$1, 0)) -> 0 | K41: =INDEX(Raw!$B$4:$AO$39, MATCH(K$1, Raw!$A$4:$A$39, 0), MATCH($C41, Raw!$B$1:$AO$1, 0)) -> 0 | ... AF41: =INDEX(Raw!$B$4:$AO$39, MATCH(AF$1, Raw!$A$4:$A$39, 0), MATCH($C41, Raw!$B$1:$AO$1, 0)) -> 0

Sheet Export
A1: TICKER | B1: ASOF_DATE | C1: YR | D1: NET_INCOME | E1: D_A | F1: OTHER_NONCASH | G1: TOTAL_NONCASH | H1: CHANGE_AR | I1: CHANGE_INVENTORY | J1: CHANGE_AP | K1: CHANGE_ASSETS_LIABILITIES | L1: TOTAL_CHANGE_IN_ASSETS_LIABILITIES | M1: OPERATING_CASHFLOW | N1: NET_CHANGE_PPE | O1: NET_CHANGE_INTANGIBLE_ASSETS | P1: NET_AQUISITIONS_DIVESTITURES | Q1: NET_CHANGE_SHORT_INVESTMENTS | R1: NET_CHANGE_LONG_INVESTMENTS | S1: NET_CHANGE_TOTAL_INVESTMENTS | T1: OTHER_INVESTING_ACTIVITIES | U1: INVESTING_ACTIVITIES_CASHFLOW | V1: NET_LONG_DEBT | W1: NET_CURRENT_DEBT | X1: NET_TOTAL_DEBT_ISSUANCE_RETIREMENT | Y1: NET_COMMON_EQUITY_ISSUES_REPURCHASED | Z1: NET_TOTAL_EQUITY_ISSUED_REPURCHASED | AA1: TOTAL_COMMON_PERFERED_DIVIDENDS_PAID | AB1: OTHER_FINANCIAL_ACTIVITIES | AC1: CASHFLOW_FINANCIAL_ACTIVITIES | AD1: NET_CASHFLOW | AE1: STOCK_BASED_COMPENSATION | AF1: COMMON_STOCK_DIVIDENDS_PAID | AG1: SOURCE_FILE | AH1: LOAD_BATCH_ID | AI1: LOADED_AT
A2: =Lookup!A2 -> KO | B2: =Lookup!B2 -> 46089 | C2: =Lookup!C2 -> 2025 | D2: =Lookup!D2 -> 13137000000 | E2: =Lookup!E2 -> 1050000000 | F2: =Lookup!F2 -> 429000000 | G2: =Lookup!G2 -> 1479000000 | H2: =Lookup!H2 -> 0 | ... AF2: =Lookup!AF2 -> -8779000000 | AG2: {=MID(CELL("filename",J1),FIND("[",CELL("filename",J1))+1,FIND("]",CELL("filename",J1))-FIND("[",CELL("filename",J1))-1)} -> KO_CASH_YR.xlsx | AH2: =_xlfn.CONCAT(LEFT(AG2,10),"-001") -> KO_CASH_YR-001 | AI2: =NOW() -> 46089.955
A3: =Lookup!A3 -> KO | B3: =Lookup!B3 -> 46089 | C3: =Lookup!C3 -> 2024 | D3: =Lookup!D3 -> 10649000000 | E3: =Lookup!E3 -> 1075000000 | F3: =Lookup!F3 -> 1315000000 | G3: =Lookup!G3 -> 2390000000 | H3: =Lookup!H3 -> 0 | ... AF3: =Lookup!AF3 -> -8359000000 | AG3: {=MID(CELL("filename",J2),FIND("[",CELL("filename",J2))+1,FIND("]",CELL("filename",J2))-FIND("[",CELL("filename",J2))-1)} -> KO_CASH_YR.xlsx | AH3: =_xlfn.CONCAT(LEFT(AG3,10),"-001") -> KO_CASH_YR-001 | AI3: =NOW() -> 46089.955
A4: =Lookup!A4 -> KO | B4: =Lookup!B4 -> 46089 | C4: =Lookup!C4 -> 2023 | D4: =Lookup!D4 -> 10703000000 | E4: =Lookup!E4 -> 1128000000 | F4: =Lookup!F4 -> 614000000 | G4: =Lookup!G4 -> 1742000000 | H4: =Lookup!H4 -> 0 | ... AF4: =Lookup!AF4 -> -7952000000 | AG4: {=MID(CELL("filename",J3),FIND("[",CELL("filename",J3))+1,FIND("]",CELL("filename",J3))-FIND("[",CELL("filename",J3))-1)} -> KO_CASH_YR.xlsx | AH4: =_xlfn.CONCAT(LEFT(AG4,10),"-001") -> KO_CASH_YR-001 | AI4: =NOW() -> 46089.955
A5: =Lookup!A5 -> KO | B5: =Lookup!B5 -> 46089 | C5: =Lookup!C5 -> 2022 | D5: =Lookup!D5 -> 9571000000 | E5: =Lookup!E5 -> 1260000000 | F5: =Lookup!F5 -> 792000000 | G5: =Lookup!G5 -> 2052000000 | H5: =Lookup!H5 -> 0 | ... AF5: =Lookup!AF5 -> -7616000000 | AG5: {=MID(CELL("filename",J4),FIND("[",CELL("filename",J4))+1,FIND("]",CELL("filename",J4))-FIND("[",CELL("filename",J4))-1)} -> KO_CASH_YR.xlsx | AH5: =_xlfn.CONCAT(LEFT(AG5,10),"-001") -> KO_CASH_YR-001 | AI5: =NOW() -> 46089.955
A6: =Lookup!A6 -> KO | B6: =Lookup!B6 -> 46089 | C6: =Lookup!C6 -> 2021 | D6: =Lookup!D6 -> 9804000000 | E6: =Lookup!E6 -> 1452000000 | F6: =Lookup!F6 -> 44000000 | G6: =Lookup!G6 -> 1496000000 | H6: =Lookup!H6 -> 0 | ... AF6: =Lookup!AF6 -> -7252000000 | AG6: {=MID(CELL("filename",J5),FIND("[",CELL("filename",J5))+1,FIND("]",CELL("filename",J5))-FIND("[",CELL("filename",J5))-1)} -> KO_CASH_YR.xlsx | AH6: =_xlfn.CONCAT(LEFT(AG6,10),"-001") -> KO_CASH_YR-001 | AI6: =NOW() -> 46089.955
A7: =Lookup!A7 -> KO | B7: =Lookup!B7 -> 46089 | C7: =Lookup!C7 -> 2020 | D7: =Lookup!D7 -> 7768000000 | E7: =Lookup!E7 -> 1536000000 | F7: =Lookup!F7 -> -150000000 | G7: =Lookup!G7 -> 1386000000 | H7: =Lookup!H7 -> 0 | ... AF7: =Lookup!AF7 -> -7047000000 | AG7: {=MID(CELL("filename",J6),FIND("[",CELL("filename",J6))+1,FIND("]",CELL("filename",J6))-FIND("[",CELL("filename",J6))-1)} -> KO_CASH_YR.xlsx | AH7: =_xlfn.CONCAT(LEFT(AG7,10),"-001") -> KO_CASH_YR-001 | AI7: =NOW() -> 46089.955
A8: =Lookup!A8 -> KO | B8: =Lookup!B8 -> 46089 | C8: =Lookup!C8 -> 2019 | D8: =Lookup!D8 -> 8985000000 | E8: =Lookup!E8 -> 1365000000 | F8: =Lookup!F8 -> -245000000 | G8: =Lookup!G8 -> 1120000000 | H8: =Lookup!H8 -> 0 | ... AF8: =Lookup!AF8 -> -6845000000 | AG8: {=MID(CELL("filename",J7),FIND("[",CELL("filename",J7))+1,FIND("]",CELL("filename",J7))-FIND("[",CELL("filename",J7))-1)} -> KO_CASH_YR.xlsx | AH8: =_xlfn.CONCAT(LEFT(AG8,10),"-001") -> KO_CASH_YR-001 | AI8: =NOW() -> 46089.955
A9: =Lookup!A9 -> KO | B9: =Lookup!B9 -> 46089 | C9: =Lookup!C9 -> 2018 | D9: =Lookup!D9 -> 6476000000 | E9: =Lookup!E9 -> 1086000000 | F9: =Lookup!F9 -> 1305000000 | G9: =Lookup!G9 -> 2391000000 | H9: =Lookup!H9 -> 0 | ... AF9: =Lookup!AF9 -> -6644000000 | AG9: {=MID(CELL("filename",J8),FIND("[",CELL("filename",J8))+1,FIND("]",CELL("filename",J8))-FIND("[",CELL("filename",J8))-1)} -> KO_CASH_YR.xlsx | AH9: =_xlfn.CONCAT(LEFT(AG9,10),"-001") -> KO_CASH_YR-001 | AI9: =NOW() -> 46089.955
A10: =Lookup!A10 -> KO | B10: =Lookup!B10 -> 46089 | C10: =Lookup!C10 -> 2017 | D10: =Lookup!D10 -> 1283000000 | E10: =Lookup!E10 -> 1260000000 | F10: =Lookup!F10 -> 1056000000 | G10: =Lookup!G10 -> 2316000000 | H10: =Lookup!H10 -> 0 | ... AF10: =Lookup!AF10 -> -6320000000 | AG10: {=MID(CELL("filename",J9),FIND("[",CELL("filename",J9))+1,FIND("]",CELL("filename",J9))-FIND("[",CELL("filename",J9))-1)} -> KO_CASH_YR.xlsx | AH10: =_xlfn.CONCAT(LEFT(AG10,10),"-001") -> KO_CASH_YR-001 | AI10: =NOW() -> 46089.955
A11: =Lookup!A11 -> KO | B11: =Lookup!B11 -> 46089 | C11: =Lookup!C11 -> 2016 | D11: =Lookup!D11 -> 6550000000 | E11: =Lookup!E11 -> 1787000000 | F11: =Lookup!F11 -> 680000000 | G11: =Lookup!G11 -> 2467000000 | H11: =Lookup!H11 -> 0 | ... AF11: =Lookup!AF11 -> -6043000000 | AG11: {=MID(CELL("filename",J10),FIND("[",CELL("filename",J10))+1,FIND("]",CELL("filename",J10))-FIND("[",CELL("filename",J10))-1)} -> KO_CASH_YR.xlsx | AH11: =_xlfn.CONCAT(LEFT(AG11,10),"-001") -> KO_CASH_YR-001 | AI11: =NOW() -> 46089.955
A12: =Lookup!A12 -> KO | B12: =Lookup!B12 -> 46089 | C12: =Lookup!C12 -> 2015 | D12: =Lookup!D12 -> 7366000000 | E12: =Lookup!E12 -> 1970000000 | F12: =Lookup!F12 -> 1349000000 | G12: =Lookup!G12 -> 3319000000 | H12: =Lookup!H12 -> 0 | ... AF12: =Lookup!AF12 -> -5741000000 | AG12: {=MID(CELL("filename",J11),FIND("[",CELL("filename",J11))+1,FIND("]",CELL("filename",J11))-FIND("[",CELL("filename",J11))-1)} -> KO_CASH_YR.xlsx | AH12: =_xlfn.CONCAT(LEFT(AG12,10),"-001") -> KO_CASH_YR-001 | AI12: =NOW() -> 46089.955
A13: =Lookup!A13 -> KO | B13: =Lookup!B13 -> 46089 | C13: =Lookup!C13 -> 2014 | D13: =Lookup!D13 -> 7124000000 | E13: =Lookup!E13 -> 1976000000 | F13: =Lookup!F13 -> 1954000000 | G13: =Lookup!G13 -> 3930000000 | H13: =Lookup!H13 -> 0 | ... AF13: =Lookup!AF13 -> -5350000000 | AG13: {=MID(CELL("filename",J12),FIND("[",CELL("filename",J12))+1,FIND("]",CELL("filename",J12))-FIND("[",CELL("filename",J12))-1)} -> KO_CASH_YR.xlsx | AH13: =_xlfn.CONCAT(LEFT(AG13,10),"-001") -> KO_CASH_YR-001 | AI13: =NOW() -> 46089.955
... A41: =Lookup!A41 -> KO | B41: =Lookup!B41 -> 46089 | C41: =Lookup!C41 -> 1986 | D41: =Lookup!D41 -> 934347000 | E41: =Lookup!E41 -> 166829000 | F41: =Lookup!F41 -> 0 | G41: =Lookup!G41 -> 166829000 | H41: =Lookup!H41 -> 0 | ... AF41: =Lookup!AF41 -> 0 | AG41: {=MID(CELL("filename",J40),FIND("[",CELL("filename",J40))+1,FIND("]",CELL("filename",J40))-FIND("[",CELL("filename",J40))-1)} -> KO_CASH_YR.xlsx | AH41: =_xlfn.CONCAT(LEFT(AG41,10),"-001") -> KO_CASH_YR-001 | AI41: =NOW() -> 46089.955
